# Recovered from: /home/chenying/researches/cloudpss-toolkit/cloudpss_skills_v2/tests/__pycache__/test_vsi_weak_bus.cpython-312-pytest-9.0.2.pyc
# Original source: /home/chenying/researches/cloudpss-toolkit/cloudpss_skills_v2/tests/test_vsi_weak_bus.py
# WARNING: This file was reconstructed from .pyc bytecode.
# The structure is accurate but implementation details may need manual review.


def TestVSIValidation():
    """TestVSIValidation"""
pass  # TODO: restore


def TestVSICalculation():
    """TestVSICalculation"""
pass  # TODO: restore


def TestVSIBusMatching():
    """TestVSIBusMatching"""
pass  # TODO: restore


def TestVSIWeakBuses():
    """TestVSIWeakBuses"""
pass  # TODO: restore


def TestVSIStatistics():
    """TestVSIStatistics"""
pass  # TODO: restore


def TestVSIRun():
    """TestVSIRun"""
pass  # TODO: restore



# === FULL DISASSEMBLY (for manual reconstruction) ===
#   0           0 RESUME                   0
# 
#   1           2 LOAD_CONST               0 ('Tests for VSIWeakBusSkill v2.')
#               4 STORE_NAME               0 (__doc__)
# 
#   3           6 LOAD_CONST               1 (0)
#               8 LOAD_CONST               2 (None)
#              10 IMPORT_NAME              1 (builtins)
#              12 STORE_NAME               2 (@py_builtins)
#              14 LOAD_CONST               1 (0)
#              16 LOAD_CONST               2 (None)
#              18 IMPORT_NAME              3 (_pytest.assertion.rewrite)
#              20 IMPORT_FROM              4 (assertion)
#              22 SWAP                     2
#              24 POP_TOP
#              26 IMPORT_FROM              5 (rewrite)
#              28 STORE_NAME               6 (@pytest_ar)
#              30 POP_TOP
#              32 LOAD_CONST               1 (0)
#              34 LOAD_CONST               2 (None)
#              36 IMPORT_NAME              7 (pytest)
#              38 STORE_NAME               7 (pytest)
# 
#   4          40 LOAD_CONST               1 (0)
#              42 LOAD_CONST               3 (('VSIWeakBusSkill',))
#              44 IMPORT_NAME              8 (cloudpss_skills_v2.skills.vsi_weak_bus)
#              46 IMPORT_FROM              9 (VSIWeakBusSkill)
#              48 STORE_NAME               9 (VSIWeakBusSkill)
#              50 POP_TOP
# 
#   7          52 PUSH_NULL
#              54 LOAD_BUILD_CLASS
#              56 LOAD_CONST               4 (<code object TestVSIValidation at 0x73cd945fe4f0, file "/home/chenying/researches/cloudpss-toolkit/cloudpss_skills_v2/tests/test_vsi_weak_bus.py", line 7>)
#              58 MAKE_FUNCTION            0
#              60 LOAD_CONST               5 ('TestVSIValidation')
#              62 CALL                     2
#              70 STORE_NAME              10 (TestVSIValidation)
# 
#  20          72 PUSH_NULL
#              74 LOAD_BUILD_CLASS
#              76 LOAD_CONST               6 (<code object TestVSICalculation at 0x73cd945fe330, file "/home/chenying/researches/cloudpss-toolkit/cloudpss_skills_v2/tests/test_vsi_weak_bus.py", line 20>)
#              78 MAKE_FUNCTION            0
#              80 LOAD_CONST               7 ('TestVSICalculation')
#              82 CALL                     2
#              90 STORE_NAME              11 (TestVSICalculation)
# 
#  38          92 PUSH_NULL
#              94 LOAD_BUILD_CLASS
#              96 LOAD_CONST               8 (<code object TestVSIBusMatching at 0x73cd945fe090, file "/home/chenying/researches/cloudpss-toolkit/cloudpss_skills_v2/tests/test_vsi_weak_bus.py", line 38>)
#              98 MAKE_FUNCTION            0
#             100 LOAD_CONST               9 ('TestVSIBusMatching')
#             102 CALL                     2
#             110 STORE_NAME              12 (TestVSIBusMatching)
# 
#  52         112 PUSH_NULL
#             114 LOAD_BUILD_CLASS
#             116 LOAD_CONST              10 (<code object TestVSIWeakBuses at 0x73cd945fea30, file "/home/chenying/researches/cloudpss-toolkit/cloudpss_skills_v2/tests/test_vsi_weak_bus.py", line 52>)
#             118 MAKE_FUNCTION            0
#             120 LOAD_CONST              11 ('TestVSIWeakBuses')
#             122 CALL                     2
#             130 STORE_NAME              13 (TestVSIWeakBuses)
# 
#  74         132 PUSH_NULL
#             134 LOAD_BUILD_CLASS
#             136 LOAD_CONST              12 (<code object TestVSIStatistics at 0x73cd945fecd0, file "/home/chenying/researches/cloudpss-toolkit/cloudpss_skills_v2/tests/test_vsi_weak_bus.py", line 74>)
#             138 MAKE_FUNCTION            0
#             140 LOAD_CONST              13 ('TestVSIStatistics')
#             142 CALL                     2
#             150 STORE_NAME              14 (TestVSIStatistics)
# 
#  91         152 PUSH_NULL
#             154 LOAD_BUILD_CLASS
#             156 LOAD_CONST              14 (<code object TestVSIRun at 0x73cd945fe250, file "/home/chenying/researches/cloudpss-toolkit/cloudpss_skills_v2/tests/test_vsi_weak_bus.py", line 91>)
#             158 MAKE_FUNCTION            0
#             160 LOAD_CONST              15 ('TestVSIRun')
#             162 CALL                     2
#             170 STORE_NAME              15 (TestVSIRun)
#             172 RETURN_CONST             2 (None)
# 
# Disassembly of <code object TestVSIValidation at 0x73cd945fe4f0, file "/home/chenying/researches/cloudpss-toolkit/cloudpss_skills_v2/tests/test_vsi_weak_bus.py", line 7>:
#   7           0 RESUME                   0
#               2 LOAD_NAME                0 (__name__)
#               4 STORE_NAME               1 (__module__)
#               6 LOAD_CONST               0 ('TestVSIValidation')
#               8 STORE_NAME               2 (__qualname__)
# 
#   8          10 LOAD_CONST               1 (<code object test_validate_missing_model at 0x3afa7230, file "/home/chenying/researches/cloudpss-toolkit/cloudpss_skills_v2/tests/test_vsi_weak_bus.py", line 8>)
#              12 MAKE_FUNCTION            0
#              14 STORE_NAME               3 (test_validate_missing_model)
# 
#  13          16 LOAD_CONST               2 (<code object test_validate_valid_config at 0x3afa3fb0, file "/home/chenying/researches/cloudpss-toolkit/cloudpss_skills_v2/tests/test_vsi_weak_bus.py", line 13>)
#              18 MAKE_FUNCTION            0
#              20 STORE_NAME               4 (test_validate_valid_config)
#              22 RETURN_CONST             3 (None)
# 
# Disassembly of <code object test_validate_missing_model at 0x3afa7230, file "/home/chenying/researches/cloudpss-toolkit/cloudpss_skills_v2/tests/test_vsi_weak_bus.py", line 8>:
#   8           0 RESUME                   0
# 
#   9           2 LOAD_GLOBAL              1 (NULL + VSIWeakBusSkill)
#              12 CALL                     0
#              20 STORE_FAST               1 (skill)
# 
#  10          22 LOAD_FAST                1 (skill)
#              24 LOAD_ATTR                3 (NULL|self + validate)
#              44 BUILD_MAP                0
#              46 CALL                     1
#              54 UNPACK_SEQUENCE          2
#              58 STORE_FAST               2 (valid)
#              60 STORE_FAST               3 (errors)
# 
#  11          62 LOAD_CONST               1 (False)
#              64 STORE_FAST               4 (@py_assert2)
#              66 LOAD_FAST                2 (valid)
#              68 LOAD_FAST                4 (@py_assert2)
#              70 IS_OP                    0
#              72 STORE_FAST               5 (@py_assert1)
#              74 LOAD_FAST                5 (@py_assert1)
#              76 POP_JUMP_IF_TRUE       153 (to 384)
#              78 LOAD_GLOBAL              5 (NULL + @pytest_ar)
#              88 LOAD_ATTR                6 (_call_reprcompare)
#             108 LOAD_CONST               2 (('is',))
#             110 LOAD_FAST                5 (@py_assert1)
#             112 BUILD_TUPLE              1
#             114 LOAD_CONST               3 (('%(py0)s is %(py3)s',))
#             116 LOAD_FAST                2 (valid)
#             118 LOAD_FAST                4 (@py_assert2)
#             120 BUILD_TUPLE              2
#             122 CALL                     4
#             130 LOAD_CONST               4 ('valid')
#             132 LOAD_GLOBAL              9 (NULL + @py_builtins)
#             142 LOAD_ATTR               10 (locals)
#             162 CALL                     0
#             170 CONTAINS_OP              0
#             172 POP_JUMP_IF_TRUE        21 (to 216)
#             174 LOAD_GLOBAL              5 (NULL + @pytest_ar)
#             184 LOAD_ATTR               12 (_should_repr_global_name)
#             204 LOAD_FAST                2 (valid)
#             206 CALL                     1
#             214 POP_JUMP_IF_FALSE       21 (to 258)
#         >>  216 LOAD_GLOBAL              5 (NULL + @pytest_ar)
#             226 LOAD_ATTR               14 (_saferepr)
#             246 LOAD_FAST                2 (valid)
#             248 CALL                     1
#             256 JUMP_FORWARD             1 (to 260)
#         >>  258 LOAD_CONST               4 ('valid')
#         >>  260 LOAD_GLOBAL              5 (NULL + @pytest_ar)
#             270 LOAD_ATTR               14 (_saferepr)
#             290 LOAD_FAST                4 (@py_assert2)
#             292 CALL                     1
#             300 LOAD_CONST               5 (('py0', 'py3'))
#             302 BUILD_CONST_KEY_MAP      2
#             304 BINARY_OP                6 (%)
#             308 STORE_FAST               6 (@py_format4)
#             310 LOAD_CONST               6 ('assert %(py5)s')
#             312 LOAD_CONST               7 ('py5')
#             314 LOAD_FAST                6 (@py_format4)
#             316 BUILD_MAP                1
#             318 BINARY_OP                6 (%)
#             322 STORE_FAST               7 (@py_format6)
#             324 LOAD_GLOBAL             17 (NULL + AssertionError)
#             334 LOAD_GLOBAL              5 (NULL + @pytest_ar)
#             344 LOAD_ATTR               18 (_format_explanation)
#             364 LOAD_FAST                7 (@py_format6)
#             366 CALL                     1
#             374 CALL                     1
#             382 RAISE_VARARGS            1
#         >>  384 LOAD_CONST               0 (None)
#             386 COPY                     1
#             388 STORE_FAST               5 (@py_assert1)
#             390 STORE_FAST               4 (@py_assert2)
#             392 RETURN_CONST             0 (None)
# 
# Disassembly of <code object test_validate_valid_config at 0x3afa3fb0, file "/home/chenying/researches/cloudpss-toolkit/cloudpss_skills_v2/tests/test_vsi_weak_bus.py", line 13>:
#  13           0 RESUME                   0
# 
#  14           2 LOAD_GLOBAL              1 (NULL + VSIWeakBusSkill)
#              12 CALL                     0
#              20 STORE_FAST               1 (skill)
# 
#  15          22 LOAD_CONST               1 ('model')
#              24 LOAD_CONST               2 ('rid')
#              26 LOAD_CONST               3 ('model/test/IEEE39')
#              28 BUILD_MAP                1
#              30 BUILD_MAP                1
#              32 STORE_FAST               2 (config)
# 
#  16          34 LOAD_FAST                1 (skill)
#              36 LOAD_ATTR                3 (NULL|self + validate)
#              56 LOAD_FAST                2 (config)
#              58 CALL                     1
#              66 UNPACK_SEQUENCE          2
#              70 STORE_FAST               3 (valid)
#              72 STORE_FAST               4 (errors)
# 
#  17          74 LOAD_CONST               4 (True)
#              76 STORE_FAST               5 (@py_assert2)
#              78 LOAD_FAST                3 (valid)
#              80 LOAD_FAST                5 (@py_assert2)
#              82 IS_OP                    0
#              84 STORE_FAST               6 (@py_assert1)
#              86 LOAD_FAST                6 (@py_assert1)
#              88 POP_JUMP_IF_TRUE       153 (to 396)
#              90 LOAD_GLOBAL              5 (NULL + @pytest_ar)
#             100 LOAD_ATTR                6 (_call_reprcompare)
#             120 LOAD_CONST               5 (('is',))
#             122 LOAD_FAST                6 (@py_assert1)
#             124 BUILD_TUPLE              1
#             126 LOAD_CONST               6 (('%(py0)s is %(py3)s',))
#             128 LOAD_FAST                3 (valid)
#             130 LOAD_FAST                5 (@py_assert2)
#             132 BUILD_TUPLE              2
#             134 CALL                     4
#             142 LOAD_CONST               7 ('valid')
#             144 LOAD_GLOBAL              9 (NULL + @py_builtins)
#             154 LOAD_ATTR               10 (locals)
#             174 CALL                     0
#             182 CONTAINS_OP              0
#             184 POP_JUMP_IF_TRUE        21 (to 228)
#             186 LOAD_GLOBAL              5 (NULL + @pytest_ar)
#             196 LOAD_ATTR               12 (_should_repr_global_name)
#             216 LOAD_FAST                3 (valid)
#             218 CALL                     1
#             226 POP_JUMP_IF_FALSE       21 (to 270)
#         >>  228 LOAD_GLOBAL              5 (NULL + @pytest_ar)
#             238 LOAD_ATTR               14 (_saferepr)
#             258 LOAD_FAST                3 (valid)
#             260 CALL                     1
#             268 JUMP_FORWARD             1 (to 272)
#         >>  270 LOAD_CONST               7 ('valid')
#         >>  272 LOAD_GLOBAL              5 (NULL + @pytest_ar)
#             282 LOAD_ATTR               14 (_saferepr)
#             302 LOAD_FAST                5 (@py_assert2)
#             304 CALL                     1
#             312 LOAD_CONST               8 (('py0', 'py3'))
#             314 BUILD_CONST_KEY_MAP      2
#             316 BINARY_OP                6 (%)
#             320 STORE_FAST               7 (@py_format4)
#             322 LOAD_CONST               9 ('assert %(py5)s')
#             324 LOAD_CONST              10 ('py5')
#             326 LOAD_FAST                7 (@py_format4)
#             328 BUILD_MAP                1
#             330 BINARY_OP                6 (%)
#             334 STORE_FAST               8 (@py_format6)
#             336 LOAD_GLOBAL             17 (NULL + AssertionError)
#             346 LOAD_GLOBAL              5 (NULL + @pytest_ar)
#             356 LOAD_ATTR               18 (_format_explanation)
#             376 LOAD_FAST                8 (@py_format6)
#             378 CALL                     1
#             386 CALL                     1
#             394 RAISE_VARARGS            1
#         >>  396 LOAD_CONST               0 (None)
#             398 COPY                     1
#             400 STORE_FAST               6 (@py_assert1)
#             402 STORE_FAST               5 (@py_assert2)
#             404 RETURN_CONST             0 (None)
# 
# Disassembly of <code object TestVSICalculation at 0x73cd945fe330, file "/home/chenying/researches/cloudpss-toolkit/cloudpss_skills_v2/tests/test_vsi_weak_bus.py", line 20>:
#  20           0 RESUME                   0
#               2 LOAD_NAME                0 (__name__)
#               4 STORE_NAME               1 (__module__)
#               6 LOAD_CONST               0 ('TestVSICalculation')
#               8 STORE_NAME               2 (__qualname__)
# 
#  21          10 LOAD_CONST               1 (<code object test_calculate_vsi_normal at 0x3af9a920, file "/home/chenying/researches/cloudpss-toolkit/cloudpss_skills_v2/tests/test_vsi_weak_bus.py", line 21>)
#              12 MAKE_FUNCTION            0
#              14 STORE_NAME               3 (test_calculate_vsi_normal)
# 
#  27          16 LOAD_CONST               2 (<code object test_calculate_vsi_zero_injection at 0x3af90d20, file "/home/chenying/researches/cloudpss-toolkit/cloudpss_skills_v2/tests/test_vsi_weak_bus.py", line 27>)
#              18 MAKE_FUNCTION            0
#              20 STORE_NAME               4 (test_calculate_vsi_zero_injection)
# 
#  32          22 LOAD_CONST               3 (<code object test_calculate_vsi_no_change at 0x3ae632d0, file "/home/chenying/researches/cloudpss-toolkit/cloudpss_skills_v2/tests/test_vsi_weak_bus.py", line 32>)
#              24 MAKE_FUNCTION            0
#              26 STORE_NAME               5 (test_calculate_vsi_no_change)
#              28 RETURN_CONST             4 (None)
# 
# Disassembly of <code object test_calculate_vsi_normal at 0x3af9a920, file "/home/chenying/researches/cloudpss-toolkit/cloudpss_skills_v2/tests/test_vsi_weak_bus.py", line 21>:
#  21           0 RESUME                   0
# 
#  22           2 LOAD_GLOBAL              1 (NULL + VSIWeakBusSkill)
#              12 CALL                     0
#              20 STORE_FAST               1 (skill)
# 
#  23          22 LOAD_FAST                1 (skill)
#              24 LOAD_ATTR                3 (NULL|self + _calculate_vsi)
#              44 LOAD_CONST               1 (1.0)
#              46 LOAD_CONST               2 (0.95)
#              48 LOAD_CONST               3 (100.0)
#              50 KW_NAMES                 4 (('voltage_pre', 'voltage_post', 'q_injected'))
#              52 CALL                     3
#              60 STORE_FAST               2 (vsi)
# 
#  24          62 LOAD_CONST               5 (0.0005)
#              64 STORE_FAST               3 (expected)
# 
#  25          66 LOAD_FAST                2 (vsi)
#              68 LOAD_FAST                3 (expected)
#              70 BINARY_OP               10 (-)
#              74 STORE_FAST               4 (@py_assert3)
#              76 LOAD_GLOBAL              5 (NULL + abs)
#              86 LOAD_FAST                4 (@py_assert3)
#              88 CALL                     1
#              96 STORE_FAST               5 (@py_assert4)
#              98 LOAD_CONST               6 (1e-10)
#             100 STORE_FAST               6 (@py_assert7)
#             102 LOAD_FAST                5 (@py_assert4)
#             104 LOAD_FAST                6 (@py_assert7)
#             106 COMPARE_OP               2 (<)
#             110 STORE_FAST               7 (@py_assert6)
#             112 LOAD_FAST                7 (@py_assert6)
#             114 EXTENDED_ARG             1
#             116 POP_JUMP_IF_TRUE       311 (to 740)
#             118 LOAD_GLOBAL              7 (NULL + @pytest_ar)
#             128 LOAD_ATTR                8 (_call_reprcompare)
#             148 LOAD_CONST               7 (('<',))
#             150 LOAD_FAST                7 (@py_assert6)
#             152 BUILD_TUPLE              1
#             154 LOAD_CONST               8 (('%(py5)s\n{%(py5)s = %(py0)s((%(py1)s - %(py2)s))\n} < %(py8)s',))
#             156 LOAD_FAST                5 (@py_assert4)
#             158 LOAD_FAST                6 (@py_assert7)
#             160 BUILD_TUPLE              2
#             162 CALL                     4
#             170 LOAD_CONST               9 ('abs')
#             172 LOAD_GLOBAL             11 (NULL + @py_builtins)
#             182 LOAD_ATTR               12 (locals)
#             202 CALL                     0
#             210 CONTAINS_OP              0
#             212 POP_JUMP_IF_TRUE        25 (to 264)
#             214 LOAD_GLOBAL              7 (NULL + @pytest_ar)
#             224 LOAD_ATTR               14 (_should_repr_global_name)
#             244 LOAD_GLOBAL              4 (abs)
#             254 CALL                     1
#             262 POP_JUMP_IF_FALSE       25 (to 314)
#         >>  264 LOAD_GLOBAL              7 (NULL + @pytest_ar)
#             274 LOAD_ATTR               16 (_saferepr)
#             294 LOAD_GLOBAL              4 (abs)
#             304 CALL                     1
#             312 JUMP_FORWARD             1 (to 316)
#         >>  314 LOAD_CONST               9 ('abs')
#         >>  316 LOAD_CONST              10 ('vsi')
#             318 LOAD_GLOBAL             11 (NULL + @py_builtins)
#             328 LOAD_ATTR               12 (locals)
#             348 CALL                     0
#             356 CONTAINS_OP              0
#             358 POP_JUMP_IF_TRUE        21 (to 402)
#             360 LOAD_GLOBAL              7 (NULL + @pytest_ar)
#             370 LOAD_ATTR               14 (_should_repr_global_name)
#             390 LOAD_FAST                2 (vsi)
#             392 CALL                     1
#             400 POP_JUMP_IF_FALSE       21 (to 444)
#         >>  402 LOAD_GLOBAL              7 (NULL + @pytest_ar)
#             412 LOAD_ATTR               16 (_saferepr)
#             432 LOAD_FAST                2 (vsi)
#             434 CALL                     1
#             442 JUMP_FORWARD             1 (to 446)
#         >>  444 LOAD_CONST              10 ('vsi')
#         >>  446 LOAD_CONST              11 ('expected')
#             448 LOAD_GLOBAL             11 (NULL + @py_builtins)
#             458 LOAD_ATTR               12 (locals)
#             478 CALL                     0
#             486 CONTAINS_OP              0
#             488 POP_JUMP_IF_TRUE        21 (to 532)
#             490 LOAD_GLOBAL              7 (NULL + @pytest_ar)
#             500 LOAD_ATTR               14 (_should_repr_global_name)
#             520 LOAD_FAST                3 (expected)
#             522 CALL                     1
#             530 POP_JUMP_IF_FALSE       21 (to 574)
#         >>  532 LOAD_GLOBAL              7 (NULL + @pytest_ar)
#             542 LOAD_ATTR               16 (_saferepr)
#             562 LOAD_FAST                3 (expected)
#             564 CALL                     1
#             572 JUMP_FORWARD             1 (to 576)
#         >>  574 LOAD_CONST              11 ('expected')
#         >>  576 LOAD_GLOBAL              7 (NULL + @pytest_ar)
#             586 LOAD_ATTR               16 (_saferepr)
#             606 LOAD_FAST                5 (@py_assert4)
#             608 CALL                     1
#             616 LOAD_GLOBAL              7 (NULL + @pytest_ar)
#             626 LOAD_ATTR               16 (_saferepr)
#             646 LOAD_FAST                6 (@py_assert7)
#             648 CALL                     1
#             656 LOAD_CONST              12 (('py0', 'py1', 'py2', 'py5', 'py8'))
#             658 BUILD_CONST_KEY_MAP      5
#             660 BINARY_OP                6 (%)
#             664 STORE_FAST               8 (@py_format9)
#             666 LOAD_CONST              13 ('assert %(py10)s')
#             668 LOAD_CONST              14 ('py10')
#             670 LOAD_FAST                8 (@py_format9)
#             672 BUILD_MAP                1
#             674 BINARY_OP                6 (%)
#             678 STORE_FAST               9 (@py_format11)
#             680 LOAD_GLOBAL             19 (NULL + AssertionError)
#             690 LOAD_GLOBAL              7 (NULL + @pytest_ar)
#             700 LOAD_ATTR               20 (_format_explanation)
#             720 LOAD_FAST                9 (@py_format11)
#             722 CALL                     1
#             730 CALL                     1
#             738 RAISE_VARARGS            1
#         >>  740 LOAD_CONST               0 (None)
#             742 COPY                     1
#             744 STORE_FAST               4 (@py_assert3)
#             746 COPY                     1
#             748 STORE_FAST               5 (@py_assert4)
#             750 COPY                     1
#             752 STORE_FAST               7 (@py_assert6)
#             754 STORE_FAST               6 (@py_assert7)
#             756 RETURN_CONST             0 (None)
# 
# Disassembly of <code object test_calculate_vsi_zero_injection at 0x3af90d20, file "/home/chenying/researches/cloudpss-toolkit/cloudpss_skills_v2/tests/test_vsi_weak_bus.py", line 27>:
#  27           0 RESUME                   0
# 
#  28           2 LOAD_GLOBAL              1 (NULL + VSIWeakBusSkill)
#              12 CALL                     0
#              20 STORE_FAST               1 (skill)
# 
#  29          22 LOAD_FAST                1 (skill)
#              24 LOAD_ATTR                3 (NULL|self + _calculate_vsi)
#              44 LOAD_CONST               1 (1.0)
#              46 LOAD_CONST               2 (0.95)
#              48 LOAD_CONST               3 (0.0)
#              50 KW_NAMES                 4 (('voltage_pre', 'voltage_post', 'q_injected'))
#              52 CALL                     3
#              60 STORE_FAST               2 (vsi)
# 
#  30          62 LOAD_CONST               3 (0.0)
#              64 STORE_FAST               3 (@py_assert2)
#              66 LOAD_FAST                2 (vsi)
#              68 LOAD_FAST                3 (@py_assert2)
#              70 COMPARE_OP              40 (==)
#              74 STORE_FAST               4 (@py_assert1)
#              76 LOAD_FAST                4 (@py_assert1)
#              78 POP_JUMP_IF_TRUE       153 (to 386)
#              80 LOAD_GLOBAL              5 (NULL + @pytest_ar)
#              90 LOAD_ATTR                6 (_call_reprcompare)
#             110 LOAD_CONST               5 (('==',))
#             112 LOAD_FAST                4 (@py_assert1)
#             114 BUILD_TUPLE              1
#             116 LOAD_CONST               6 (('%(py0)s == %(py3)s',))
#             118 LOAD_FAST                2 (vsi)
#             120 LOAD_FAST                3 (@py_assert2)
#             122 BUILD_TUPLE              2
#             124 CALL                     4
#             132 LOAD_CONST               7 ('vsi')
#             134 LOAD_GLOBAL              9 (NULL + @py_builtins)
#             144 LOAD_ATTR               10 (locals)
#             164 CALL                     0
#             172 CONTAINS_OP              0
#             174 POP_JUMP_IF_TRUE        21 (to 218)
#             176 LOAD_GLOBAL              5 (NULL + @pytest_ar)
#             186 LOAD_ATTR               12 (_should_repr_global_name)
#             206 LOAD_FAST                2 (vsi)
#             208 CALL                     1
#             216 POP_JUMP_IF_FALSE       21 (to 260)
#         >>  218 LOAD_GLOBAL              5 (NULL + @pytest_ar)
#             228 LOAD_ATTR               14 (_saferepr)
#             248 LOAD_FAST                2 (vsi)
#             250 CALL                     1
#             258 JUMP_FORWARD             1 (to 262)
#         >>  260 LOAD_CONST               7 ('vsi')
#         >>  262 LOAD_GLOBAL              5 (NULL + @pytest_ar)
#             272 LOAD_ATTR               14 (_saferepr)
#             292 LOAD_FAST                3 (@py_assert2)
#             294 CALL                     1
#             302 LOAD_CONST               8 (('py0', 'py3'))
#             304 BUILD_CONST_KEY_MAP      2
#             306 BINARY_OP                6 (%)
#             310 STORE_FAST               5 (@py_format4)
#             312 LOAD_CONST               9 ('assert %(py5)s')
#             314 LOAD_CONST              10 ('py5')
#             316 LOAD_FAST                5 (@py_format4)
#             318 BUILD_MAP                1
#             320 BINARY_OP                6 (%)
#             324 STORE_FAST               6 (@py_format6)
#             326 LOAD_GLOBAL             17 (NULL + AssertionError)
#             336 LOAD_GLOBAL              5 (NULL + @pytest_ar)
#             346 LOAD_ATTR               18 (_format_explanation)
#             366 LOAD_FAST                6 (@py_format6)
#             368 CALL                     1
#             376 CALL                     1
#             384 RAISE_VARARGS            1
#         >>  386 LOAD_CONST               0 (None)
#             388 COPY                     1
#             390 STORE_FAST               4 (@py_assert1)
#             392 STORE_FAST               3 (@py_assert2)
#             394 RETURN_CONST             0 (None)
# 
# Disassembly of <code object test_calculate_vsi_no_change at 0x3ae632d0, file "/home/chenying/researches/cloudpss-toolkit/cloudpss_skills_v2/tests/test_vsi_weak_bus.py", line 32>:
#  32           0 RESUME                   0
# 
#  33           2 LOAD_GLOBAL              1 (NULL + VSIWeakBusSkill)
#              12 CALL                     0
#              20 STORE_FAST               1 (skill)
# 
#  34          22 LOAD_FAST                1 (skill)
#              24 LOAD_ATTR                3 (NULL|self + _calculate_vsi)
#              44 LOAD_CONST               1 (1.0)
#              46 LOAD_CONST               1 (1.0)
#              48 LOAD_CONST               2 (100.0)
#              50 KW_NAMES                 3 (('voltage_pre', 'voltage_post', 'q_injected'))
#              52 CALL                     3
#              60 STORE_FAST               2 (vsi)
# 
#  35          62 LOAD_CONST               4 (0.0)
#              64 STORE_FAST               3 (@py_assert2)
#              66 LOAD_FAST                2 (vsi)
#              68 LOAD_FAST                3 (@py_assert2)
#              70 COMPARE_OP              40 (==)
#              74 STORE_FAST               4 (@py_assert1)
#              76 LOAD_FAST                4 (@py_assert1)
#              78 POP_JUMP_IF_TRUE       153 (to 386)
#              80 LOAD_GLOBAL              5 (NULL + @pytest_ar)
#              90 LOAD_ATTR                6 (_call_reprcompare)
#             110 LOAD_CONST               5 (('==',))
#             112 LOAD_FAST                4 (@py_assert1)
#             114 BUILD_TUPLE              1
#             116 LOAD_CONST               6 (('%(py0)s == %(py3)s',))
#             118 LOAD_FAST                2 (vsi)
#             120 LOAD_FAST                3 (@py_assert2)
#             122 BUILD_TUPLE              2
#             124 CALL                     4
#             132 LOAD_CONST               7 ('vsi')
#             134 LOAD_GLOBAL              9 (NULL + @py_builtins)
#             144 LOAD_ATTR               10 (locals)
#             164 CALL                     0
#             172 CONTAINS_OP              0
#             174 POP_JUMP_IF_TRUE        21 (to 218)
#             176 LOAD_GLOBAL              5 (NULL + @pytest_ar)
#             186 LOAD_ATTR               12 (_should_repr_global_name)
#             206 LOAD_FAST                2 (vsi)
#             208 CALL                     1
#             216 POP_JUMP_IF_FALSE       21 (to 260)
#         >>  218 LOAD_GLOBAL              5 (NULL + @pytest_ar)
#             228 LOAD_ATTR               14 (_saferepr)
#             248 LOAD_FAST                2 (vsi)
#             250 CALL                     1
#             258 JUMP_FORWARD             1 (to 262)
#         >>  260 LOAD_CONST               7 ('vsi')
#         >>  262 LOAD_GLOBAL              5 (NULL + @pytest_ar)
#             272 LOAD_ATTR               14 (_saferepr)
#             292 LOAD_FAST                3 (@py_assert2)
#             294 CALL                     1
#             302 LOAD_CONST               8 (('py0', 'py3'))
#             304 BUILD_CONST_KEY_MAP      2
#             306 BINARY_OP                6 (%)
#             310 STORE_FAST               5 (@py_format4)
#             312 LOAD_CONST               9 ('assert %(py5)s')
#             314 LOAD_CONST              10 ('py5')
#             316 LOAD_FAST                5 (@py_format4)
#             318 BUILD_MAP                1
#             320 BINARY_OP                6 (%)
#             324 STORE_FAST               6 (@py_format6)
#             326 LOAD_GLOBAL             17 (NULL + AssertionError)
#             336 LOAD_GLOBAL              5 (NULL + @pytest_ar)
#             346 LOAD_ATTR               18 (_format_explanation)
#             366 LOAD_FAST                6 (@py_format6)
#             368 CALL                     1
#             376 CALL                     1
#             384 RAISE_VARARGS            1
#         >>  386 LOAD_CONST               0 (None)
#             388 COPY                     1
#             390 STORE_FAST               4 (@py_assert1)
#             392 STORE_FAST               3 (@py_assert2)
#             394 RETURN_CONST             0 (None)
# 
# Disassembly of <code object TestVSIBusMatching at 0x73cd945fe090, file "/home/chenying/researches/cloudpss-toolkit/cloudpss_skills_v2/tests/test_vsi_weak_bus.py", line 38>:
#  38           0 RESUME                   0
#               2 LOAD_NAME                0 (__name__)
#               4 STORE_NAME               1 (__module__)
#               6 LOAD_CONST               0 ('TestVSIBusMatching')
#               8 STORE_NAME               2 (__qualname__)
# 
#  39          10 LOAD_CONST               1 (<code object test_matches_bus_identifier_exact at 0x3af9ce50, file "/home/chenying/researches/cloudpss-toolkit/cloudpss_skills_v2/tests/test_vsi_weak_bus.py", line 39>)
#              12 MAKE_FUNCTION            0
#              14 STORE_NAME               3 (test_matches_bus_identifier_exact)
# 
#  43          16 LOAD_CONST               2 (<code object test_matches_bus_identifier_case_insensitive at 0x3afa4f50, file "/home/chenying/researches/cloudpss-toolkit/cloudpss_skills_v2/tests/test_vsi_weak_bus.py", line 43>)
#              18 MAKE_FUNCTION            0
#              20 STORE_NAME               4 (test_matches_bus_identifier_case_insensitive)
# 
#  47          22 LOAD_CONST               3 (<code object test_matches_bus_identifier_underscore at 0x3aee3ab0, file "/home/chenying/researches/cloudpss-toolkit/cloudpss_skills_v2/tests/test_vsi_weak_bus.py", line 47>)
#              24 MAKE_FUNCTION            0
#              26 STORE_NAME               5 (test_matches_bus_identifier_underscore)
#              28 RETURN_CONST             4 (None)
# 
# Disassembly of <code object test_matches_bus_identifier_exact at 0x3af9ce50, file "/home/chenying/researches/cloudpss-toolkit/cloudpss_skills_v2/tests/test_vsi_weak_bus.py", line 39>:
#  39           0 RESUME                   0
# 
#  40           2 LOAD_GLOBAL              1 (NULL + VSIWeakBusSkill)
#              12 CALL                     0
#              20 STORE_FAST               1 (skill)
# 
#  41          22 LOAD_FAST                1 (skill)
#              24 LOAD_ATTR                2 (_matches_bus_identifier)
#              44 STORE_FAST               2 (@py_assert1)
#              46 LOAD_CONST               1 ('Bus7')
#              48 STORE_FAST               3 (@py_assert3)
#              50 LOAD_CONST               1 ('Bus7')
#              52 STORE_FAST               4 (@py_assert5)
#              54 PUSH_NULL
#              56 LOAD_FAST                2 (@py_assert1)
#              58 LOAD_FAST                3 (@py_assert3)
#              60 LOAD_FAST                4 (@py_assert5)
#              62 CALL                     2
#              70 STORE_FAST               5 (@py_assert7)
#              72 LOAD_CONST               2 (True)
#              74 STORE_FAST               6 (@py_assert10)
#              76 LOAD_FAST                5 (@py_assert7)
#              78 LOAD_FAST                6 (@py_assert10)
#              80 IS_OP                    0
#              82 STORE_FAST               7 (@py_assert9)
#              84 LOAD_FAST                7 (@py_assert9)
#              86 POP_JUMP_IF_TRUE       233 (to 554)
#              88 LOAD_GLOBAL              5 (NULL + @pytest_ar)
#              98 LOAD_ATTR                6 (_call_reprcompare)
#             118 LOAD_CONST               3 (('is',))
#             120 LOAD_FAST                7 (@py_assert9)
#             122 BUILD_TUPLE              1
#             124 LOAD_CONST               4 (('%(py8)s\n{%(py8)s = %(py2)s\n{%(py2)s = %(py0)s._matches_bus_identifier\n}(%(py4)s, %(py6)s)\n} is %(py11)s',))
#             126 LOAD_FAST                5 (@py_assert7)
#             128 LOAD_FAST                6 (@py_assert10)
#             130 BUILD_TUPLE              2
#             132 CALL                     4
#             140 LOAD_CONST               5 ('skill')
#             142 LOAD_GLOBAL              9 (NULL + @py_builtins)
#             152 LOAD_ATTR               10 (locals)
#             172 CALL                     0
#             180 CONTAINS_OP              0
#             182 POP_JUMP_IF_TRUE        21 (to 226)
#             184 LOAD_GLOBAL              5 (NULL + @pytest_ar)
#             194 LOAD_ATTR               12 (_should_repr_global_name)
#             214 LOAD_FAST                1 (skill)
#             216 CALL                     1
#             224 POP_JUMP_IF_FALSE       21 (to 268)
#         >>  226 LOAD_GLOBAL              5 (NULL + @pytest_ar)
#             236 LOAD_ATTR               14 (_saferepr)
#             256 LOAD_FAST                1 (skill)
#             258 CALL                     1
#             266 JUMP_FORWARD             1 (to 270)
#         >>  268 LOAD_CONST               5 ('skill')
#         >>  270 LOAD_GLOBAL              5 (NULL + @pytest_ar)
#             280 LOAD_ATTR               14 (_saferepr)
#             300 LOAD_FAST                2 (@py_assert1)
#             302 CALL                     1
#             310 LOAD_GLOBAL              5 (NULL + @pytest_ar)
#             320 LOAD_ATTR               14 (_saferepr)
#             340 LOAD_FAST                3 (@py_assert3)
#             342 CALL                     1
#             350 LOAD_GLOBAL              5 (NULL + @pytest_ar)
#             360 LOAD_ATTR               14 (_saferepr)
#             380 LOAD_FAST                4 (@py_assert5)
#             382 CALL                     1
#             390 LOAD_GLOBAL              5 (NULL + @pytest_ar)
#             400 LOAD_ATTR               14 (_saferepr)
#             420 LOAD_FAST                5 (@py_assert7)
#             422 CALL                     1
#             430 LOAD_GLOBAL              5 (NULL + @pytest_ar)
#             440 LOAD_ATTR               14 (_saferepr)
#             460 LOAD_FAST                6 (@py_assert10)
#             462 CALL                     1
#             470 LOAD_CONST               6 (('py0', 'py2', 'py4', 'py6', 'py8', 'py11'))
#             472 BUILD_CONST_KEY_MAP      6
#             474 BINARY_OP                6 (%)
#             478 STORE_FAST               8 (@py_format12)
#             480 LOAD_CONST               7 ('assert %(py13)s')
#             482 LOAD_CONST               8 ('py13')
#             484 LOAD_FAST                8 (@py_format12)
#             486 BUILD_MAP                1
#             488 BINARY_OP                6 (%)
#             492 STORE_FAST               9 (@py_format14)
#             494 LOAD_GLOBAL             17 (NULL + AssertionError)
#             504 LOAD_GLOBAL              5 (NULL + @pytest_ar)
#             514 LOAD_ATTR               18 (_format_explanation)
#             534 LOAD_FAST                9 (@py_format14)
#             536 CALL                     1
#             544 CALL                     1
#             552 RAISE_VARARGS            1
#         >>  554 LOAD_CONST               0 (None)
#             556 COPY                     1
#             558 STORE_FAST               2 (@py_assert1)
#             560 COPY                     1
#             562 STORE_FAST               3 (@py_assert3)
#             564 COPY                     1
#             566 STORE_FAST               4 (@py_assert5)
#             568 COPY                     1
#             570 STORE_FAST               5 (@py_assert7)
#             572 COPY                     1
#             574 STORE_FAST               7 (@py_assert9)
#             576 STORE_FAST               6 (@py_assert10)
#             578 RETURN_CONST             0 (None)
# 
# Disassembly of <code object test_matches_bus_identifier_case_insensitive at 0x3afa4f50, file "/home/chenying/researches/cloudpss-toolkit/cloudpss_skills_v2/tests/test_vsi_weak_bus.py", line 43>:
#  43           0 RESUME                   0
# 
#  44           2 LOAD_GLOBAL              1 (NULL + VSIWeakBusSkill)
#              12 CALL                     0
#              20 STORE_FAST               1 (skill)
# 
#  45          22 LOAD_FAST                1 (skill)
#              24 LOAD_ATTR                2 (_matches_bus_identifier)
#              44 STORE_FAST               2 (@py_assert1)
#              46 LOAD_CONST               1 ('bus7')
#              48 STORE_FAST               3 (@py_assert3)
#              50 LOAD_CONST               2 ('Bus7')
#              52 STORE_FAST               4 (@py_assert5)
#              54 PUSH_NULL
#              56 LOAD_FAST                2 (@py_assert1)
#              58 LOAD_FAST                3 (@py_assert3)
#              60 LOAD_FAST                4 (@py_assert5)
#              62 CALL                     2
#              70 STORE_FAST               5 (@py_assert7)
#              72 LOAD_CONST               3 (True)
#              74 STORE_FAST               6 (@py_assert10)
#              76 LOAD_FAST                5 (@py_assert7)
#              78 LOAD_FAST                6 (@py_assert10)
#              80 IS_OP                    0
#              82 STORE_FAST               7 (@py_assert9)
#              84 LOAD_FAST                7 (@py_assert9)
#              86 POP_JUMP_IF_TRUE       233 (to 554)
#              88 LOAD_GLOBAL              5 (NULL + @pytest_ar)
#              98 LOAD_ATTR                6 (_call_reprcompare)
#             118 LOAD_CONST               4 (('is',))
#             120 LOAD_FAST                7 (@py_assert9)
#             122 BUILD_TUPLE              1
#             124 LOAD_CONST               5 (('%(py8)s\n{%(py8)s = %(py2)s\n{%(py2)s = %(py0)s._matches_bus_identifier\n}(%(py4)s, %(py6)s)\n} is %(py11)s',))
#             126 LOAD_FAST                5 (@py_assert7)
#             128 LOAD_FAST                6 (@py_assert10)
#             130 BUILD_TUPLE              2
#             132 CALL                     4
#             140 LOAD_CONST               6 ('skill')
#             142 LOAD_GLOBAL              9 (NULL + @py_builtins)
#             152 LOAD_ATTR               10 (locals)
#             172 CALL                     0
#             180 CONTAINS_OP              0
#             182 POP_JUMP_IF_TRUE        21 (to 226)
#             184 LOAD_GLOBAL              5 (NULL + @pytest_ar)
#             194 LOAD_ATTR               12 (_should_repr_global_name)
#             214 LOAD_FAST                1 (skill)
#             216 CALL                     1
#             224 POP_JUMP_IF_FALSE       21 (to 268)
#         >>  226 LOAD_GLOBAL              5 (NULL + @pytest_ar)
#             236 LOAD_ATTR               14 (_saferepr)
#             256 LOAD_FAST                1 (skill)
#             258 CALL                     1
#             266 JUMP_FORWARD             1 (to 270)
#         >>  268 LOAD_CONST               6 ('skill')
#         >>  270 LOAD_GLOBAL              5 (NULL + @pytest_ar)
#             280 LOAD_ATTR               14 (_saferepr)
#             300 LOAD_FAST                2 (@py_assert1)
#             302 CALL                     1
#             310 LOAD_GLOBAL              5 (NULL + @pytest_ar)
#             320 LOAD_ATTR               14 (_saferepr)
#             340 LOAD_FAST                3 (@py_assert3)
#             342 CALL                     1
#             350 LOAD_GLOBAL              5 (NULL + @pytest_ar)
#             360 LOAD_ATTR               14 (_saferepr)
#             380 LOAD_FAST                4 (@py_assert5)
#             382 CALL                     1
#             390 LOAD_GLOBAL              5 (NULL + @pytest_ar)
#             400 LOAD_ATTR               14 (_saferepr)
#             420 LOAD_FAST                5 (@py_assert7)
#             422 CALL                     1
#             430 LOAD_GLOBAL              5 (NULL + @pytest_ar)
#             440 LOAD_ATTR               14 (_saferepr)
#             460 LOAD_FAST                6 (@py_assert10)
#             462 CALL                     1
#             470 LOAD_CONST               7 (('py0', 'py2', 'py4', 'py6', 'py8', 'py11'))
#             472 BUILD_CONST_KEY_MAP      6
#             474 BINARY_OP                6 (%)
#             478 STORE_FAST               8 (@py_format12)
#             480 LOAD_CONST               8 ('assert %(py13)s')
#             482 LOAD_CONST               9 ('py13')
#             484 LOAD_FAST                8 (@py_format12)
#             486 BUILD_MAP                1
#             488 BINARY_OP                6 (%)
#             492 STORE_FAST               9 (@py_format14)
#             494 LOAD_GLOBAL             17 (NULL + AssertionError)
#             504 LOAD_GLOBAL              5 (NULL + @pytest_ar)
#             514 LOAD_ATTR               18 (_format_explanation)
#             534 LOAD_FAST                9 (@py_format14)
#             536 CALL                     1
#             544 CALL                     1
#             552 RAISE_VARARGS            1
#         >>  554 LOAD_CONST               0 (None)
#             556 COPY                     1
#             558 STORE_FAST               2 (@py_assert1)
#             560 COPY                     1
#             562 STORE_FAST               3 (@py_assert3)
#             564 COPY                     1
#             566 STORE_FAST               4 (@py_assert5)
#             568 COPY                     1
#             570 STORE_FAST               5 (@py_assert7)
#             572 COPY                     1
#             574 STORE_FAST               7 (@py_assert9)
#             576 STORE_FAST               6 (@py_assert10)
#             578 RETURN_CONST             0 (None)
# 
# Disassembly of <code object test_matches_bus_identifier_underscore at 0x3aee3ab0, file "/home/chenying/researches/cloudpss-toolkit/cloudpss_skills_v2/tests/test_vsi_weak_bus.py", line 47>:
#  47           0 RESUME                   0
# 
#  48           2 LOAD_GLOBAL              1 (NULL + VSIWeakBusSkill)
#              12 CALL                     0
#              20 STORE_FAST               1 (skill)
# 
#  49          22 LOAD_FAST                1 (skill)
#              24 LOAD_ATTR                2 (_matches_bus_identifier)
#              44 STORE_FAST               2 (@py_assert1)
#              46 LOAD_CONST               1 ('Bus_7')
#              48 STORE_FAST               3 (@py_assert3)
#              50 LOAD_CONST               2 ('Bus 7')
#              52 STORE_FAST               4 (@py_assert5)
#              54 PUSH_NULL
#              56 LOAD_FAST                2 (@py_assert1)
#              58 LOAD_FAST                3 (@py_assert3)
#              60 LOAD_FAST                4 (@py_assert5)
#              62 CALL                     2
#              70 STORE_FAST               5 (@py_assert7)
#              72 LOAD_CONST               3 (True)
#              74 STORE_FAST               6 (@py_assert10)
#              76 LOAD_FAST                5 (@py_assert7)
#              78 LOAD_FAST                6 (@py_assert10)
#              80 IS_OP                    0
#              82 STORE_FAST               7 (@py_assert9)
#              84 LOAD_FAST                7 (@py_assert9)
#              86 POP_JUMP_IF_TRUE       233 (to 554)
#              88 LOAD_GLOBAL              5 (NULL + @pytest_ar)
#              98 LOAD_ATTR                6 (_call_reprcompare)
#             118 LOAD_CONST               4 (('is',))
#             120 LOAD_FAST                7 (@py_assert9)
#             122 BUILD_TUPLE              1
#             124 LOAD_CONST               5 (('%(py8)s\n{%(py8)s = %(py2)s\n{%(py2)s = %(py0)s._matches_bus_identifier\n}(%(py4)s, %(py6)s)\n} is %(py11)s',))
#             126 LOAD_FAST                5 (@py_assert7)
#             128 LOAD_FAST                6 (@py_assert10)
#             130 BUILD_TUPLE              2
#             132 CALL                     4
#             140 LOAD_CONST               6 ('skill')
#             142 LOAD_GLOBAL              9 (NULL + @py_builtins)
#             152 LOAD_ATTR               10 (locals)
#             172 CALL                     0
#             180 CONTAINS_OP              0
#             182 POP_JUMP_IF_TRUE        21 (to 226)
#             184 LOAD_GLOBAL              5 (NULL + @pytest_ar)
#             194 LOAD_ATTR               12 (_should_repr_global_name)
#             214 LOAD_FAST                1 (skill)
#             216 CALL                     1
#             224 POP_JUMP_IF_FALSE       21 (to 268)
#         >>  226 LOAD_GLOBAL              5 (NULL + @pytest_ar)
#             236 LOAD_ATTR               14 (_saferepr)
#             256 LOAD_FAST                1 (skill)
#             258 CALL                     1
#             266 JUMP_FORWARD             1 (to 270)
#         >>  268 LOAD_CONST               6 ('skill')
#         >>  270 LOAD_GLOBAL              5 (NULL + @pytest_ar)
#             280 LOAD_ATTR               14 (_saferepr)
#             300 LOAD_FAST                2 (@py_assert1)
#             302 CALL                     1
#             310 LOAD_GLOBAL              5 (NULL + @pytest_ar)
#             320 LOAD_ATTR               14 (_saferepr)
#             340 LOAD_FAST                3 (@py_assert3)
#             342 CALL                     1
#             350 LOAD_GLOBAL              5 (NULL + @pytest_ar)
#             360 LOAD_ATTR               14 (_saferepr)
#             380 LOAD_FAST                4 (@py_assert5)
#             382 CALL                     1
#             390 LOAD_GLOBAL              5 (NULL + @pytest_ar)
#             400 LOAD_ATTR               14 (_saferepr)
#             420 LOAD_FAST                5 (@py_assert7)
#             422 CALL                     1
#             430 LOAD_GLOBAL              5 (NULL + @pytest_ar)
#             440 LOAD_ATTR               14 (_saferepr)
#             460 LOAD_FAST                6 (@py_assert10)
#             462 CALL                     1
#             470 LOAD_CONST               7 (('py0', 'py2', 'py4', 'py6', 'py8', 'py11'))
#             472 BUILD_CONST_KEY_MAP      6
#             474 BINARY_OP                6 (%)
#             478 STORE_FAST               8 (@py_format12)
#             480 LOAD_CONST               8 ('assert %(py13)s')
#             482 LOAD_CONST               9 ('py13')
#             484 LOAD_FAST                8 (@py_format12)
#             486 BUILD_MAP                1
#             488 BINARY_OP                6 (%)
#             492 STORE_FAST               9 (@py_format14)
#             494 LOAD_GLOBAL             17 (NULL + AssertionError)
#             504 LOAD_GLOBAL              5 (NULL + @pytest_ar)
#             514 LOAD_ATTR               18 (_format_explanation)
#             534 LOAD_FAST                9 (@py_format14)
#             536 CALL                     1
#             544 CALL                     1
#             552 RAISE_VARARGS            1
#         >>  554 LOAD_CONST               0 (None)
#             556 COPY                     1
#             558 STORE_FAST               2 (@py_assert1)
#             560 COPY                     1
#             562 STORE_FAST               3 (@py_assert3)
#             564 COPY                     1
#             566 STORE_FAST               4 (@py_assert5)
#             568 COPY                     1
#             570 STORE_FAST               5 (@py_assert7)
#             572 COPY                     1
#             574 STORE_FAST               7 (@py_assert9)
#             576 STORE_FAST               6 (@py_assert10)
#             578 RETURN_CONST             0 (None)
# 
# Disassembly of <code object TestVSIWeakBuses at 0x73cd945fea30, file "/home/chenying/researches/cloudpss-toolkit/cloudpss_skills_v2/tests/test_vsi_weak_bus.py", line 52>:
#  52           0 RESUME                   0
#               2 LOAD_NAME                0 (__name__)
#               4 STORE_NAME               1 (__module__)
#               6 LOAD_CONST               0 ('TestVSIWeakBuses')
#               8 STORE_NAME               2 (__qualname__)
# 
#  53          10 LOAD_CONST               1 (<code object test_identify_weak_buses at 0x3afa6250, file "/home/chenying/researches/cloudpss-toolkit/cloudpss_skills_v2/tests/test_vsi_weak_bus.py", line 53>)
#              12 MAKE_FUNCTION            0
#              14 STORE_NAME               3 (test_identify_weak_buses)
# 
#  67          16 LOAD_CONST               2 (<code object test_identify_weak_buses_sorted at 0x3af39de0, file "/home/chenying/researches/cloudpss-toolkit/cloudpss_skills_v2/tests/test_vsi_weak_bus.py", line 67>)
#              18 MAKE_FUNCTION            0
#              20 STORE_NAME               4 (test_identify_weak_buses_sorted)
#              22 RETURN_CONST             3 (None)
# 
# Disassembly of <code object test_identify_weak_buses at 0x3afa6250, file "/home/chenying/researches/cloudpss-toolkit/cloudpss_skills_v2/tests/test_vsi_weak_bus.py", line 53>:
#  53           0 RESUME                   0
# 
#  54           2 LOAD_GLOBAL              1 (NULL + VSIWeakBusSkill)
#              12 CALL                     0
#              20 STORE_FAST               1 (skill)
# 
#  56          22 LOAD_CONST               1 (0.005)
# 
#  57          24 LOAD_CONST               2 (0.05)
# 
#  58          26 LOAD_CONST               3 (0.02)
# 
#  59          28 LOAD_CONST               4 (0.001)
# 
#  55          30 LOAD_CONST               5 (('Bus1', 'Bus2', 'Bus3', 'Bus4'))
#              32 BUILD_CONST_KEY_MAP      4
#              34 STORE_FAST               2 (vsi_results)
# 
#  61          36 LOAD_FAST                1 (skill)
#              38 LOAD_ATTR                3 (NULL|self + _identify_weak_buses)
#              58 LOAD_FAST                2 (vsi_results)
#              60 LOAD_CONST               6 (0.01)
#              62 LOAD_CONST               7 (10)
#              64 KW_NAMES                 8 (('threshold', 'top_n'))
#              66 CALL                     3
#              74 STORE_FAST               3 (weak)
# 
#  62          76 LOAD_GLOBAL              5 (NULL + len)
#              86 LOAD_FAST                3 (weak)
#              88 CALL                     1
#              96 STORE_FAST               4 (@py_assert2)
#              98 LOAD_CONST               9 (2)
#             100 STORE_FAST               5 (@py_assert5)
#             102 LOAD_FAST                4 (@py_assert2)
#             104 LOAD_FAST                5 (@py_assert5)
#             106 COMPARE_OP              40 (==)
#             110 STORE_FAST               6 (@py_assert4)
#             112 LOAD_FAST                6 (@py_assert4)
#             114 POP_JUMP_IF_TRUE       246 (to 608)
#             116 LOAD_GLOBAL              7 (NULL + @pytest_ar)
#             126 LOAD_ATTR                8 (_call_reprcompare)
#             146 LOAD_CONST              10 (('==',))
#             148 LOAD_FAST                6 (@py_assert4)
#             150 BUILD_TUPLE              1
#             152 LOAD_CONST              11 (('%(py3)s\n{%(py3)s = %(py0)s(%(py1)s)\n} == %(py6)s',))
#             154 LOAD_FAST                4 (@py_assert2)
#             156 LOAD_FAST                5 (@py_assert5)
#             158 BUILD_TUPLE              2
#             160 CALL                     4
#             168 LOAD_CONST              12 ('len')
#             170 LOAD_GLOBAL             11 (NULL + @py_builtins)
#             180 LOAD_ATTR               12 (locals)
#             200 CALL                     0
#             208 CONTAINS_OP              0
#             210 POP_JUMP_IF_TRUE        25 (to 262)
#             212 LOAD_GLOBAL              7 (NULL + @pytest_ar)
#             222 LOAD_ATTR               14 (_should_repr_global_name)
#             242 LOAD_GLOBAL              4 (len)
#             252 CALL                     1
#             260 POP_JUMP_IF_FALSE       25 (to 312)
#         >>  262 LOAD_GLOBAL              7 (NULL + @pytest_ar)
#             272 LOAD_ATTR               16 (_saferepr)
#             292 LOAD_GLOBAL              4 (len)
#             302 CALL                     1
#             310 JUMP_FORWARD             1 (to 314)
#         >>  312 LOAD_CONST              12 ('len')
#         >>  314 LOAD_CONST              13 ('weak')
#             316 LOAD_GLOBAL             11 (NULL + @py_builtins)
#             326 LOAD_ATTR               12 (locals)
#             346 CALL                     0
#             354 CONTAINS_OP              0
#             356 POP_JUMP_IF_TRUE        21 (to 400)
#             358 LOAD_GLOBAL              7 (NULL + @pytest_ar)
#             368 LOAD_ATTR               14 (_should_repr_global_name)
#             388 LOAD_FAST                3 (weak)
#             390 CALL                     1
#             398 POP_JUMP_IF_FALSE       21 (to 442)
#         >>  400 LOAD_GLOBAL              7 (NULL + @pytest_ar)
#             410 LOAD_ATTR               16 (_saferepr)
#             430 LOAD_FAST                3 (weak)
#             432 CALL                     1
#             440 JUMP_FORWARD             1 (to 444)
#         >>  442 LOAD_CONST              13 ('weak')
#         >>  444 LOAD_GLOBAL              7 (NULL + @pytest_ar)
#             454 LOAD_ATTR               16 (_saferepr)
#             474 LOAD_FAST                4 (@py_assert2)
#             476 CALL                     1
#             484 LOAD_GLOBAL              7 (NULL + @pytest_ar)
#             494 LOAD_ATTR               16 (_saferepr)
#             514 LOAD_FAST                5 (@py_assert5)
#             516 CALL                     1
#             524 LOAD_CONST              14 (('py0', 'py1', 'py3', 'py6'))
#             526 BUILD_CONST_KEY_MAP      4
#             528 BINARY_OP                6 (%)
#             532 STORE_FAST               7 (@py_format7)
#             534 LOAD_CONST              15 ('assert %(py8)s')
#             536 LOAD_CONST              16 ('py8')
#             538 LOAD_FAST                7 (@py_format7)
#             540 BUILD_MAP                1
#             542 BINARY_OP                6 (%)
#             546 STORE_FAST               8 (@py_format9)
#             548 LOAD_GLOBAL             19 (NULL + AssertionError)
#             558 LOAD_GLOBAL              7 (NULL + @pytest_ar)
#             568 LOAD_ATTR               20 (_format_explanation)
#             588 LOAD_FAST                8 (@py_format9)
#             590 CALL                     1
#             598 CALL                     1
#             606 RAISE_VARARGS            1
#         >>  608 LOAD_CONST               0 (None)
#             610 COPY                     1
#             612 STORE_FAST               4 (@py_assert2)
#             614 COPY                     1
#             616 STORE_FAST               6 (@py_assert4)
#             618 STORE_FAST               5 (@py_assert5)
# 
#  63         620 LOAD_FAST                3 (weak)
#             622 GET_ITER
#             624 LOAD_FAST_AND_CLEAR      9 (w)
#             626 SWAP                     2
#             628 BUILD_LIST               0
#             630 SWAP                     2
#         >>  632 FOR_ITER                 7 (to 650)
#             636 STORE_FAST               9 (w)
#             638 LOAD_FAST                9 (w)
#             640 LOAD_CONST              17 ('label')
#             642 BINARY_SUBSCR
#             646 LIST_APPEND              2
#             648 JUMP_BACKWARD            9 (to 632)
#         >>  650 END_FOR
#             652 STORE_FAST              10 (weak_labels)
#             654 STORE_FAST               9 (w)
# 
#  64         656 LOAD_CONST              18 ('Bus2')
#             658 STORE_FAST              11 (@py_assert0)
#             660 LOAD_FAST               11 (@py_assert0)
#             662 LOAD_FAST               10 (weak_labels)
#             664 CONTAINS_OP              0
#             666 STORE_FAST               4 (@py_assert2)
#             668 LOAD_FAST                4 (@py_assert2)
#             670 POP_JUMP_IF_TRUE       153 (to 978)
#             672 LOAD_GLOBAL              7 (NULL + @pytest_ar)
#             682 LOAD_ATTR                8 (_call_reprcompare)
#             702 LOAD_CONST              19 (('in',))
#             704 LOAD_FAST                4 (@py_assert2)
#             706 BUILD_TUPLE              1
#             708 LOAD_CONST              20 (('%(py1)s in %(py3)s',))
#             710 LOAD_FAST               11 (@py_assert0)
#             712 LOAD_FAST               10 (weak_labels)
#             714 BUILD_TUPLE              2
#             716 CALL                     4
#             724 LOAD_GLOBAL              7 (NULL + @pytest_ar)
#             734 LOAD_ATTR               16 (_saferepr)
#             754 LOAD_FAST               11 (@py_assert0)
#             756 CALL                     1
#             764 LOAD_CONST              21 ('weak_labels')
#             766 LOAD_GLOBAL             11 (NULL + @py_builtins)
#             776 LOAD_ATTR               12 (locals)
#             796 CALL                     0
#             804 CONTAINS_OP              0
#             806 POP_JUMP_IF_TRUE        21 (to 850)
#             808 LOAD_GLOBAL              7 (NULL + @pytest_ar)
#             818 LOAD_ATTR               14 (_should_repr_global_name)
#             838 LOAD_FAST               10 (weak_labels)
#             840 CALL                     1
#             848 POP_JUMP_IF_FALSE       21 (to 892)
#         >>  850 LOAD_GLOBAL              7 (NULL + @pytest_ar)
#             860 LOAD_ATTR               16 (_saferepr)
#             880 LOAD_FAST               10 (weak_labels)
#             882 CALL                     1
#             890 JUMP_FORWARD             1 (to 894)
#         >>  892 LOAD_CONST              21 ('weak_labels')
#         >>  894 LOAD_CONST              22 (('py1', 'py3'))
#             896 BUILD_CONST_KEY_MAP      2
#             898 BINARY_OP                6 (%)
#             902 STORE_FAST              12 (@py_format4)
#             904 LOAD_CONST              23 ('assert %(py5)s')
#             906 LOAD_CONST              24 ('py5')
#             908 LOAD_FAST               12 (@py_format4)
#             910 BUILD_MAP                1
#             912 BINARY_OP                6 (%)
#             916 STORE_FAST              13 (@py_format6)
#             918 LOAD_GLOBAL             19 (NULL + AssertionError)
#             928 LOAD_GLOBAL              7 (NULL + @pytest_ar)
#             938 LOAD_ATTR               20 (_format_explanation)
#             958 LOAD_FAST               13 (@py_format6)
#             960 CALL                     1
#             968 CALL                     1
#             976 RAISE_VARARGS            1
#         >>  978 LOAD_CONST               0 (None)
#             980 COPY                     1
#             982 STORE_FAST              11 (@py_assert0)
#             984 STORE_FAST               4 (@py_assert2)
# 
#  65         986 LOAD_CONST              25 ('Bus3')
#             988 STORE_FAST              11 (@py_assert0)
#             990 LOAD_FAST               11 (@py_assert0)
#             992 LOAD_FAST               10 (weak_labels)
#             994 CONTAINS_OP              0
#             996 STORE_FAST               4 (@py_assert2)
#             998 LOAD_FAST                4 (@py_assert2)
#            1000 POP_JUMP_IF_TRUE       153 (to 1308)
#            1002 LOAD_GLOBAL              7 (NULL + @pytest_ar)
#            1012 LOAD_ATTR                8 (_call_reprcompare)
#            1032 LOAD_CONST              19 (('in',))
#            1034 LOAD_FAST                4 (@py_assert2)
#            1036 BUILD_TUPLE              1
#            1038 LOAD_CONST              20 (('%(py1)s in %(py3)s',))
#            1040 LOAD_FAST               11 (@py_assert0)
#            1042 LOAD_FAST               10 (weak_labels)
#            1044 BUILD_TUPLE              2
#            1046 CALL                     4
#            1054 LOAD_GLOBAL              7 (NULL + @pytest_ar)
#            1064 LOAD_ATTR               16 (_saferepr)
#            1084 LOAD_FAST               11 (@py_assert0)
#            1086 CALL                     1
#            1094 LOAD_CONST              21 ('weak_labels')
#            1096 LOAD_GLOBAL             11 (NULL + @py_builtins)
#            1106 LOAD_ATTR               12 (locals)
#            1126 CALL                     0
#            1134 CONTAINS_OP              0
#            1136 POP_JUMP_IF_TRUE        21 (to 1180)
#            1138 LOAD_GLOBAL              7 (NULL + @pytest_ar)
#            1148 LOAD_ATTR               14 (_should_repr_global_name)
#            1168 LOAD_FAST               10 (weak_labels)
#            1170 CALL                     1
#            1178 POP_JUMP_IF_FALSE       21 (to 1222)
#         >> 1180 LOAD_GLOBAL              7 (NULL + @pytest_ar)
#            1190 LOAD_ATTR               16 (_saferepr)
#            1210 LOAD_FAST               10 (weak_labels)
#            1212 CALL                     1
#            1220 JUMP_FORWARD             1 (to 1224)
#         >> 1222 LOAD_CONST              21 ('weak_labels')
#         >> 1224 LOAD_CONST              22 (('py1', 'py3'))
#            1226 BUILD_CONST_KEY_MAP      2
#            1228 BINARY_OP                6 (%)
#            1232 STORE_FAST              12 (@py_format4)
#            1234 LOAD_CONST              23 ('assert %(py5)s')
#            1236 LOAD_CONST              24 ('py5')
#            1238 LOAD_FAST               12 (@py_format4)
#            1240 BUILD_MAP                1
#            1242 BINARY_OP                6 (%)
#            1246 STORE_FAST              13 (@py_format6)
#            1248 LOAD_GLOBAL             19 (NULL + AssertionError)
#            1258 LOAD_GLOBAL              7 (NULL + @pytest_ar)
#            1268 LOAD_ATTR               20 (_format_explanation)
#            1288 LOAD_FAST               13 (@py_format6)
#            1290 CALL                     1
#            1298 CALL                     1
#            1306 RAISE_VARARGS            1
#         >> 1308 LOAD_CONST               0 (None)
#            1310 COPY                     1
#            1312 STORE_FAST              11 (@py_assert0)
#            1314 STORE_FAST               4 (@py_assert2)
#            1316 RETURN_CONST             0 (None)
#         >> 1318 SWAP                     2
#            1320 POP_TOP
# 
#  63        1322 SWAP                     2
#            1324 STORE_FAST               9 (w)
#            1326 RERAISE                  0
# ExceptionTable:
#   628 to 650 -> 1318 [2]
# 
# Disassembly of <code object test_identify_weak_buses_sorted at 0x3af39de0, file "/home/chenying/researches/cloudpss-toolkit/cloudpss_skills_v2/tests/test_vsi_weak_bus.py", line 67>:
#  67           0 RESUME                   0
# 
#  68           2 LOAD_GLOBAL              1 (NULL + VSIWeakBusSkill)
#              12 CALL                     0
#              20 STORE_FAST               1 (skill)
# 
#  69          22 LOAD_CONST               1 (0.02)
#              24 LOAD_CONST               2 (0.05)
#              26 LOAD_CONST               3 (('Bus1', 'Bus2'))
#              28 BUILD_CONST_KEY_MAP      2
#              30 STORE_FAST               2 (vsi_results)
# 
#  70          32 LOAD_FAST                1 (skill)
#              34 LOAD_ATTR                3 (NULL|self + _identify_weak_buses)
#              54 LOAD_FAST                2 (vsi_results)
#              56 LOAD_CONST               4 (0.01)
#              58 LOAD_CONST               5 (10)
#              60 KW_NAMES                 6 (('threshold', 'top_n'))
#              62 CALL                     3
#              70 STORE_FAST               3 (weak)
# 
#  71          72 LOAD_FAST                3 (weak)
#              74 LOAD_CONST               7 (0)
#              76 BINARY_SUBSCR
#              80 LOAD_CONST               8 ('vsi')
#              82 BINARY_SUBSCR
#              86 STORE_FAST               4 (@py_assert0)
#              88 LOAD_FAST                3 (weak)
#              90 LOAD_CONST               9 (1)
#              92 BINARY_SUBSCR
#              96 LOAD_CONST               8 ('vsi')
#              98 BINARY_SUBSCR
#             102 STORE_FAST               5 (@py_assert3)
#             104 LOAD_FAST                4 (@py_assert0)
#             106 LOAD_FAST                5 (@py_assert3)
#             108 COMPARE_OP              92 (>=)
#             112 STORE_FAST               6 (@py_assert2)
#             114 LOAD_FAST                6 (@py_assert2)
#             116 POP_JUMP_IF_TRUE       108 (to 334)
#             118 LOAD_GLOBAL              5 (NULL + @pytest_ar)
#             128 LOAD_ATTR                6 (_call_reprcompare)
#             148 LOAD_CONST              10 (('>=',))
#             150 LOAD_FAST                6 (@py_assert2)
#             152 BUILD_TUPLE              1
#             154 LOAD_CONST              11 (('%(py1)s >= %(py4)s',))
#             156 LOAD_FAST                4 (@py_assert0)
#             158 LOAD_FAST                5 (@py_assert3)
#             160 BUILD_TUPLE              2
#             162 CALL                     4
#             170 LOAD_GLOBAL              5 (NULL + @pytest_ar)
#             180 LOAD_ATTR                8 (_saferepr)
#             200 LOAD_FAST                4 (@py_assert0)
#             202 CALL                     1
#             210 LOAD_GLOBAL              5 (NULL + @pytest_ar)
#             220 LOAD_ATTR                8 (_saferepr)
#             240 LOAD_FAST                5 (@py_assert3)
#             242 CALL                     1
#             250 LOAD_CONST              12 (('py1', 'py4'))
#             252 BUILD_CONST_KEY_MAP      2
#             254 BINARY_OP                6 (%)
#             258 STORE_FAST               7 (@py_format5)
#             260 LOAD_CONST              13 ('assert %(py6)s')
#             262 LOAD_CONST              14 ('py6')
#             264 LOAD_FAST                7 (@py_format5)
#             266 BUILD_MAP                1
#             268 BINARY_OP                6 (%)
#             272 STORE_FAST               8 (@py_format7)
#             274 LOAD_GLOBAL             11 (NULL + AssertionError)
#             284 LOAD_GLOBAL              5 (NULL + @pytest_ar)
#             294 LOAD_ATTR               12 (_format_explanation)
#             314 LOAD_FAST                8 (@py_format7)
#             316 CALL                     1
#             324 CALL                     1
#             332 RAISE_VARARGS            1
#         >>  334 LOAD_CONST               0 (None)
#             336 COPY                     1
#             338 STORE_FAST               4 (@py_assert0)
#             340 COPY                     1
#             342 STORE_FAST               6 (@py_assert2)
#             344 STORE_FAST               5 (@py_assert3)
#             346 RETURN_CONST             0 (None)
# 
# Disassembly of <code object TestVSIStatistics at 0x73cd945fecd0, file "/home/chenying/researches/cloudpss-toolkit/cloudpss_skills_v2/tests/test_vsi_weak_bus.py", line 74>:
#  74           0 RESUME                   0
#               2 LOAD_NAME                0 (__name__)
#               4 STORE_NAME               1 (__module__)
#               6 LOAD_CONST               0 ('TestVSIStatistics')
#               8 STORE_NAME               2 (__qualname__)
# 
#  75          10 LOAD_CONST               1 (<code object test_compute_vsi_statistics at 0x3aeca6c0, file "/home/chenying/researches/cloudpss-toolkit/cloudpss_skills_v2/tests/test_vsi_weak_bus.py", line 75>)
#              12 MAKE_FUNCTION            0
#              14 STORE_NAME               3 (test_compute_vsi_statistics)
# 
#  84          16 LOAD_CONST               2 (<code object test_compute_vsi_statistics_empty at 0x3af909c0, file "/home/chenying/researches/cloudpss-toolkit/cloudpss_skills_v2/tests/test_vsi_weak_bus.py", line 84>)
#              18 MAKE_FUNCTION            0
#              20 STORE_NAME               4 (test_compute_vsi_statistics_empty)
#              22 RETURN_CONST             3 (None)
# 
# Disassembly of <code object test_compute_vsi_statistics at 0x3aeca6c0, file "/home/chenying/researches/cloudpss-toolkit/cloudpss_skills_v2/tests/test_vsi_weak_bus.py", line 75>:
#  75           0 RESUME                   0
# 
#  76           2 LOAD_GLOBAL              1 (NULL + VSIWeakBusSkill)
#              12 CALL                     0
#              20 STORE_FAST               1 (skill)
# 
#  77          22 LOAD_CONST               1 (0.01)
#              24 LOAD_CONST               2 (0.05)
#              26 LOAD_CONST               3 (0.03)
#              28 LOAD_CONST               4 (('Bus1', 'Bus2', 'Bus3'))
#              30 BUILD_CONST_KEY_MAP      3
#              32 STORE_FAST               2 (vsi_values)
# 
#  78          34 LOAD_FAST                1 (skill)
#              36 LOAD_ATTR                3 (NULL|self + _compute_vsi_statistics)
#              56 LOAD_FAST                2 (vsi_values)
#              58 LOAD_CONST               1 (0.01)
#              60 KW_NAMES                 5 (('threshold',))
#              62 CALL                     2
#              70 STORE_FAST               3 (stats)
# 
#  79          72 LOAD_FAST                3 (stats)
#              74 LOAD_CONST               6 ('max')
#              76 BINARY_SUBSCR
#              80 STORE_FAST               4 (@py_assert0)
#              82 LOAD_CONST               2 (0.05)
#              84 STORE_FAST               5 (@py_assert3)
#              86 LOAD_FAST                4 (@py_assert0)
#              88 LOAD_FAST                5 (@py_assert3)
#              90 COMPARE_OP              40 (==)
#              94 STORE_FAST               6 (@py_assert2)
#              96 LOAD_FAST                6 (@py_assert2)
#              98 POP_JUMP_IF_TRUE       108 (to 316)
#             100 LOAD_GLOBAL              5 (NULL + @pytest_ar)
#             110 LOAD_ATTR                6 (_call_reprcompare)
#             130 LOAD_CONST               7 (('==',))
#             132 LOAD_FAST                6 (@py_assert2)
#             134 BUILD_TUPLE              1
#             136 LOAD_CONST               8 (('%(py1)s == %(py4)s',))
#             138 LOAD_FAST                4 (@py_assert0)
#             140 LOAD_FAST                5 (@py_assert3)
#             142 BUILD_TUPLE              2
#             144 CALL                     4
#             152 LOAD_GLOBAL              5 (NULL + @pytest_ar)
#             162 LOAD_ATTR                8 (_saferepr)
#             182 LOAD_FAST                4 (@py_assert0)
#             184 CALL                     1
#             192 LOAD_GLOBAL              5 (NULL + @pytest_ar)
#             202 LOAD_ATTR                8 (_saferepr)
#             222 LOAD_FAST                5 (@py_assert3)
#             224 CALL                     1
#             232 LOAD_CONST               9 (('py1', 'py4'))
#             234 BUILD_CONST_KEY_MAP      2
#             236 BINARY_OP                6 (%)
#             240 STORE_FAST               7 (@py_format5)
#             242 LOAD_CONST              10 ('assert %(py6)s')
#             244 LOAD_CONST              11 ('py6')
#             246 LOAD_FAST                7 (@py_format5)
#             248 BUILD_MAP                1
#             250 BINARY_OP                6 (%)
#             254 STORE_FAST               8 (@py_format7)
#             256 LOAD_GLOBAL             11 (NULL + AssertionError)
#             266 LOAD_GLOBAL              5 (NULL + @pytest_ar)
#             276 LOAD_ATTR               12 (_format_explanation)
#             296 LOAD_FAST                8 (@py_format7)
#             298 CALL                     1
#             306 CALL                     1
#             314 RAISE_VARARGS            1
#         >>  316 LOAD_CONST               0 (None)
#             318 COPY                     1
#             320 STORE_FAST               4 (@py_assert0)
#             322 COPY                     1
#             324 STORE_FAST               6 (@py_assert2)
#             326 STORE_FAST               5 (@py_assert3)
# 
#  80         328 LOAD_FAST                3 (stats)
#             330 LOAD_CONST              12 ('min')
#             332 BINARY_SUBSCR
#             336 STORE_FAST               4 (@py_assert0)
#             338 LOAD_CONST               1 (0.01)
#             340 STORE_FAST               5 (@py_assert3)
#             342 LOAD_FAST                4 (@py_assert0)
#             344 LOAD_FAST                5 (@py_assert3)
#             346 COMPARE_OP              40 (==)
#             350 STORE_FAST               6 (@py_assert2)
#             352 LOAD_FAST                6 (@py_assert2)
#             354 POP_JUMP_IF_TRUE       108 (to 572)
#             356 LOAD_GLOBAL              5 (NULL + @pytest_ar)
#             366 LOAD_ATTR                6 (_call_reprcompare)
#             386 LOAD_CONST               7 (('==',))
#             388 LOAD_FAST                6 (@py_assert2)
#             390 BUILD_TUPLE              1
#             392 LOAD_CONST               8 (('%(py1)s == %(py4)s',))
#             394 LOAD_FAST                4 (@py_assert0)
#             396 LOAD_FAST                5 (@py_assert3)
#             398 BUILD_TUPLE              2
#             400 CALL                     4
#             408 LOAD_GLOBAL              5 (NULL + @pytest_ar)
#             418 LOAD_ATTR                8 (_saferepr)
#             438 LOAD_FAST                4 (@py_assert0)
#             440 CALL                     1
#             448 LOAD_GLOBAL              5 (NULL + @pytest_ar)
#             458 LOAD_ATTR                8 (_saferepr)
#             478 LOAD_FAST                5 (@py_assert3)
#             480 CALL                     1
#             488 LOAD_CONST               9 (('py1', 'py4'))
#             490 BUILD_CONST_KEY_MAP      2
#             492 BINARY_OP                6 (%)
#             496 STORE_FAST               7 (@py_format5)
#             498 LOAD_CONST              10 ('assert %(py6)s')
#             500 LOAD_CONST              11 ('py6')
#             502 LOAD_FAST                7 (@py_format5)
#             504 BUILD_MAP                1
#             506 BINARY_OP                6 (%)
#             510 STORE_FAST               8 (@py_format7)
#             512 LOAD_GLOBAL             11 (NULL + AssertionError)
#             522 LOAD_GLOBAL              5 (NULL + @pytest_ar)
#             532 LOAD_ATTR               12 (_format_explanation)
#             552 LOAD_FAST                8 (@py_format7)
#             554 CALL                     1
#             562 CALL                     1
#             570 RAISE_VARARGS            1
#         >>  572 LOAD_CONST               0 (None)
#             574 COPY                     1
#             576 STORE_FAST               4 (@py_assert0)
#             578 COPY                     1
#             580 STORE_FAST               6 (@py_assert2)
#             582 STORE_FAST               5 (@py_assert3)
# 
#  81         584 LOAD_FAST                3 (stats)
#             586 LOAD_CONST              13 ('mean')
#             588 BINARY_SUBSCR
#             592 STORE_FAST               9 (@py_assert1)
#             594 LOAD_CONST               3 (0.03)
#             596 STORE_FAST               5 (@py_assert3)
#             598 LOAD_FAST                9 (@py_assert1)
#             600 LOAD_FAST                5 (@py_assert3)
#             602 BINARY_OP               10 (-)
#             606 STORE_FAST              10 (@py_assert5)
#             608 LOAD_GLOBAL             15 (NULL + abs)
#             618 LOAD_FAST               10 (@py_assert5)
#             620 CALL                     1
#             628 STORE_FAST              11 (@py_assert6)
#             630 LOAD_CONST              14 (1e-10)
#             632 STORE_FAST              12 (@py_assert9)
#             634 LOAD_FAST               11 (@py_assert6)
#             636 LOAD_FAST               12 (@py_assert9)
#             638 COMPARE_OP               2 (<)
#             642 STORE_FAST              13 (@py_assert8)
#             644 LOAD_FAST               13 (@py_assert8)
#             646 POP_JUMP_IF_TRUE       221 (to 1090)
#             648 LOAD_GLOBAL              5 (NULL + @pytest_ar)
#             658 LOAD_ATTR                6 (_call_reprcompare)
#             678 LOAD_CONST              15 (('<',))
#             680 LOAD_FAST               13 (@py_assert8)
#             682 BUILD_TUPLE              1
#             684 LOAD_CONST              16 (('%(py7)s\n{%(py7)s = %(py0)s((%(py2)s - %(py4)s))\n} < %(py10)s',))
#             686 LOAD_FAST               11 (@py_assert6)
#             688 LOAD_FAST               12 (@py_assert9)
#             690 BUILD_TUPLE              2
#             692 CALL                     4
#             700 LOAD_CONST              17 ('abs')
#             702 LOAD_GLOBAL             17 (NULL + @py_builtins)
#             712 LOAD_ATTR               18 (locals)
#             732 CALL                     0
#             740 CONTAINS_OP              0
#             742 POP_JUMP_IF_TRUE        25 (to 794)
#             744 LOAD_GLOBAL              5 (NULL + @pytest_ar)
#             754 LOAD_ATTR               20 (_should_repr_global_name)
#             774 LOAD_GLOBAL             14 (abs)
#             784 CALL                     1
#             792 POP_JUMP_IF_FALSE       25 (to 844)
#         >>  794 LOAD_GLOBAL              5 (NULL + @pytest_ar)
#             804 LOAD_ATTR                8 (_saferepr)
#             824 LOAD_GLOBAL             14 (abs)
#             834 CALL                     1
#             842 JUMP_FORWARD             1 (to 846)
#         >>  844 LOAD_CONST              17 ('abs')
#         >>  846 LOAD_GLOBAL              5 (NULL + @pytest_ar)
#             856 LOAD_ATTR                8 (_saferepr)
#             876 LOAD_FAST                9 (@py_assert1)
#             878 CALL                     1
#             886 LOAD_GLOBAL              5 (NULL + @pytest_ar)
#             896 LOAD_ATTR                8 (_saferepr)
#             916 LOAD_FAST                5 (@py_assert3)
#             918 CALL                     1
#             926 LOAD_GLOBAL              5 (NULL + @pytest_ar)
#             936 LOAD_ATTR                8 (_saferepr)
#             956 LOAD_FAST               11 (@py_assert6)
#             958 CALL                     1
#             966 LOAD_GLOBAL              5 (NULL + @pytest_ar)
#             976 LOAD_ATTR                8 (_saferepr)
#             996 LOAD_FAST               12 (@py_assert9)
#             998 CALL                     1
#            1006 LOAD_CONST              18 (('py0', 'py2', 'py4', 'py7', 'py10'))
#            1008 BUILD_CONST_KEY_MAP      5
#            1010 BINARY_OP                6 (%)
#            1014 STORE_FAST              14 (@py_format11)
#            1016 LOAD_CONST              19 ('assert %(py12)s')
#            1018 LOAD_CONST              20 ('py12')
#            1020 LOAD_FAST               14 (@py_format11)
#            1022 BUILD_MAP                1
#            1024 BINARY_OP                6 (%)
#            1028 STORE_FAST              15 (@py_format13)
#            1030 LOAD_GLOBAL             11 (NULL + AssertionError)
#            1040 LOAD_GLOBAL              5 (NULL + @pytest_ar)
#            1050 LOAD_ATTR               12 (_format_explanation)
#            1070 LOAD_FAST               15 (@py_format13)
#            1072 CALL                     1
#            1080 CALL                     1
#            1088 RAISE_VARARGS            1
#         >> 1090 LOAD_CONST               0 (None)
#            1092 COPY                     1
#            1094 STORE_FAST               9 (@py_assert1)
#            1096 COPY                     1
#            1098 STORE_FAST               5 (@py_assert3)
#            1100 COPY                     1
#            1102 STORE_FAST              10 (@py_assert5)
#            1104 COPY                     1
#            1106 STORE_FAST              11 (@py_assert6)
#            1108 COPY                     1
#            1110 STORE_FAST              13 (@py_assert8)
#            1112 STORE_FAST              12 (@py_assert9)
# 
#  82        1114 LOAD_FAST                3 (stats)
#            1116 LOAD_CONST              21 ('weak_count')
#            1118 BINARY_SUBSCR
#            1122 STORE_FAST               4 (@py_assert0)
#            1124 LOAD_CONST              22 (3)
#            1126 STORE_FAST               5 (@py_assert3)
#            1128 LOAD_FAST                4 (@py_assert0)
#            1130 LOAD_FAST                5 (@py_assert3)
#            1132 COMPARE_OP              40 (==)
#            1136 STORE_FAST               6 (@py_assert2)
#            1138 LOAD_FAST                6 (@py_assert2)
#            1140 POP_JUMP_IF_TRUE       108 (to 1358)
#            1142 LOAD_GLOBAL              5 (NULL + @pytest_ar)
#            1152 LOAD_ATTR                6 (_call_reprcompare)
#            1172 LOAD_CONST               7 (('==',))
#            1174 LOAD_FAST                6 (@py_assert2)
#            1176 BUILD_TUPLE              1
#            1178 LOAD_CONST               8 (('%(py1)s == %(py4)s',))
#            1180 LOAD_FAST                4 (@py_assert0)
#            1182 LOAD_FAST                5 (@py_assert3)
#            1184 BUILD_TUPLE              2
#            1186 CALL                     4
#            1194 LOAD_GLOBAL              5 (NULL + @pytest_ar)
#            1204 LOAD_ATTR                8 (_saferepr)
#            1224 LOAD_FAST                4 (@py_assert0)
#            1226 CALL                     1
#            1234 LOAD_GLOBAL              5 (NULL + @pytest_ar)
#            1244 LOAD_ATTR                8 (_saferepr)
#            1264 LOAD_FAST                5 (@py_assert3)
#            1266 CALL                     1
#            1274 LOAD_CONST               9 (('py1', 'py4'))
#            1276 BUILD_CONST_KEY_MAP      2
#            1278 BINARY_OP                6 (%)
#            1282 STORE_FAST               7 (@py_format5)
#            1284 LOAD_CONST              10 ('assert %(py6)s')
#            1286 LOAD_CONST              11 ('py6')
#            1288 LOAD_FAST                7 (@py_format5)
#            1290 BUILD_MAP                1
#            1292 BINARY_OP                6 (%)
#            1296 STORE_FAST               8 (@py_format7)
#            1298 LOAD_GLOBAL             11 (NULL + AssertionError)
#            1308 LOAD_GLOBAL              5 (NULL + @pytest_ar)
#            1318 LOAD_ATTR               12 (_format_explanation)
#            1338 LOAD_FAST                8 (@py_format7)
#            1340 CALL                     1
#            1348 CALL                     1
#            1356 RAISE_VARARGS            1
#         >> 1358 LOAD_CONST               0 (None)
#            1360 COPY                     1
#            1362 STORE_FAST               4 (@py_assert0)
#            1364 COPY                     1
#            1366 STORE_FAST               6 (@py_assert2)
#            1368 STORE_FAST               5 (@py_assert3)
#            1370 RETURN_CONST             0 (None)
# 
# Disassembly of <code object test_compute_vsi_statistics_empty at 0x3af909c0, file "/home/chenying/researches/cloudpss-toolkit/cloudpss_skills_v2/tests/test_vsi_weak_bus.py", line 84>:
#  84           0 RESUME                   0
# 
#  85           2 LOAD_GLOBAL              1 (NULL + VSIWeakBusSkill)
#              12 CALL                     0
#              20 STORE_FAST               1 (skill)
# 
#  86          22 LOAD_FAST                1 (skill)
#              24 LOAD_ATTR                3 (NULL|self + _compute_vsi_statistics)
#              44 BUILD_MAP                0
#              46 LOAD_CONST               1 (0.01)
#              48 KW_NAMES                 2 (('threshold',))
#              50 CALL                     2
#              58 STORE_FAST               2 (stats)
# 
#  87          60 LOAD_FAST                2 (stats)
#              62 LOAD_CONST               3 ('max')
#              64 BINARY_SUBSCR
#              68 STORE_FAST               3 (@py_assert0)
#              70 LOAD_CONST               4 (0)
#              72 STORE_FAST               4 (@py_assert3)
#              74 LOAD_FAST                3 (@py_assert0)
#              76 LOAD_FAST                4 (@py_assert3)
#              78 COMPARE_OP              40 (==)
#              82 STORE_FAST               5 (@py_assert2)
#              84 LOAD_FAST                5 (@py_assert2)
#              86 POP_JUMP_IF_TRUE       108 (to 304)
#              88 LOAD_GLOBAL              5 (NULL + @pytest_ar)
#              98 LOAD_ATTR                6 (_call_reprcompare)
#             118 LOAD_CONST               5 (('==',))
#             120 LOAD_FAST                5 (@py_assert2)
#             122 BUILD_TUPLE              1
#             124 LOAD_CONST               6 (('%(py1)s == %(py4)s',))
#             126 LOAD_FAST                3 (@py_assert0)
#             128 LOAD_FAST                4 (@py_assert3)
#             130 BUILD_TUPLE              2
#             132 CALL                     4
#             140 LOAD_GLOBAL              5 (NULL + @pytest_ar)
#             150 LOAD_ATTR                8 (_saferepr)
#             170 LOAD_FAST                3 (@py_assert0)
#             172 CALL                     1
#             180 LOAD_GLOBAL              5 (NULL + @pytest_ar)
#             190 LOAD_ATTR                8 (_saferepr)
#             210 LOAD_FAST                4 (@py_assert3)
#             212 CALL                     1
#             220 LOAD_CONST               7 (('py1', 'py4'))
#             222 BUILD_CONST_KEY_MAP      2
#             224 BINARY_OP                6 (%)
#             228 STORE_FAST               6 (@py_format5)
#             230 LOAD_CONST               8 ('assert %(py6)s')
#             232 LOAD_CONST               9 ('py6')
#             234 LOAD_FAST                6 (@py_format5)
#             236 BUILD_MAP                1
#             238 BINARY_OP                6 (%)
#             242 STORE_FAST               7 (@py_format7)
#             244 LOAD_GLOBAL             11 (NULL + AssertionError)
#             254 LOAD_GLOBAL              5 (NULL + @pytest_ar)
#             264 LOAD_ATTR               12 (_format_explanation)
#             284 LOAD_FAST                7 (@py_format7)
#             286 CALL                     1
#             294 CALL                     1
#             302 RAISE_VARARGS            1
#         >>  304 LOAD_CONST               0 (None)
#             306 COPY                     1
#             308 STORE_FAST               3 (@py_assert0)
#             310 COPY                     1
#             312 STORE_FAST               5 (@py_assert2)
#             314 STORE_FAST               4 (@py_assert3)
# 
#  88         316 LOAD_FAST                2 (stats)
#             318 LOAD_CONST              10 ('weak_count')
#             320 BINARY_SUBSCR
#             324 STORE_FAST               3 (@py_assert0)
#             326 LOAD_CONST               4 (0)
#             328 STORE_FAST               4 (@py_assert3)
#             330 LOAD_FAST                3 (@py_assert0)
#             332 LOAD_FAST                4 (@py_assert3)
#             334 COMPARE_OP              40 (==)
#             338 STORE_FAST               5 (@py_assert2)
#             340 LOAD_FAST                5 (@py_assert2)
#             342 POP_JUMP_IF_TRUE       108 (to 560)
#             344 LOAD_GLOBAL              5 (NULL + @pytest_ar)
#             354 LOAD_ATTR                6 (_call_reprcompare)
#             374 LOAD_CONST               5 (('==',))
#             376 LOAD_FAST                5 (@py_assert2)
#             378 BUILD_TUPLE              1
#             380 LOAD_CONST               6 (('%(py1)s == %(py4)s',))
#             382 LOAD_FAST                3 (@py_assert0)
#             384 LOAD_FAST                4 (@py_assert3)
#             386 BUILD_TUPLE              2
#             388 CALL                     4
#             396 LOAD_GLOBAL              5 (NULL + @pytest_ar)
#             406 LOAD_ATTR                8 (_saferepr)
#             426 LOAD_FAST                3 (@py_assert0)
#             428 CALL                     1
#             436 LOAD_GLOBAL              5 (NULL + @pytest_ar)
#             446 LOAD_ATTR                8 (_saferepr)
#             466 LOAD_FAST                4 (@py_assert3)
#             468 CALL                     1
#             476 LOAD_CONST               7 (('py1', 'py4'))
#             478 BUILD_CONST_KEY_MAP      2
#             480 BINARY_OP                6 (%)
#             484 STORE_FAST               6 (@py_format5)
#             486 LOAD_CONST               8 ('assert %(py6)s')
#             488 LOAD_CONST               9 ('py6')
#             490 LOAD_FAST                6 (@py_format5)
#             492 BUILD_MAP                1
#             494 BINARY_OP                6 (%)
#             498 STORE_FAST               7 (@py_format7)
#             500 LOAD_GLOBAL             11 (NULL + AssertionError)
#             510 LOAD_GLOBAL              5 (NULL + @pytest_ar)
#             520 LOAD_ATTR               12 (_format_explanation)
#             540 LOAD_FAST                7 (@py_format7)
#             542 CALL                     1
#             550 CALL                     1
#             558 RAISE_VARARGS            1
#         >>  560 LOAD_CONST               0 (None)
#             562 COPY                     1
#             564 STORE_FAST               3 (@py_assert0)
#             566 COPY                     1
#             568 STORE_FAST               5 (@py_assert2)
#             570 STORE_FAST               4 (@py_assert3)
#             572 RETURN_CONST             0 (None)
# 
# Disassembly of <code object TestVSIRun at 0x73cd945fe250, file "/home/chenying/researches/cloudpss-toolkit/cloudpss_skills_v2/tests/test_vsi_weak_bus.py", line 91>:
#  91           0 RESUME                   0
#               2 LOAD_NAME                0 (__name__)
#               4 STORE_NAME               1 (__module__)
#               6 LOAD_CONST               0 ('TestVSIRun')
#               8 STORE_NAME               2 (__qualname__)
# 
#  92          10 LOAD_CONST               1 (<code object test_run_invalid_config_returns_failure at 0x3af9ee00, file "/home/chenying/researches/cloudpss-toolkit/cloudpss_skills_v2/tests/test_vsi_weak_bus.py", line 92>)
#              12 MAKE_FUNCTION            0
#              14 STORE_NAME               3 (test_run_invalid_config_returns_failure)
#              16 RETURN_CONST             2 (None)
# 
# Disassembly of <code object test_run_invalid_config_returns_failure at 0x3af9ee00, file "/home/chenying/researches/cloudpss-toolkit/cloudpss_skills_v2/tests/test_vsi_weak_bus.py", line 92>:
#  92           0 RESUME                   0
# 
#  93           2 LOAD_GLOBAL              1 (NULL + VSIWeakBusSkill)
#              12 CALL                     0
#              20 STORE_FAST               1 (skill)
# 
#  94          22 LOAD_FAST                1 (skill)
#              24 LOAD_ATTR                3 (NULL|self + run)
#              44 BUILD_MAP                0
#              46 CALL                     1
#              54 STORE_FAST               2 (result)
# 
#  95          56 LOAD_FAST                2 (result)
#              58 LOAD_ATTR                4 (status)
#              78 STORE_FAST               3 (@py_assert1)
#              80 LOAD_FAST                3 (@py_assert1)
#              82 LOAD_ATTR                6 (value)
#             102 STORE_FAST               4 (@py_assert3)
#             104 LOAD_CONST               1 ('FAILED')
#             106 LOAD_CONST               2 ('failed')
#             108 BUILD_LIST               2
#             110 STORE_FAST               5 (@py_assert6)
#             112 LOAD_FAST                4 (@py_assert3)
#             114 LOAD_FAST                5 (@py_assert6)
#             116 CONTAINS_OP              0
#             118 STORE_FAST               6 (@py_assert5)
#             120 LOAD_FAST                6 (@py_assert5)
#             122 POP_JUMP_IF_TRUE       193 (to 510)
#             124 LOAD_GLOBAL              9 (NULL + @pytest_ar)
#             134 LOAD_ATTR               10 (_call_reprcompare)
#             154 LOAD_CONST               3 (('in',))
#             156 LOAD_FAST                6 (@py_assert5)
#             158 BUILD_TUPLE              1
#             160 LOAD_CONST               4 (('%(py4)s\n{%(py4)s = %(py2)s\n{%(py2)s = %(py0)s.status\n}.value\n} in %(py7)s',))
#             162 LOAD_FAST                4 (@py_assert3)
#             164 LOAD_FAST                5 (@py_assert6)
#             166 BUILD_TUPLE              2
#             168 CALL                     4
#             176 LOAD_CONST               5 ('result')
#             178 LOAD_GLOBAL             13 (NULL + @py_builtins)
#             188 LOAD_ATTR               14 (locals)
#             208 CALL                     0
#             216 CONTAINS_OP              0
#             218 POP_JUMP_IF_TRUE        21 (to 262)
#             220 LOAD_GLOBAL              9 (NULL + @pytest_ar)
#             230 LOAD_ATTR               16 (_should_repr_global_name)
#             250 LOAD_FAST                2 (result)
#             252 CALL                     1
#             260 POP_JUMP_IF_FALSE       21 (to 304)
#         >>  262 LOAD_GLOBAL              9 (NULL + @pytest_ar)
#             272 LOAD_ATTR               18 (_saferepr)
#             292 LOAD_FAST                2 (result)
#             294 CALL                     1
#             302 JUMP_FORWARD             1 (to 306)
#         >>  304 LOAD_CONST               5 ('result')
#         >>  306 LOAD_GLOBAL              9 (NULL + @pytest_ar)
#             316 LOAD_ATTR               18 (_saferepr)
#             336 LOAD_FAST                3 (@py_assert1)
#             338 CALL                     1
#             346 LOAD_GLOBAL              9 (NULL + @pytest_ar)
#             356 LOAD_ATTR               18 (_saferepr)
#             376 LOAD_FAST                4 (@py_assert3)
#             378 CALL                     1
#             386 LOAD_GLOBAL              9 (NULL + @pytest_ar)
#             396 LOAD_ATTR               18 (_saferepr)
#             416 LOAD_FAST                5 (@py_assert6)
#             418 CALL                     1
#             426 LOAD_CONST               6 (('py0', 'py2', 'py4', 'py7'))
#             428 BUILD_CONST_KEY_MAP      4
#             430 BINARY_OP                6 (%)
#             434 STORE_FAST               7 (@py_format8)
#             436 LOAD_CONST               7 ('assert %(py9)s')
#             438 LOAD_CONST               8 ('py9')
#             440 LOAD_FAST                7 (@py_format8)
#             442 BUILD_MAP                1
#             444 BINARY_OP                6 (%)
#             448 STORE_FAST               8 (@py_format10)
#             450 LOAD_GLOBAL             21 (NULL + AssertionError)
#             460 LOAD_GLOBAL              9 (NULL + @pytest_ar)
#             470 LOAD_ATTR               22 (_format_explanation)
#             490 LOAD_FAST                8 (@py_format10)
#             492 CALL                     1
#             500 CALL                     1
#             508 RAISE_VARARGS            1
#         >>  510 LOAD_CONST               0 (None)
#             512 COPY                     1
#             514 STORE_FAST               3 (@py_assert1)
#             516 COPY                     1
#             518 STORE_FAST               4 (@py_assert3)
#             520 COPY                     1
#             522 STORE_FAST               6 (@py_assert5)
#             524 STORE_FAST               5 (@py_assert6)
#             526 RETURN_CONST             0 (None)
# 