# Recovered from: /home/chenying/researches/cloudpss-toolkit/cloudpss_skills_v2/tests/__pycache__/test_disturbance_severity.cpython-312-pytest-9.0.2.pyc
# Original source: /home/chenying/researches/cloudpss-toolkit/cloudpss_skills_v2/tests/test_disturbance_severity.py
# WARNING: This file was reconstructed from .pyc bytecode.
# The structure is accurate but implementation details may need manual review.


def TestDisturbanceSeverityValidation():
    """TestDisturbanceSeverityValidation"""
pass  # TODO: restore


def TestDisturbanceSeverityDV():
    """TestDisturbanceSeverityDV"""
pass  # TODO: restore


def TestDisturbanceSeveritySI():
    """TestDisturbanceSeveritySI"""
pass  # TODO: restore


def TestDisturbanceSeverityAssessment():
    """TestDisturbanceSeverityAssessment"""
pass  # TODO: restore


def TestDisturbanceSeverityWeakPoints():
    """TestDisturbanceSeverityWeakPoints"""
pass  # TODO: restore


def TestDisturbanceSeverityRun():
    """TestDisturbanceSeverityRun"""
pass  # TODO: restore



# === FULL DISASSEMBLY (for manual reconstruction) ===
#   0           0 RESUME                   0
# 
#   1           2 LOAD_CONST               0 ('Tests for DisturbanceSeveritySkill v2.')
#               4 STORE_NAME               0 (__doc__)
# 
#   3           6 LOAD_CONST               1 (0)
#               8 LOAD_CONST               2 (None)
#              10 IMPORT_NAME              1 (builtins)
#              12 STORE_NAME               2 (@py_builtins)
#              14 LOAD_CONST               1 (0)
#              16 LOAD_CONST               2 (None)
#              18 IMPORT_NAME              3 (_pytest.assertion.rewrite)
#              20 IMPORT_FROM              4 (assertion)
#              22 SWAP                     2
#              24 POP_TOP
#              26 IMPORT_FROM              5 (rewrite)
#              28 STORE_NAME               6 (@pytest_ar)
#              30 POP_TOP
#              32 LOAD_CONST               1 (0)
#              34 LOAD_CONST               2 (None)
#              36 IMPORT_NAME              7 (numpy)
#              38 STORE_NAME               8 (np)
# 
#   4          40 LOAD_CONST               1 (0)
#              42 LOAD_CONST               2 (None)
#              44 IMPORT_NAME              9 (pytest)
#              46 STORE_NAME               9 (pytest)
# 
#   5          48 LOAD_CONST               1 (0)
#              50 LOAD_CONST               3 (('DisturbanceSeveritySkill',))
#              52 IMPORT_NAME             10 (cloudpss_skills_v2.skills.disturbance_severity)
#              54 IMPORT_FROM             11 (DisturbanceSeveritySkill)
#              56 STORE_NAME              11 (DisturbanceSeveritySkill)
#              58 POP_TOP
# 
#   8          60 PUSH_NULL
#              62 LOAD_BUILD_CLASS
#              64 LOAD_CONST               4 (<code object TestDisturbanceSeverityValidation at 0x73cd945ff210, file "/home/chenying/researches/cloudpss-toolkit/cloudpss_skills_v2/tests/test_disturbance_severity.py", line 8>)
#              66 MAKE_FUNCTION            0
#              68 LOAD_CONST               5 ('TestDisturbanceSeverityValidation')
#              70 CALL                     2
#              78 STORE_NAME              12 (TestDisturbanceSeverityValidation)
# 
#  23          80 PUSH_NULL
#              82 LOAD_BUILD_CLASS
#              84 LOAD_CONST               6 (<code object TestDisturbanceSeverityDV at 0x73cd945fe090, file "/home/chenying/researches/cloudpss-toolkit/cloudpss_skills_v2/tests/test_disturbance_severity.py", line 23>)
#              86 MAKE_FUNCTION            0
#              88 LOAD_CONST               7 ('TestDisturbanceSeverityDV')
#              90 CALL                     2
#              98 STORE_NAME              13 (TestDisturbanceSeverityDV)
# 
#  64         100 PUSH_NULL
#             102 LOAD_BUILD_CLASS
#             104 LOAD_CONST               8 (<code object TestDisturbanceSeveritySI at 0x73cd945fea30, file "/home/chenying/researches/cloudpss-toolkit/cloudpss_skills_v2/tests/test_disturbance_severity.py", line 64>)
#             106 MAKE_FUNCTION            0
#             108 LOAD_CONST               9 ('TestDisturbanceSeveritySI')
#             110 CALL                     2
#             118 STORE_NAME              14 (TestDisturbanceSeveritySI)
# 
#  85         120 PUSH_NULL
#             122 LOAD_BUILD_CLASS
#             124 LOAD_CONST              10 (<code object TestDisturbanceSeverityAssessment at 0x73cd945ff050, file "/home/chenying/researches/cloudpss-toolkit/cloudpss_skills_v2/tests/test_disturbance_severity.py", line 85>)
#             126 MAKE_FUNCTION            0
#             128 LOAD_CONST              11 ('TestDisturbanceSeverityAssessment')
#             130 CALL                     2
#             138 STORE_NAME              15 (TestDisturbanceSeverityAssessment)
# 
#  99         140 PUSH_NULL
#             142 LOAD_BUILD_CLASS
#             144 LOAD_CONST              12 (<code object TestDisturbanceSeverityWeakPoints at 0x73cd945fe6b0, file "/home/chenying/researches/cloudpss-toolkit/cloudpss_skills_v2/tests/test_disturbance_severity.py", line 99>)
#             146 MAKE_FUNCTION            0
#             148 LOAD_CONST              13 ('TestDisturbanceSeverityWeakPoints')
#             150 CALL                     2
#             158 STORE_NAME              16 (TestDisturbanceSeverityWeakPoints)
# 
# 112         160 PUSH_NULL
#             162 LOAD_BUILD_CLASS
#             164 LOAD_CONST              14 (<code object TestDisturbanceSeverityRun at 0x73cd945fe330, file "/home/chenying/researches/cloudpss-toolkit/cloudpss_skills_v2/tests/test_disturbance_severity.py", line 112>)
#             166 MAKE_FUNCTION            0
#             168 LOAD_CONST              15 ('TestDisturbanceSeverityRun')
#             170 CALL                     2
#             178 STORE_NAME              17 (TestDisturbanceSeverityRun)
#             180 RETURN_CONST             2 (None)
# 
# Disassembly of <code object TestDisturbanceSeverityValidation at 0x73cd945ff210, file "/home/chenying/researches/cloudpss-toolkit/cloudpss_skills_v2/tests/test_disturbance_severity.py", line 8>:
#   8           0 RESUME                   0
#               2 LOAD_NAME                0 (__name__)
#               4 STORE_NAME               1 (__module__)
#               6 LOAD_CONST               0 ('TestDisturbanceSeverityValidation')
#               8 STORE_NAME               2 (__qualname__)
# 
#   9          10 LOAD_CONST               1 (<code object test_validate_missing_model at 0x3af8e200, file "/home/chenying/researches/cloudpss-toolkit/cloudpss_skills_v2/tests/test_disturbance_severity.py", line 9>)
#              12 MAKE_FUNCTION            0
#              14 STORE_NAME               3 (test_validate_missing_model)
# 
#  15          16 LOAD_CONST               2 (<code object test_validate_valid_config at 0x3afa5260, file "/home/chenying/researches/cloudpss-toolkit/cloudpss_skills_v2/tests/test_disturbance_severity.py", line 15>)
#              18 MAKE_FUNCTION            0
#              20 STORE_NAME               4 (test_validate_valid_config)
#              22 RETURN_CONST             3 (None)
# 
# Disassembly of <code object test_validate_missing_model at 0x3af8e200, file "/home/chenying/researches/cloudpss-toolkit/cloudpss_skills_v2/tests/test_disturbance_severity.py", line 9>:
#   9           0 RESUME                   0
# 
#  10           2 LOAD_GLOBAL              1 (NULL + DisturbanceSeveritySkill)
#              12 CALL                     0
#              20 STORE_FAST               1 (skill)
# 
#  11          22 LOAD_FAST                1 (skill)
#              24 LOAD_ATTR                3 (NULL|self + validate)
#              44 BUILD_MAP                0
#              46 CALL                     1
#              54 UNPACK_SEQUENCE          2
#              58 STORE_FAST               2 (valid)
#              60 STORE_FAST               3 (errors)
# 
#  12          62 LOAD_CONST               1 (False)
#              64 STORE_FAST               4 (@py_assert2)
#              66 LOAD_FAST                2 (valid)
#              68 LOAD_FAST                4 (@py_assert2)
#              70 IS_OP                    0
#              72 STORE_FAST               5 (@py_assert1)
#              74 LOAD_FAST                5 (@py_assert1)
#              76 POP_JUMP_IF_TRUE       153 (to 384)
#              78 LOAD_GLOBAL              5 (NULL + @pytest_ar)
#              88 LOAD_ATTR                6 (_call_reprcompare)
#             108 LOAD_CONST               2 (('is',))
#             110 LOAD_FAST                5 (@py_assert1)
#             112 BUILD_TUPLE              1
#             114 LOAD_CONST               3 (('%(py0)s is %(py3)s',))
#             116 LOAD_FAST                2 (valid)
#             118 LOAD_FAST                4 (@py_assert2)
#             120 BUILD_TUPLE              2
#             122 CALL                     4
#             130 LOAD_CONST               4 ('valid')
#             132 LOAD_GLOBAL              9 (NULL + @py_builtins)
#             142 LOAD_ATTR               10 (locals)
#             162 CALL                     0
#             170 CONTAINS_OP              0
#             172 POP_JUMP_IF_TRUE        21 (to 216)
#             174 LOAD_GLOBAL              5 (NULL + @pytest_ar)
#             184 LOAD_ATTR               12 (_should_repr_global_name)
#             204 LOAD_FAST                2 (valid)
#             206 CALL                     1
#             214 POP_JUMP_IF_FALSE       21 (to 258)
#         >>  216 LOAD_GLOBAL              5 (NULL + @pytest_ar)
#             226 LOAD_ATTR               14 (_saferepr)
#             246 LOAD_FAST                2 (valid)
#             248 CALL                     1
#             256 JUMP_FORWARD             1 (to 260)
#         >>  258 LOAD_CONST               4 ('valid')
#         >>  260 LOAD_GLOBAL              5 (NULL + @pytest_ar)
#             270 LOAD_ATTR               14 (_saferepr)
#             290 LOAD_FAST                4 (@py_assert2)
#             292 CALL                     1
#             300 LOAD_CONST               5 (('py0', 'py3'))
#             302 BUILD_CONST_KEY_MAP      2
#             304 BINARY_OP                6 (%)
#             308 STORE_FAST               6 (@py_format4)
#             310 LOAD_CONST               6 ('assert %(py5)s')
#             312 LOAD_CONST               7 ('py5')
#             314 LOAD_FAST                6 (@py_format4)
#             316 BUILD_MAP                1
#             318 BINARY_OP                6 (%)
#             322 STORE_FAST               7 (@py_format6)
#             324 LOAD_GLOBAL             17 (NULL + AssertionError)
#             334 LOAD_GLOBAL              5 (NULL + @pytest_ar)
#             344 LOAD_ATTR               18 (_format_explanation)
#             364 LOAD_FAST                7 (@py_format6)
#             366 CALL                     1
#             374 CALL                     1
#             382 RAISE_VARARGS            1
#         >>  384 LOAD_CONST               0 (None)
#             386 COPY                     1
#             388 STORE_FAST               5 (@py_assert1)
#             390 STORE_FAST               4 (@py_assert2)
# 
#  13         392 LOAD_CONST               8 (<code object <genexpr> at 0x73cd93b06970, file "/home/chenying/researches/cloudpss-toolkit/cloudpss_skills_v2/tests/test_disturbance_severity.py", line 13>)
#             394 MAKE_FUNCTION            0
#             396 LOAD_FAST                3 (errors)
#             398 GET_ITER
#             400 CALL                     0
#             408 STORE_FAST               5 (@py_assert1)
#             410 LOAD_GLOBAL             21 (NULL + any)
#             420 LOAD_FAST                5 (@py_assert1)
#             422 CALL                     1
#             430 STORE_FAST               8 (@py_assert3)
#             432 LOAD_FAST                8 (@py_assert3)
#             434 POP_JUMP_IF_TRUE       149 (to 734)
#             436 LOAD_CONST               9 ('assert %(py4)s\n{%(py4)s = %(py0)s(%(py2)s)\n}')
#             438 LOAD_CONST              10 ('any')
#             440 LOAD_GLOBAL              9 (NULL + @py_builtins)
#             450 LOAD_ATTR               10 (locals)
#             470 CALL                     0
#             478 CONTAINS_OP              0
#             480 POP_JUMP_IF_TRUE        25 (to 532)
#             482 LOAD_GLOBAL              5 (NULL + @pytest_ar)
#             492 LOAD_ATTR               12 (_should_repr_global_name)
#             512 LOAD_GLOBAL             20 (any)
#             522 CALL                     1
#             530 POP_JUMP_IF_FALSE       25 (to 582)
#         >>  532 LOAD_GLOBAL              5 (NULL + @pytest_ar)
#             542 LOAD_ATTR               14 (_saferepr)
#             562 LOAD_GLOBAL             20 (any)
#             572 CALL                     1
#             580 JUMP_FORWARD             1 (to 584)
#         >>  582 LOAD_CONST              10 ('any')
#         >>  584 LOAD_GLOBAL              5 (NULL + @pytest_ar)
#             594 LOAD_ATTR               14 (_saferepr)
#             614 LOAD_FAST                5 (@py_assert1)
#             616 CALL                     1
#             624 LOAD_GLOBAL              5 (NULL + @pytest_ar)
#             634 LOAD_ATTR               14 (_saferepr)
#             654 LOAD_FAST                8 (@py_assert3)
#             656 CALL                     1
#             664 LOAD_CONST              11 (('py0', 'py2', 'py4'))
#             666 BUILD_CONST_KEY_MAP      3
#             668 BINARY_OP                6 (%)
#             672 STORE_FAST               9 (@py_format5)
#             674 LOAD_GLOBAL             17 (NULL + AssertionError)
#             684 LOAD_GLOBAL              5 (NULL + @pytest_ar)
#             694 LOAD_ATTR               18 (_format_explanation)
#             714 LOAD_FAST                9 (@py_format5)
#             716 CALL                     1
#             724 CALL                     1
#             732 RAISE_VARARGS            1
#         >>  734 LOAD_CONST               0 (None)
#             736 COPY                     1
#             738 STORE_FAST               5 (@py_assert1)
#             740 STORE_FAST               8 (@py_assert3)
#             742 RETURN_CONST             0 (None)
# 
# Disassembly of <code object <genexpr> at 0x73cd93b06970, file "/home/chenying/researches/cloudpss-toolkit/cloudpss_skills_v2/tests/test_disturbance_severity.py", line 13>:
#  13           0 RETURN_GENERATOR
#               2 POP_TOP
#               4 RESUME                   0
#               6 LOAD_FAST                0 (.0)
#         >>    8 FOR_ITER                 8 (to 28)
#              12 STORE_FAST               1 (e)
#              14 LOAD_CONST               0 ('model.rid')
#              16 LOAD_FAST                1 (e)
#              18 CONTAINS_OP              0
#              20 YIELD_VALUE              1
#              22 RESUME                   1
#              24 POP_TOP
#              26 JUMP_BACKWARD           10 (to 8)
#         >>   28 END_FOR
#              30 RETURN_CONST             1 (None)
#         >>   32 CALL_INTRINSIC_1         3 (INTRINSIC_STOPITERATION_ERROR)
#              34 RERAISE                  1
# ExceptionTable:
#   4 to 30 -> 32 [0] lasti
# 
# Disassembly of <code object test_validate_valid_config at 0x3afa5260, file "/home/chenying/researches/cloudpss-toolkit/cloudpss_skills_v2/tests/test_disturbance_severity.py", line 15>:
#  15           0 RESUME                   0
# 
#  16           2 LOAD_GLOBAL              1 (NULL + DisturbanceSeveritySkill)
#              12 CALL                     0
#              20 STORE_FAST               1 (skill)
# 
#  17          22 LOAD_CONST               1 ('model')
#              24 LOAD_CONST               2 ('rid')
#              26 LOAD_CONST               3 ('model/test/IEEE39')
#              28 BUILD_MAP                1
#              30 BUILD_MAP                1
#              32 STORE_FAST               2 (config)
# 
#  18          34 LOAD_FAST                1 (skill)
#              36 LOAD_ATTR                3 (NULL|self + validate)
#              56 LOAD_FAST                2 (config)
#              58 CALL                     1
#              66 UNPACK_SEQUENCE          2
#              70 STORE_FAST               3 (valid)
#              72 STORE_FAST               4 (errors)
# 
#  19          74 LOAD_CONST               4 (True)
#              76 STORE_FAST               5 (@py_assert2)
#              78 LOAD_FAST                3 (valid)
#              80 LOAD_FAST                5 (@py_assert2)
#              82 IS_OP                    0
#              84 STORE_FAST               6 (@py_assert1)
#              86 LOAD_FAST                6 (@py_assert1)
#              88 POP_JUMP_IF_TRUE       153 (to 396)
#              90 LOAD_GLOBAL              5 (NULL + @pytest_ar)
#             100 LOAD_ATTR                6 (_call_reprcompare)
#             120 LOAD_CONST               5 (('is',))
#             122 LOAD_FAST                6 (@py_assert1)
#             124 BUILD_TUPLE              1
#             126 LOAD_CONST               6 (('%(py0)s is %(py3)s',))
#             128 LOAD_FAST                3 (valid)
#             130 LOAD_FAST                5 (@py_assert2)
#             132 BUILD_TUPLE              2
#             134 CALL                     4
#             142 LOAD_CONST               7 ('valid')
#             144 LOAD_GLOBAL              9 (NULL + @py_builtins)
#             154 LOAD_ATTR               10 (locals)
#             174 CALL                     0
#             182 CONTAINS_OP              0
#             184 POP_JUMP_IF_TRUE        21 (to 228)
#             186 LOAD_GLOBAL              5 (NULL + @pytest_ar)
#             196 LOAD_ATTR               12 (_should_repr_global_name)
#             216 LOAD_FAST                3 (valid)
#             218 CALL                     1
#             226 POP_JUMP_IF_FALSE       21 (to 270)
#         >>  228 LOAD_GLOBAL              5 (NULL + @pytest_ar)
#             238 LOAD_ATTR               14 (_saferepr)
#             258 LOAD_FAST                3 (valid)
#             260 CALL                     1
#             268 JUMP_FORWARD             1 (to 272)
#         >>  270 LOAD_CONST               7 ('valid')
#         >>  272 LOAD_GLOBAL              5 (NULL + @pytest_ar)
#             282 LOAD_ATTR               14 (_saferepr)
#             302 LOAD_FAST                5 (@py_assert2)
#             304 CALL                     1
#             312 LOAD_CONST               8 (('py0', 'py3'))
#             314 BUILD_CONST_KEY_MAP      2
#             316 BINARY_OP                6 (%)
#             320 STORE_FAST               7 (@py_format4)
#             322 LOAD_CONST               9 ('assert %(py5)s')
#             324 LOAD_CONST              10 ('py5')
#             326 LOAD_FAST                7 (@py_format4)
#             328 BUILD_MAP                1
#             330 BINARY_OP                6 (%)
#             334 STORE_FAST               8 (@py_format6)
#             336 LOAD_GLOBAL             17 (NULL + AssertionError)
#             346 LOAD_GLOBAL              5 (NULL + @pytest_ar)
#             356 LOAD_ATTR               18 (_format_explanation)
#             376 LOAD_FAST                8 (@py_format6)
#             378 CALL                     1
#             386 CALL                     1
#             394 RAISE_VARARGS            1
#         >>  396 LOAD_CONST               0 (None)
#             398 COPY                     1
#             400 STORE_FAST               6 (@py_assert1)
#             402 STORE_FAST               5 (@py_assert2)
# 
#  20         404 LOAD_GLOBAL             21 (NULL + len)
#             414 LOAD_FAST                4 (errors)
#             416 CALL                     1
#             424 STORE_FAST               5 (@py_assert2)
#             426 LOAD_CONST              11 (0)
#             428 STORE_FAST               9 (@py_assert5)
#             430 LOAD_FAST                5 (@py_assert2)
#             432 LOAD_FAST                9 (@py_assert5)
#             434 COMPARE_OP              40 (==)
#             438 STORE_FAST              10 (@py_assert4)
#             440 LOAD_FAST               10 (@py_assert4)
#             442 POP_JUMP_IF_TRUE       246 (to 936)
#             444 LOAD_GLOBAL              5 (NULL + @pytest_ar)
#             454 LOAD_ATTR                6 (_call_reprcompare)
#             474 LOAD_CONST              12 (('==',))
#             476 LOAD_FAST               10 (@py_assert4)
#             478 BUILD_TUPLE              1
#             480 LOAD_CONST              13 (('%(py3)s\n{%(py3)s = %(py0)s(%(py1)s)\n} == %(py6)s',))
#             482 LOAD_FAST                5 (@py_assert2)
#             484 LOAD_FAST                9 (@py_assert5)
#             486 BUILD_TUPLE              2
#             488 CALL                     4
#             496 LOAD_CONST              14 ('len')
#             498 LOAD_GLOBAL              9 (NULL + @py_builtins)
#             508 LOAD_ATTR               10 (locals)
#             528 CALL                     0
#             536 CONTAINS_OP              0
#             538 POP_JUMP_IF_TRUE        25 (to 590)
#             540 LOAD_GLOBAL              5 (NULL + @pytest_ar)
#             550 LOAD_ATTR               12 (_should_repr_global_name)
#             570 LOAD_GLOBAL             20 (len)
#             580 CALL                     1
#             588 POP_JUMP_IF_FALSE       25 (to 640)
#         >>  590 LOAD_GLOBAL              5 (NULL + @pytest_ar)
#             600 LOAD_ATTR               14 (_saferepr)
#             620 LOAD_GLOBAL             20 (len)
#             630 CALL                     1
#             638 JUMP_FORWARD             1 (to 642)
#         >>  640 LOAD_CONST              14 ('len')
#         >>  642 LOAD_CONST              15 ('errors')
#             644 LOAD_GLOBAL              9 (NULL + @py_builtins)
#             654 LOAD_ATTR               10 (locals)
#             674 CALL                     0
#             682 CONTAINS_OP              0
#             684 POP_JUMP_IF_TRUE        21 (to 728)
#             686 LOAD_GLOBAL              5 (NULL + @pytest_ar)
#             696 LOAD_ATTR               12 (_should_repr_global_name)
#             716 LOAD_FAST                4 (errors)
#             718 CALL                     1
#             726 POP_JUMP_IF_FALSE       21 (to 770)
#         >>  728 LOAD_GLOBAL              5 (NULL + @pytest_ar)
#             738 LOAD_ATTR               14 (_saferepr)
#             758 LOAD_FAST                4 (errors)
#             760 CALL                     1
#             768 JUMP_FORWARD             1 (to 772)
#         >>  770 LOAD_CONST              15 ('errors')
#         >>  772 LOAD_GLOBAL              5 (NULL + @pytest_ar)
#             782 LOAD_ATTR               14 (_saferepr)
#             802 LOAD_FAST                5 (@py_assert2)
#             804 CALL                     1
#             812 LOAD_GLOBAL              5 (NULL + @pytest_ar)
#             822 LOAD_ATTR               14 (_saferepr)
#             842 LOAD_FAST                9 (@py_assert5)
#             844 CALL                     1
#             852 LOAD_CONST              16 (('py0', 'py1', 'py3', 'py6'))
#             854 BUILD_CONST_KEY_MAP      4
#             856 BINARY_OP                6 (%)
#             860 STORE_FAST              11 (@py_format7)
#             862 LOAD_CONST              17 ('assert %(py8)s')
#             864 LOAD_CONST              18 ('py8')
#             866 LOAD_FAST               11 (@py_format7)
#             868 BUILD_MAP                1
#             870 BINARY_OP                6 (%)
#             874 STORE_FAST              12 (@py_format9)
#             876 LOAD_GLOBAL             17 (NULL + AssertionError)
#             886 LOAD_GLOBAL              5 (NULL + @pytest_ar)
#             896 LOAD_ATTR               18 (_format_explanation)
#             916 LOAD_FAST               12 (@py_format9)
#             918 CALL                     1
#             926 CALL                     1
#             934 RAISE_VARARGS            1
#         >>  936 LOAD_CONST               0 (None)
#             938 COPY                     1
#             940 STORE_FAST               5 (@py_assert2)
#             942 COPY                     1
#             944 STORE_FAST              10 (@py_assert4)
#             946 STORE_FAST               9 (@py_assert5)
#             948 RETURN_CONST             0 (None)
# 
# Disassembly of <code object TestDisturbanceSeverityDV at 0x73cd945fe090, file "/home/chenying/researches/cloudpss-toolkit/cloudpss_skills_v2/tests/test_disturbance_severity.py", line 23>:
#  23           0 RESUME                   0
#               2 LOAD_NAME                0 (__name__)
#               4 STORE_NAME               1 (__module__)
#               6 LOAD_CONST               0 ('TestDisturbanceSeverityDV')
#               8 STORE_NAME               2 (__qualname__)
# 
#  24          10 LOAD_CONST               1 (<code object test_calculate_dv_positive_margin at 0x3af9a920, file "/home/chenying/researches/cloudpss-toolkit/cloudpss_skills_v2/tests/test_disturbance_severity.py", line 24>)
#              12 MAKE_FUNCTION            0
#              14 STORE_NAME               3 (test_calculate_dv_positive_margin)
# 
#  39          16 LOAD_CONST               2 (<code object test_calculate_dv_negative_margin at 0x3af3a2f0, file "/home/chenying/researches/cloudpss-toolkit/cloudpss_skills_v2/tests/test_disturbance_severity.py", line 39>)
#              18 MAKE_FUNCTION            0
#              20 STORE_NAME               4 (test_calculate_dv_negative_margin)
# 
#  52          22 LOAD_CONST               3 (<code object test_calculate_dv_steady_voltage at 0x3af994a0, file "/home/chenying/researches/cloudpss-toolkit/cloudpss_skills_v2/tests/test_disturbance_severity.py", line 52>)
#              24 MAKE_FUNCTION            0
#              26 STORE_NAME               5 (test_calculate_dv_steady_voltage)
#              28 RETURN_CONST             4 (None)
# 
# Disassembly of <code object test_calculate_dv_positive_margin at 0x3af9a920, file "/home/chenying/researches/cloudpss-toolkit/cloudpss_skills_v2/tests/test_disturbance_severity.py", line 24>:
#  24           0 RESUME                   0
# 
#  25           2 LOAD_GLOBAL              1 (NULL + DisturbanceSeveritySkill)
#              12 CALL                     0
#              20 STORE_FAST               1 (skill)
# 
#  26          22 LOAD_GLOBAL              3 (NULL + np)
#              32 LOAD_ATTR                4 (linspace)
#              52 LOAD_CONST               1 (0)
#              54 LOAD_CONST               2 (10)
#              56 LOAD_CONST               3 (1000)
#              58 CALL                     3
#              66 STORE_FAST               2 (time)
# 
#  27          68 LOAD_GLOBAL              3 (NULL + np)
#              78 LOAD_ATTR                6 (ones)
#              98 LOAD_CONST               3 (1000)
#             100 CALL                     1
#             108 STORE_FAST               3 (voltage)
# 
#  28         110 LOAD_CONST               4 (0.85)
#             112 LOAD_FAST                3 (voltage)
#             114 LOAD_CONST               5 (400)
#             116 LOAD_CONST               6 (500)
#             118 STORE_SLICE
# 
#  29         120 LOAD_CONST               7 (4.0)
#             122 STORE_FAST               4 (disturbance_time)
# 
#  30         124 BUILD_LIST               0
#             126 LOAD_CONST               8 ((0.1, 3.0, 0.75, 1.25))
#             128 LIST_EXTEND              1
#             130 BUILD_LIST               1
#             132 STORE_FAST               5 (judge_criteria)
# 
#  31         134 LOAD_FAST                1 (skill)
#             136 LOAD_ATTR                9 (NULL|self + _calculate_dv)
# 
#  32         156 LOAD_FAST                3 (voltage)
#             158 LOAD_FAST                2 (time)
#             160 LOAD_FAST                4 (disturbance_time)
#             162 LOAD_CONST               9 (0.5)
#             164 LOAD_FAST                5 (judge_criteria)
# 
#  31         166 CALL                     5
#             174 STORE_FAST               6 (result)
# 
#  34         176 LOAD_FAST                6 (result)
#             178 LOAD_CONST              10 ('dv_up')
#             180 BINARY_SUBSCR
#             184 STORE_FAST               7 (@py_assert0)
#             186 LOAD_CONST               0 (None)
#             188 STORE_FAST               8 (@py_assert3)
#             190 LOAD_FAST                7 (@py_assert0)
#             192 LOAD_FAST                8 (@py_assert3)
#             194 IS_OP                    1
#             196 STORE_FAST               9 (@py_assert2)
#             198 LOAD_FAST                9 (@py_assert2)
#             200 POP_JUMP_IF_TRUE       108 (to 418)
#             202 LOAD_GLOBAL             11 (NULL + @pytest_ar)
#             212 LOAD_ATTR               12 (_call_reprcompare)
#             232 LOAD_CONST              11 (('is not',))
#             234 LOAD_FAST                9 (@py_assert2)
#             236 BUILD_TUPLE              1
#             238 LOAD_CONST              12 (('%(py1)s is not %(py4)s',))
#             240 LOAD_FAST                7 (@py_assert0)
#             242 LOAD_FAST                8 (@py_assert3)
#             244 BUILD_TUPLE              2
#             246 CALL                     4
#             254 LOAD_GLOBAL             11 (NULL + @pytest_ar)
#             264 LOAD_ATTR               14 (_saferepr)
#             284 LOAD_FAST                7 (@py_assert0)
#             286 CALL                     1
#             294 LOAD_GLOBAL             11 (NULL + @pytest_ar)
#             304 LOAD_ATTR               14 (_saferepr)
#             324 LOAD_FAST                8 (@py_assert3)
#             326 CALL                     1
#             334 LOAD_CONST              13 (('py1', 'py4'))
#             336 BUILD_CONST_KEY_MAP      2
#             338 BINARY_OP                6 (%)
#             342 STORE_FAST              10 (@py_format5)
#             344 LOAD_CONST              14 ('assert %(py6)s')
#             346 LOAD_CONST              15 ('py6')
#             348 LOAD_FAST               10 (@py_format5)
#             350 BUILD_MAP                1
#             352 BINARY_OP                6 (%)
#             356 STORE_FAST              11 (@py_format7)
#             358 LOAD_GLOBAL             17 (NULL + AssertionError)
#             368 LOAD_GLOBAL             11 (NULL + @pytest_ar)
#             378 LOAD_ATTR               18 (_format_explanation)
#             398 LOAD_FAST               11 (@py_format7)
#             400 CALL                     1
#             408 CALL                     1
#             416 RAISE_VARARGS            1
#         >>  418 LOAD_CONST               0 (None)
#             420 COPY                     1
#             422 STORE_FAST               7 (@py_assert0)
#             424 COPY                     1
#             426 STORE_FAST               9 (@py_assert2)
#             428 STORE_FAST               8 (@py_assert3)
# 
#  35         430 LOAD_FAST                6 (result)
#             432 LOAD_CONST              10 ('dv_up')
#             434 BINARY_SUBSCR
#             438 STORE_FAST               7 (@py_assert0)
#             440 LOAD_CONST               1 (0)
#             442 STORE_FAST               8 (@py_assert3)
#             444 LOAD_FAST                7 (@py_assert0)
#             446 LOAD_FAST                8 (@py_assert3)
#             448 COMPARE_OP              68 (>)
#             452 STORE_FAST               9 (@py_assert2)
#             454 LOAD_FAST                9 (@py_assert2)
#             456 POP_JUMP_IF_TRUE       108 (to 674)
#             458 LOAD_GLOBAL             11 (NULL + @pytest_ar)
#             468 LOAD_ATTR               12 (_call_reprcompare)
#             488 LOAD_CONST              16 (('>',))
#             490 LOAD_FAST                9 (@py_assert2)
#             492 BUILD_TUPLE              1
#             494 LOAD_CONST              17 (('%(py1)s > %(py4)s',))
#             496 LOAD_FAST                7 (@py_assert0)
#             498 LOAD_FAST                8 (@py_assert3)
#             500 BUILD_TUPLE              2
#             502 CALL                     4
#             510 LOAD_GLOBAL             11 (NULL + @pytest_ar)
#             520 LOAD_ATTR               14 (_saferepr)
#             540 LOAD_FAST                7 (@py_assert0)
#             542 CALL                     1
#             550 LOAD_GLOBAL             11 (NULL + @pytest_ar)
#             560 LOAD_ATTR               14 (_saferepr)
#             580 LOAD_FAST                8 (@py_assert3)
#             582 CALL                     1
#             590 LOAD_CONST              13 (('py1', 'py4'))
#             592 BUILD_CONST_KEY_MAP      2
#             594 BINARY_OP                6 (%)
#             598 STORE_FAST              10 (@py_format5)
#             600 LOAD_CONST              14 ('assert %(py6)s')
#             602 LOAD_CONST              15 ('py6')
#             604 LOAD_FAST               10 (@py_format5)
#             606 BUILD_MAP                1
#             608 BINARY_OP                6 (%)
#             612 STORE_FAST              11 (@py_format7)
#             614 LOAD_GLOBAL             17 (NULL + AssertionError)
#             624 LOAD_GLOBAL             11 (NULL + @pytest_ar)
#             634 LOAD_ATTR               18 (_format_explanation)
#             654 LOAD_FAST               11 (@py_format7)
#             656 CALL                     1
#             664 CALL                     1
#             672 RAISE_VARARGS            1
#         >>  674 LOAD_CONST               0 (None)
#             676 COPY                     1
#             678 STORE_FAST               7 (@py_assert0)
#             680 COPY                     1
#             682 STORE_FAST               9 (@py_assert2)
#             684 STORE_FAST               8 (@py_assert3)
# 
#  36         686 LOAD_FAST                6 (result)
#             688 LOAD_CONST              18 ('dv_down')
#             690 BINARY_SUBSCR
#             694 STORE_FAST               7 (@py_assert0)
#             696 LOAD_CONST               0 (None)
#             698 STORE_FAST               8 (@py_assert3)
#             700 LOAD_FAST                7 (@py_assert0)
#             702 LOAD_FAST                8 (@py_assert3)
#             704 IS_OP                    1
#             706 STORE_FAST               9 (@py_assert2)
#             708 LOAD_FAST                9 (@py_assert2)
#             710 POP_JUMP_IF_TRUE       108 (to 928)
#             712 LOAD_GLOBAL             11 (NULL + @pytest_ar)
#             722 LOAD_ATTR               12 (_call_reprcompare)
#             742 LOAD_CONST              11 (('is not',))
#             744 LOAD_FAST                9 (@py_assert2)
#             746 BUILD_TUPLE              1
#             748 LOAD_CONST              12 (('%(py1)s is not %(py4)s',))
#             750 LOAD_FAST                7 (@py_assert0)
#             752 LOAD_FAST                8 (@py_assert3)
#             754 BUILD_TUPLE              2
#             756 CALL                     4
#             764 LOAD_GLOBAL             11 (NULL + @pytest_ar)
#             774 LOAD_ATTR               14 (_saferepr)
#             794 LOAD_FAST                7 (@py_assert0)
#             796 CALL                     1
#             804 LOAD_GLOBAL             11 (NULL + @pytest_ar)
#             814 LOAD_ATTR               14 (_saferepr)
#             834 LOAD_FAST                8 (@py_assert3)
#             836 CALL                     1
#             844 LOAD_CONST              13 (('py1', 'py4'))
#             846 BUILD_CONST_KEY_MAP      2
#             848 BINARY_OP                6 (%)
#             852 STORE_FAST              10 (@py_format5)
#             854 LOAD_CONST              14 ('assert %(py6)s')
#             856 LOAD_CONST              15 ('py6')
#             858 LOAD_FAST               10 (@py_format5)
#             860 BUILD_MAP                1
#             862 BINARY_OP                6 (%)
#             866 STORE_FAST              11 (@py_format7)
#             868 LOAD_GLOBAL             17 (NULL + AssertionError)
#             878 LOAD_GLOBAL             11 (NULL + @pytest_ar)
#             888 LOAD_ATTR               18 (_format_explanation)
#             908 LOAD_FAST               11 (@py_format7)
#             910 CALL                     1
#             918 CALL                     1
#             926 RAISE_VARARGS            1
#         >>  928 LOAD_CONST               0 (None)
#             930 COPY                     1
#             932 STORE_FAST               7 (@py_assert0)
#             934 COPY                     1
#             936 STORE_FAST               9 (@py_assert2)
#             938 STORE_FAST               8 (@py_assert3)
# 
#  37         940 LOAD_FAST                6 (result)
#             942 LOAD_CONST              18 ('dv_down')
#             944 BINARY_SUBSCR
#             948 STORE_FAST               7 (@py_assert0)
#             950 LOAD_CONST               1 (0)
#             952 STORE_FAST               8 (@py_assert3)
#             954 LOAD_FAST                7 (@py_assert0)
#             956 LOAD_FAST                8 (@py_assert3)
#             958 COMPARE_OP              68 (>)
#             962 STORE_FAST               9 (@py_assert2)
#             964 LOAD_FAST                9 (@py_assert2)
#             966 POP_JUMP_IF_TRUE       108 (to 1184)
#             968 LOAD_GLOBAL             11 (NULL + @pytest_ar)
#             978 LOAD_ATTR               12 (_call_reprcompare)
#             998 LOAD_CONST              16 (('>',))
#            1000 LOAD_FAST                9 (@py_assert2)
#            1002 BUILD_TUPLE              1
#            1004 LOAD_CONST              17 (('%(py1)s > %(py4)s',))
#            1006 LOAD_FAST                7 (@py_assert0)
#            1008 LOAD_FAST                8 (@py_assert3)
#            1010 BUILD_TUPLE              2
#            1012 CALL                     4
#            1020 LOAD_GLOBAL             11 (NULL + @pytest_ar)
#            1030 LOAD_ATTR               14 (_saferepr)
#            1050 LOAD_FAST                7 (@py_assert0)
#            1052 CALL                     1
#            1060 LOAD_GLOBAL             11 (NULL + @pytest_ar)
#            1070 LOAD_ATTR               14 (_saferepr)
#            1090 LOAD_FAST                8 (@py_assert3)
#            1092 CALL                     1
#            1100 LOAD_CONST              13 (('py1', 'py4'))
#            1102 BUILD_CONST_KEY_MAP      2
#            1104 BINARY_OP                6 (%)
#            1108 STORE_FAST              10 (@py_format5)
#            1110 LOAD_CONST              14 ('assert %(py6)s')
#            1112 LOAD_CONST              15 ('py6')
#            1114 LOAD_FAST               10 (@py_format5)
#            1116 BUILD_MAP                1
#            1118 BINARY_OP                6 (%)
#            1122 STORE_FAST              11 (@py_format7)
#            1124 LOAD_GLOBAL             17 (NULL + AssertionError)
#            1134 LOAD_GLOBAL             11 (NULL + @pytest_ar)
#            1144 LOAD_ATTR               18 (_format_explanation)
#            1164 LOAD_FAST               11 (@py_format7)
#            1166 CALL                     1
#            1174 CALL                     1
#            1182 RAISE_VARARGS            1
#         >> 1184 LOAD_CONST               0 (None)
#            1186 COPY                     1
#            1188 STORE_FAST               7 (@py_assert0)
#            1190 COPY                     1
#            1192 STORE_FAST               9 (@py_assert2)
#            1194 STORE_FAST               8 (@py_assert3)
#            1196 RETURN_CONST             0 (None)
# 
# Disassembly of <code object test_calculate_dv_negative_margin at 0x3af3a2f0, file "/home/chenying/researches/cloudpss-toolkit/cloudpss_skills_v2/tests/test_disturbance_severity.py", line 39>:
#  39           0 RESUME                   0
# 
#  40           2 LOAD_GLOBAL              1 (NULL + DisturbanceSeveritySkill)
#              12 CALL                     0
#              20 STORE_FAST               1 (skill)
# 
#  41          22 LOAD_GLOBAL              3 (NULL + np)
#              32 LOAD_ATTR                4 (linspace)
#              52 LOAD_CONST               1 (0)
#              54 LOAD_CONST               2 (10)
#              56 LOAD_CONST               3 (1000)
#              58 CALL                     3
#              66 STORE_FAST               2 (time)
# 
#  42          68 LOAD_GLOBAL              3 (NULL + np)
#              78 LOAD_ATTR                6 (ones)
#              98 LOAD_CONST               3 (1000)
#             100 CALL                     1
#             108 STORE_FAST               3 (voltage)
# 
#  43         110 LOAD_CONST               4 (0.6)
#             112 LOAD_FAST                3 (voltage)
#             114 LOAD_CONST               5 (400)
#             116 LOAD_CONST               6 (500)
#             118 STORE_SLICE
# 
#  44         120 LOAD_CONST               7 (4.0)
#             122 STORE_FAST               4 (disturbance_time)
# 
#  45         124 BUILD_LIST               0
#             126 LOAD_CONST               8 ((0.1, 3.0, 0.75, 1.25))
#             128 LIST_EXTEND              1
#             130 BUILD_LIST               1
#             132 STORE_FAST               5 (judge_criteria)
# 
#  46         134 LOAD_FAST                1 (skill)
#             136 LOAD_ATTR                9 (NULL|self + _calculate_dv)
# 
#  47         156 LOAD_FAST                3 (voltage)
#             158 LOAD_FAST                2 (time)
#             160 LOAD_FAST                4 (disturbance_time)
#             162 LOAD_CONST               9 (0.5)
#             164 LOAD_FAST                5 (judge_criteria)
# 
#  46         166 CALL                     5
#             174 STORE_FAST               6 (result)
# 
#  49         176 LOAD_FAST                6 (result)
#             178 LOAD_CONST              10 ('dv_down')
#             180 BINARY_SUBSCR
#             184 STORE_FAST               7 (@py_assert0)
#             186 LOAD_CONST               0 (None)
#             188 STORE_FAST               8 (@py_assert3)
#             190 LOAD_FAST                7 (@py_assert0)
#             192 LOAD_FAST                8 (@py_assert3)
#             194 IS_OP                    1
#             196 STORE_FAST               9 (@py_assert2)
#             198 LOAD_FAST                9 (@py_assert2)
#             200 POP_JUMP_IF_TRUE       108 (to 418)
#             202 LOAD_GLOBAL             11 (NULL + @pytest_ar)
#             212 LOAD_ATTR               12 (_call_reprcompare)
#             232 LOAD_CONST              11 (('is not',))
#             234 LOAD_FAST                9 (@py_assert2)
#             236 BUILD_TUPLE              1
#             238 LOAD_CONST              12 (('%(py1)s is not %(py4)s',))
#             240 LOAD_FAST                7 (@py_assert0)
#             242 LOAD_FAST                8 (@py_assert3)
#             244 BUILD_TUPLE              2
#             246 CALL                     4
#             254 LOAD_GLOBAL             11 (NULL + @pytest_ar)
#             264 LOAD_ATTR               14 (_saferepr)
#             284 LOAD_FAST                7 (@py_assert0)
#             286 CALL                     1
#             294 LOAD_GLOBAL             11 (NULL + @pytest_ar)
#             304 LOAD_ATTR               14 (_saferepr)
#             324 LOAD_FAST                8 (@py_assert3)
#             326 CALL                     1
#             334 LOAD_CONST              13 (('py1', 'py4'))
#             336 BUILD_CONST_KEY_MAP      2
#             338 BINARY_OP                6 (%)
#             342 STORE_FAST              10 (@py_format5)
#             344 LOAD_CONST              14 ('assert %(py6)s')
#             346 LOAD_CONST              15 ('py6')
#             348 LOAD_FAST               10 (@py_format5)
#             350 BUILD_MAP                1
#             352 BINARY_OP                6 (%)
#             356 STORE_FAST              11 (@py_format7)
#             358 LOAD_GLOBAL             17 (NULL + AssertionError)
#             368 LOAD_GLOBAL             11 (NULL + @pytest_ar)
#             378 LOAD_ATTR               18 (_format_explanation)
#             398 LOAD_FAST               11 (@py_format7)
#             400 CALL                     1
#             408 CALL                     1
#             416 RAISE_VARARGS            1
#         >>  418 LOAD_CONST               0 (None)
#             420 COPY                     1
#             422 STORE_FAST               7 (@py_assert0)
#             424 COPY                     1
#             426 STORE_FAST               9 (@py_assert2)
#             428 STORE_FAST               8 (@py_assert3)
# 
#  50         430 LOAD_FAST                6 (result)
#             432 LOAD_CONST              10 ('dv_down')
#             434 BINARY_SUBSCR
#             438 STORE_FAST               7 (@py_assert0)
#             440 LOAD_CONST               1 (0)
#             442 STORE_FAST               8 (@py_assert3)
#             444 LOAD_FAST                7 (@py_assert0)
#             446 LOAD_FAST                8 (@py_assert3)
#             448 COMPARE_OP               2 (<)
#             452 STORE_FAST               9 (@py_assert2)
#             454 LOAD_FAST                9 (@py_assert2)
#             456 POP_JUMP_IF_TRUE       108 (to 674)
#             458 LOAD_GLOBAL             11 (NULL + @pytest_ar)
#             468 LOAD_ATTR               12 (_call_reprcompare)
#             488 LOAD_CONST              16 (('<',))
#             490 LOAD_FAST                9 (@py_assert2)
#             492 BUILD_TUPLE              1
#             494 LOAD_CONST              17 (('%(py1)s < %(py4)s',))
#             496 LOAD_FAST                7 (@py_assert0)
#             498 LOAD_FAST                8 (@py_assert3)
#             500 BUILD_TUPLE              2
#             502 CALL                     4
#             510 LOAD_GLOBAL             11 (NULL + @pytest_ar)
#             520 LOAD_ATTR               14 (_saferepr)
#             540 LOAD_FAST                7 (@py_assert0)
#             542 CALL                     1
#             550 LOAD_GLOBAL             11 (NULL + @pytest_ar)
#             560 LOAD_ATTR               14 (_saferepr)
#             580 LOAD_FAST                8 (@py_assert3)
#             582 CALL                     1
#             590 LOAD_CONST              13 (('py1', 'py4'))
#             592 BUILD_CONST_KEY_MAP      2
#             594 BINARY_OP                6 (%)
#             598 STORE_FAST              10 (@py_format5)
#             600 LOAD_CONST              14 ('assert %(py6)s')
#             602 LOAD_CONST              15 ('py6')
#             604 LOAD_FAST               10 (@py_format5)
#             606 BUILD_MAP                1
#             608 BINARY_OP                6 (%)
#             612 STORE_FAST              11 (@py_format7)
#             614 LOAD_GLOBAL             17 (NULL + AssertionError)
#             624 LOAD_GLOBAL             11 (NULL + @pytest_ar)
#             634 LOAD_ATTR               18 (_format_explanation)
#             654 LOAD_FAST               11 (@py_format7)
#             656 CALL                     1
#             664 CALL                     1
#             672 RAISE_VARARGS            1
#         >>  674 LOAD_CONST               0 (None)
#             676 COPY                     1
#             678 STORE_FAST               7 (@py_assert0)
#             680 COPY                     1
#             682 STORE_FAST               9 (@py_assert2)
#             684 STORE_FAST               8 (@py_assert3)
#             686 RETURN_CONST             0 (None)
# 
# Disassembly of <code object test_calculate_dv_steady_voltage at 0x3af994a0, file "/home/chenying/researches/cloudpss-toolkit/cloudpss_skills_v2/tests/test_disturbance_severity.py", line 52>:
#  52           0 RESUME                   0
# 
#  53           2 LOAD_GLOBAL              1 (NULL + DisturbanceSeveritySkill)
#              12 CALL                     0
#              20 STORE_FAST               1 (skill)
# 
#  54          22 LOAD_GLOBAL              3 (NULL + np)
#              32 LOAD_ATTR                4 (linspace)
#              52 LOAD_CONST               1 (0)
#              54 LOAD_CONST               2 (10)
#              56 LOAD_CONST               3 (1000)
#              58 CALL                     3
#              66 STORE_FAST               2 (time)
# 
#  55          68 LOAD_GLOBAL              3 (NULL + np)
#              78 LOAD_ATTR                6 (ones)
#              98 LOAD_CONST               3 (1000)
#             100 CALL                     1
#             108 LOAD_CONST               4 (1.05)
#             110 BINARY_OP                5 (*)
#             114 STORE_FAST               3 (voltage)
# 
#  56         116 LOAD_CONST               5 (4.0)
#             118 STORE_FAST               4 (disturbance_time)
# 
#  57         120 BUILD_LIST               0
#             122 LOAD_CONST               6 ((0.1, 3.0, 0.75, 1.25))
#             124 LIST_EXTEND              1
#             126 BUILD_LIST               1
#             128 STORE_FAST               5 (judge_criteria)
# 
#  58         130 LOAD_FAST                1 (skill)
#             132 LOAD_ATTR                9 (NULL|self + _calculate_dv)
# 
#  59         152 LOAD_FAST                3 (voltage)
#             154 LOAD_FAST                2 (time)
#             156 LOAD_FAST                4 (disturbance_time)
#             158 LOAD_CONST               7 (0.5)
#             160 LOAD_FAST                5 (judge_criteria)
# 
#  58         162 CALL                     5
#             170 STORE_FAST               6 (result)
# 
#  61         172 LOAD_FAST                6 (result)
#             174 LOAD_CONST               8 ('v_steady')
#             176 BINARY_SUBSCR
#             180 STORE_FAST               7 (@py_assert1)
#             182 LOAD_CONST               4 (1.05)
#             184 STORE_FAST               8 (@py_assert3)
#             186 LOAD_FAST                7 (@py_assert1)
#             188 LOAD_FAST                8 (@py_assert3)
#             190 BINARY_OP               10 (-)
#             194 STORE_FAST               9 (@py_assert5)
#             196 LOAD_GLOBAL             11 (NULL + abs)
#             206 LOAD_FAST                9 (@py_assert5)
#             208 CALL                     1
#             216 STORE_FAST              10 (@py_assert6)
#             218 LOAD_CONST               9 (0.01)
#             220 STORE_FAST              11 (@py_assert9)
#             222 LOAD_FAST               10 (@py_assert6)
#             224 LOAD_FAST               11 (@py_assert9)
#             226 COMPARE_OP               2 (<)
#             230 STORE_FAST              12 (@py_assert8)
#             232 LOAD_FAST               12 (@py_assert8)
#             234 POP_JUMP_IF_TRUE       221 (to 678)
#             236 LOAD_GLOBAL             13 (NULL + @pytest_ar)
#             246 LOAD_ATTR               14 (_call_reprcompare)
#             266 LOAD_CONST              10 (('<',))
#             268 LOAD_FAST               12 (@py_assert8)
#             270 BUILD_TUPLE              1
#             272 LOAD_CONST              11 (('%(py7)s\n{%(py7)s = %(py0)s((%(py2)s - %(py4)s))\n} < %(py10)s',))
#             274 LOAD_FAST               10 (@py_assert6)
#             276 LOAD_FAST               11 (@py_assert9)
#             278 BUILD_TUPLE              2
#             280 CALL                     4
#             288 LOAD_CONST              12 ('abs')
#             290 LOAD_GLOBAL             17 (NULL + @py_builtins)
#             300 LOAD_ATTR               18 (locals)
#             320 CALL                     0
#             328 CONTAINS_OP              0
#             330 POP_JUMP_IF_TRUE        25 (to 382)
#             332 LOAD_GLOBAL             13 (NULL + @pytest_ar)
#             342 LOAD_ATTR               20 (_should_repr_global_name)
#             362 LOAD_GLOBAL             10 (abs)
#             372 CALL                     1
#             380 POP_JUMP_IF_FALSE       25 (to 432)
#         >>  382 LOAD_GLOBAL             13 (NULL + @pytest_ar)
#             392 LOAD_ATTR               22 (_saferepr)
#             412 LOAD_GLOBAL             10 (abs)
#             422 CALL                     1
#             430 JUMP_FORWARD             1 (to 434)
#         >>  432 LOAD_CONST              12 ('abs')
#         >>  434 LOAD_GLOBAL             13 (NULL + @pytest_ar)
#             444 LOAD_ATTR               22 (_saferepr)
#             464 LOAD_FAST                7 (@py_assert1)
#             466 CALL                     1
#             474 LOAD_GLOBAL             13 (NULL + @pytest_ar)
#             484 LOAD_ATTR               22 (_saferepr)
#             504 LOAD_FAST                8 (@py_assert3)
#             506 CALL                     1
#             514 LOAD_GLOBAL             13 (NULL + @pytest_ar)
#             524 LOAD_ATTR               22 (_saferepr)
#             544 LOAD_FAST               10 (@py_assert6)
#             546 CALL                     1
#             554 LOAD_GLOBAL             13 (NULL + @pytest_ar)
#             564 LOAD_ATTR               22 (_saferepr)
#             584 LOAD_FAST               11 (@py_assert9)
#             586 CALL                     1
#             594 LOAD_CONST              13 (('py0', 'py2', 'py4', 'py7', 'py10'))
#             596 BUILD_CONST_KEY_MAP      5
#             598 BINARY_OP                6 (%)
#             602 STORE_FAST              13 (@py_format11)
#             604 LOAD_CONST              14 ('assert %(py12)s')
#             606 LOAD_CONST              15 ('py12')
#             608 LOAD_FAST               13 (@py_format11)
#             610 BUILD_MAP                1
#             612 BINARY_OP                6 (%)
#             616 STORE_FAST              14 (@py_format13)
#             618 LOAD_GLOBAL             25 (NULL + AssertionError)
#             628 LOAD_GLOBAL             13 (NULL + @pytest_ar)
#             638 LOAD_ATTR               26 (_format_explanation)
#             658 LOAD_FAST               14 (@py_format13)
#             660 CALL                     1
#             668 CALL                     1
#             676 RAISE_VARARGS            1
#         >>  678 LOAD_CONST               0 (None)
#             680 COPY                     1
#             682 STORE_FAST               7 (@py_assert1)
#             684 COPY                     1
#             686 STORE_FAST               8 (@py_assert3)
#             688 COPY                     1
#             690 STORE_FAST               9 (@py_assert5)
#             692 COPY                     1
#             694 STORE_FAST              10 (@py_assert6)
#             696 COPY                     1
#             698 STORE_FAST              12 (@py_assert8)
#             700 STORE_FAST              11 (@py_assert9)
#             702 RETURN_CONST             0 (None)
# 
# Disassembly of <code object TestDisturbanceSeveritySI at 0x73cd945fea30, file "/home/chenying/researches/cloudpss-toolkit/cloudpss_skills_v2/tests/test_disturbance_severity.py", line 64>:
#  64           0 RESUME                   0
#               2 LOAD_NAME                0 (__name__)
#               4 STORE_NAME               1 (__module__)
#               6 LOAD_CONST               0 ('TestDisturbanceSeveritySI')
#               8 STORE_NAME               2 (__qualname__)
# 
#  65          10 LOAD_CONST               1 (<code object test_calculate_si at 0x3aefe140, file "/home/chenying/researches/cloudpss-toolkit/cloudpss_skills_v2/tests/test_disturbance_severity.py", line 65>)
#              12 MAKE_FUNCTION            0
#              14 STORE_NAME               3 (test_calculate_si)
# 
#  75          16 LOAD_CONST               2 (<code object test_calculate_si_no_deviation at 0x3af9e540, file "/home/chenying/researches/cloudpss-toolkit/cloudpss_skills_v2/tests/test_disturbance_severity.py", line 75>)
#              18 MAKE_FUNCTION            0
#              20 STORE_NAME               4 (test_calculate_si_no_deviation)
#              22 RETURN_CONST             3 (None)
# 
# Disassembly of <code object test_calculate_si at 0x3aefe140, file "/home/chenying/researches/cloudpss-toolkit/cloudpss_skills_v2/tests/test_disturbance_severity.py", line 65>:
#  65           0 RESUME                   0
# 
#  66           2 LOAD_GLOBAL              1 (NULL + DisturbanceSeveritySkill)
#              12 CALL                     0
#              20 STORE_FAST               1 (skill)
# 
#  67          22 LOAD_GLOBAL              3 (NULL + np)
#              32 LOAD_ATTR                4 (linspace)
#              52 LOAD_CONST               1 (0)
#              54 LOAD_CONST               2 (10)
#              56 LOAD_CONST               3 (10000)
#              58 CALL                     3
#              66 STORE_FAST               2 (time)
# 
#  68          68 LOAD_GLOBAL              3 (NULL + np)
#              78 LOAD_ATTR                6 (ones)
#              98 LOAD_CONST               3 (10000)
#             100 CALL                     1
#             108 STORE_FAST               3 (voltage)
# 
#  69         110 LOAD_CONST               4 (0.8)
#             112 LOAD_FAST                3 (voltage)
#             114 LOAD_CONST               5 (4000)
#             116 LOAD_CONST               6 (5000)
#             118 STORE_SLICE
# 
#  70         120 LOAD_FAST                1 (skill)
#             122 LOAD_ATTR                9 (NULL|self + _calculate_si)
# 
#  71         142 LOAD_FAST                3 (voltage)
#             144 LOAD_FAST                2 (time)
#             146 LOAD_CONST               7 (4.0)
#             148 LOAD_CONST               8 (0.5)
# 
#  70         150 KW_NAMES                 9 (('disturbance_time', 'pre_fault_window'))
#             152 CALL                     4
#             160 STORE_FAST               4 (si)
# 
#  73         162 LOAD_CONST               1 (0)
#             164 STORE_FAST               5 (@py_assert2)
#             166 LOAD_FAST                4 (si)
#             168 LOAD_FAST                5 (@py_assert2)
#             170 COMPARE_OP              68 (>)
#             174 STORE_FAST               6 (@py_assert1)
#             176 LOAD_FAST                6 (@py_assert1)
#             178 POP_JUMP_IF_TRUE       153 (to 486)
#             180 LOAD_GLOBAL             11 (NULL + @pytest_ar)
#             190 LOAD_ATTR               12 (_call_reprcompare)
#             210 LOAD_CONST              10 (('>',))
#             212 LOAD_FAST                6 (@py_assert1)
#             214 BUILD_TUPLE              1
#             216 LOAD_CONST              11 (('%(py0)s > %(py3)s',))
#             218 LOAD_FAST                4 (si)
#             220 LOAD_FAST                5 (@py_assert2)
#             222 BUILD_TUPLE              2
#             224 CALL                     4
#             232 LOAD_CONST              12 ('si')
#             234 LOAD_GLOBAL             15 (NULL + @py_builtins)
#             244 LOAD_ATTR               16 (locals)
#             264 CALL                     0
#             272 CONTAINS_OP              0
#             274 POP_JUMP_IF_TRUE        21 (to 318)
#             276 LOAD_GLOBAL             11 (NULL + @pytest_ar)
#             286 LOAD_ATTR               18 (_should_repr_global_name)
#             306 LOAD_FAST                4 (si)
#             308 CALL                     1
#             316 POP_JUMP_IF_FALSE       21 (to 360)
#         >>  318 LOAD_GLOBAL             11 (NULL + @pytest_ar)
#             328 LOAD_ATTR               20 (_saferepr)
#             348 LOAD_FAST                4 (si)
#             350 CALL                     1
#             358 JUMP_FORWARD             1 (to 362)
#         >>  360 LOAD_CONST              12 ('si')
#         >>  362 LOAD_GLOBAL             11 (NULL + @pytest_ar)
#             372 LOAD_ATTR               20 (_saferepr)
#             392 LOAD_FAST                5 (@py_assert2)
#             394 CALL                     1
#             402 LOAD_CONST              13 (('py0', 'py3'))
#             404 BUILD_CONST_KEY_MAP      2
#             406 BINARY_OP                6 (%)
#             410 STORE_FAST               7 (@py_format4)
#             412 LOAD_CONST              14 ('assert %(py5)s')
#             414 LOAD_CONST              15 ('py5')
#             416 LOAD_FAST                7 (@py_format4)
#             418 BUILD_MAP                1
#             420 BINARY_OP                6 (%)
#             424 STORE_FAST               8 (@py_format6)
#             426 LOAD_GLOBAL             23 (NULL + AssertionError)
#             436 LOAD_GLOBAL             11 (NULL + @pytest_ar)
#             446 LOAD_ATTR               24 (_format_explanation)
#             466 LOAD_FAST                8 (@py_format6)
#             468 CALL                     1
#             476 CALL                     1
#             484 RAISE_VARARGS            1
#         >>  486 LOAD_CONST               0 (None)
#             488 COPY                     1
#             490 STORE_FAST               6 (@py_assert1)
#             492 STORE_FAST               5 (@py_assert2)
#             494 RETURN_CONST             0 (None)
# 
# Disassembly of <code object test_calculate_si_no_deviation at 0x3af9e540, file "/home/chenying/researches/cloudpss-toolkit/cloudpss_skills_v2/tests/test_disturbance_severity.py", line 75>:
#  75           0 RESUME                   0
# 
#  76           2 LOAD_GLOBAL              1 (NULL + DisturbanceSeveritySkill)
#              12 CALL                     0
#              20 STORE_FAST               1 (skill)
# 
#  77          22 LOAD_GLOBAL              3 (NULL + np)
#              32 LOAD_ATTR                4 (linspace)
#              52 LOAD_CONST               1 (0)
#              54 LOAD_CONST               2 (10)
#              56 LOAD_CONST               3 (1000)
#              58 CALL                     3
#              66 STORE_FAST               2 (time)
# 
#  78          68 LOAD_GLOBAL              3 (NULL + np)
#              78 LOAD_ATTR                6 (ones)
#              98 LOAD_CONST               3 (1000)
#             100 CALL                     1
#             108 STORE_FAST               3 (voltage)
# 
#  79         110 LOAD_FAST                1 (skill)
#             112 LOAD_ATTR                9 (NULL|self + _calculate_si)
# 
#  80         132 LOAD_FAST                3 (voltage)
#             134 LOAD_FAST                2 (time)
#             136 LOAD_CONST               4 (4.0)
#             138 LOAD_CONST               5 (0.5)
# 
#  79         140 KW_NAMES                 6 (('disturbance_time', 'pre_fault_window'))
#             142 CALL                     4
#             150 STORE_FAST               4 (si)
# 
#  82         152 LOAD_CONST               7 (0.0)
#             154 STORE_FAST               5 (@py_assert2)
#             156 LOAD_FAST                4 (si)
#             158 LOAD_FAST                5 (@py_assert2)
#             160 COMPARE_OP              40 (==)
#             164 STORE_FAST               6 (@py_assert1)
#             166 LOAD_FAST                6 (@py_assert1)
#             168 POP_JUMP_IF_TRUE       153 (to 476)
#             170 LOAD_GLOBAL             11 (NULL + @pytest_ar)
#             180 LOAD_ATTR               12 (_call_reprcompare)
#             200 LOAD_CONST               8 (('==',))
#             202 LOAD_FAST                6 (@py_assert1)
#             204 BUILD_TUPLE              1
#             206 LOAD_CONST               9 (('%(py0)s == %(py3)s',))
#             208 LOAD_FAST                4 (si)
#             210 LOAD_FAST                5 (@py_assert2)
#             212 BUILD_TUPLE              2
#             214 CALL                     4
#             222 LOAD_CONST              10 ('si')
#             224 LOAD_GLOBAL             15 (NULL + @py_builtins)
#             234 LOAD_ATTR               16 (locals)
#             254 CALL                     0
#             262 CONTAINS_OP              0
#             264 POP_JUMP_IF_TRUE        21 (to 308)
#             266 LOAD_GLOBAL             11 (NULL + @pytest_ar)
#             276 LOAD_ATTR               18 (_should_repr_global_name)
#             296 LOAD_FAST                4 (si)
#             298 CALL                     1
#             306 POP_JUMP_IF_FALSE       21 (to 350)
#         >>  308 LOAD_GLOBAL             11 (NULL + @pytest_ar)
#             318 LOAD_ATTR               20 (_saferepr)
#             338 LOAD_FAST                4 (si)
#             340 CALL                     1
#             348 JUMP_FORWARD             1 (to 352)
#         >>  350 LOAD_CONST              10 ('si')
#         >>  352 LOAD_GLOBAL             11 (NULL + @pytest_ar)
#             362 LOAD_ATTR               20 (_saferepr)
#             382 LOAD_FAST                5 (@py_assert2)
#             384 CALL                     1
#             392 LOAD_CONST              11 (('py0', 'py3'))
#             394 BUILD_CONST_KEY_MAP      2
#             396 BINARY_OP                6 (%)
#             400 STORE_FAST               7 (@py_format4)
#             402 LOAD_CONST              12 ('assert %(py5)s')
#             404 LOAD_CONST              13 ('py5')
#             406 LOAD_FAST                7 (@py_format4)
#             408 BUILD_MAP                1
#             410 BINARY_OP                6 (%)
#             414 STORE_FAST               8 (@py_format6)
#             416 LOAD_GLOBAL             23 (NULL + AssertionError)
#             426 LOAD_GLOBAL             11 (NULL + @pytest_ar)
#             436 LOAD_ATTR               24 (_format_explanation)
#             456 LOAD_FAST                8 (@py_format6)
#             458 CALL                     1
#             466 CALL                     1
#             474 RAISE_VARARGS            1
#         >>  476 LOAD_CONST               0 (None)
#             478 COPY                     1
#             480 STORE_FAST               6 (@py_assert1)
#             482 STORE_FAST               5 (@py_assert2)
#             484 RETURN_CONST             0 (None)
# 
# Disassembly of <code object TestDisturbanceSeverityAssessment at 0x73cd945ff050, file "/home/chenying/researches/cloudpss-toolkit/cloudpss_skills_v2/tests/test_disturbance_severity.py", line 85>:
#  85           0 RESUME                   0
#               2 LOAD_NAME                0 (__name__)
#               4 STORE_NAME               1 (__module__)
#               6 LOAD_CONST               0 ('TestDisturbanceSeverityAssessment')
#               8 STORE_NAME               2 (__qualname__)
# 
#  86          10 LOAD_CONST               1 (<code object test_assess_severity_critical at 0x3afa23c0, file "/home/chenying/researches/cloudpss-toolkit/cloudpss_skills_v2/tests/test_disturbance_severity.py", line 86>)
#              12 MAKE_FUNCTION            0
#              14 STORE_NAME               3 (test_assess_severity_critical)
# 
#  90          16 LOAD_CONST               2 (<code object test_assess_severity_warning at 0x3af95770, file "/home/chenying/researches/cloudpss-toolkit/cloudpss_skills_v2/tests/test_disturbance_severity.py", line 90>)
#              18 MAKE_FUNCTION            0
#              20 STORE_NAME               4 (test_assess_severity_warning)
# 
#  94          22 LOAD_CONST               3 (<code object test_assess_severity_observe at 0x3af91360, file "/home/chenying/researches/cloudpss-toolkit/cloudpss_skills_v2/tests/test_disturbance_severity.py", line 94>)
#              24 MAKE_FUNCTION            0
#              26 STORE_NAME               5 (test_assess_severity_observe)
#              28 RETURN_CONST             4 (None)
# 
# Disassembly of <code object test_assess_severity_critical at 0x3afa23c0, file "/home/chenying/researches/cloudpss-toolkit/cloudpss_skills_v2/tests/test_disturbance_severity.py", line 86>:
#  86           0 RESUME                   0
# 
#  87           2 LOAD_GLOBAL              1 (NULL + DisturbanceSeveritySkill)
#              12 CALL                     0
#              20 STORE_FAST               1 (skill)
# 
#  88          22 LOAD_FAST                1 (skill)
#              24 LOAD_ATTR                2 (_assess_severity)
#              44 STORE_FAST               2 (@py_assert1)
#              46 LOAD_CONST               1 (0.1)
#              48 STORE_FAST               3 (@py_assert3)
#              50 LOAD_FAST                3 (@py_assert3)
#              52 UNARY_NEGATIVE
#              54 STORE_FAST               4 (@py_assert5)
#              56 LOAD_CONST               1 (0.1)
#              58 STORE_FAST               5 (@py_assert6)
#              60 LOAD_CONST               1 (0.1)
#              62 STORE_FAST               6 (@py_assert8)
#              64 PUSH_NULL
#              66 LOAD_FAST                2 (@py_assert1)
#              68 LOAD_FAST                4 (@py_assert5)
#              70 LOAD_FAST                5 (@py_assert6)
#              72 LOAD_FAST                6 (@py_assert8)
#              74 KW_NAMES                 2 (('dv_up', 'dv_down', 'si'))
#              76 CALL                     3
#              84 STORE_FAST               7 (@py_assert10)
#              86 LOAD_CONST               3 ('critical')
#              88 STORE_FAST               8 (@py_assert13)
#              90 LOAD_FAST                7 (@py_assert10)
#              92 LOAD_FAST                8 (@py_assert13)
#              94 COMPARE_OP              40 (==)
#              98 STORE_FAST               9 (@py_assert12)
#             100 LOAD_FAST                9 (@py_assert12)
#             102 POP_JUMP_IF_TRUE       253 (to 610)
#             104 LOAD_GLOBAL              5 (NULL + @pytest_ar)
#             114 LOAD_ATTR                6 (_call_reprcompare)
#             134 LOAD_CONST               4 (('==',))
#             136 LOAD_FAST                9 (@py_assert12)
#             138 BUILD_TUPLE              1
#             140 LOAD_CONST               5 (('%(py11)s\n{%(py11)s = %(py2)s\n{%(py2)s = %(py0)s._assess_severity\n}(dv_up=-%(py4)s, dv_down=%(py7)s, si=%(py9)s)\n} == %(py14)s',))
#             142 LOAD_FAST                7 (@py_assert10)
#             144 LOAD_FAST                8 (@py_assert13)
#             146 BUILD_TUPLE              2
#             148 CALL                     4
#             156 LOAD_CONST               6 ('skill')
#             158 LOAD_GLOBAL              9 (NULL + @py_builtins)
#             168 LOAD_ATTR               10 (locals)
#             188 CALL                     0
#             196 CONTAINS_OP              0
#             198 POP_JUMP_IF_TRUE        21 (to 242)
#             200 LOAD_GLOBAL              5 (NULL + @pytest_ar)
#             210 LOAD_ATTR               12 (_should_repr_global_name)
#             230 LOAD_FAST                1 (skill)
#             232 CALL                     1
#             240 POP_JUMP_IF_FALSE       21 (to 284)
#         >>  242 LOAD_GLOBAL              5 (NULL + @pytest_ar)
#             252 LOAD_ATTR               14 (_saferepr)
#             272 LOAD_FAST                1 (skill)
#             274 CALL                     1
#             282 JUMP_FORWARD             1 (to 286)
#         >>  284 LOAD_CONST               6 ('skill')
#         >>  286 LOAD_GLOBAL              5 (NULL + @pytest_ar)
#             296 LOAD_ATTR               14 (_saferepr)
#             316 LOAD_FAST                2 (@py_assert1)
#             318 CALL                     1
#             326 LOAD_GLOBAL              5 (NULL + @pytest_ar)
#             336 LOAD_ATTR               14 (_saferepr)
#             356 LOAD_FAST                3 (@py_assert3)
#             358 CALL                     1
#             366 LOAD_GLOBAL              5 (NULL + @pytest_ar)
#             376 LOAD_ATTR               14 (_saferepr)
#             396 LOAD_FAST                5 (@py_assert6)
#             398 CALL                     1
#             406 LOAD_GLOBAL              5 (NULL + @pytest_ar)
#             416 LOAD_ATTR               14 (_saferepr)
#             436 LOAD_FAST                6 (@py_assert8)
#             438 CALL                     1
#             446 LOAD_GLOBAL              5 (NULL + @pytest_ar)
#             456 LOAD_ATTR               14 (_saferepr)
#             476 LOAD_FAST                7 (@py_assert10)
#             478 CALL                     1
#             486 LOAD_GLOBAL              5 (NULL + @pytest_ar)
#             496 LOAD_ATTR               14 (_saferepr)
#             516 LOAD_FAST                8 (@py_assert13)
#             518 CALL                     1
#             526 LOAD_CONST               7 (('py0', 'py2', 'py4', 'py7', 'py9', 'py11', 'py14'))
#             528 BUILD_CONST_KEY_MAP      7
#             530 BINARY_OP                6 (%)
#             534 STORE_FAST              10 (@py_format15)
#             536 LOAD_CONST               8 ('assert %(py16)s')
#             538 LOAD_CONST               9 ('py16')
#             540 LOAD_FAST               10 (@py_format15)
#             542 BUILD_MAP                1
#             544 BINARY_OP                6 (%)
#             548 STORE_FAST              11 (@py_format17)
#             550 LOAD_GLOBAL             17 (NULL + AssertionError)
#             560 LOAD_GLOBAL              5 (NULL + @pytest_ar)
#             570 LOAD_ATTR               18 (_format_explanation)
#             590 LOAD_FAST               11 (@py_format17)
#             592 CALL                     1
#             600 CALL                     1
#             608 RAISE_VARARGS            1
#         >>  610 LOAD_CONST               0 (None)
#             612 COPY                     1
#             614 STORE_FAST               2 (@py_assert1)
#             616 COPY                     1
#             618 STORE_FAST               3 (@py_assert3)
#             620 COPY                     1
#             622 STORE_FAST               4 (@py_assert5)
#             624 COPY                     1
#             626 STORE_FAST               5 (@py_assert6)
#             628 COPY                     1
#             630 STORE_FAST               6 (@py_assert8)
#             632 COPY                     1
#             634 STORE_FAST               7 (@py_assert10)
#             636 COPY                     1
#             638 STORE_FAST               9 (@py_assert12)
#             640 STORE_FAST               8 (@py_assert13)
#             642 RETURN_CONST             0 (None)
# 
# Disassembly of <code object test_assess_severity_warning at 0x3af95770, file "/home/chenying/researches/cloudpss-toolkit/cloudpss_skills_v2/tests/test_disturbance_severity.py", line 90>:
#  90           0 RESUME                   0
# 
#  91           2 LOAD_GLOBAL              1 (NULL + DisturbanceSeveritySkill)
#              12 CALL                     0
#              20 STORE_FAST               1 (skill)
# 
#  92          22 LOAD_FAST                1 (skill)
#              24 LOAD_ATTR                2 (_assess_severity)
#              44 STORE_FAST               2 (@py_assert1)
#              46 LOAD_CONST               1 (0.1)
#              48 STORE_FAST               3 (@py_assert3)
#              50 LOAD_CONST               1 (0.1)
#              52 STORE_FAST               4 (@py_assert5)
#              54 LOAD_CONST               2 (0.8)
#              56 STORE_FAST               5 (@py_assert7)
#              58 PUSH_NULL
#              60 LOAD_FAST                2 (@py_assert1)
#              62 LOAD_FAST                3 (@py_assert3)
#              64 LOAD_FAST                4 (@py_assert5)
#              66 LOAD_FAST                5 (@py_assert7)
#              68 KW_NAMES                 3 (('dv_up', 'dv_down', 'si'))
#              70 CALL                     3
#              78 STORE_FAST               6 (@py_assert9)
#              80 LOAD_CONST               4 ('warning')
#              82 STORE_FAST               7 (@py_assert12)
#              84 LOAD_FAST                6 (@py_assert9)
#              86 LOAD_FAST                7 (@py_assert12)
#              88 COMPARE_OP              40 (==)
#              92 STORE_FAST               8 (@py_assert11)
#              94 LOAD_FAST                8 (@py_assert11)
#              96 POP_JUMP_IF_TRUE       253 (to 604)
#              98 LOAD_GLOBAL              5 (NULL + @pytest_ar)
#             108 LOAD_ATTR                6 (_call_reprcompare)
#             128 LOAD_CONST               5 (('==',))
#             130 LOAD_FAST                8 (@py_assert11)
#             132 BUILD_TUPLE              1
#             134 LOAD_CONST               6 (('%(py10)s\n{%(py10)s = %(py2)s\n{%(py2)s = %(py0)s._assess_severity\n}(dv_up=%(py4)s, dv_down=%(py6)s, si=%(py8)s)\n} == %(py13)s',))
#             136 LOAD_FAST                6 (@py_assert9)
#             138 LOAD_FAST                7 (@py_assert12)
#             140 BUILD_TUPLE              2
#             142 CALL                     4
#             150 LOAD_CONST               7 ('skill')
#             152 LOAD_GLOBAL              9 (NULL + @py_builtins)
#             162 LOAD_ATTR               10 (locals)
#             182 CALL                     0
#             190 CONTAINS_OP              0
#             192 POP_JUMP_IF_TRUE        21 (to 236)
#             194 LOAD_GLOBAL              5 (NULL + @pytest_ar)
#             204 LOAD_ATTR               12 (_should_repr_global_name)
#             224 LOAD_FAST                1 (skill)
#             226 CALL                     1
#             234 POP_JUMP_IF_FALSE       21 (to 278)
#         >>  236 LOAD_GLOBAL              5 (NULL + @pytest_ar)
#             246 LOAD_ATTR               14 (_saferepr)
#             266 LOAD_FAST                1 (skill)
#             268 CALL                     1
#             276 JUMP_FORWARD             1 (to 280)
#         >>  278 LOAD_CONST               7 ('skill')
#         >>  280 LOAD_GLOBAL              5 (NULL + @pytest_ar)
#             290 LOAD_ATTR               14 (_saferepr)
#             310 LOAD_FAST                2 (@py_assert1)
#             312 CALL                     1
#             320 LOAD_GLOBAL              5 (NULL + @pytest_ar)
#             330 LOAD_ATTR               14 (_saferepr)
#             350 LOAD_FAST                3 (@py_assert3)
#             352 CALL                     1
#             360 LOAD_GLOBAL              5 (NULL + @pytest_ar)
#             370 LOAD_ATTR               14 (_saferepr)
#             390 LOAD_FAST                4 (@py_assert5)
#             392 CALL                     1
#             400 LOAD_GLOBAL              5 (NULL + @pytest_ar)
#             410 LOAD_ATTR               14 (_saferepr)
#             430 LOAD_FAST                5 (@py_assert7)
#             432 CALL                     1
#             440 LOAD_GLOBAL              5 (NULL + @pytest_ar)
#             450 LOAD_ATTR               14 (_saferepr)
#             470 LOAD_FAST                6 (@py_assert9)
#             472 CALL                     1
#             480 LOAD_GLOBAL              5 (NULL + @pytest_ar)
#             490 LOAD_ATTR               14 (_saferepr)
#             510 LOAD_FAST                7 (@py_assert12)
#             512 CALL                     1
#             520 LOAD_CONST               8 (('py0', 'py2', 'py4', 'py6', 'py8', 'py10', 'py13'))
#             522 BUILD_CONST_KEY_MAP      7
#             524 BINARY_OP                6 (%)
#             528 STORE_FAST               9 (@py_format14)
#             530 LOAD_CONST               9 ('assert %(py15)s')
#             532 LOAD_CONST              10 ('py15')
#             534 LOAD_FAST                9 (@py_format14)
#             536 BUILD_MAP                1
#             538 BINARY_OP                6 (%)
#             542 STORE_FAST              10 (@py_format16)
#             544 LOAD_GLOBAL             17 (NULL + AssertionError)
#             554 LOAD_GLOBAL              5 (NULL + @pytest_ar)
#             564 LOAD_ATTR               18 (_format_explanation)
#             584 LOAD_FAST               10 (@py_format16)
#             586 CALL                     1
#             594 CALL                     1
#             602 RAISE_VARARGS            1
#         >>  604 LOAD_CONST               0 (None)
#             606 COPY                     1
#             608 STORE_FAST               2 (@py_assert1)
#             610 COPY                     1
#             612 STORE_FAST               3 (@py_assert3)
#             614 COPY                     1
#             616 STORE_FAST               4 (@py_assert5)
#             618 COPY                     1
#             620 STORE_FAST               5 (@py_assert7)
#             622 COPY                     1
#             624 STORE_FAST               6 (@py_assert9)
#             626 COPY                     1
#             628 STORE_FAST               8 (@py_assert11)
#             630 STORE_FAST               7 (@py_assert12)
#             632 RETURN_CONST             0 (None)
# 
# Disassembly of <code object test_assess_severity_observe at 0x3af91360, file "/home/chenying/researches/cloudpss-toolkit/cloudpss_skills_v2/tests/test_disturbance_severity.py", line 94>:
#  94           0 RESUME                   0
# 
#  95           2 LOAD_GLOBAL              1 (NULL + DisturbanceSeveritySkill)
#              12 CALL                     0
#              20 STORE_FAST               1 (skill)
# 
#  96          22 LOAD_FAST                1 (skill)
#              24 LOAD_ATTR                2 (_assess_severity)
#              44 STORE_FAST               2 (@py_assert1)
#              46 LOAD_CONST               1 (0.1)
#              48 STORE_FAST               3 (@py_assert3)
#              50 LOAD_CONST               1 (0.1)
#              52 STORE_FAST               4 (@py_assert5)
#              54 LOAD_CONST               1 (0.1)
#              56 STORE_FAST               5 (@py_assert7)
#              58 PUSH_NULL
#              60 LOAD_FAST                2 (@py_assert1)
#              62 LOAD_FAST                3 (@py_assert3)
#              64 LOAD_FAST                4 (@py_assert5)
#              66 LOAD_FAST                5 (@py_assert7)
#              68 KW_NAMES                 2 (('dv_up', 'dv_down', 'si'))
#              70 CALL                     3
#              78 STORE_FAST               6 (@py_assert9)
#              80 LOAD_CONST               3 ('observe')
#              82 STORE_FAST               7 (@py_assert12)
#              84 LOAD_FAST                6 (@py_assert9)
#              86 LOAD_FAST                7 (@py_assert12)
#              88 COMPARE_OP              40 (==)
#              92 STORE_FAST               8 (@py_assert11)
#              94 LOAD_FAST                8 (@py_assert11)
#              96 POP_JUMP_IF_TRUE       253 (to 604)
#              98 LOAD_GLOBAL              5 (NULL + @pytest_ar)
#             108 LOAD_ATTR                6 (_call_reprcompare)
#             128 LOAD_CONST               4 (('==',))
#             130 LOAD_FAST                8 (@py_assert11)
#             132 BUILD_TUPLE              1
#             134 LOAD_CONST               5 (('%(py10)s\n{%(py10)s = %(py2)s\n{%(py2)s = %(py0)s._assess_severity\n}(dv_up=%(py4)s, dv_down=%(py6)s, si=%(py8)s)\n} == %(py13)s',))
#             136 LOAD_FAST                6 (@py_assert9)
#             138 LOAD_FAST                7 (@py_assert12)
#             140 BUILD_TUPLE              2
#             142 CALL                     4
#             150 LOAD_CONST               6 ('skill')
#             152 LOAD_GLOBAL              9 (NULL + @py_builtins)
#             162 LOAD_ATTR               10 (locals)
#             182 CALL                     0
#             190 CONTAINS_OP              0
#             192 POP_JUMP_IF_TRUE        21 (to 236)
#             194 LOAD_GLOBAL              5 (NULL + @pytest_ar)
#             204 LOAD_ATTR               12 (_should_repr_global_name)
#             224 LOAD_FAST                1 (skill)
#             226 CALL                     1
#             234 POP_JUMP_IF_FALSE       21 (to 278)
#         >>  236 LOAD_GLOBAL              5 (NULL + @pytest_ar)
#             246 LOAD_ATTR               14 (_saferepr)
#             266 LOAD_FAST                1 (skill)
#             268 CALL                     1
#             276 JUMP_FORWARD             1 (to 280)
#         >>  278 LOAD_CONST               6 ('skill')
#         >>  280 LOAD_GLOBAL              5 (NULL + @pytest_ar)
#             290 LOAD_ATTR               14 (_saferepr)
#             310 LOAD_FAST                2 (@py_assert1)
#             312 CALL                     1
#             320 LOAD_GLOBAL              5 (NULL + @pytest_ar)
#             330 LOAD_ATTR               14 (_saferepr)
#             350 LOAD_FAST                3 (@py_assert3)
#             352 CALL                     1
#             360 LOAD_GLOBAL              5 (NULL + @pytest_ar)
#             370 LOAD_ATTR               14 (_saferepr)
#             390 LOAD_FAST                4 (@py_assert5)
#             392 CALL                     1
#             400 LOAD_GLOBAL              5 (NULL + @pytest_ar)
#             410 LOAD_ATTR               14 (_saferepr)
#             430 LOAD_FAST                5 (@py_assert7)
#             432 CALL                     1
#             440 LOAD_GLOBAL              5 (NULL + @pytest_ar)
#             450 LOAD_ATTR               14 (_saferepr)
#             470 LOAD_FAST                6 (@py_assert9)
#             472 CALL                     1
#             480 LOAD_GLOBAL              5 (NULL + @pytest_ar)
#             490 LOAD_ATTR               14 (_saferepr)
#             510 LOAD_FAST                7 (@py_assert12)
#             512 CALL                     1
#             520 LOAD_CONST               7 (('py0', 'py2', 'py4', 'py6', 'py8', 'py10', 'py13'))
#             522 BUILD_CONST_KEY_MAP      7
#             524 BINARY_OP                6 (%)
#             528 STORE_FAST               9 (@py_format14)
#             530 LOAD_CONST               8 ('assert %(py15)s')
#             532 LOAD_CONST               9 ('py15')
#             534 LOAD_FAST                9 (@py_format14)
#             536 BUILD_MAP                1
#             538 BINARY_OP                6 (%)
#             542 STORE_FAST              10 (@py_format16)
#             544 LOAD_GLOBAL             17 (NULL + AssertionError)
#             554 LOAD_GLOBAL              5 (NULL + @pytest_ar)
#             564 LOAD_ATTR               18 (_format_explanation)
#             584 LOAD_FAST               10 (@py_format16)
#             586 CALL                     1
#             594 CALL                     1
#             602 RAISE_VARARGS            1
#         >>  604 LOAD_CONST               0 (None)
#             606 COPY                     1
#             608 STORE_FAST               2 (@py_assert1)
#             610 COPY                     1
#             612 STORE_FAST               3 (@py_assert3)
#             614 COPY                     1
#             616 STORE_FAST               4 (@py_assert5)
#             618 COPY                     1
#             620 STORE_FAST               5 (@py_assert7)
#             622 COPY                     1
#             624 STORE_FAST               6 (@py_assert9)
#             626 COPY                     1
#             628 STORE_FAST               8 (@py_assert11)
#             630 STORE_FAST               7 (@py_assert12)
#             632 RETURN_CONST             0 (None)
# 
# Disassembly of <code object TestDisturbanceSeverityWeakPoints at 0x73cd945fe6b0, file "/home/chenying/researches/cloudpss-toolkit/cloudpss_skills_v2/tests/test_disturbance_severity.py", line 99>:
#  99           0 RESUME                   0
#               2 LOAD_NAME                0 (__name__)
#               4 STORE_NAME               1 (__module__)
#               6 LOAD_CONST               0 ('TestDisturbanceSeverityWeakPoints')
#               8 STORE_NAME               2 (__qualname__)
# 
# 100          10 LOAD_CONST               1 (<code object test_identify_weak_points at 0x3afac750, file "/home/chenying/researches/cloudpss-toolkit/cloudpss_skills_v2/tests/test_disturbance_severity.py", line 100>)
#              12 MAKE_FUNCTION            0
#              14 STORE_NAME               3 (test_identify_weak_points)
#              16 RETURN_CONST             2 (None)
# 
# Disassembly of <code object test_identify_weak_points at 0x3afac750, file "/home/chenying/researches/cloudpss-toolkit/cloudpss_skills_v2/tests/test_disturbance_severity.py", line 100>:
# 100           0 RESUME                   0
# 
# 101           2 LOAD_GLOBAL              1 (NULL + DisturbanceSeveritySkill)
#              12 CALL                     0
#              20 STORE_FAST               1 (skill)
# 
# 103          22 LOAD_CONST               1 ('Bus1')
#              24 LOAD_CONST               2 (0.1)
#              26 LOAD_CONST               2 (0.1)
#              28 LOAD_CONST               3 (('dv_up', 'dv_down'))
#              30 BUILD_CONST_KEY_MAP      2
#              32 LOAD_CONST               2 (0.1)
#              34 LOAD_CONST               4 (('name', 'dv', 'si'))
#              36 BUILD_CONST_KEY_MAP      3
# 
# 104          38 LOAD_CONST               5 ('Bus2')
#              40 LOAD_CONST               6 (-0.1)
#              42 LOAD_CONST               2 (0.1)
#              44 LOAD_CONST               3 (('dv_up', 'dv_down'))
#              46 BUILD_CONST_KEY_MAP      2
#              48 LOAD_CONST               7 (0.8)
#              50 LOAD_CONST               4 (('name', 'dv', 'si'))
#              52 BUILD_CONST_KEY_MAP      3
# 
# 105          54 LOAD_CONST               8 ('Bus3')
#              56 LOAD_CONST               9 (0.2)
#              58 LOAD_CONST               9 (0.2)
#              60 LOAD_CONST               3 (('dv_up', 'dv_down'))
#              62 BUILD_CONST_KEY_MAP      2
#              64 LOAD_CONST              10 (0.05)
#              66 LOAD_CONST               4 (('name', 'dv', 'si'))
#              68 BUILD_CONST_KEY_MAP      3
# 
# 102          70 BUILD_LIST               3
#              72 STORE_FAST               2 (results)
# 
# 107          74 LOAD_FAST                1 (skill)
#              76 LOAD_ATTR                3 (NULL|self + _identify_weak_points)
#              96 LOAD_FAST                2 (results)
#              98 CALL                     1
#             106 STORE_FAST               3 (weak)
# 
# 108         108 LOAD_GLOBAL              5 (NULL + len)
#             118 LOAD_FAST                3 (weak)
#             120 CALL                     1
#             128 STORE_FAST               4 (@py_assert2)
#             130 LOAD_CONST              11 (1)
#             132 STORE_FAST               5 (@py_assert5)
#             134 LOAD_FAST                4 (@py_assert2)
#             136 LOAD_FAST                5 (@py_assert5)
#             138 COMPARE_OP              40 (==)
#             142 STORE_FAST               6 (@py_assert4)
#             144 LOAD_FAST                6 (@py_assert4)
#             146 POP_JUMP_IF_TRUE       246 (to 640)
#             148 LOAD_GLOBAL              7 (NULL + @pytest_ar)
#             158 LOAD_ATTR                8 (_call_reprcompare)
#             178 LOAD_CONST              12 (('==',))
#             180 LOAD_FAST                6 (@py_assert4)
#             182 BUILD_TUPLE              1
#             184 LOAD_CONST              13 (('%(py3)s\n{%(py3)s = %(py0)s(%(py1)s)\n} == %(py6)s',))
#             186 LOAD_FAST                4 (@py_assert2)
#             188 LOAD_FAST                5 (@py_assert5)
#             190 BUILD_TUPLE              2
#             192 CALL                     4
#             200 LOAD_CONST              14 ('len')
#             202 LOAD_GLOBAL             11 (NULL + @py_builtins)
#             212 LOAD_ATTR               12 (locals)
#             232 CALL                     0
#             240 CONTAINS_OP              0
#             242 POP_JUMP_IF_TRUE        25 (to 294)
#             244 LOAD_GLOBAL              7 (NULL + @pytest_ar)
#             254 LOAD_ATTR               14 (_should_repr_global_name)
#             274 LOAD_GLOBAL              4 (len)
#             284 CALL                     1
#             292 POP_JUMP_IF_FALSE       25 (to 344)
#         >>  294 LOAD_GLOBAL              7 (NULL + @pytest_ar)
#             304 LOAD_ATTR               16 (_saferepr)
#             324 LOAD_GLOBAL              4 (len)
#             334 CALL                     1
#             342 JUMP_FORWARD             1 (to 346)
#         >>  344 LOAD_CONST              14 ('len')
#         >>  346 LOAD_CONST              15 ('weak')
#             348 LOAD_GLOBAL             11 (NULL + @py_builtins)
#             358 LOAD_ATTR               12 (locals)
#             378 CALL                     0
#             386 CONTAINS_OP              0
#             388 POP_JUMP_IF_TRUE        21 (to 432)
#             390 LOAD_GLOBAL              7 (NULL + @pytest_ar)
#             400 LOAD_ATTR               14 (_should_repr_global_name)
#             420 LOAD_FAST                3 (weak)
#             422 CALL                     1
#             430 POP_JUMP_IF_FALSE       21 (to 474)
#         >>  432 LOAD_GLOBAL              7 (NULL + @pytest_ar)
#             442 LOAD_ATTR               16 (_saferepr)
#             462 LOAD_FAST                3 (weak)
#             464 CALL                     1
#             472 JUMP_FORWARD             1 (to 476)
#         >>  474 LOAD_CONST              15 ('weak')
#         >>  476 LOAD_GLOBAL              7 (NULL + @pytest_ar)
#             486 LOAD_ATTR               16 (_saferepr)
#             506 LOAD_FAST                4 (@py_assert2)
#             508 CALL                     1
#             516 LOAD_GLOBAL              7 (NULL + @pytest_ar)
#             526 LOAD_ATTR               16 (_saferepr)
#             546 LOAD_FAST                5 (@py_assert5)
#             548 CALL                     1
#             556 LOAD_CONST              16 (('py0', 'py1', 'py3', 'py6'))
#             558 BUILD_CONST_KEY_MAP      4
#             560 BINARY_OP                6 (%)
#             564 STORE_FAST               7 (@py_format7)
#             566 LOAD_CONST              17 ('assert %(py8)s')
#             568 LOAD_CONST              18 ('py8')
#             570 LOAD_FAST                7 (@py_format7)
#             572 BUILD_MAP                1
#             574 BINARY_OP                6 (%)
#             578 STORE_FAST               8 (@py_format9)
#             580 LOAD_GLOBAL             19 (NULL + AssertionError)
#             590 LOAD_GLOBAL              7 (NULL + @pytest_ar)
#             600 LOAD_ATTR               20 (_format_explanation)
#             620 LOAD_FAST                8 (@py_format9)
#             622 CALL                     1
#             630 CALL                     1
#             638 RAISE_VARARGS            1
#         >>  640 LOAD_CONST               0 (None)
#             642 COPY                     1
#             644 STORE_FAST               4 (@py_assert2)
#             646 COPY                     1
#             648 STORE_FAST               6 (@py_assert4)
#             650 STORE_FAST               5 (@py_assert5)
# 
# 109         652 LOAD_FAST                3 (weak)
#             654 LOAD_CONST              19 (0)
#             656 BINARY_SUBSCR
#             660 LOAD_CONST              20 ('name')
#             662 BINARY_SUBSCR
#             666 STORE_FAST               9 (@py_assert0)
#             668 LOAD_CONST               5 ('Bus2')
#             670 STORE_FAST              10 (@py_assert3)
#             672 LOAD_FAST                9 (@py_assert0)
#             674 LOAD_FAST               10 (@py_assert3)
#             676 COMPARE_OP              40 (==)
#             680 STORE_FAST               4 (@py_assert2)
#             682 LOAD_FAST                4 (@py_assert2)
#             684 POP_JUMP_IF_TRUE       108 (to 902)
#             686 LOAD_GLOBAL              7 (NULL + @pytest_ar)
#             696 LOAD_ATTR                8 (_call_reprcompare)
#             716 LOAD_CONST              12 (('==',))
#             718 LOAD_FAST                4 (@py_assert2)
#             720 BUILD_TUPLE              1
#             722 LOAD_CONST              21 (('%(py1)s == %(py4)s',))
#             724 LOAD_FAST                9 (@py_assert0)
#             726 LOAD_FAST               10 (@py_assert3)
#             728 BUILD_TUPLE              2
#             730 CALL                     4
#             738 LOAD_GLOBAL              7 (NULL + @pytest_ar)
#             748 LOAD_ATTR               16 (_saferepr)
#             768 LOAD_FAST                9 (@py_assert0)
#             770 CALL                     1
#             778 LOAD_GLOBAL              7 (NULL + @pytest_ar)
#             788 LOAD_ATTR               16 (_saferepr)
#             808 LOAD_FAST               10 (@py_assert3)
#             810 CALL                     1
#             818 LOAD_CONST              22 (('py1', 'py4'))
#             820 BUILD_CONST_KEY_MAP      2
#             822 BINARY_OP                6 (%)
#             826 STORE_FAST              11 (@py_format5)
#             828 LOAD_CONST              23 ('assert %(py6)s')
#             830 LOAD_CONST              24 ('py6')
#             832 LOAD_FAST               11 (@py_format5)
#             834 BUILD_MAP                1
#             836 BINARY_OP                6 (%)
#             840 STORE_FAST               7 (@py_format7)
#             842 LOAD_GLOBAL             19 (NULL + AssertionError)
#             852 LOAD_GLOBAL              7 (NULL + @pytest_ar)
#             862 LOAD_ATTR               20 (_format_explanation)
#             882 LOAD_FAST                7 (@py_format7)
#             884 CALL                     1
#             892 CALL                     1
#             900 RAISE_VARARGS            1
#         >>  902 LOAD_CONST               0 (None)
#             904 COPY                     1
#             906 STORE_FAST               9 (@py_assert0)
#             908 COPY                     1
#             910 STORE_FAST               4 (@py_assert2)
#             912 STORE_FAST              10 (@py_assert3)
#             914 RETURN_CONST             0 (None)
# 
# Disassembly of <code object TestDisturbanceSeverityRun at 0x73cd945fe330, file "/home/chenying/researches/cloudpss-toolkit/cloudpss_skills_v2/tests/test_disturbance_severity.py", line 112>:
# 112           0 RESUME                   0
#               2 LOAD_NAME                0 (__name__)
#               4 STORE_NAME               1 (__module__)
#               6 LOAD_CONST               0 ('TestDisturbanceSeverityRun')
#               8 STORE_NAME               2 (__qualname__)
# 
# 113          10 LOAD_CONST               1 (<code object test_run_invalid_config_returns_failure at 0x3afa13e0, file "/home/chenying/researches/cloudpss-toolkit/cloudpss_skills_v2/tests/test_disturbance_severity.py", line 113>)
#              12 MAKE_FUNCTION            0
#              14 STORE_NAME               3 (test_run_invalid_config_returns_failure)
#              16 RETURN_CONST             2 (None)
# 
# Disassembly of <code object test_run_invalid_config_returns_failure at 0x3afa13e0, file "/home/chenying/researches/cloudpss-toolkit/cloudpss_skills_v2/tests/test_disturbance_severity.py", line 113>:
# 113           0 RESUME                   0
# 
# 114           2 LOAD_GLOBAL              1 (NULL + DisturbanceSeveritySkill)
#              12 CALL                     0
#              20 STORE_FAST               1 (skill)
# 
# 115          22 LOAD_FAST                1 (skill)
#              24 LOAD_ATTR                3 (NULL|self + run)
#              44 BUILD_MAP                0
#              46 CALL                     1
#              54 STORE_FAST               2 (result)
# 
# 116          56 LOAD_FAST                2 (result)
#              58 LOAD_ATTR                4 (status)
#              78 STORE_FAST               3 (@py_assert1)
#              80 LOAD_FAST                3 (@py_assert1)
#              82 LOAD_ATTR                6 (value)
#             102 STORE_FAST               4 (@py_assert3)
#             104 LOAD_CONST               1 ('FAILED')
#             106 LOAD_CONST               2 ('failed')
#             108 BUILD_LIST               2
#             110 STORE_FAST               5 (@py_assert6)
#             112 LOAD_FAST                4 (@py_assert3)
#             114 LOAD_FAST                5 (@py_assert6)
#             116 CONTAINS_OP              0
#             118 STORE_FAST               6 (@py_assert5)
#             120 LOAD_FAST                6 (@py_assert5)
#             122 POP_JUMP_IF_TRUE       193 (to 510)
#             124 LOAD_GLOBAL              9 (NULL + @pytest_ar)
#             134 LOAD_ATTR               10 (_call_reprcompare)
#             154 LOAD_CONST               3 (('in',))
#             156 LOAD_FAST                6 (@py_assert5)
#             158 BUILD_TUPLE              1
#             160 LOAD_CONST               4 (('%(py4)s\n{%(py4)s = %(py2)s\n{%(py2)s = %(py0)s.status\n}.value\n} in %(py7)s',))
#             162 LOAD_FAST                4 (@py_assert3)
#             164 LOAD_FAST                5 (@py_assert6)
#             166 BUILD_TUPLE              2
#             168 CALL                     4
#             176 LOAD_CONST               5 ('result')
#             178 LOAD_GLOBAL             13 (NULL + @py_builtins)
#             188 LOAD_ATTR               14 (locals)
#             208 CALL                     0
#             216 CONTAINS_OP              0
#             218 POP_JUMP_IF_TRUE        21 (to 262)
#             220 LOAD_GLOBAL              9 (NULL + @pytest_ar)
#             230 LOAD_ATTR               16 (_should_repr_global_name)
#             250 LOAD_FAST                2 (result)
#             252 CALL                     1
#             260 POP_JUMP_IF_FALSE       21 (to 304)
#         >>  262 LOAD_GLOBAL              9 (NULL + @pytest_ar)
#             272 LOAD_ATTR               18 (_saferepr)
#             292 LOAD_FAST                2 (result)
#             294 CALL                     1
#             302 JUMP_FORWARD             1 (to 306)
#         >>  304 LOAD_CONST               5 ('result')
#         >>  306 LOAD_GLOBAL              9 (NULL + @pytest_ar)
#             316 LOAD_ATTR               18 (_saferepr)
#             336 LOAD_FAST                3 (@py_assert1)
#             338 CALL                     1
#             346 LOAD_GLOBAL              9 (NULL + @pytest_ar)
#             356 LOAD_ATTR               18 (_saferepr)
#             376 LOAD_FAST                4 (@py_assert3)
#             378 CALL                     1
#             386 LOAD_GLOBAL              9 (NULL + @pytest_ar)
#             396 LOAD_ATTR               18 (_saferepr)
#             416 LOAD_FAST                5 (@py_assert6)
#             418 CALL                     1
#             426 LOAD_CONST               6 (('py0', 'py2', 'py4', 'py7'))
#             428 BUILD_CONST_KEY_MAP      4
#             430 BINARY_OP                6 (%)
#             434 STORE_FAST               7 (@py_format8)
#             436 LOAD_CONST               7 ('assert %(py9)s')
#             438 LOAD_CONST               8 ('py9')
#             440 LOAD_FAST                7 (@py_format8)
#             442 BUILD_MAP                1
#             444 BINARY_OP                6 (%)
#             448 STORE_FAST               8 (@py_format10)
#             450 LOAD_GLOBAL             21 (NULL + AssertionError)
#             460 LOAD_GLOBAL              9 (NULL + @pytest_ar)
#             470 LOAD_ATTR               22 (_format_explanation)
#             490 LOAD_FAST                8 (@py_format10)
#             492 CALL                     1
#             500 CALL                     1
#             508 RAISE_VARARGS            1
#         >>  510 LOAD_CONST               0 (None)
#             512 COPY                     1
#             514 STORE_FAST               3 (@py_assert1)
#             516 COPY                     1
#             518 STORE_FAST               4 (@py_assert3)
#             520 COPY                     1
#             522 STORE_FAST               6 (@py_assert5)
#             524 STORE_FAST               5 (@py_assert6)
#             526 RETURN_CONST             0 (None)
# 