# Recovered from: /home/chenying/researches/cloudpss-toolkit/cloudpss_skills_v2/tests/__pycache__/test_emt_n1_screening.cpython-312-pytest-9.0.2.pyc
# Original source: /home/chenying/researches/cloudpss-toolkit/cloudpss_skills_v2/tests/test_emt_n1_screening.py
# WARNING: This file was reconstructed from .pyc bytecode.
# The structure is accurate but implementation details may need manual review.


def TestEmtN1Validation():
    """TestEmtN1Validation"""
pass  # TODO: restore


def TestEmtN1Severity():
    """TestEmtN1Severity"""
pass  # TODO: restore


def TestEmtN1PostfaultGap():
    """TestEmtN1PostfaultGap"""
pass  # TODO: restore


def TestEmtN1Ranking():
    """TestEmtN1Ranking"""
pass  # TODO: restore


def TestEmtN1Run():
    """TestEmtN1Run"""
pass  # TODO: restore



# === FULL DISASSEMBLY (for manual reconstruction) ===
#   0           0 RESUME                   0
# 
#   1           2 LOAD_CONST               0 ('Tests for EmtN1ScreeningSkill v2.')
#               4 STORE_NAME               0 (__doc__)
# 
#   3           6 LOAD_CONST               1 (0)
#               8 LOAD_CONST               2 (None)
#              10 IMPORT_NAME              1 (builtins)
#              12 STORE_NAME               2 (@py_builtins)
#              14 LOAD_CONST               1 (0)
#              16 LOAD_CONST               2 (None)
#              18 IMPORT_NAME              3 (_pytest.assertion.rewrite)
#              20 IMPORT_FROM              4 (assertion)
#              22 SWAP                     2
#              24 POP_TOP
#              26 IMPORT_FROM              5 (rewrite)
#              28 STORE_NAME               6 (@pytest_ar)
#              30 POP_TOP
#              32 LOAD_CONST               1 (0)
#              34 LOAD_CONST               2 (None)
#              36 IMPORT_NAME              7 (pytest)
#              38 STORE_NAME               7 (pytest)
# 
#   4          40 LOAD_CONST               1 (0)
#              42 LOAD_CONST               3 (('EmtN1ScreeningSkill',))
#              44 IMPORT_NAME              8 (cloudpss_skills_v2.skills.emt_n1_screening)
#              46 IMPORT_FROM              9 (EmtN1ScreeningSkill)
#              48 STORE_NAME               9 (EmtN1ScreeningSkill)
#              50 POP_TOP
# 
#   7          52 PUSH_NULL
#              54 LOAD_BUILD_CLASS
#              56 LOAD_CONST               4 (<code object TestEmtN1Validation at 0x73cd945fe090, file "/home/chenying/researches/cloudpss-toolkit/cloudpss_skills_v2/tests/test_emt_n1_screening.py", line 7>)
#              58 MAKE_FUNCTION            0
#              60 LOAD_CONST               5 ('TestEmtN1Validation')
#              62 CALL                     2
#              70 STORE_NAME              10 (TestEmtN1Validation)
# 
#  20          72 PUSH_NULL
#              74 LOAD_BUILD_CLASS
#              76 LOAD_CONST               6 (<code object TestEmtN1Severity at 0x73cd945fc110, file "/home/chenying/researches/cloudpss-toolkit/cloudpss_skills_v2/tests/test_emt_n1_screening.py", line 20>)
#              78 MAKE_FUNCTION            0
#              80 LOAD_CONST               7 ('TestEmtN1Severity')
#              82 CALL                     2
#              90 STORE_NAME              11 (TestEmtN1Severity)
# 
#  37          92 PUSH_NULL
#              94 LOAD_BUILD_CLASS
#              96 LOAD_CONST               8 (<code object TestEmtN1PostfaultGap at 0x73cd945fdfb0, file "/home/chenying/researches/cloudpss-toolkit/cloudpss_skills_v2/tests/test_emt_n1_screening.py", line 37>)
#              98 MAKE_FUNCTION            0
#             100 LOAD_CONST               9 ('TestEmtN1PostfaultGap')
#             102 CALL                     2
#             110 STORE_NAME              12 (TestEmtN1PostfaultGap)
# 
#  49         112 PUSH_NULL
#             114 LOAD_BUILD_CLASS
#             116 LOAD_CONST              10 (<code object TestEmtN1Ranking at 0x73cd945fedb0, file "/home/chenying/researches/cloudpss-toolkit/cloudpss_skills_v2/tests/test_emt_n1_screening.py", line 49>)
#             118 MAKE_FUNCTION            0
#             120 LOAD_CONST              11 ('TestEmtN1Ranking')
#             122 CALL                     2
#             130 STORE_NAME              13 (TestEmtN1Ranking)
# 
#  82         132 PUSH_NULL
#             134 LOAD_BUILD_CLASS
#             136 LOAD_CONST              12 (<code object TestEmtN1Run at 0x73cd945ff210, file "/home/chenying/researches/cloudpss-toolkit/cloudpss_skills_v2/tests/test_emt_n1_screening.py", line 82>)
#             138 MAKE_FUNCTION            0
#             140 LOAD_CONST              13 ('TestEmtN1Run')
#             142 CALL                     2
#             150 STORE_NAME              14 (TestEmtN1Run)
#             152 RETURN_CONST             2 (None)
# 
# Disassembly of <code object TestEmtN1Validation at 0x73cd945fe090, file "/home/chenying/researches/cloudpss-toolkit/cloudpss_skills_v2/tests/test_emt_n1_screening.py", line 7>:
#   7           0 RESUME                   0
#               2 LOAD_NAME                0 (__name__)
#               4 STORE_NAME               1 (__module__)
#               6 LOAD_CONST               0 ('TestEmtN1Validation')
#               8 STORE_NAME               2 (__qualname__)
# 
#   8          10 LOAD_CONST               1 (<code object test_validate_missing_model at 0x3afa3fb0, file "/home/chenying/researches/cloudpss-toolkit/cloudpss_skills_v2/tests/test_emt_n1_screening.py", line 8>)
#              12 MAKE_FUNCTION            0
#              14 STORE_NAME               3 (test_validate_missing_model)
# 
#  13          16 LOAD_CONST               2 (<code object test_validate_valid_config at 0x3af90d20, file "/home/chenying/researches/cloudpss-toolkit/cloudpss_skills_v2/tests/test_emt_n1_screening.py", line 13>)
#              18 MAKE_FUNCTION            0
#              20 STORE_NAME               4 (test_validate_valid_config)
#              22 RETURN_CONST             3 (None)
# 
# Disassembly of <code object test_validate_missing_model at 0x3afa3fb0, file "/home/chenying/researches/cloudpss-toolkit/cloudpss_skills_v2/tests/test_emt_n1_screening.py", line 8>:
#   8           0 RESUME                   0
# 
#   9           2 LOAD_GLOBAL              1 (NULL + EmtN1ScreeningSkill)
#              12 CALL                     0
#              20 STORE_FAST               1 (skill)
# 
#  10          22 LOAD_FAST                1 (skill)
#              24 LOAD_ATTR                3 (NULL|self + validate)
#              44 BUILD_MAP                0
#              46 CALL                     1
#              54 UNPACK_SEQUENCE          2
#              58 STORE_FAST               2 (valid)
#              60 STORE_FAST               3 (errors)
# 
#  11          62 LOAD_CONST               1 (False)
#              64 STORE_FAST               4 (@py_assert2)
#              66 LOAD_FAST                2 (valid)
#              68 LOAD_FAST                4 (@py_assert2)
#              70 IS_OP                    0
#              72 STORE_FAST               5 (@py_assert1)
#              74 LOAD_FAST                5 (@py_assert1)
#              76 POP_JUMP_IF_TRUE       153 (to 384)
#              78 LOAD_GLOBAL              5 (NULL + @pytest_ar)
#              88 LOAD_ATTR                6 (_call_reprcompare)
#             108 LOAD_CONST               2 (('is',))
#             110 LOAD_FAST                5 (@py_assert1)
#             112 BUILD_TUPLE              1
#             114 LOAD_CONST               3 (('%(py0)s is %(py3)s',))
#             116 LOAD_FAST                2 (valid)
#             118 LOAD_FAST                4 (@py_assert2)
#             120 BUILD_TUPLE              2
#             122 CALL                     4
#             130 LOAD_CONST               4 ('valid')
#             132 LOAD_GLOBAL              9 (NULL + @py_builtins)
#             142 LOAD_ATTR               10 (locals)
#             162 CALL                     0
#             170 CONTAINS_OP              0
#             172 POP_JUMP_IF_TRUE        21 (to 216)
#             174 LOAD_GLOBAL              5 (NULL + @pytest_ar)
#             184 LOAD_ATTR               12 (_should_repr_global_name)
#             204 LOAD_FAST                2 (valid)
#             206 CALL                     1
#             214 POP_JUMP_IF_FALSE       21 (to 258)
#         >>  216 LOAD_GLOBAL              5 (NULL + @pytest_ar)
#             226 LOAD_ATTR               14 (_saferepr)
#             246 LOAD_FAST                2 (valid)
#             248 CALL                     1
#             256 JUMP_FORWARD             1 (to 260)
#         >>  258 LOAD_CONST               4 ('valid')
#         >>  260 LOAD_GLOBAL              5 (NULL + @pytest_ar)
#             270 LOAD_ATTR               14 (_saferepr)
#             290 LOAD_FAST                4 (@py_assert2)
#             292 CALL                     1
#             300 LOAD_CONST               5 (('py0', 'py3'))
#             302 BUILD_CONST_KEY_MAP      2
#             304 BINARY_OP                6 (%)
#             308 STORE_FAST               6 (@py_format4)
#             310 LOAD_CONST               6 ('assert %(py5)s')
#             312 LOAD_CONST               7 ('py5')
#             314 LOAD_FAST                6 (@py_format4)
#             316 BUILD_MAP                1
#             318 BINARY_OP                6 (%)
#             322 STORE_FAST               7 (@py_format6)
#             324 LOAD_GLOBAL             17 (NULL + AssertionError)
#             334 LOAD_GLOBAL              5 (NULL + @pytest_ar)
#             344 LOAD_ATTR               18 (_format_explanation)
#             364 LOAD_FAST                7 (@py_format6)
#             366 CALL                     1
#             374 CALL                     1
#             382 RAISE_VARARGS            1
#         >>  384 LOAD_CONST               0 (None)
#             386 COPY                     1
#             388 STORE_FAST               5 (@py_assert1)
#             390 STORE_FAST               4 (@py_assert2)
#             392 RETURN_CONST             0 (None)
# 
# Disassembly of <code object test_validate_valid_config at 0x3af90d20, file "/home/chenying/researches/cloudpss-toolkit/cloudpss_skills_v2/tests/test_emt_n1_screening.py", line 13>:
#  13           0 RESUME                   0
# 
#  14           2 LOAD_GLOBAL              1 (NULL + EmtN1ScreeningSkill)
#              12 CALL                     0
#              20 STORE_FAST               1 (skill)
# 
#  15          22 LOAD_CONST               1 ('model')
#              24 LOAD_CONST               2 ('rid')
#              26 LOAD_CONST               3 ('model/test/IEEE3')
#              28 BUILD_MAP                1
#              30 BUILD_MAP                1
#              32 STORE_FAST               2 (config)
# 
#  16          34 LOAD_FAST                1 (skill)
#              36 LOAD_ATTR                3 (NULL|self + validate)
#              56 LOAD_FAST                2 (config)
#              58 CALL                     1
#              66 UNPACK_SEQUENCE          2
#              70 STORE_FAST               3 (valid)
#              72 STORE_FAST               4 (errors)
# 
#  17          74 LOAD_CONST               4 (True)
#              76 STORE_FAST               5 (@py_assert2)
#              78 LOAD_FAST                3 (valid)
#              80 LOAD_FAST                5 (@py_assert2)
#              82 IS_OP                    0
#              84 STORE_FAST               6 (@py_assert1)
#              86 LOAD_FAST                6 (@py_assert1)
#              88 POP_JUMP_IF_TRUE       153 (to 396)
#              90 LOAD_GLOBAL              5 (NULL + @pytest_ar)
#             100 LOAD_ATTR                6 (_call_reprcompare)
#             120 LOAD_CONST               5 (('is',))
#             122 LOAD_FAST                6 (@py_assert1)
#             124 BUILD_TUPLE              1
#             126 LOAD_CONST               6 (('%(py0)s is %(py3)s',))
#             128 LOAD_FAST                3 (valid)
#             130 LOAD_FAST                5 (@py_assert2)
#             132 BUILD_TUPLE              2
#             134 CALL                     4
#             142 LOAD_CONST               7 ('valid')
#             144 LOAD_GLOBAL              9 (NULL + @py_builtins)
#             154 LOAD_ATTR               10 (locals)
#             174 CALL                     0
#             182 CONTAINS_OP              0
#             184 POP_JUMP_IF_TRUE        21 (to 228)
#             186 LOAD_GLOBAL              5 (NULL + @pytest_ar)
#             196 LOAD_ATTR               12 (_should_repr_global_name)
#             216 LOAD_FAST                3 (valid)
#             218 CALL                     1
#             226 POP_JUMP_IF_FALSE       21 (to 270)
#         >>  228 LOAD_GLOBAL              5 (NULL + @pytest_ar)
#             238 LOAD_ATTR               14 (_saferepr)
#             258 LOAD_FAST                3 (valid)
#             260 CALL                     1
#             268 JUMP_FORWARD             1 (to 272)
#         >>  270 LOAD_CONST               7 ('valid')
#         >>  272 LOAD_GLOBAL              5 (NULL + @pytest_ar)
#             282 LOAD_ATTR               14 (_saferepr)
#             302 LOAD_FAST                5 (@py_assert2)
#             304 CALL                     1
#             312 LOAD_CONST               8 (('py0', 'py3'))
#             314 BUILD_CONST_KEY_MAP      2
#             316 BINARY_OP                6 (%)
#             320 STORE_FAST               7 (@py_format4)
#             322 LOAD_CONST               9 ('assert %(py5)s')
#             324 LOAD_CONST              10 ('py5')
#             326 LOAD_FAST                7 (@py_format4)
#             328 BUILD_MAP                1
#             330 BINARY_OP                6 (%)
#             334 STORE_FAST               8 (@py_format6)
#             336 LOAD_GLOBAL             17 (NULL + AssertionError)
#             346 LOAD_GLOBAL              5 (NULL + @pytest_ar)
#             356 LOAD_ATTR               18 (_format_explanation)
#             376 LOAD_FAST                8 (@py_format6)
#             378 CALL                     1
#             386 CALL                     1
#             394 RAISE_VARARGS            1
#         >>  396 LOAD_CONST               0 (None)
#             398 COPY                     1
#             400 STORE_FAST               6 (@py_assert1)
#             402 STORE_FAST               5 (@py_assert2)
#             404 RETURN_CONST             0 (None)
# 
# Disassembly of <code object TestEmtN1Severity at 0x73cd945fc110, file "/home/chenying/researches/cloudpss-toolkit/cloudpss_skills_v2/tests/test_emt_n1_screening.py", line 20>:
#  20           0 RESUME                   0
#               2 LOAD_NAME                0 (__name__)
#               4 STORE_NAME               1 (__module__)
#               6 LOAD_CONST               0 ('TestEmtN1Severity')
#               8 STORE_NAME               2 (__qualname__)
# 
#  21          10 LOAD_CONST               1 (<code object test_assess_severity_level_critical at 0x3aef1020, file "/home/chenying/researches/cloudpss-toolkit/cloudpss_skills_v2/tests/test_emt_n1_screening.py", line 21>)
#              12 MAKE_FUNCTION            0
#              14 STORE_NAME               3 (test_assess_severity_level_critical)
# 
#  26          16 LOAD_CONST               2 (<code object test_assess_severity_level_warning at 0x3aef7030, file "/home/chenying/researches/cloudpss-toolkit/cloudpss_skills_v2/tests/test_emt_n1_screening.py", line 26>)
#              18 MAKE_FUNCTION            0
#              20 STORE_NAME               4 (test_assess_severity_level_warning)
# 
#  31          22 LOAD_CONST               3 (<code object test_assess_severity_level_observe at 0x3aec4850, file "/home/chenying/researches/cloudpss-toolkit/cloudpss_skills_v2/tests/test_emt_n1_screening.py", line 31>)
#              24 MAKE_FUNCTION            0
#              26 STORE_NAME               5 (test_assess_severity_level_observe)
#              28 RETURN_CONST             4 (None)
# 
# Disassembly of <code object test_assess_severity_level_critical at 0x3aef1020, file "/home/chenying/researches/cloudpss-toolkit/cloudpss_skills_v2/tests/test_emt_n1_screening.py", line 21>:
#  21           0 RESUME                   0
# 
#  22           2 LOAD_GLOBAL              1 (NULL + EmtN1ScreeningSkill)
#              12 CALL                     0
#              20 STORE_FAST               1 (skill)
# 
#  23          22 LOAD_CONST               1 (10.0)
#              24 LOAD_CONST               2 (15.0)
#              26 LOAD_CONST               3 (('warning', 'critical'))
#              28 BUILD_CONST_KEY_MAP      2
#              30 STORE_FAST               2 (thresholds)
# 
#  24          32 LOAD_FAST                1 (skill)
#              34 LOAD_ATTR                2 (_assess_severity_level)
#              54 STORE_FAST               3 (@py_assert1)
#              56 LOAD_CONST               4 (20.0)
#              58 STORE_FAST               4 (@py_assert3)
#              60 PUSH_NULL
#              62 LOAD_FAST                3 (@py_assert1)
#              64 LOAD_FAST                4 (@py_assert3)
#              66 LOAD_FAST                2 (thresholds)
#              68 CALL                     2
#              76 STORE_FAST               5 (@py_assert6)
#              78 LOAD_CONST               5 ('critical')
#              80 STORE_FAST               6 (@py_assert9)
#              82 LOAD_FAST                5 (@py_assert6)
#              84 LOAD_FAST                6 (@py_assert9)
#              86 COMPARE_OP              40 (==)
#              90 STORE_FAST               7 (@py_assert8)
#              92 LOAD_FAST                7 (@py_assert8)
#              94 EXTENDED_ARG             1
#              96 POP_JUMP_IF_TRUE       278 (to 654)
#              98 LOAD_GLOBAL              5 (NULL + @pytest_ar)
#             108 LOAD_ATTR                6 (_call_reprcompare)
#             128 LOAD_CONST               6 (('==',))
#             130 LOAD_FAST                7 (@py_assert8)
#             132 BUILD_TUPLE              1
#             134 LOAD_CONST               7 (('%(py7)s\n{%(py7)s = %(py2)s\n{%(py2)s = %(py0)s._assess_severity_level\n}(%(py4)s, %(py5)s)\n} == %(py10)s',))
#             136 LOAD_FAST                5 (@py_assert6)
#             138 LOAD_FAST                6 (@py_assert9)
#             140 BUILD_TUPLE              2
#             142 CALL                     4
#             150 LOAD_CONST               8 ('skill')
#             152 LOAD_GLOBAL              9 (NULL + @py_builtins)
#             162 LOAD_ATTR               10 (locals)
#             182 CALL                     0
#             190 CONTAINS_OP              0
#             192 POP_JUMP_IF_TRUE        21 (to 236)
#             194 LOAD_GLOBAL              5 (NULL + @pytest_ar)
#             204 LOAD_ATTR               12 (_should_repr_global_name)
#             224 LOAD_FAST                1 (skill)
#             226 CALL                     1
#             234 POP_JUMP_IF_FALSE       21 (to 278)
#         >>  236 LOAD_GLOBAL              5 (NULL + @pytest_ar)
#             246 LOAD_ATTR               14 (_saferepr)
#             266 LOAD_FAST                1 (skill)
#             268 CALL                     1
#             276 JUMP_FORWARD             1 (to 280)
#         >>  278 LOAD_CONST               8 ('skill')
#         >>  280 LOAD_GLOBAL              5 (NULL + @pytest_ar)
#             290 LOAD_ATTR               14 (_saferepr)
#             310 LOAD_FAST                3 (@py_assert1)
#             312 CALL                     1
#             320 LOAD_GLOBAL              5 (NULL + @pytest_ar)
#             330 LOAD_ATTR               14 (_saferepr)
#             350 LOAD_FAST                4 (@py_assert3)
#             352 CALL                     1
#             360 LOAD_CONST               9 ('thresholds')
#             362 LOAD_GLOBAL              9 (NULL + @py_builtins)
#             372 LOAD_ATTR               10 (locals)
#             392 CALL                     0
#             400 CONTAINS_OP              0
#             402 POP_JUMP_IF_TRUE        21 (to 446)
#             404 LOAD_GLOBAL              5 (NULL + @pytest_ar)
#             414 LOAD_ATTR               12 (_should_repr_global_name)
#             434 LOAD_FAST                2 (thresholds)
#             436 CALL                     1
#             444 POP_JUMP_IF_FALSE       21 (to 488)
#         >>  446 LOAD_GLOBAL              5 (NULL + @pytest_ar)
#             456 LOAD_ATTR               14 (_saferepr)
#             476 LOAD_FAST                2 (thresholds)
#             478 CALL                     1
#             486 JUMP_FORWARD             1 (to 490)
#         >>  488 LOAD_CONST               9 ('thresholds')
#         >>  490 LOAD_GLOBAL              5 (NULL + @pytest_ar)
#             500 LOAD_ATTR               14 (_saferepr)
#             520 LOAD_FAST                5 (@py_assert6)
#             522 CALL                     1
#             530 LOAD_GLOBAL              5 (NULL + @pytest_ar)
#             540 LOAD_ATTR               14 (_saferepr)
#             560 LOAD_FAST                6 (@py_assert9)
#             562 CALL                     1
#             570 LOAD_CONST              10 (('py0', 'py2', 'py4', 'py5', 'py7', 'py10'))
#             572 BUILD_CONST_KEY_MAP      6
#             574 BINARY_OP                6 (%)
#             578 STORE_FAST               8 (@py_format11)
#             580 LOAD_CONST              11 ('assert %(py12)s')
#             582 LOAD_CONST              12 ('py12')
#             584 LOAD_FAST                8 (@py_format11)
#             586 BUILD_MAP                1
#             588 BINARY_OP                6 (%)
#             592 STORE_FAST               9 (@py_format13)
#             594 LOAD_GLOBAL             17 (NULL + AssertionError)
#             604 LOAD_GLOBAL              5 (NULL + @pytest_ar)
#             614 LOAD_ATTR               18 (_format_explanation)
#             634 LOAD_FAST                9 (@py_format13)
#             636 CALL                     1
#             644 CALL                     1
#             652 RAISE_VARARGS            1
#         >>  654 LOAD_CONST               0 (None)
#             656 COPY                     1
#             658 STORE_FAST               3 (@py_assert1)
#             660 COPY                     1
#             662 STORE_FAST               4 (@py_assert3)
#             664 COPY                     1
#             666 STORE_FAST               5 (@py_assert6)
#             668 COPY                     1
#             670 STORE_FAST               7 (@py_assert8)
#             672 STORE_FAST               6 (@py_assert9)
#             674 RETURN_CONST             0 (None)
# 
# Disassembly of <code object test_assess_severity_level_warning at 0x3aef7030, file "/home/chenying/researches/cloudpss-toolkit/cloudpss_skills_v2/tests/test_emt_n1_screening.py", line 26>:
#  26           0 RESUME                   0
# 
#  27           2 LOAD_GLOBAL              1 (NULL + EmtN1ScreeningSkill)
#              12 CALL                     0
#              20 STORE_FAST               1 (skill)
# 
#  28          22 LOAD_CONST               1 (10.0)
#              24 LOAD_CONST               2 (15.0)
#              26 LOAD_CONST               3 (('warning', 'critical'))
#              28 BUILD_CONST_KEY_MAP      2
#              30 STORE_FAST               2 (thresholds)
# 
#  29          32 LOAD_FAST                1 (skill)
#              34 LOAD_ATTR                2 (_assess_severity_level)
#              54 STORE_FAST               3 (@py_assert1)
#              56 LOAD_CONST               4 (12.0)
#              58 STORE_FAST               4 (@py_assert3)
#              60 PUSH_NULL
#              62 LOAD_FAST                3 (@py_assert1)
#              64 LOAD_FAST                4 (@py_assert3)
#              66 LOAD_FAST                2 (thresholds)
#              68 CALL                     2
#              76 STORE_FAST               5 (@py_assert6)
#              78 LOAD_CONST               5 ('warning')
#              80 STORE_FAST               6 (@py_assert9)
#              82 LOAD_FAST                5 (@py_assert6)
#              84 LOAD_FAST                6 (@py_assert9)
#              86 COMPARE_OP              40 (==)
#              90 STORE_FAST               7 (@py_assert8)
#              92 LOAD_FAST                7 (@py_assert8)
#              94 EXTENDED_ARG             1
#              96 POP_JUMP_IF_TRUE       278 (to 654)
#              98 LOAD_GLOBAL              5 (NULL + @pytest_ar)
#             108 LOAD_ATTR                6 (_call_reprcompare)
#             128 LOAD_CONST               6 (('==',))
#             130 LOAD_FAST                7 (@py_assert8)
#             132 BUILD_TUPLE              1
#             134 LOAD_CONST               7 (('%(py7)s\n{%(py7)s = %(py2)s\n{%(py2)s = %(py0)s._assess_severity_level\n}(%(py4)s, %(py5)s)\n} == %(py10)s',))
#             136 LOAD_FAST                5 (@py_assert6)
#             138 LOAD_FAST                6 (@py_assert9)
#             140 BUILD_TUPLE              2
#             142 CALL                     4
#             150 LOAD_CONST               8 ('skill')
#             152 LOAD_GLOBAL              9 (NULL + @py_builtins)
#             162 LOAD_ATTR               10 (locals)
#             182 CALL                     0
#             190 CONTAINS_OP              0
#             192 POP_JUMP_IF_TRUE        21 (to 236)
#             194 LOAD_GLOBAL              5 (NULL + @pytest_ar)
#             204 LOAD_ATTR               12 (_should_repr_global_name)
#             224 LOAD_FAST                1 (skill)
#             226 CALL                     1
#             234 POP_JUMP_IF_FALSE       21 (to 278)
#         >>  236 LOAD_GLOBAL              5 (NULL + @pytest_ar)
#             246 LOAD_ATTR               14 (_saferepr)
#             266 LOAD_FAST                1 (skill)
#             268 CALL                     1
#             276 JUMP_FORWARD             1 (to 280)
#         >>  278 LOAD_CONST               8 ('skill')
#         >>  280 LOAD_GLOBAL              5 (NULL + @pytest_ar)
#             290 LOAD_ATTR               14 (_saferepr)
#             310 LOAD_FAST                3 (@py_assert1)
#             312 CALL                     1
#             320 LOAD_GLOBAL              5 (NULL + @pytest_ar)
#             330 LOAD_ATTR               14 (_saferepr)
#             350 LOAD_FAST                4 (@py_assert3)
#             352 CALL                     1
#             360 LOAD_CONST               9 ('thresholds')
#             362 LOAD_GLOBAL              9 (NULL + @py_builtins)
#             372 LOAD_ATTR               10 (locals)
#             392 CALL                     0
#             400 CONTAINS_OP              0
#             402 POP_JUMP_IF_TRUE        21 (to 446)
#             404 LOAD_GLOBAL              5 (NULL + @pytest_ar)
#             414 LOAD_ATTR               12 (_should_repr_global_name)
#             434 LOAD_FAST                2 (thresholds)
#             436 CALL                     1
#             444 POP_JUMP_IF_FALSE       21 (to 488)
#         >>  446 LOAD_GLOBAL              5 (NULL + @pytest_ar)
#             456 LOAD_ATTR               14 (_saferepr)
#             476 LOAD_FAST                2 (thresholds)
#             478 CALL                     1
#             486 JUMP_FORWARD             1 (to 490)
#         >>  488 LOAD_CONST               9 ('thresholds')
#         >>  490 LOAD_GLOBAL              5 (NULL + @pytest_ar)
#             500 LOAD_ATTR               14 (_saferepr)
#             520 LOAD_FAST                5 (@py_assert6)
#             522 CALL                     1
#             530 LOAD_GLOBAL              5 (NULL + @pytest_ar)
#             540 LOAD_ATTR               14 (_saferepr)
#             560 LOAD_FAST                6 (@py_assert9)
#             562 CALL                     1
#             570 LOAD_CONST              10 (('py0', 'py2', 'py4', 'py5', 'py7', 'py10'))
#             572 BUILD_CONST_KEY_MAP      6
#             574 BINARY_OP                6 (%)
#             578 STORE_FAST               8 (@py_format11)
#             580 LOAD_CONST              11 ('assert %(py12)s')
#             582 LOAD_CONST              12 ('py12')
#             584 LOAD_FAST                8 (@py_format11)
#             586 BUILD_MAP                1
#             588 BINARY_OP                6 (%)
#             592 STORE_FAST               9 (@py_format13)
#             594 LOAD_GLOBAL             17 (NULL + AssertionError)
#             604 LOAD_GLOBAL              5 (NULL + @pytest_ar)
#             614 LOAD_ATTR               18 (_format_explanation)
#             634 LOAD_FAST                9 (@py_format13)
#             636 CALL                     1
#             644 CALL                     1
#             652 RAISE_VARARGS            1
#         >>  654 LOAD_CONST               0 (None)
#             656 COPY                     1
#             658 STORE_FAST               3 (@py_assert1)
#             660 COPY                     1
#             662 STORE_FAST               4 (@py_assert3)
#             664 COPY                     1
#             666 STORE_FAST               5 (@py_assert6)
#             668 COPY                     1
#             670 STORE_FAST               7 (@py_assert8)
#             672 STORE_FAST               6 (@py_assert9)
#             674 RETURN_CONST             0 (None)
# 
# Disassembly of <code object test_assess_severity_level_observe at 0x3aec4850, file "/home/chenying/researches/cloudpss-toolkit/cloudpss_skills_v2/tests/test_emt_n1_screening.py", line 31>:
#  31           0 RESUME                   0
# 
#  32           2 LOAD_GLOBAL              1 (NULL + EmtN1ScreeningSkill)
#              12 CALL                     0
#              20 STORE_FAST               1 (skill)
# 
#  33          22 LOAD_CONST               1 (10.0)
#              24 LOAD_CONST               2 (15.0)
#              26 LOAD_CONST               3 (('warning', 'critical'))
#              28 BUILD_CONST_KEY_MAP      2
#              30 STORE_FAST               2 (thresholds)
# 
#  34          32 LOAD_FAST                1 (skill)
#              34 LOAD_ATTR                2 (_assess_severity_level)
#              54 STORE_FAST               3 (@py_assert1)
#              56 LOAD_CONST               4 (5.0)
#              58 STORE_FAST               4 (@py_assert3)
#              60 PUSH_NULL
#              62 LOAD_FAST                3 (@py_assert1)
#              64 LOAD_FAST                4 (@py_assert3)
#              66 LOAD_FAST                2 (thresholds)
#              68 CALL                     2
#              76 STORE_FAST               5 (@py_assert6)
#              78 LOAD_CONST               5 ('observe')
#              80 STORE_FAST               6 (@py_assert9)
#              82 LOAD_FAST                5 (@py_assert6)
#              84 LOAD_FAST                6 (@py_assert9)
#              86 COMPARE_OP              40 (==)
#              90 STORE_FAST               7 (@py_assert8)
#              92 LOAD_FAST                7 (@py_assert8)
#              94 EXTENDED_ARG             1
#              96 POP_JUMP_IF_TRUE       278 (to 654)
#              98 LOAD_GLOBAL              5 (NULL + @pytest_ar)
#             108 LOAD_ATTR                6 (_call_reprcompare)
#             128 LOAD_CONST               6 (('==',))
#             130 LOAD_FAST                7 (@py_assert8)
#             132 BUILD_TUPLE              1
#             134 LOAD_CONST               7 (('%(py7)s\n{%(py7)s = %(py2)s\n{%(py2)s = %(py0)s._assess_severity_level\n}(%(py4)s, %(py5)s)\n} == %(py10)s',))
#             136 LOAD_FAST                5 (@py_assert6)
#             138 LOAD_FAST                6 (@py_assert9)
#             140 BUILD_TUPLE              2
#             142 CALL                     4
#             150 LOAD_CONST               8 ('skill')
#             152 LOAD_GLOBAL              9 (NULL + @py_builtins)
#             162 LOAD_ATTR               10 (locals)
#             182 CALL                     0
#             190 CONTAINS_OP              0
#             192 POP_JUMP_IF_TRUE        21 (to 236)
#             194 LOAD_GLOBAL              5 (NULL + @pytest_ar)
#             204 LOAD_ATTR               12 (_should_repr_global_name)
#             224 LOAD_FAST                1 (skill)
#             226 CALL                     1
#             234 POP_JUMP_IF_FALSE       21 (to 278)
#         >>  236 LOAD_GLOBAL              5 (NULL + @pytest_ar)
#             246 LOAD_ATTR               14 (_saferepr)
#             266 LOAD_FAST                1 (skill)
#             268 CALL                     1
#             276 JUMP_FORWARD             1 (to 280)
#         >>  278 LOAD_CONST               8 ('skill')
#         >>  280 LOAD_GLOBAL              5 (NULL + @pytest_ar)
#             290 LOAD_ATTR               14 (_saferepr)
#             310 LOAD_FAST                3 (@py_assert1)
#             312 CALL                     1
#             320 LOAD_GLOBAL              5 (NULL + @pytest_ar)
#             330 LOAD_ATTR               14 (_saferepr)
#             350 LOAD_FAST                4 (@py_assert3)
#             352 CALL                     1
#             360 LOAD_CONST               9 ('thresholds')
#             362 LOAD_GLOBAL              9 (NULL + @py_builtins)
#             372 LOAD_ATTR               10 (locals)
#             392 CALL                     0
#             400 CONTAINS_OP              0
#             402 POP_JUMP_IF_TRUE        21 (to 446)
#             404 LOAD_GLOBAL              5 (NULL + @pytest_ar)
#             414 LOAD_ATTR               12 (_should_repr_global_name)
#             434 LOAD_FAST                2 (thresholds)
#             436 CALL                     1
#             444 POP_JUMP_IF_FALSE       21 (to 488)
#         >>  446 LOAD_GLOBAL              5 (NULL + @pytest_ar)
#             456 LOAD_ATTR               14 (_saferepr)
#             476 LOAD_FAST                2 (thresholds)
#             478 CALL                     1
#             486 JUMP_FORWARD             1 (to 490)
#         >>  488 LOAD_CONST               9 ('thresholds')
#         >>  490 LOAD_GLOBAL              5 (NULL + @pytest_ar)
#             500 LOAD_ATTR               14 (_saferepr)
#             520 LOAD_FAST                5 (@py_assert6)
#             522 CALL                     1
#             530 LOAD_GLOBAL              5 (NULL + @pytest_ar)
#             540 LOAD_ATTR               14 (_saferepr)
#             560 LOAD_FAST                6 (@py_assert9)
#             562 CALL                     1
#             570 LOAD_CONST              10 (('py0', 'py2', 'py4', 'py5', 'py7', 'py10'))
#             572 BUILD_CONST_KEY_MAP      6
#             574 BINARY_OP                6 (%)
#             578 STORE_FAST               8 (@py_format11)
#             580 LOAD_CONST              11 ('assert %(py12)s')
#             582 LOAD_CONST              12 ('py12')
#             584 LOAD_FAST                8 (@py_format11)
#             586 BUILD_MAP                1
#             588 BINARY_OP                6 (%)
#             592 STORE_FAST               9 (@py_format13)
#             594 LOAD_GLOBAL             17 (NULL + AssertionError)
#             604 LOAD_GLOBAL              5 (NULL + @pytest_ar)
#             614 LOAD_ATTR               18 (_format_explanation)
#             634 LOAD_FAST                9 (@py_format13)
#             636 CALL                     1
#             644 CALL                     1
#             652 RAISE_VARARGS            1
#         >>  654 LOAD_CONST               0 (None)
#             656 COPY                     1
#             658 STORE_FAST               3 (@py_assert1)
#             660 COPY                     1
#             662 STORE_FAST               4 (@py_assert3)
#             664 COPY                     1
#             666 STORE_FAST               5 (@py_assert6)
#             668 COPY                     1
#             670 STORE_FAST               7 (@py_assert8)
#             672 STORE_FAST               6 (@py_assert9)
#             674 RETURN_CONST             0 (None)
# 
# Disassembly of <code object TestEmtN1PostfaultGap at 0x73cd945fdfb0, file "/home/chenying/researches/cloudpss-toolkit/cloudpss_skills_v2/tests/test_emt_n1_screening.py", line 37>:
#  37           0 RESUME                   0
#               2 LOAD_NAME                0 (__name__)
#               4 STORE_NAME               1 (__module__)
#               6 LOAD_CONST               0 ('TestEmtN1PostfaultGap')
#               8 STORE_NAME               2 (__qualname__)
# 
#  38          10 LOAD_CONST               1 (<code object test_calculate_postfault_gap at 0x3aea30a0, file "/home/chenying/researches/cloudpss-toolkit/cloudpss_skills_v2/tests/test_emt_n1_screening.py", line 38>)
#              12 MAKE_FUNCTION            0
#              14 STORE_NAME               3 (test_calculate_postfault_gap)
# 
#  43          16 LOAD_CONST               2 (<code object test_calculate_postfault_gap_no_drop at 0x3ae632d0, file "/home/chenying/researches/cloudpss-toolkit/cloudpss_skills_v2/tests/test_emt_n1_screening.py", line 43>)
#              18 MAKE_FUNCTION            0
#              20 STORE_NAME               4 (test_calculate_postfault_gap_no_drop)
#              22 RETURN_CONST             3 (None)
# 
# Disassembly of <code object test_calculate_postfault_gap at 0x3aea30a0, file "/home/chenying/researches/cloudpss-toolkit/cloudpss_skills_v2/tests/test_emt_n1_screening.py", line 38>:
#  38           0 RESUME                   0
# 
#  39           2 LOAD_GLOBAL              1 (NULL + EmtN1ScreeningSkill)
#              12 CALL                     0
#              20 STORE_FAST               1 (skill)
# 
#  40          22 LOAD_FAST                1 (skill)
#              24 LOAD_ATTR                3 (NULL|self + _calculate_postfault_gap)
#              44 LOAD_CONST               1 (1.0)
#              46 LOAD_CONST               2 (0.85)
#              48 KW_NAMES                 3 (('prefault_rms', 'postfault_rms'))
#              50 CALL                     2
#              58 STORE_FAST               2 (gap)
# 
#  41          60 LOAD_CONST               4 (0.15)
#              62 STORE_FAST               3 (@py_assert2)
#              64 LOAD_FAST                2 (gap)
#              66 LOAD_FAST                3 (@py_assert2)
#              68 BINARY_OP               10 (-)
#              72 STORE_FAST               4 (@py_assert4)
#              74 LOAD_GLOBAL              5 (NULL + abs)
#              84 LOAD_FAST                4 (@py_assert4)
#              86 CALL                     1
#              94 STORE_FAST               5 (@py_assert5)
#              96 LOAD_CONST               5 (1e-10)
#              98 STORE_FAST               6 (@py_assert8)
#             100 LOAD_FAST                5 (@py_assert5)
#             102 LOAD_FAST                6 (@py_assert8)
#             104 COMPARE_OP               2 (<)
#             108 STORE_FAST               7 (@py_assert7)
#             110 LOAD_FAST                7 (@py_assert7)
#             112 EXTENDED_ARG             1
#             114 POP_JUMP_IF_TRUE       266 (to 648)
#             116 LOAD_GLOBAL              7 (NULL + @pytest_ar)
#             126 LOAD_ATTR                8 (_call_reprcompare)
#             146 LOAD_CONST               6 (('<',))
#             148 LOAD_FAST                7 (@py_assert7)
#             150 BUILD_TUPLE              1
#             152 LOAD_CONST               7 (('%(py6)s\n{%(py6)s = %(py0)s((%(py1)s - %(py3)s))\n} < %(py9)s',))
#             154 LOAD_FAST                5 (@py_assert5)
#             156 LOAD_FAST                6 (@py_assert8)
#             158 BUILD_TUPLE              2
#             160 CALL                     4
#             168 LOAD_CONST               8 ('abs')
#             170 LOAD_GLOBAL             11 (NULL + @py_builtins)
#             180 LOAD_ATTR               12 (locals)
#             200 CALL                     0
#             208 CONTAINS_OP              0
#             210 POP_JUMP_IF_TRUE        25 (to 262)
#             212 LOAD_GLOBAL              7 (NULL + @pytest_ar)
#             222 LOAD_ATTR               14 (_should_repr_global_name)
#             242 LOAD_GLOBAL              4 (abs)
#             252 CALL                     1
#             260 POP_JUMP_IF_FALSE       25 (to 312)
#         >>  262 LOAD_GLOBAL              7 (NULL + @pytest_ar)
#             272 LOAD_ATTR               16 (_saferepr)
#             292 LOAD_GLOBAL              4 (abs)
#             302 CALL                     1
#             310 JUMP_FORWARD             1 (to 314)
#         >>  312 LOAD_CONST               8 ('abs')
#         >>  314 LOAD_CONST               9 ('gap')
#             316 LOAD_GLOBAL             11 (NULL + @py_builtins)
#             326 LOAD_ATTR               12 (locals)
#             346 CALL                     0
#             354 CONTAINS_OP              0
#             356 POP_JUMP_IF_TRUE        21 (to 400)
#             358 LOAD_GLOBAL              7 (NULL + @pytest_ar)
#             368 LOAD_ATTR               14 (_should_repr_global_name)
#             388 LOAD_FAST                2 (gap)
#             390 CALL                     1
#             398 POP_JUMP_IF_FALSE       21 (to 442)
#         >>  400 LOAD_GLOBAL              7 (NULL + @pytest_ar)
#             410 LOAD_ATTR               16 (_saferepr)
#             430 LOAD_FAST                2 (gap)
#             432 CALL                     1
#             440 JUMP_FORWARD             1 (to 444)
#         >>  442 LOAD_CONST               9 ('gap')
#         >>  444 LOAD_GLOBAL              7 (NULL + @pytest_ar)
#             454 LOAD_ATTR               16 (_saferepr)
#             474 LOAD_FAST                3 (@py_assert2)
#             476 CALL                     1
#             484 LOAD_GLOBAL              7 (NULL + @pytest_ar)
#             494 LOAD_ATTR               16 (_saferepr)
#             514 LOAD_FAST                5 (@py_assert5)
#             516 CALL                     1
#             524 LOAD_GLOBAL              7 (NULL + @pytest_ar)
#             534 LOAD_ATTR               16 (_saferepr)
#             554 LOAD_FAST                6 (@py_assert8)
#             556 CALL                     1
#             564 LOAD_CONST              10 (('py0', 'py1', 'py3', 'py6', 'py9'))
#             566 BUILD_CONST_KEY_MAP      5
#             568 BINARY_OP                6 (%)
#             572 STORE_FAST               8 (@py_format10)
#             574 LOAD_CONST              11 ('assert %(py11)s')
#             576 LOAD_CONST              12 ('py11')
#             578 LOAD_FAST                8 (@py_format10)
#             580 BUILD_MAP                1
#             582 BINARY_OP                6 (%)
#             586 STORE_FAST               9 (@py_format12)
#             588 LOAD_GLOBAL             19 (NULL + AssertionError)
#             598 LOAD_GLOBAL              7 (NULL + @pytest_ar)
#             608 LOAD_ATTR               20 (_format_explanation)
#             628 LOAD_FAST                9 (@py_format12)
#             630 CALL                     1
#             638 CALL                     1
#             646 RAISE_VARARGS            1
#         >>  648 LOAD_CONST               0 (None)
#             650 COPY                     1
#             652 STORE_FAST               3 (@py_assert2)
#             654 COPY                     1
#             656 STORE_FAST               4 (@py_assert4)
#             658 COPY                     1
#             660 STORE_FAST               5 (@py_assert5)
#             662 COPY                     1
#             664 STORE_FAST               7 (@py_assert7)
#             666 STORE_FAST               6 (@py_assert8)
#             668 RETURN_CONST             0 (None)
# 
# Disassembly of <code object test_calculate_postfault_gap_no_drop at 0x3ae632d0, file "/home/chenying/researches/cloudpss-toolkit/cloudpss_skills_v2/tests/test_emt_n1_screening.py", line 43>:
#  43           0 RESUME                   0
# 
#  44           2 LOAD_GLOBAL              1 (NULL + EmtN1ScreeningSkill)
#              12 CALL                     0
#              20 STORE_FAST               1 (skill)
# 
#  45          22 LOAD_FAST                1 (skill)
#              24 LOAD_ATTR                3 (NULL|self + _calculate_postfault_gap)
#              44 LOAD_CONST               1 (1.0)
#              46 LOAD_CONST               1 (1.0)
#              48 KW_NAMES                 2 (('prefault_rms', 'postfault_rms'))
#              50 CALL                     2
#              58 STORE_FAST               2 (gap)
# 
#  46          60 LOAD_CONST               3 (0.0)
#              62 STORE_FAST               3 (@py_assert2)
#              64 LOAD_FAST                2 (gap)
#              66 LOAD_FAST                3 (@py_assert2)
#              68 COMPARE_OP              40 (==)
#              72 STORE_FAST               4 (@py_assert1)
#              74 LOAD_FAST                4 (@py_assert1)
#              76 POP_JUMP_IF_TRUE       153 (to 384)
#              78 LOAD_GLOBAL              5 (NULL + @pytest_ar)
#              88 LOAD_ATTR                6 (_call_reprcompare)
#             108 LOAD_CONST               4 (('==',))
#             110 LOAD_FAST                4 (@py_assert1)
#             112 BUILD_TUPLE              1
#             114 LOAD_CONST               5 (('%(py0)s == %(py3)s',))
#             116 LOAD_FAST                2 (gap)
#             118 LOAD_FAST                3 (@py_assert2)
#             120 BUILD_TUPLE              2
#             122 CALL                     4
#             130 LOAD_CONST               6 ('gap')
#             132 LOAD_GLOBAL              9 (NULL + @py_builtins)
#             142 LOAD_ATTR               10 (locals)
#             162 CALL                     0
#             170 CONTAINS_OP              0
#             172 POP_JUMP_IF_TRUE        21 (to 216)
#             174 LOAD_GLOBAL              5 (NULL + @pytest_ar)
#             184 LOAD_ATTR               12 (_should_repr_global_name)
#             204 LOAD_FAST                2 (gap)
#             206 CALL                     1
#             214 POP_JUMP_IF_FALSE       21 (to 258)
#         >>  216 LOAD_GLOBAL              5 (NULL + @pytest_ar)
#             226 LOAD_ATTR               14 (_saferepr)
#             246 LOAD_FAST                2 (gap)
#             248 CALL                     1
#             256 JUMP_FORWARD             1 (to 260)
#         >>  258 LOAD_CONST               6 ('gap')
#         >>  260 LOAD_GLOBAL              5 (NULL + @pytest_ar)
#             270 LOAD_ATTR               14 (_saferepr)
#             290 LOAD_FAST                3 (@py_assert2)
#             292 CALL                     1
#             300 LOAD_CONST               7 (('py0', 'py3'))
#             302 BUILD_CONST_KEY_MAP      2
#             304 BINARY_OP                6 (%)
#             308 STORE_FAST               5 (@py_format4)
#             310 LOAD_CONST               8 ('assert %(py5)s')
#             312 LOAD_CONST               9 ('py5')
#             314 LOAD_FAST                5 (@py_format4)
#             316 BUILD_MAP                1
#             318 BINARY_OP                6 (%)
#             322 STORE_FAST               6 (@py_format6)
#             324 LOAD_GLOBAL             17 (NULL + AssertionError)
#             334 LOAD_GLOBAL              5 (NULL + @pytest_ar)
#             344 LOAD_ATTR               18 (_format_explanation)
#             364 LOAD_FAST                6 (@py_format6)
#             366 CALL                     1
#             374 CALL                     1
#             382 RAISE_VARARGS            1
#         >>  384 LOAD_CONST               0 (None)
#             386 COPY                     1
#             388 STORE_FAST               4 (@py_assert1)
#             390 STORE_FAST               3 (@py_assert2)
#             392 RETURN_CONST             0 (None)
# 
# Disassembly of <code object TestEmtN1Ranking at 0x73cd945fedb0, file "/home/chenying/researches/cloudpss-toolkit/cloudpss_skills_v2/tests/test_emt_n1_screening.py", line 49>:
#  49           0 RESUME                   0
#               2 LOAD_NAME                0 (__name__)
#               4 STORE_NAME               1 (__module__)
#               6 LOAD_CONST               0 ('TestEmtN1Ranking')
#               8 STORE_NAME               2 (__qualname__)
# 
#  50          10 LOAD_CONST               1 (<code object test_rank_results at 0x3af9c2b0, file "/home/chenying/researches/cloudpss-toolkit/cloudpss_skills_v2/tests/test_emt_n1_screening.py", line 50>)
#              12 MAKE_FUNCTION            0
#              14 STORE_NAME               3 (test_rank_results)
# 
#  66          16 LOAD_CONST               2 (<code object test_build_digest at 0x3afac750, file "/home/chenying/researches/cloudpss-toolkit/cloudpss_skills_v2/tests/test_emt_n1_screening.py", line 66>)
#              18 MAKE_FUNCTION            0
#              20 STORE_NAME               4 (test_build_digest)
#              22 RETURN_CONST             3 (None)
# 
# Disassembly of <code object test_rank_results at 0x3af9c2b0, file "/home/chenying/researches/cloudpss-toolkit/cloudpss_skills_v2/tests/test_emt_n1_screening.py", line 50>:
#  50           0 RESUME                   0
# 
#  51           2 LOAD_GLOBAL              1 (NULL + EmtN1ScreeningSkill)
#              12 CALL                     0
#              20 STORE_FAST               1 (skill)
# 
#  53          22 LOAD_CONST               1 ('L1')
#              24 LOAD_CONST               2 (5.0)
#              26 LOAD_CONST               3 (('branch_id', 'worst_postfault_gap'))
#              28 BUILD_CONST_KEY_MAP      2
# 
#  54          30 LOAD_CONST               4 ('L2')
#              32 LOAD_CONST               5 (20.0)
#              34 LOAD_CONST               3 (('branch_id', 'worst_postfault_gap'))
#              36 BUILD_CONST_KEY_MAP      2
# 
#  55          38 LOAD_CONST               6 ('L3')
#              40 LOAD_CONST               7 (12.0)
#              42 LOAD_CONST               3 (('branch_id', 'worst_postfault_gap'))
#              44 BUILD_CONST_KEY_MAP      2
# 
#  52          46 BUILD_LIST               3
#              48 STORE_FAST               2 (results)
# 
#  57          50 LOAD_CONST               8 (10.0)
#              52 LOAD_CONST               9 (15.0)
#              54 LOAD_CONST              10 (('warning', 'critical'))
#              56 BUILD_CONST_KEY_MAP      2
#              58 STORE_FAST               3 (thresholds)
# 
#  58          60 LOAD_FAST                1 (skill)
#              62 LOAD_ATTR                3 (NULL|self + _rank_results)
#              82 LOAD_FAST                2 (results)
#              84 LOAD_FAST                3 (thresholds)
#              86 CALL                     2
#              94 STORE_FAST               4 (ranked)
# 
#  59          96 LOAD_FAST                4 (ranked)
#              98 LOAD_CONST              11 (0)
#             100 BINARY_SUBSCR
#             104 LOAD_CONST              12 ('branch_id')
#             106 BINARY_SUBSCR
#             110 STORE_FAST               5 (@py_assert0)
#             112 LOAD_CONST               4 ('L2')
#             114 STORE_FAST               6 (@py_assert3)
#             116 LOAD_FAST                5 (@py_assert0)
#             118 LOAD_FAST                6 (@py_assert3)
#             120 COMPARE_OP              40 (==)
#             124 STORE_FAST               7 (@py_assert2)
#             126 LOAD_FAST                7 (@py_assert2)
#             128 POP_JUMP_IF_TRUE       108 (to 346)
#             130 LOAD_GLOBAL              5 (NULL + @pytest_ar)
#             140 LOAD_ATTR                6 (_call_reprcompare)
#             160 LOAD_CONST              13 (('==',))
#             162 LOAD_FAST                7 (@py_assert2)
#             164 BUILD_TUPLE              1
#             166 LOAD_CONST              14 (('%(py1)s == %(py4)s',))
#             168 LOAD_FAST                5 (@py_assert0)
#             170 LOAD_FAST                6 (@py_assert3)
#             172 BUILD_TUPLE              2
#             174 CALL                     4
#             182 LOAD_GLOBAL              5 (NULL + @pytest_ar)
#             192 LOAD_ATTR                8 (_saferepr)
#             212 LOAD_FAST                5 (@py_assert0)
#             214 CALL                     1
#             222 LOAD_GLOBAL              5 (NULL + @pytest_ar)
#             232 LOAD_ATTR                8 (_saferepr)
#             252 LOAD_FAST                6 (@py_assert3)
#             254 CALL                     1
#             262 LOAD_CONST              15 (('py1', 'py4'))
#             264 BUILD_CONST_KEY_MAP      2
#             266 BINARY_OP                6 (%)
#             270 STORE_FAST               8 (@py_format5)
#             272 LOAD_CONST              16 ('assert %(py6)s')
#             274 LOAD_CONST              17 ('py6')
#             276 LOAD_FAST                8 (@py_format5)
#             278 BUILD_MAP                1
#             280 BINARY_OP                6 (%)
#             284 STORE_FAST               9 (@py_format7)
#             286 LOAD_GLOBAL             11 (NULL + AssertionError)
#             296 LOAD_GLOBAL              5 (NULL + @pytest_ar)
#             306 LOAD_ATTR               12 (_format_explanation)
#             326 LOAD_FAST                9 (@py_format7)
#             328 CALL                     1
#             336 CALL                     1
#             344 RAISE_VARARGS            1
#         >>  346 LOAD_CONST               0 (None)
#             348 COPY                     1
#             350 STORE_FAST               5 (@py_assert0)
#             352 COPY                     1
#             354 STORE_FAST               7 (@py_assert2)
#             356 STORE_FAST               6 (@py_assert3)
# 
#  60         358 LOAD_FAST                4 (ranked)
#             360 LOAD_CONST              11 (0)
#             362 BINARY_SUBSCR
#             366 LOAD_CONST              18 ('severity')
#             368 BINARY_SUBSCR
#             372 STORE_FAST               5 (@py_assert0)
#             374 LOAD_CONST              19 ('critical')
#             376 STORE_FAST               6 (@py_assert3)
#             378 LOAD_FAST                5 (@py_assert0)
#             380 LOAD_FAST                6 (@py_assert3)
#             382 COMPARE_OP              40 (==)
#             386 STORE_FAST               7 (@py_assert2)
#             388 LOAD_FAST                7 (@py_assert2)
#             390 POP_JUMP_IF_TRUE       108 (to 608)
#             392 LOAD_GLOBAL              5 (NULL + @pytest_ar)
#             402 LOAD_ATTR                6 (_call_reprcompare)
#             422 LOAD_CONST              13 (('==',))
#             424 LOAD_FAST                7 (@py_assert2)
#             426 BUILD_TUPLE              1
#             428 LOAD_CONST              14 (('%(py1)s == %(py4)s',))
#             430 LOAD_FAST                5 (@py_assert0)
#             432 LOAD_FAST                6 (@py_assert3)
#             434 BUILD_TUPLE              2
#             436 CALL                     4
#             444 LOAD_GLOBAL              5 (NULL + @pytest_ar)
#             454 LOAD_ATTR                8 (_saferepr)
#             474 LOAD_FAST                5 (@py_assert0)
#             476 CALL                     1
#             484 LOAD_GLOBAL              5 (NULL + @pytest_ar)
#             494 LOAD_ATTR                8 (_saferepr)
#             514 LOAD_FAST                6 (@py_assert3)
#             516 CALL                     1
#             524 LOAD_CONST              15 (('py1', 'py4'))
#             526 BUILD_CONST_KEY_MAP      2
#             528 BINARY_OP                6 (%)
#             532 STORE_FAST               8 (@py_format5)
#             534 LOAD_CONST              16 ('assert %(py6)s')
#             536 LOAD_CONST              17 ('py6')
#             538 LOAD_FAST                8 (@py_format5)
#             540 BUILD_MAP                1
#             542 BINARY_OP                6 (%)
#             546 STORE_FAST               9 (@py_format7)
#             548 LOAD_GLOBAL             11 (NULL + AssertionError)
#             558 LOAD_GLOBAL              5 (NULL + @pytest_ar)
#             568 LOAD_ATTR               12 (_format_explanation)
#             588 LOAD_FAST                9 (@py_format7)
#             590 CALL                     1
#             598 CALL                     1
#             606 RAISE_VARARGS            1
#         >>  608 LOAD_CONST               0 (None)
#             610 COPY                     1
#             612 STORE_FAST               5 (@py_assert0)
#             614 COPY                     1
#             616 STORE_FAST               7 (@py_assert2)
#             618 STORE_FAST               6 (@py_assert3)
# 
#  61         620 LOAD_FAST                4 (ranked)
#             622 LOAD_CONST              20 (1)
#             624 BINARY_SUBSCR
#             628 LOAD_CONST              12 ('branch_id')
#             630 BINARY_SUBSCR
#             634 STORE_FAST               5 (@py_assert0)
#             636 LOAD_CONST               6 ('L3')
#             638 STORE_FAST               6 (@py_assert3)
#             640 LOAD_FAST                5 (@py_assert0)
#             642 LOAD_FAST                6 (@py_assert3)
#             644 COMPARE_OP              40 (==)
#             648 STORE_FAST               7 (@py_assert2)
#             650 LOAD_FAST                7 (@py_assert2)
#             652 POP_JUMP_IF_TRUE       108 (to 870)
#             654 LOAD_GLOBAL              5 (NULL + @pytest_ar)
#             664 LOAD_ATTR                6 (_call_reprcompare)
#             684 LOAD_CONST              13 (('==',))
#             686 LOAD_FAST                7 (@py_assert2)
#             688 BUILD_TUPLE              1
#             690 LOAD_CONST              14 (('%(py1)s == %(py4)s',))
#             692 LOAD_FAST                5 (@py_assert0)
#             694 LOAD_FAST                6 (@py_assert3)
#             696 BUILD_TUPLE              2
#             698 CALL                     4
#             706 LOAD_GLOBAL              5 (NULL + @pytest_ar)
#             716 LOAD_ATTR                8 (_saferepr)
#             736 LOAD_FAST                5 (@py_assert0)
#             738 CALL                     1
#             746 LOAD_GLOBAL              5 (NULL + @pytest_ar)
#             756 LOAD_ATTR                8 (_saferepr)
#             776 LOAD_FAST                6 (@py_assert3)
#             778 CALL                     1
#             786 LOAD_CONST              15 (('py1', 'py4'))
#             788 BUILD_CONST_KEY_MAP      2
#             790 BINARY_OP                6 (%)
#             794 STORE_FAST               8 (@py_format5)
#             796 LOAD_CONST              16 ('assert %(py6)s')
#             798 LOAD_CONST              17 ('py6')
#             800 LOAD_FAST                8 (@py_format5)
#             802 BUILD_MAP                1
#             804 BINARY_OP                6 (%)
#             808 STORE_FAST               9 (@py_format7)
#             810 LOAD_GLOBAL             11 (NULL + AssertionError)
#             820 LOAD_GLOBAL              5 (NULL + @pytest_ar)
#             830 LOAD_ATTR               12 (_format_explanation)
#             850 LOAD_FAST                9 (@py_format7)
#             852 CALL                     1
#             860 CALL                     1
#             868 RAISE_VARARGS            1
#         >>  870 LOAD_CONST               0 (None)
#             872 COPY                     1
#             874 STORE_FAST               5 (@py_assert0)
#             876 COPY                     1
#             878 STORE_FAST               7 (@py_assert2)
#             880 STORE_FAST               6 (@py_assert3)
# 
#  62         882 LOAD_FAST                4 (ranked)
#             884 LOAD_CONST              20 (1)
#             886 BINARY_SUBSCR
#             890 LOAD_CONST              18 ('severity')
#             892 BINARY_SUBSCR
#             896 STORE_FAST               5 (@py_assert0)
#             898 LOAD_CONST              21 ('warning')
#             900 STORE_FAST               6 (@py_assert3)
#             902 LOAD_FAST                5 (@py_assert0)
#             904 LOAD_FAST                6 (@py_assert3)
#             906 COMPARE_OP              40 (==)
#             910 STORE_FAST               7 (@py_assert2)
#             912 LOAD_FAST                7 (@py_assert2)
#             914 POP_JUMP_IF_TRUE       108 (to 1132)
#             916 LOAD_GLOBAL              5 (NULL + @pytest_ar)
#             926 LOAD_ATTR                6 (_call_reprcompare)
#             946 LOAD_CONST              13 (('==',))
#             948 LOAD_FAST                7 (@py_assert2)
#             950 BUILD_TUPLE              1
#             952 LOAD_CONST              14 (('%(py1)s == %(py4)s',))
#             954 LOAD_FAST                5 (@py_assert0)
#             956 LOAD_FAST                6 (@py_assert3)
#             958 BUILD_TUPLE              2
#             960 CALL                     4
#             968 LOAD_GLOBAL              5 (NULL + @pytest_ar)
#             978 LOAD_ATTR                8 (_saferepr)
#             998 LOAD_FAST                5 (@py_assert0)
#            1000 CALL                     1
#            1008 LOAD_GLOBAL              5 (NULL + @pytest_ar)
#            1018 LOAD_ATTR                8 (_saferepr)
#            1038 LOAD_FAST                6 (@py_assert3)
#            1040 CALL                     1
#            1048 LOAD_CONST              15 (('py1', 'py4'))
#            1050 BUILD_CONST_KEY_MAP      2
#            1052 BINARY_OP                6 (%)
#            1056 STORE_FAST               8 (@py_format5)
#            1058 LOAD_CONST              16 ('assert %(py6)s')
#            1060 LOAD_CONST              17 ('py6')
#            1062 LOAD_FAST                8 (@py_format5)
#            1064 BUILD_MAP                1
#            1066 BINARY_OP                6 (%)
#            1070 STORE_FAST               9 (@py_format7)
#            1072 LOAD_GLOBAL             11 (NULL + AssertionError)
#            1082 LOAD_GLOBAL              5 (NULL + @pytest_ar)
#            1092 LOAD_ATTR               12 (_format_explanation)
#            1112 LOAD_FAST                9 (@py_format7)
#            1114 CALL                     1
#            1122 CALL                     1
#            1130 RAISE_VARARGS            1
#         >> 1132 LOAD_CONST               0 (None)
#            1134 COPY                     1
#            1136 STORE_FAST               5 (@py_assert0)
#            1138 COPY                     1
#            1140 STORE_FAST               7 (@py_assert2)
#            1142 STORE_FAST               6 (@py_assert3)
# 
#  63        1144 LOAD_FAST                4 (ranked)
#            1146 LOAD_CONST              22 (2)
#            1148 BINARY_SUBSCR
#            1152 LOAD_CONST              12 ('branch_id')
#            1154 BINARY_SUBSCR
#            1158 STORE_FAST               5 (@py_assert0)
#            1160 LOAD_CONST               1 ('L1')
#            1162 STORE_FAST               6 (@py_assert3)
#            1164 LOAD_FAST                5 (@py_assert0)
#            1166 LOAD_FAST                6 (@py_assert3)
#            1168 COMPARE_OP              40 (==)
#            1172 STORE_FAST               7 (@py_assert2)
#            1174 LOAD_FAST                7 (@py_assert2)
#            1176 POP_JUMP_IF_TRUE       108 (to 1394)
#            1178 LOAD_GLOBAL              5 (NULL + @pytest_ar)
#            1188 LOAD_ATTR                6 (_call_reprcompare)
#            1208 LOAD_CONST              13 (('==',))
#            1210 LOAD_FAST                7 (@py_assert2)
#            1212 BUILD_TUPLE              1
#            1214 LOAD_CONST              14 (('%(py1)s == %(py4)s',))
#            1216 LOAD_FAST                5 (@py_assert0)
#            1218 LOAD_FAST                6 (@py_assert3)
#            1220 BUILD_TUPLE              2
#            1222 CALL                     4
#            1230 LOAD_GLOBAL              5 (NULL + @pytest_ar)
#            1240 LOAD_ATTR                8 (_saferepr)
#            1260 LOAD_FAST                5 (@py_assert0)
#            1262 CALL                     1
#            1270 LOAD_GLOBAL              5 (NULL + @pytest_ar)
#            1280 LOAD_ATTR                8 (_saferepr)
#            1300 LOAD_FAST                6 (@py_assert3)
#            1302 CALL                     1
#            1310 LOAD_CONST              15 (('py1', 'py4'))
#            1312 BUILD_CONST_KEY_MAP      2
#            1314 BINARY_OP                6 (%)
#            1318 STORE_FAST               8 (@py_format5)
#            1320 LOAD_CONST              16 ('assert %(py6)s')
#            1322 LOAD_CONST              17 ('py6')
#            1324 LOAD_FAST                8 (@py_format5)
#            1326 BUILD_MAP                1
#            1328 BINARY_OP                6 (%)
#            1332 STORE_FAST               9 (@py_format7)
#            1334 LOAD_GLOBAL             11 (NULL + AssertionError)
#            1344 LOAD_GLOBAL              5 (NULL + @pytest_ar)
#            1354 LOAD_ATTR               12 (_format_explanation)
#            1374 LOAD_FAST                9 (@py_format7)
#            1376 CALL                     1
#            1384 CALL                     1
#            1392 RAISE_VARARGS            1
#         >> 1394 LOAD_CONST               0 (None)
#            1396 COPY                     1
#            1398 STORE_FAST               5 (@py_assert0)
#            1400 COPY                     1
#            1402 STORE_FAST               7 (@py_assert2)
#            1404 STORE_FAST               6 (@py_assert3)
# 
#  64        1406 LOAD_FAST                4 (ranked)
#            1408 LOAD_CONST              22 (2)
#            1410 BINARY_SUBSCR
#            1414 LOAD_CONST              18 ('severity')
#            1416 BINARY_SUBSCR
#            1420 STORE_FAST               5 (@py_assert0)
#            1422 LOAD_CONST              23 ('observe')
#            1424 STORE_FAST               6 (@py_assert3)
#            1426 LOAD_FAST                5 (@py_assert0)
#            1428 LOAD_FAST                6 (@py_assert3)
#            1430 COMPARE_OP              40 (==)
#            1434 STORE_FAST               7 (@py_assert2)
#            1436 LOAD_FAST                7 (@py_assert2)
#            1438 POP_JUMP_IF_TRUE       108 (to 1656)
#            1440 LOAD_GLOBAL              5 (NULL + @pytest_ar)
#            1450 LOAD_ATTR                6 (_call_reprcompare)
#            1470 LOAD_CONST              13 (('==',))
#            1472 LOAD_FAST                7 (@py_assert2)
#            1474 BUILD_TUPLE              1
#            1476 LOAD_CONST              14 (('%(py1)s == %(py4)s',))
#            1478 LOAD_FAST                5 (@py_assert0)
#            1480 LOAD_FAST                6 (@py_assert3)
#            1482 BUILD_TUPLE              2
#            1484 CALL                     4
#            1492 LOAD_GLOBAL              5 (NULL + @pytest_ar)
#            1502 LOAD_ATTR                8 (_saferepr)
#            1522 LOAD_FAST                5 (@py_assert0)
#            1524 CALL                     1
#            1532 LOAD_GLOBAL              5 (NULL + @pytest_ar)
#            1542 LOAD_ATTR                8 (_saferepr)
#            1562 LOAD_FAST                6 (@py_assert3)
#            1564 CALL                     1
#            1572 LOAD_CONST              15 (('py1', 'py4'))
#            1574 BUILD_CONST_KEY_MAP      2
#            1576 BINARY_OP                6 (%)
#            1580 STORE_FAST               8 (@py_format5)
#            1582 LOAD_CONST              16 ('assert %(py6)s')
#            1584 LOAD_CONST              17 ('py6')
#            1586 LOAD_FAST                8 (@py_format5)
#            1588 BUILD_MAP                1
#            1590 BINARY_OP                6 (%)
#            1594 STORE_FAST               9 (@py_format7)
#            1596 LOAD_GLOBAL             11 (NULL + AssertionError)
#            1606 LOAD_GLOBAL              5 (NULL + @pytest_ar)
#            1616 LOAD_ATTR               12 (_format_explanation)
#            1636 LOAD_FAST                9 (@py_format7)
#            1638 CALL                     1
#            1646 CALL                     1
#            1654 RAISE_VARARGS            1
#         >> 1656 LOAD_CONST               0 (None)
#            1658 COPY                     1
#            1660 STORE_FAST               5 (@py_assert0)
#            1662 COPY                     1
#            1664 STORE_FAST               7 (@py_assert2)
#            1666 STORE_FAST               6 (@py_assert3)
#            1668 RETURN_CONST             0 (None)
# 
# Disassembly of <code object test_build_digest at 0x3afac750, file "/home/chenying/researches/cloudpss-toolkit/cloudpss_skills_v2/tests/test_emt_n1_screening.py", line 66>:
#  66           0 RESUME                   0
# 
#  67           2 LOAD_GLOBAL              1 (NULL + EmtN1ScreeningSkill)
#              12 CALL                     0
#              20 STORE_FAST               1 (skill)
# 
#  69          22 LOAD_CONST               1 ('severity')
#              24 LOAD_CONST               2 ('critical')
#              26 BUILD_MAP                1
# 
#  70          28 LOAD_CONST               1 ('severity')
#              30 LOAD_CONST               3 ('warning')
#              32 BUILD_MAP                1
# 
#  71          34 LOAD_CONST               1 ('severity')
#              36 LOAD_CONST               4 ('observe')
#              38 BUILD_MAP                1
# 
#  72          40 LOAD_CONST               1 ('severity')
#              42 LOAD_CONST               4 ('observe')
#              44 BUILD_MAP                1
# 
#  68          46 BUILD_LIST               4
#              48 STORE_FAST               2 (results)
# 
#  74          50 LOAD_CONST               5 ('branch_name')
#              52 LOAD_CONST               6 ('baseline')
#              54 BUILD_MAP                1
#              56 STORE_FAST               3 (baseline)
# 
#  75          58 LOAD_FAST                1 (skill)
#              60 LOAD_ATTR                3 (NULL|self + _build_digest)
#              80 LOAD_FAST                3 (baseline)
#              82 LOAD_FAST                2 (results)
#              84 CALL                     2
#              92 STORE_FAST               4 (digest)
# 
#  76          94 LOAD_FAST                4 (digest)
#              96 LOAD_CONST               7 ('severity_counts')
#              98 BINARY_SUBSCR
#             102 LOAD_CONST               2 ('critical')
#             104 BINARY_SUBSCR
#             108 STORE_FAST               5 (@py_assert0)
#             110 LOAD_CONST               8 (1)
#             112 STORE_FAST               6 (@py_assert3)
#             114 LOAD_FAST                5 (@py_assert0)
#             116 LOAD_FAST                6 (@py_assert3)
#             118 COMPARE_OP              40 (==)
#             122 STORE_FAST               7 (@py_assert2)
#             124 LOAD_FAST                7 (@py_assert2)
#             126 POP_JUMP_IF_TRUE       108 (to 344)
#             128 LOAD_GLOBAL              5 (NULL + @pytest_ar)
#             138 LOAD_ATTR                6 (_call_reprcompare)
#             158 LOAD_CONST               9 (('==',))
#             160 LOAD_FAST                7 (@py_assert2)
#             162 BUILD_TUPLE              1
#             164 LOAD_CONST              10 (('%(py1)s == %(py4)s',))
#             166 LOAD_FAST                5 (@py_assert0)
#             168 LOAD_FAST                6 (@py_assert3)
#             170 BUILD_TUPLE              2
#             172 CALL                     4
#             180 LOAD_GLOBAL              5 (NULL + @pytest_ar)
#             190 LOAD_ATTR                8 (_saferepr)
#             210 LOAD_FAST                5 (@py_assert0)
#             212 CALL                     1
#             220 LOAD_GLOBAL              5 (NULL + @pytest_ar)
#             230 LOAD_ATTR                8 (_saferepr)
#             250 LOAD_FAST                6 (@py_assert3)
#             252 CALL                     1
#             260 LOAD_CONST              11 (('py1', 'py4'))
#             262 BUILD_CONST_KEY_MAP      2
#             264 BINARY_OP                6 (%)
#             268 STORE_FAST               8 (@py_format5)
#             270 LOAD_CONST              12 ('assert %(py6)s')
#             272 LOAD_CONST              13 ('py6')
#             274 LOAD_FAST                8 (@py_format5)
#             276 BUILD_MAP                1
#             278 BINARY_OP                6 (%)
#             282 STORE_FAST               9 (@py_format7)
#             284 LOAD_GLOBAL             11 (NULL + AssertionError)
#             294 LOAD_GLOBAL              5 (NULL + @pytest_ar)
#             304 LOAD_ATTR               12 (_format_explanation)
#             324 LOAD_FAST                9 (@py_format7)
#             326 CALL                     1
#             334 CALL                     1
#             342 RAISE_VARARGS            1
#         >>  344 LOAD_CONST               0 (None)
#             346 COPY                     1
#             348 STORE_FAST               5 (@py_assert0)
#             350 COPY                     1
#             352 STORE_FAST               7 (@py_assert2)
#             354 STORE_FAST               6 (@py_assert3)
# 
#  77         356 LOAD_FAST                4 (digest)
#             358 LOAD_CONST               7 ('severity_counts')
#             360 BINARY_SUBSCR
#             364 LOAD_CONST               3 ('warning')
#             366 BINARY_SUBSCR
#             370 STORE_FAST               5 (@py_assert0)
#             372 LOAD_CONST               8 (1)
#             374 STORE_FAST               6 (@py_assert3)
#             376 LOAD_FAST                5 (@py_assert0)
#             378 LOAD_FAST                6 (@py_assert3)
#             380 COMPARE_OP              40 (==)
#             384 STORE_FAST               7 (@py_assert2)
#             386 LOAD_FAST                7 (@py_assert2)
#             388 POP_JUMP_IF_TRUE       108 (to 606)
#             390 LOAD_GLOBAL              5 (NULL + @pytest_ar)
#             400 LOAD_ATTR                6 (_call_reprcompare)
#             420 LOAD_CONST               9 (('==',))
#             422 LOAD_FAST                7 (@py_assert2)
#             424 BUILD_TUPLE              1
#             426 LOAD_CONST              10 (('%(py1)s == %(py4)s',))
#             428 LOAD_FAST                5 (@py_assert0)
#             430 LOAD_FAST                6 (@py_assert3)
#             432 BUILD_TUPLE              2
#             434 CALL                     4
#             442 LOAD_GLOBAL              5 (NULL + @pytest_ar)
#             452 LOAD_ATTR                8 (_saferepr)
#             472 LOAD_FAST                5 (@py_assert0)
#             474 CALL                     1
#             482 LOAD_GLOBAL              5 (NULL + @pytest_ar)
#             492 LOAD_ATTR                8 (_saferepr)
#             512 LOAD_FAST                6 (@py_assert3)
#             514 CALL                     1
#             522 LOAD_CONST              11 (('py1', 'py4'))
#             524 BUILD_CONST_KEY_MAP      2
#             526 BINARY_OP                6 (%)
#             530 STORE_FAST               8 (@py_format5)
#             532 LOAD_CONST              12 ('assert %(py6)s')
#             534 LOAD_CONST              13 ('py6')
#             536 LOAD_FAST                8 (@py_format5)
#             538 BUILD_MAP                1
#             540 BINARY_OP                6 (%)
#             544 STORE_FAST               9 (@py_format7)
#             546 LOAD_GLOBAL             11 (NULL + AssertionError)
#             556 LOAD_GLOBAL              5 (NULL + @pytest_ar)
#             566 LOAD_ATTR               12 (_format_explanation)
#             586 LOAD_FAST                9 (@py_format7)
#             588 CALL                     1
#             596 CALL                     1
#             604 RAISE_VARARGS            1
#         >>  606 LOAD_CONST               0 (None)
#             608 COPY                     1
#             610 STORE_FAST               5 (@py_assert0)
#             612 COPY                     1
#             614 STORE_FAST               7 (@py_assert2)
#             616 STORE_FAST               6 (@py_assert3)
# 
#  78         618 LOAD_FAST                4 (digest)
#             620 LOAD_CONST               7 ('severity_counts')
#             622 BINARY_SUBSCR
#             626 LOAD_CONST               4 ('observe')
#             628 BINARY_SUBSCR
#             632 STORE_FAST               5 (@py_assert0)
#             634 LOAD_CONST              14 (2)
#             636 STORE_FAST               6 (@py_assert3)
#             638 LOAD_FAST                5 (@py_assert0)
#             640 LOAD_FAST                6 (@py_assert3)
#             642 COMPARE_OP              40 (==)
#             646 STORE_FAST               7 (@py_assert2)
#             648 LOAD_FAST                7 (@py_assert2)
#             650 POP_JUMP_IF_TRUE       108 (to 868)
#             652 LOAD_GLOBAL              5 (NULL + @pytest_ar)
#             662 LOAD_ATTR                6 (_call_reprcompare)
#             682 LOAD_CONST               9 (('==',))
#             684 LOAD_FAST                7 (@py_assert2)
#             686 BUILD_TUPLE              1
#             688 LOAD_CONST              10 (('%(py1)s == %(py4)s',))
#             690 LOAD_FAST                5 (@py_assert0)
#             692 LOAD_FAST                6 (@py_assert3)
#             694 BUILD_TUPLE              2
#             696 CALL                     4
#             704 LOAD_GLOBAL              5 (NULL + @pytest_ar)
#             714 LOAD_ATTR                8 (_saferepr)
#             734 LOAD_FAST                5 (@py_assert0)
#             736 CALL                     1
#             744 LOAD_GLOBAL              5 (NULL + @pytest_ar)
#             754 LOAD_ATTR                8 (_saferepr)
#             774 LOAD_FAST                6 (@py_assert3)
#             776 CALL                     1
#             784 LOAD_CONST              11 (('py1', 'py4'))
#             786 BUILD_CONST_KEY_MAP      2
#             788 BINARY_OP                6 (%)
#             792 STORE_FAST               8 (@py_format5)
#             794 LOAD_CONST              12 ('assert %(py6)s')
#             796 LOAD_CONST              13 ('py6')
#             798 LOAD_FAST                8 (@py_format5)
#             800 BUILD_MAP                1
#             802 BINARY_OP                6 (%)
#             806 STORE_FAST               9 (@py_format7)
#             808 LOAD_GLOBAL             11 (NULL + AssertionError)
#             818 LOAD_GLOBAL              5 (NULL + @pytest_ar)
#             828 LOAD_ATTR               12 (_format_explanation)
#             848 LOAD_FAST                9 (@py_format7)
#             850 CALL                     1
#             858 CALL                     1
#             866 RAISE_VARARGS            1
#         >>  868 LOAD_CONST               0 (None)
#             870 COPY                     1
#             872 STORE_FAST               5 (@py_assert0)
#             874 COPY                     1
#             876 STORE_FAST               7 (@py_assert2)
#             878 STORE_FAST               6 (@py_assert3)
# 
#  79         880 LOAD_FAST                4 (digest)
#             882 LOAD_CONST              15 ('total_cases')
#             884 BINARY_SUBSCR
#             888 STORE_FAST               5 (@py_assert0)
#             890 LOAD_CONST              16 (4)
#             892 STORE_FAST               6 (@py_assert3)
#             894 LOAD_FAST                5 (@py_assert0)
#             896 LOAD_FAST                6 (@py_assert3)
#             898 COMPARE_OP              40 (==)
#             902 STORE_FAST               7 (@py_assert2)
#             904 LOAD_FAST                7 (@py_assert2)
#             906 POP_JUMP_IF_TRUE       108 (to 1124)
#             908 LOAD_GLOBAL              5 (NULL + @pytest_ar)
#             918 LOAD_ATTR                6 (_call_reprcompare)
#             938 LOAD_CONST               9 (('==',))
#             940 LOAD_FAST                7 (@py_assert2)
#             942 BUILD_TUPLE              1
#             944 LOAD_CONST              10 (('%(py1)s == %(py4)s',))
#             946 LOAD_FAST                5 (@py_assert0)
#             948 LOAD_FAST                6 (@py_assert3)
#             950 BUILD_TUPLE              2
#             952 CALL                     4
#             960 LOAD_GLOBAL              5 (NULL + @pytest_ar)
#             970 LOAD_ATTR                8 (_saferepr)
#             990 LOAD_FAST                5 (@py_assert0)
#             992 CALL                     1
#            1000 LOAD_GLOBAL              5 (NULL + @pytest_ar)
#            1010 LOAD_ATTR                8 (_saferepr)
#            1030 LOAD_FAST                6 (@py_assert3)
#            1032 CALL                     1
#            1040 LOAD_CONST              11 (('py1', 'py4'))
#            1042 BUILD_CONST_KEY_MAP      2
#            1044 BINARY_OP                6 (%)
#            1048 STORE_FAST               8 (@py_format5)
#            1050 LOAD_CONST              12 ('assert %(py6)s')
#            1052 LOAD_CONST              13 ('py6')
#            1054 LOAD_FAST                8 (@py_format5)
#            1056 BUILD_MAP                1
#            1058 BINARY_OP                6 (%)
#            1062 STORE_FAST               9 (@py_format7)
#            1064 LOAD_GLOBAL             11 (NULL + AssertionError)
#            1074 LOAD_GLOBAL              5 (NULL + @pytest_ar)
#            1084 LOAD_ATTR               12 (_format_explanation)
#            1104 LOAD_FAST                9 (@py_format7)
#            1106 CALL                     1
#            1114 CALL                     1
#            1122 RAISE_VARARGS            1
#         >> 1124 LOAD_CONST               0 (None)
#            1126 COPY                     1
#            1128 STORE_FAST               5 (@py_assert0)
#            1130 COPY                     1
#            1132 STORE_FAST               7 (@py_assert2)
#            1134 STORE_FAST               6 (@py_assert3)
#            1136 RETURN_CONST             0 (None)
# 
# Disassembly of <code object TestEmtN1Run at 0x73cd945ff210, file "/home/chenying/researches/cloudpss-toolkit/cloudpss_skills_v2/tests/test_emt_n1_screening.py", line 82>:
#  82           0 RESUME                   0
#               2 LOAD_NAME                0 (__name__)
#               4 STORE_NAME               1 (__module__)
#               6 LOAD_CONST               0 ('TestEmtN1Run')
#               8 STORE_NAME               2 (__qualname__)
# 
#  83          10 LOAD_CONST               1 (<code object test_run_invalid_config_returns_failure at 0x3afa13e0, file "/home/chenying/researches/cloudpss-toolkit/cloudpss_skills_v2/tests/test_emt_n1_screening.py", line 83>)
#              12 MAKE_FUNCTION            0
#              14 STORE_NAME               3 (test_run_invalid_config_returns_failure)
#              16 RETURN_CONST             2 (None)
# 
# Disassembly of <code object test_run_invalid_config_returns_failure at 0x3afa13e0, file "/home/chenying/researches/cloudpss-toolkit/cloudpss_skills_v2/tests/test_emt_n1_screening.py", line 83>:
#  83           0 RESUME                   0
# 
#  84           2 LOAD_GLOBAL              1 (NULL + EmtN1ScreeningSkill)
#              12 CALL                     0
#              20 STORE_FAST               1 (skill)
# 
#  85          22 LOAD_FAST                1 (skill)
#              24 LOAD_ATTR                3 (NULL|self + run)
#              44 BUILD_MAP                0
#              46 CALL                     1
#              54 STORE_FAST               2 (result)
# 
#  86          56 LOAD_FAST                2 (result)
#              58 LOAD_ATTR                4 (status)
#              78 STORE_FAST               3 (@py_assert1)
#              80 LOAD_FAST                3 (@py_assert1)
#              82 LOAD_ATTR                6 (value)
#             102 STORE_FAST               4 (@py_assert3)
#             104 LOAD_CONST               1 ('FAILED')
#             106 LOAD_CONST               2 ('failed')
#             108 BUILD_LIST               2
#             110 STORE_FAST               5 (@py_assert6)
#             112 LOAD_FAST                4 (@py_assert3)
#             114 LOAD_FAST                5 (@py_assert6)
#             116 CONTAINS_OP              0
#             118 STORE_FAST               6 (@py_assert5)
#             120 LOAD_FAST                6 (@py_assert5)
#             122 POP_JUMP_IF_TRUE       193 (to 510)
#             124 LOAD_GLOBAL              9 (NULL + @pytest_ar)
#             134 LOAD_ATTR               10 (_call_reprcompare)
#             154 LOAD_CONST               3 (('in',))
#             156 LOAD_FAST                6 (@py_assert5)
#             158 BUILD_TUPLE              1
#             160 LOAD_CONST               4 (('%(py4)s\n{%(py4)s = %(py2)s\n{%(py2)s = %(py0)s.status\n}.value\n} in %(py7)s',))
#             162 LOAD_FAST                4 (@py_assert3)
#             164 LOAD_FAST                5 (@py_assert6)
#             166 BUILD_TUPLE              2
#             168 CALL                     4
#             176 LOAD_CONST               5 ('result')
#             178 LOAD_GLOBAL             13 (NULL + @py_builtins)
#             188 LOAD_ATTR               14 (locals)
#             208 CALL                     0
#             216 CONTAINS_OP              0
#             218 POP_JUMP_IF_TRUE        21 (to 262)
#             220 LOAD_GLOBAL              9 (NULL + @pytest_ar)
#             230 LOAD_ATTR               16 (_should_repr_global_name)
#             250 LOAD_FAST                2 (result)
#             252 CALL                     1
#             260 POP_JUMP_IF_FALSE       21 (to 304)
#         >>  262 LOAD_GLOBAL              9 (NULL + @pytest_ar)
#             272 LOAD_ATTR               18 (_saferepr)
#             292 LOAD_FAST                2 (result)
#             294 CALL                     1
#             302 JUMP_FORWARD             1 (to 306)
#         >>  304 LOAD_CONST               5 ('result')
#         >>  306 LOAD_GLOBAL              9 (NULL + @pytest_ar)
#             316 LOAD_ATTR               18 (_saferepr)
#             336 LOAD_FAST                3 (@py_assert1)
#             338 CALL                     1
#             346 LOAD_GLOBAL              9 (NULL + @pytest_ar)
#             356 LOAD_ATTR               18 (_saferepr)
#             376 LOAD_FAST                4 (@py_assert3)
#             378 CALL                     1
#             386 LOAD_GLOBAL              9 (NULL + @pytest_ar)
#             396 LOAD_ATTR               18 (_saferepr)
#             416 LOAD_FAST                5 (@py_assert6)
#             418 CALL                     1
#             426 LOAD_CONST               6 (('py0', 'py2', 'py4', 'py7'))
#             428 BUILD_CONST_KEY_MAP      4
#             430 BINARY_OP                6 (%)
#             434 STORE_FAST               7 (@py_format8)
#             436 LOAD_CONST               7 ('assert %(py9)s')
#             438 LOAD_CONST               8 ('py9')
#             440 LOAD_FAST                7 (@py_format8)
#             442 BUILD_MAP                1
#             444 BINARY_OP                6 (%)
#             448 STORE_FAST               8 (@py_format10)
#             450 LOAD_GLOBAL             21 (NULL + AssertionError)
#             460 LOAD_GLOBAL              9 (NULL + @pytest_ar)
#             470 LOAD_ATTR               22 (_format_explanation)
#             490 LOAD_FAST                8 (@py_format10)
#             492 CALL                     1
#             500 CALL                     1
#             508 RAISE_VARARGS            1
#         >>  510 LOAD_CONST               0 (None)
#             512 COPY                     1
#             514 STORE_FAST               3 (@py_assert1)
#             516 COPY                     1
#             518 STORE_FAST               4 (@py_assert3)
#             520 COPY                     1
#             522 STORE_FAST               6 (@py_assert5)
#             524 STORE_FAST               5 (@py_assert6)
#             526 RETURN_CONST             0 (None)
# 