# Recovered from: /home/chenying/researches/cloudpss-toolkit/cloudpss_skills_v2/tests/__pycache__/test_contingency_analysis.cpython-312-pytest-9.0.2.pyc
# Original source: /home/chenying/researches/cloudpss-toolkit/cloudpss_skills_v2/tests/test_contingency_analysis.py
# WARNING: This file was reconstructed from .pyc bytecode.
# The structure is accurate but implementation details may need manual review.


def TestContingencyAnalysisValidate():
    """TestContingencyAnalysisValidate"""
pass  # TODO: restore


def TestContingencyAnalysisGenerate():
    """TestContingencyAnalysisGenerate"""
pass  # TODO: restore


def TestContingencyAnalysisSeverity():
    """TestContingencyAnalysisSeverity"""
pass  # TODO: restore


def TestContingencyAnalysisWeakPoints():
    """TestContingencyAnalysisWeakPoints"""
pass  # TODO: restore


def TestContingencyAnalysisRun():
    """TestContingencyAnalysisRun"""
pass  # TODO: restore



# === FULL DISASSEMBLY (for manual reconstruction) ===
#   0           0 RESUME                   0
# 
#   1           2 LOAD_CONST               0 ('Tests for contingency_analysis skill (v2 pattern).')
#               4 STORE_NAME               0 (__doc__)
# 
#   3           6 LOAD_CONST               1 (0)
#               8 LOAD_CONST               2 (None)
#              10 IMPORT_NAME              1 (builtins)
#              12 STORE_NAME               2 (@py_builtins)
#              14 LOAD_CONST               1 (0)
#              16 LOAD_CONST               2 (None)
#              18 IMPORT_NAME              3 (_pytest.assertion.rewrite)
#              20 IMPORT_FROM              4 (assertion)
#              22 SWAP                     2
#              24 POP_TOP
#              26 IMPORT_FROM              5 (rewrite)
#              28 STORE_NAME               6 (@pytest_ar)
#              30 POP_TOP
#              32 LOAD_CONST               1 (0)
#              34 LOAD_CONST               2 (None)
#              36 IMPORT_NAME              7 (pytest)
#              38 STORE_NAME               7 (pytest)
# 
#   4          40 LOAD_CONST               1 (0)
#              42 LOAD_CONST               3 (('SkillResult', 'SkillStatus'))
#              44 IMPORT_NAME              8 (cloudpss_skills_v2.core)
#              46 IMPORT_FROM              9 (SkillResult)
#              48 STORE_NAME               9 (SkillResult)
#              50 IMPORT_FROM             10 (SkillStatus)
#              52 STORE_NAME              10 (SkillStatus)
#              54 POP_TOP
# 
#   5          56 LOAD_CONST               1 (0)
#              58 LOAD_CONST               4 (('ContingencyAnalysisSkill',))
#              60 IMPORT_NAME             11 (cloudpss_skills_v2.skills.contingency_analysis)
#              62 IMPORT_FROM             12 (ContingencyAnalysisSkill)
#              64 STORE_NAME              12 (ContingencyAnalysisSkill)
#              66 POP_TOP
# 
#   8          68 PUSH_NULL
#              70 LOAD_BUILD_CLASS
#              72 LOAD_CONST               5 (<code object TestContingencyAnalysisValidate at 0x73cd93b06970, file "/home/chenying/researches/cloudpss-toolkit/cloudpss_skills_v2/tests/test_contingency_analysis.py", line 8>)
#              74 MAKE_FUNCTION            0
#              76 LOAD_CONST               6 ('TestContingencyAnalysisValidate')
#              78 CALL                     2
#              86 STORE_NAME              13 (TestContingencyAnalysisValidate)
# 
#  59          88 PUSH_NULL
#              90 LOAD_BUILD_CLASS
#              92 LOAD_CONST               7 (<code object TestContingencyAnalysisGenerate at 0x73cd93b066a0, file "/home/chenying/researches/cloudpss-toolkit/cloudpss_skills_v2/tests/test_contingency_analysis.py", line 59>)
#              94 MAKE_FUNCTION            0
#              96 LOAD_CONST               8 ('TestContingencyAnalysisGenerate')
#              98 CALL                     2
#             106 STORE_NAME              14 (TestContingencyAnalysisGenerate)
# 
#  85         108 PUSH_NULL
#             110 LOAD_BUILD_CLASS
#             112 LOAD_CONST               9 (<code object TestContingencyAnalysisSeverity at 0x73cd945fe6b0, file "/home/chenying/researches/cloudpss-toolkit/cloudpss_skills_v2/tests/test_contingency_analysis.py", line 85>)
#             114 MAKE_FUNCTION            0
#             116 LOAD_CONST              10 ('TestContingencyAnalysisSeverity')
#             118 CALL                     2
#             126 STORE_NAME              15 (TestContingencyAnalysisSeverity)
# 
# 106         128 PUSH_NULL
#             130 LOAD_BUILD_CLASS
#             132 LOAD_CONST              11 (<code object TestContingencyAnalysisWeakPoints at 0x73cd945fe330, file "/home/chenying/researches/cloudpss-toolkit/cloudpss_skills_v2/tests/test_contingency_analysis.py", line 106>)
#             134 MAKE_FUNCTION            0
#             136 LOAD_CONST              12 ('TestContingencyAnalysisWeakPoints')
#             138 CALL                     2
#             146 STORE_NAME              16 (TestContingencyAnalysisWeakPoints)
# 
# 120         148 PUSH_NULL
#             150 LOAD_BUILD_CLASS
#             152 LOAD_CONST              13 (<code object TestContingencyAnalysisRun at 0x73cd945fc110, file "/home/chenying/researches/cloudpss-toolkit/cloudpss_skills_v2/tests/test_contingency_analysis.py", line 120>)
#             154 MAKE_FUNCTION            0
#             156 LOAD_CONST              14 ('TestContingencyAnalysisRun')
#             158 CALL                     2
#             166 STORE_NAME              17 (TestContingencyAnalysisRun)
#             168 RETURN_CONST             2 (None)
# 
# Disassembly of <code object TestContingencyAnalysisValidate at 0x73cd93b06970, file "/home/chenying/researches/cloudpss-toolkit/cloudpss_skills_v2/tests/test_contingency_analysis.py", line 8>:
#   8           0 RESUME                   0
#               2 LOAD_NAME                0 (__name__)
#               4 STORE_NAME               1 (__module__)
#               6 LOAD_CONST               0 ('TestContingencyAnalysisValidate')
#               8 STORE_NAME               2 (__qualname__)
# 
#   9          10 LOAD_CONST               1 (<code object test_valid_config at 0x3afa3560, file "/home/chenying/researches/cloudpss-toolkit/cloudpss_skills_v2/tests/test_contingency_analysis.py", line 9>)
#              12 MAKE_FUNCTION            0
#              14 STORE_NAME               3 (test_valid_config)
# 
#  23          16 LOAD_CONST               2 (<code object test_missing_model_rid at 0x3af94f70, file "/home/chenying/researches/cloudpss-toolkit/cloudpss_skills_v2/tests/test_contingency_analysis.py", line 23>)
#              18 MAKE_FUNCTION            0
#              20 STORE_NAME               4 (test_missing_model_rid)
# 
#  29          22 LOAD_CONST               3 (<code object test_invalid_level_format at 0x3af3fb70, file "/home/chenying/researches/cloudpss-toolkit/cloudpss_skills_v2/tests/test_contingency_analysis.py", line 29>)
#              24 MAKE_FUNCTION            0
#              26 STORE_NAME               5 (test_invalid_level_format)
# 
#  38          28 LOAD_CONST               4 (<code object test_voltage_limit_reversed at 0x3af981b0, file "/home/chenying/researches/cloudpss-toolkit/cloudpss_skills_v2/tests/test_contingency_analysis.py", line 38>)
#              30 MAKE_FUNCTION            0
#              32 STORE_NAME               6 (test_voltage_limit_reversed)
# 
#  49          34 LOAD_CONST               5 (<code object test_negative_thermal_limit at 0x3afad0d0, file "/home/chenying/researches/cloudpss-toolkit/cloudpss_skills_v2/tests/test_contingency_analysis.py", line 49>)
#              36 MAKE_FUNCTION            0
#              38 STORE_NAME               7 (test_negative_thermal_limit)
#              40 RETURN_CONST             6 (None)
# 
# Disassembly of <code object test_valid_config at 0x3afa3560, file "/home/chenying/researches/cloudpss-toolkit/cloudpss_skills_v2/tests/test_contingency_analysis.py", line 9>:
#   9           0 RESUME                   0
# 
#  10           2 LOAD_GLOBAL              1 (NULL + ContingencyAnalysisSkill)
#              12 CALL                     0
#              20 STORE_FAST               1 (skill)
# 
#  12          22 LOAD_CONST               1 ('rid')
#              24 LOAD_CONST               2 ('model/test/IEEE39')
#              26 BUILD_MAP                1
# 
#  13          28 LOAD_CONST               3 ('N-1')
#              30 LOAD_CONST               4 (100)
#              32 LOAD_CONST               5 (('level', 'max_combinations'))
#              34 BUILD_CONST_KEY_MAP      2
# 
#  15          36 LOAD_CONST               6 (0.95)
#              38 LOAD_CONST               7 (1.05)
#              40 LOAD_CONST               8 (('min', 'max'))
#              42 BUILD_CONST_KEY_MAP      2
# 
#  16          44 LOAD_CONST               9 (1.0)
# 
#  14          46 LOAD_CONST              10 (('voltage_limit', 'thermal_limit'))
#              48 BUILD_CONST_KEY_MAP      2
# 
#  11          50 LOAD_CONST              11 (('model', 'contingency', 'analysis'))
#              52 BUILD_CONST_KEY_MAP      3
#              54 STORE_FAST               2 (config)
# 
#  19          56 LOAD_FAST                1 (skill)
#              58 LOAD_ATTR                3 (NULL|self + validate)
#              78 LOAD_FAST                2 (config)
#              80 CALL                     1
#              88 UNPACK_SEQUENCE          2
#              92 STORE_FAST               3 (valid)
#              94 STORE_FAST               4 (errors)
# 
#  20          96 LOAD_CONST              12 (True)
#              98 STORE_FAST               5 (@py_assert2)
#             100 LOAD_FAST                3 (valid)
#             102 LOAD_FAST                5 (@py_assert2)
#             104 IS_OP                    0
#             106 STORE_FAST               6 (@py_assert1)
#             108 LOAD_FAST                6 (@py_assert1)
#             110 POP_JUMP_IF_TRUE       153 (to 418)
#             112 LOAD_GLOBAL              5 (NULL + @pytest_ar)
#             122 LOAD_ATTR                6 (_call_reprcompare)
#             142 LOAD_CONST              13 (('is',))
#             144 LOAD_FAST                6 (@py_assert1)
#             146 BUILD_TUPLE              1
#             148 LOAD_CONST              14 (('%(py0)s is %(py3)s',))
#             150 LOAD_FAST                3 (valid)
#             152 LOAD_FAST                5 (@py_assert2)
#             154 BUILD_TUPLE              2
#             156 CALL                     4
#             164 LOAD_CONST              15 ('valid')
#             166 LOAD_GLOBAL              9 (NULL + @py_builtins)
#             176 LOAD_ATTR               10 (locals)
#             196 CALL                     0
#             204 CONTAINS_OP              0
#             206 POP_JUMP_IF_TRUE        21 (to 250)
#             208 LOAD_GLOBAL              5 (NULL + @pytest_ar)
#             218 LOAD_ATTR               12 (_should_repr_global_name)
#             238 LOAD_FAST                3 (valid)
#             240 CALL                     1
#             248 POP_JUMP_IF_FALSE       21 (to 292)
#         >>  250 LOAD_GLOBAL              5 (NULL + @pytest_ar)
#             260 LOAD_ATTR               14 (_saferepr)
#             280 LOAD_FAST                3 (valid)
#             282 CALL                     1
#             290 JUMP_FORWARD             1 (to 294)
#         >>  292 LOAD_CONST              15 ('valid')
#         >>  294 LOAD_GLOBAL              5 (NULL + @pytest_ar)
#             304 LOAD_ATTR               14 (_saferepr)
#             324 LOAD_FAST                5 (@py_assert2)
#             326 CALL                     1
#             334 LOAD_CONST              16 (('py0', 'py3'))
#             336 BUILD_CONST_KEY_MAP      2
#             338 BINARY_OP                6 (%)
#             342 STORE_FAST               7 (@py_format4)
#             344 LOAD_CONST              17 ('assert %(py5)s')
#             346 LOAD_CONST              18 ('py5')
#             348 LOAD_FAST                7 (@py_format4)
#             350 BUILD_MAP                1
#             352 BINARY_OP                6 (%)
#             356 STORE_FAST               8 (@py_format6)
#             358 LOAD_GLOBAL             17 (NULL + AssertionError)
#             368 LOAD_GLOBAL              5 (NULL + @pytest_ar)
#             378 LOAD_ATTR               18 (_format_explanation)
#             398 LOAD_FAST                8 (@py_format6)
#             400 CALL                     1
#             408 CALL                     1
#             416 RAISE_VARARGS            1
#         >>  418 LOAD_CONST               0 (None)
#             420 COPY                     1
#             422 STORE_FAST               6 (@py_assert1)
#             424 STORE_FAST               5 (@py_assert2)
# 
#  21         426 BUILD_LIST               0
#             428 STORE_FAST               5 (@py_assert2)
#             430 LOAD_FAST                4 (errors)
#             432 LOAD_FAST                5 (@py_assert2)
#             434 COMPARE_OP              40 (==)
#             438 STORE_FAST               6 (@py_assert1)
#             440 LOAD_FAST                6 (@py_assert1)
#             442 POP_JUMP_IF_TRUE       153 (to 750)
#             444 LOAD_GLOBAL              5 (NULL + @pytest_ar)
#             454 LOAD_ATTR                6 (_call_reprcompare)
#             474 LOAD_CONST              19 (('==',))
#             476 LOAD_FAST                6 (@py_assert1)
#             478 BUILD_TUPLE              1
#             480 LOAD_CONST              20 (('%(py0)s == %(py3)s',))
#             482 LOAD_FAST                4 (errors)
#             484 LOAD_FAST                5 (@py_assert2)
#             486 BUILD_TUPLE              2
#             488 CALL                     4
#             496 LOAD_CONST              21 ('errors')
#             498 LOAD_GLOBAL              9 (NULL + @py_builtins)
#             508 LOAD_ATTR               10 (locals)
#             528 CALL                     0
#             536 CONTAINS_OP              0
#             538 POP_JUMP_IF_TRUE        21 (to 582)
#             540 LOAD_GLOBAL              5 (NULL + @pytest_ar)
#             550 LOAD_ATTR               12 (_should_repr_global_name)
#             570 LOAD_FAST                4 (errors)
#             572 CALL                     1
#             580 POP_JUMP_IF_FALSE       21 (to 624)
#         >>  582 LOAD_GLOBAL              5 (NULL + @pytest_ar)
#             592 LOAD_ATTR               14 (_saferepr)
#             612 LOAD_FAST                4 (errors)
#             614 CALL                     1
#             622 JUMP_FORWARD             1 (to 626)
#         >>  624 LOAD_CONST              21 ('errors')
#         >>  626 LOAD_GLOBAL              5 (NULL + @pytest_ar)
#             636 LOAD_ATTR               14 (_saferepr)
#             656 LOAD_FAST                5 (@py_assert2)
#             658 CALL                     1
#             666 LOAD_CONST              16 (('py0', 'py3'))
#             668 BUILD_CONST_KEY_MAP      2
#             670 BINARY_OP                6 (%)
#             674 STORE_FAST               7 (@py_format4)
#             676 LOAD_CONST              17 ('assert %(py5)s')
#             678 LOAD_CONST              18 ('py5')
#             680 LOAD_FAST                7 (@py_format4)
#             682 BUILD_MAP                1
#             684 BINARY_OP                6 (%)
#             688 STORE_FAST               8 (@py_format6)
#             690 LOAD_GLOBAL             17 (NULL + AssertionError)
#             700 LOAD_GLOBAL              5 (NULL + @pytest_ar)
#             710 LOAD_ATTR               18 (_format_explanation)
#             730 LOAD_FAST                8 (@py_format6)
#             732 CALL                     1
#             740 CALL                     1
#             748 RAISE_VARARGS            1
#         >>  750 LOAD_CONST               0 (None)
#             752 COPY                     1
#             754 STORE_FAST               6 (@py_assert1)
#             756 STORE_FAST               5 (@py_assert2)
#             758 RETURN_CONST             0 (None)
# 
# Disassembly of <code object test_missing_model_rid at 0x3af94f70, file "/home/chenying/researches/cloudpss-toolkit/cloudpss_skills_v2/tests/test_contingency_analysis.py", line 23>:
#  23           0 RESUME                   0
# 
#  24           2 LOAD_GLOBAL              1 (NULL + ContingencyAnalysisSkill)
#              12 CALL                     0
#              20 STORE_FAST               1 (skill)
# 
#  25          22 LOAD_FAST                1 (skill)
#              24 LOAD_ATTR                3 (NULL|self + validate)
#              44 LOAD_CONST               1 ('model')
#              46 BUILD_MAP                0
#              48 BUILD_MAP                1
#              50 CALL                     1
#              58 UNPACK_SEQUENCE          2
#              62 STORE_FAST               2 (valid)
#              64 STORE_FAST               3 (errors)
# 
#  26          66 LOAD_CONST               2 (False)
#              68 STORE_FAST               4 (@py_assert2)
#              70 LOAD_FAST                2 (valid)
#              72 LOAD_FAST                4 (@py_assert2)
#              74 IS_OP                    0
#              76 STORE_FAST               5 (@py_assert1)
#              78 LOAD_FAST                5 (@py_assert1)
#              80 POP_JUMP_IF_TRUE       153 (to 388)
#              82 LOAD_GLOBAL              5 (NULL + @pytest_ar)
#              92 LOAD_ATTR                6 (_call_reprcompare)
#             112 LOAD_CONST               3 (('is',))
#             114 LOAD_FAST                5 (@py_assert1)
#             116 BUILD_TUPLE              1
#             118 LOAD_CONST               4 (('%(py0)s is %(py3)s',))
#             120 LOAD_FAST                2 (valid)
#             122 LOAD_FAST                4 (@py_assert2)
#             124 BUILD_TUPLE              2
#             126 CALL                     4
#             134 LOAD_CONST               5 ('valid')
#             136 LOAD_GLOBAL              9 (NULL + @py_builtins)
#             146 LOAD_ATTR               10 (locals)
#             166 CALL                     0
#             174 CONTAINS_OP              0
#             176 POP_JUMP_IF_TRUE        21 (to 220)
#             178 LOAD_GLOBAL              5 (NULL + @pytest_ar)
#             188 LOAD_ATTR               12 (_should_repr_global_name)
#             208 LOAD_FAST                2 (valid)
#             210 CALL                     1
#             218 POP_JUMP_IF_FALSE       21 (to 262)
#         >>  220 LOAD_GLOBAL              5 (NULL + @pytest_ar)
#             230 LOAD_ATTR               14 (_saferepr)
#             250 LOAD_FAST                2 (valid)
#             252 CALL                     1
#             260 JUMP_FORWARD             1 (to 264)
#         >>  262 LOAD_CONST               5 ('valid')
#         >>  264 LOAD_GLOBAL              5 (NULL + @pytest_ar)
#             274 LOAD_ATTR               14 (_saferepr)
#             294 LOAD_FAST                4 (@py_assert2)
#             296 CALL                     1
#             304 LOAD_CONST               6 (('py0', 'py3'))
#             306 BUILD_CONST_KEY_MAP      2
#             308 BINARY_OP                6 (%)
#             312 STORE_FAST               6 (@py_format4)
#             314 LOAD_CONST               7 ('assert %(py5)s')
#             316 LOAD_CONST               8 ('py5')
#             318 LOAD_FAST                6 (@py_format4)
#             320 BUILD_MAP                1
#             322 BINARY_OP                6 (%)
#             326 STORE_FAST               7 (@py_format6)
#             328 LOAD_GLOBAL             17 (NULL + AssertionError)
#             338 LOAD_GLOBAL              5 (NULL + @pytest_ar)
#             348 LOAD_ATTR               18 (_format_explanation)
#             368 LOAD_FAST                7 (@py_format6)
#             370 CALL                     1
#             378 CALL                     1
#             386 RAISE_VARARGS            1
#         >>  388 LOAD_CONST               0 (None)
#             390 COPY                     1
#             392 STORE_FAST               5 (@py_assert1)
#             394 STORE_FAST               4 (@py_assert2)
# 
#  27         396 LOAD_CONST               9 (<code object <genexpr> at 0x73cd93b06880, file "/home/chenying/researches/cloudpss-toolkit/cloudpss_skills_v2/tests/test_contingency_analysis.py", line 27>)
#             398 MAKE_FUNCTION            0
#             400 LOAD_FAST                3 (errors)
#             402 GET_ITER
#             404 CALL                     0
#             412 STORE_FAST               5 (@py_assert1)
#             414 LOAD_GLOBAL             21 (NULL + any)
#             424 LOAD_FAST                5 (@py_assert1)
#             426 CALL                     1
#             434 STORE_FAST               8 (@py_assert3)
#             436 LOAD_FAST                8 (@py_assert3)
#             438 POP_JUMP_IF_TRUE       149 (to 738)
#             440 LOAD_CONST              10 ('assert %(py4)s\n{%(py4)s = %(py0)s(%(py2)s)\n}')
#             442 LOAD_CONST              11 ('any')
#             444 LOAD_GLOBAL              9 (NULL + @py_builtins)
#             454 LOAD_ATTR               10 (locals)
#             474 CALL                     0
#             482 CONTAINS_OP              0
#             484 POP_JUMP_IF_TRUE        25 (to 536)
#             486 LOAD_GLOBAL              5 (NULL + @pytest_ar)
#             496 LOAD_ATTR               12 (_should_repr_global_name)
#             516 LOAD_GLOBAL             20 (any)
#             526 CALL                     1
#             534 POP_JUMP_IF_FALSE       25 (to 586)
#         >>  536 LOAD_GLOBAL              5 (NULL + @pytest_ar)
#             546 LOAD_ATTR               14 (_saferepr)
#             566 LOAD_GLOBAL             20 (any)
#             576 CALL                     1
#             584 JUMP_FORWARD             1 (to 588)
#         >>  586 LOAD_CONST              11 ('any')
#         >>  588 LOAD_GLOBAL              5 (NULL + @pytest_ar)
#             598 LOAD_ATTR               14 (_saferepr)
#             618 LOAD_FAST                5 (@py_assert1)
#             620 CALL                     1
#             628 LOAD_GLOBAL              5 (NULL + @pytest_ar)
#             638 LOAD_ATTR               14 (_saferepr)
#             658 LOAD_FAST                8 (@py_assert3)
#             660 CALL                     1
#             668 LOAD_CONST              12 (('py0', 'py2', 'py4'))
#             670 BUILD_CONST_KEY_MAP      3
#             672 BINARY_OP                6 (%)
#             676 STORE_FAST               9 (@py_format5)
#             678 LOAD_GLOBAL             17 (NULL + AssertionError)
#             688 LOAD_GLOBAL              5 (NULL + @pytest_ar)
#             698 LOAD_ATTR               18 (_format_explanation)
#             718 LOAD_FAST                9 (@py_format5)
#             720 CALL                     1
#             728 CALL                     1
#             736 RAISE_VARARGS            1
#         >>  738 LOAD_CONST               0 (None)
#             740 COPY                     1
#             742 STORE_FAST               5 (@py_assert1)
#             744 STORE_FAST               8 (@py_assert3)
#             746 RETURN_CONST             0 (None)
# 
# Disassembly of <code object <genexpr> at 0x73cd93b06880, file "/home/chenying/researches/cloudpss-toolkit/cloudpss_skills_v2/tests/test_contingency_analysis.py", line 27>:
#  27           0 RETURN_GENERATOR
#               2 POP_TOP
#               4 RESUME                   0
#               6 LOAD_FAST                0 (.0)
#         >>    8 FOR_ITER                 8 (to 28)
#              12 STORE_FAST               1 (e)
#              14 LOAD_CONST               0 ('model.rid')
#              16 LOAD_FAST                1 (e)
#              18 CONTAINS_OP              0
#              20 YIELD_VALUE              1
#              22 RESUME                   1
#              24 POP_TOP
#              26 JUMP_BACKWARD           10 (to 8)
#         >>   28 END_FOR
#              30 RETURN_CONST             1 (None)
#         >>   32 CALL_INTRINSIC_1         3 (INTRINSIC_STOPITERATION_ERROR)
#              34 RERAISE                  1
# ExceptionTable:
#   4 to 30 -> 32 [0] lasti
# 
# Disassembly of <code object test_invalid_level_format at 0x3af3fb70, file "/home/chenying/researches/cloudpss-toolkit/cloudpss_skills_v2/tests/test_contingency_analysis.py", line 29>:
#  29           0 RESUME                   0
# 
#  30           2 LOAD_GLOBAL              1 (NULL + ContingencyAnalysisSkill)
#              12 CALL                     0
#              20 STORE_FAST               1 (skill)
# 
#  32          22 LOAD_CONST               1 ('rid')
#              24 LOAD_CONST               2 ('test')
#              26 BUILD_MAP                1
# 
#  33          28 LOAD_CONST               3 ('level')
#              30 LOAD_CONST               4 ('invalid')
#              32 BUILD_MAP                1
# 
#  31          34 LOAD_CONST               5 (('model', 'contingency'))
#              36 BUILD_CONST_KEY_MAP      2
#              38 STORE_FAST               2 (config)
# 
#  35          40 LOAD_FAST                1 (skill)
#              42 LOAD_ATTR                3 (NULL|self + validate)
#              62 LOAD_FAST                2 (config)
#              64 CALL                     1
#              72 UNPACK_SEQUENCE          2
#              76 STORE_FAST               3 (valid)
#              78 STORE_FAST               4 (errors)
# 
#  36          80 LOAD_CONST               6 (False)
#              82 STORE_FAST               5 (@py_assert2)
#              84 LOAD_FAST                3 (valid)
#              86 LOAD_FAST                5 (@py_assert2)
#              88 IS_OP                    0
#              90 STORE_FAST               6 (@py_assert1)
#              92 LOAD_FAST                6 (@py_assert1)
#              94 POP_JUMP_IF_TRUE       153 (to 402)
#              96 LOAD_GLOBAL              5 (NULL + @pytest_ar)
#             106 LOAD_ATTR                6 (_call_reprcompare)
#             126 LOAD_CONST               7 (('is',))
#             128 LOAD_FAST                6 (@py_assert1)
#             130 BUILD_TUPLE              1
#             132 LOAD_CONST               8 (('%(py0)s is %(py3)s',))
#             134 LOAD_FAST                3 (valid)
#             136 LOAD_FAST                5 (@py_assert2)
#             138 BUILD_TUPLE              2
#             140 CALL                     4
#             148 LOAD_CONST               9 ('valid')
#             150 LOAD_GLOBAL              9 (NULL + @py_builtins)
#             160 LOAD_ATTR               10 (locals)
#             180 CALL                     0
#             188 CONTAINS_OP              0
#             190 POP_JUMP_IF_TRUE        21 (to 234)
#             192 LOAD_GLOBAL              5 (NULL + @pytest_ar)
#             202 LOAD_ATTR               12 (_should_repr_global_name)
#             222 LOAD_FAST                3 (valid)
#             224 CALL                     1
#             232 POP_JUMP_IF_FALSE       21 (to 276)
#         >>  234 LOAD_GLOBAL              5 (NULL + @pytest_ar)
#             244 LOAD_ATTR               14 (_saferepr)
#             264 LOAD_FAST                3 (valid)
#             266 CALL                     1
#             274 JUMP_FORWARD             1 (to 278)
#         >>  276 LOAD_CONST               9 ('valid')
#         >>  278 LOAD_GLOBAL              5 (NULL + @pytest_ar)
#             288 LOAD_ATTR               14 (_saferepr)
#             308 LOAD_FAST                5 (@py_assert2)
#             310 CALL                     1
#             318 LOAD_CONST              10 (('py0', 'py3'))
#             320 BUILD_CONST_KEY_MAP      2
#             322 BINARY_OP                6 (%)
#             326 STORE_FAST               7 (@py_format4)
#             328 LOAD_CONST              11 ('assert %(py5)s')
#             330 LOAD_CONST              12 ('py5')
#             332 LOAD_FAST                7 (@py_format4)
#             334 BUILD_MAP                1
#             336 BINARY_OP                6 (%)
#             340 STORE_FAST               8 (@py_format6)
#             342 LOAD_GLOBAL             17 (NULL + AssertionError)
#             352 LOAD_GLOBAL              5 (NULL + @pytest_ar)
#             362 LOAD_ATTR               18 (_format_explanation)
#             382 LOAD_FAST                8 (@py_format6)
#             384 CALL                     1
#             392 CALL                     1
#             400 RAISE_VARARGS            1
#         >>  402 LOAD_CONST               0 (None)
#             404 COPY                     1
#             406 STORE_FAST               6 (@py_assert1)
#             408 STORE_FAST               5 (@py_assert2)
#             410 RETURN_CONST             0 (None)
# 
# Disassembly of <code object test_voltage_limit_reversed at 0x3af981b0, file "/home/chenying/researches/cloudpss-toolkit/cloudpss_skills_v2/tests/test_contingency_analysis.py", line 38>:
#  38           0 RESUME                   0
# 
#  39           2 LOAD_GLOBAL              1 (NULL + ContingencyAnalysisSkill)
#              12 CALL                     0
#              20 STORE_FAST               1 (skill)
# 
#  41          22 LOAD_CONST               1 ('rid')
#              24 LOAD_CONST               2 ('test')
#              26 BUILD_MAP                1
# 
#  42          28 LOAD_CONST               3 ('level')
#              30 LOAD_CONST               4 ('N-1')
#              32 BUILD_MAP                1
# 
#  43          34 LOAD_CONST               5 ('voltage_limit')
#              36 LOAD_CONST               6 (1.05)
#              38 LOAD_CONST               7 (0.95)
#              40 LOAD_CONST               8 (('min', 'max'))
#              42 BUILD_CONST_KEY_MAP      2
#              44 BUILD_MAP                1
# 
#  40          46 LOAD_CONST               9 (('model', 'contingency', 'analysis'))
#              48 BUILD_CONST_KEY_MAP      3
#              50 STORE_FAST               2 (config)
# 
#  45          52 LOAD_FAST                1 (skill)
#              54 LOAD_ATTR                3 (NULL|self + validate)
#              74 LOAD_FAST                2 (config)
#              76 CALL                     1
#              84 UNPACK_SEQUENCE          2
#              88 STORE_FAST               3 (valid)
#              90 STORE_FAST               4 (errors)
# 
#  46          92 LOAD_CONST              10 (False)
#              94 STORE_FAST               5 (@py_assert2)
#              96 LOAD_FAST                3 (valid)
#              98 LOAD_FAST                5 (@py_assert2)
#             100 IS_OP                    0
#             102 STORE_FAST               6 (@py_assert1)
#             104 LOAD_FAST                6 (@py_assert1)
#             106 POP_JUMP_IF_TRUE       153 (to 414)
#             108 LOAD_GLOBAL              5 (NULL + @pytest_ar)
#             118 LOAD_ATTR                6 (_call_reprcompare)
#             138 LOAD_CONST              11 (('is',))
#             140 LOAD_FAST                6 (@py_assert1)
#             142 BUILD_TUPLE              1
#             144 LOAD_CONST              12 (('%(py0)s is %(py3)s',))
#             146 LOAD_FAST                3 (valid)
#             148 LOAD_FAST                5 (@py_assert2)
#             150 BUILD_TUPLE              2
#             152 CALL                     4
#             160 LOAD_CONST              13 ('valid')
#             162 LOAD_GLOBAL              9 (NULL + @py_builtins)
#             172 LOAD_ATTR               10 (locals)
#             192 CALL                     0
#             200 CONTAINS_OP              0
#             202 POP_JUMP_IF_TRUE        21 (to 246)
#             204 LOAD_GLOBAL              5 (NULL + @pytest_ar)
#             214 LOAD_ATTR               12 (_should_repr_global_name)
#             234 LOAD_FAST                3 (valid)
#             236 CALL                     1
#             244 POP_JUMP_IF_FALSE       21 (to 288)
#         >>  246 LOAD_GLOBAL              5 (NULL + @pytest_ar)
#             256 LOAD_ATTR               14 (_saferepr)
#             276 LOAD_FAST                3 (valid)
#             278 CALL                     1
#             286 JUMP_FORWARD             1 (to 290)
#         >>  288 LOAD_CONST              13 ('valid')
#         >>  290 LOAD_GLOBAL              5 (NULL + @pytest_ar)
#             300 LOAD_ATTR               14 (_saferepr)
#             320 LOAD_FAST                5 (@py_assert2)
#             322 CALL                     1
#             330 LOAD_CONST              14 (('py0', 'py3'))
#             332 BUILD_CONST_KEY_MAP      2
#             334 BINARY_OP                6 (%)
#             338 STORE_FAST               7 (@py_format4)
#             340 LOAD_CONST              15 ('assert %(py5)s')
#             342 LOAD_CONST              16 ('py5')
#             344 LOAD_FAST                7 (@py_format4)
#             346 BUILD_MAP                1
#             348 BINARY_OP                6 (%)
#             352 STORE_FAST               8 (@py_format6)
#             354 LOAD_GLOBAL             17 (NULL + AssertionError)
#             364 LOAD_GLOBAL              5 (NULL + @pytest_ar)
#             374 LOAD_ATTR               18 (_format_explanation)
#             394 LOAD_FAST                8 (@py_format6)
#             396 CALL                     1
#             404 CALL                     1
#             412 RAISE_VARARGS            1
#         >>  414 LOAD_CONST               0 (None)
#             416 COPY                     1
#             418 STORE_FAST               6 (@py_assert1)
#             420 STORE_FAST               5 (@py_assert2)
# 
#  47         422 LOAD_CONST              17 (<code object <genexpr> at 0x73cd93b064c0, file "/home/chenying/researches/cloudpss-toolkit/cloudpss_skills_v2/tests/test_contingency_analysis.py", line 47>)
#             424 MAKE_FUNCTION            0
#             426 LOAD_FAST                4 (errors)
#             428 GET_ITER
#             430 CALL                     0
#             438 STORE_FAST               6 (@py_assert1)
#             440 LOAD_GLOBAL             21 (NULL + any)
#             450 LOAD_FAST                6 (@py_assert1)
#             452 CALL                     1
#             460 STORE_FAST               9 (@py_assert3)
#             462 LOAD_FAST                9 (@py_assert3)
#             464 POP_JUMP_IF_TRUE       149 (to 764)
#             466 LOAD_CONST              18 ('assert %(py4)s\n{%(py4)s = %(py0)s(%(py2)s)\n}')
#             468 LOAD_CONST              19 ('any')
#             470 LOAD_GLOBAL              9 (NULL + @py_builtins)
#             480 LOAD_ATTR               10 (locals)
#             500 CALL                     0
#             508 CONTAINS_OP              0
#             510 POP_JUMP_IF_TRUE        25 (to 562)
#             512 LOAD_GLOBAL              5 (NULL + @pytest_ar)
#             522 LOAD_ATTR               12 (_should_repr_global_name)
#             542 LOAD_GLOBAL             20 (any)
#             552 CALL                     1
#             560 POP_JUMP_IF_FALSE       25 (to 612)
#         >>  562 LOAD_GLOBAL              5 (NULL + @pytest_ar)
#             572 LOAD_ATTR               14 (_saferepr)
#             592 LOAD_GLOBAL             20 (any)
#             602 CALL                     1
#             610 JUMP_FORWARD             1 (to 614)
#         >>  612 LOAD_CONST              19 ('any')
#         >>  614 LOAD_GLOBAL              5 (NULL + @pytest_ar)
#             624 LOAD_ATTR               14 (_saferepr)
#             644 LOAD_FAST                6 (@py_assert1)
#             646 CALL                     1
#             654 LOAD_GLOBAL              5 (NULL + @pytest_ar)
#             664 LOAD_ATTR               14 (_saferepr)
#             684 LOAD_FAST                9 (@py_assert3)
#             686 CALL                     1
#             694 LOAD_CONST              20 (('py0', 'py2', 'py4'))
#             696 BUILD_CONST_KEY_MAP      3
#             698 BINARY_OP                6 (%)
#             702 STORE_FAST              10 (@py_format5)
#             704 LOAD_GLOBAL             17 (NULL + AssertionError)
#             714 LOAD_GLOBAL              5 (NULL + @pytest_ar)
#             724 LOAD_ATTR               18 (_format_explanation)
#             744 LOAD_FAST               10 (@py_format5)
#             746 CALL                     1
#             754 CALL                     1
#             762 RAISE_VARARGS            1
#         >>  764 LOAD_CONST               0 (None)
#             766 COPY                     1
#             768 STORE_FAST               6 (@py_assert1)
#             770 STORE_FAST               9 (@py_assert3)
#             772 RETURN_CONST             0 (None)
# 
# Disassembly of <code object <genexpr> at 0x73cd93b064c0, file "/home/chenying/researches/cloudpss-toolkit/cloudpss_skills_v2/tests/test_contingency_analysis.py", line 47>:
#  47           0 RETURN_GENERATOR
#               2 POP_TOP
#               4 RESUME                   0
#               6 LOAD_FAST                0 (.0)
#         >>    8 FOR_ITER                14 (to 40)
#              12 STORE_FAST               1 (e)
#              14 LOAD_CONST               0 ('min')
#              16 LOAD_FAST                1 (e)
#              18 CONTAINS_OP              0
#              20 COPY                     1
#              22 POP_JUMP_IF_FALSE        4 (to 32)
#              24 POP_TOP
#              26 LOAD_CONST               1 ('max')
#              28 LOAD_FAST                1 (e)
#              30 CONTAINS_OP              0
#         >>   32 YIELD_VALUE              1
#              34 RESUME                   1
#              36 POP_TOP
#              38 JUMP_BACKWARD           16 (to 8)
#         >>   40 END_FOR
#              42 RETURN_CONST             2 (None)
#         >>   44 CALL_INTRINSIC_1         3 (INTRINSIC_STOPITERATION_ERROR)
#              46 RERAISE                  1
# ExceptionTable:
#   4 to 42 -> 44 [0] lasti
# 
# Disassembly of <code object test_negative_thermal_limit at 0x3afad0d0, file "/home/chenying/researches/cloudpss-toolkit/cloudpss_skills_v2/tests/test_contingency_analysis.py", line 49>:
#  49           0 RESUME                   0
# 
#  50           2 LOAD_GLOBAL              1 (NULL + ContingencyAnalysisSkill)
#              12 CALL                     0
#              20 STORE_FAST               1 (skill)
# 
#  52          22 LOAD_CONST               1 ('rid')
#              24 LOAD_CONST               2 ('test')
#              26 BUILD_MAP                1
# 
#  53          28 LOAD_CONST               3 ('thermal_limit')
#              30 LOAD_CONST               4 (-1.0)
#              32 BUILD_MAP                1
# 
#  51          34 LOAD_CONST               5 (('model', 'analysis'))
#              36 BUILD_CONST_KEY_MAP      2
#              38 STORE_FAST               2 (config)
# 
#  55          40 LOAD_FAST                1 (skill)
#              42 LOAD_ATTR                3 (NULL|self + validate)
#              62 LOAD_FAST                2 (config)
#              64 CALL                     1
#              72 UNPACK_SEQUENCE          2
#              76 STORE_FAST               3 (valid)
#              78 STORE_FAST               4 (errors)
# 
#  56          80 LOAD_CONST               6 (False)
#              82 STORE_FAST               5 (@py_assert2)
#              84 LOAD_FAST                3 (valid)
#              86 LOAD_FAST                5 (@py_assert2)
#              88 IS_OP                    0
#              90 STORE_FAST               6 (@py_assert1)
#              92 LOAD_FAST                6 (@py_assert1)
#              94 POP_JUMP_IF_TRUE       153 (to 402)
#              96 LOAD_GLOBAL              5 (NULL + @pytest_ar)
#             106 LOAD_ATTR                6 (_call_reprcompare)
#             126 LOAD_CONST               7 (('is',))
#             128 LOAD_FAST                6 (@py_assert1)
#             130 BUILD_TUPLE              1
#             132 LOAD_CONST               8 (('%(py0)s is %(py3)s',))
#             134 LOAD_FAST                3 (valid)
#             136 LOAD_FAST                5 (@py_assert2)
#             138 BUILD_TUPLE              2
#             140 CALL                     4
#             148 LOAD_CONST               9 ('valid')
#             150 LOAD_GLOBAL              9 (NULL + @py_builtins)
#             160 LOAD_ATTR               10 (locals)
#             180 CALL                     0
#             188 CONTAINS_OP              0
#             190 POP_JUMP_IF_TRUE        21 (to 234)
#             192 LOAD_GLOBAL              5 (NULL + @pytest_ar)
#             202 LOAD_ATTR               12 (_should_repr_global_name)
#             222 LOAD_FAST                3 (valid)
#             224 CALL                     1
#             232 POP_JUMP_IF_FALSE       21 (to 276)
#         >>  234 LOAD_GLOBAL              5 (NULL + @pytest_ar)
#             244 LOAD_ATTR               14 (_saferepr)
#             264 LOAD_FAST                3 (valid)
#             266 CALL                     1
#             274 JUMP_FORWARD             1 (to 278)
#         >>  276 LOAD_CONST               9 ('valid')
#         >>  278 LOAD_GLOBAL              5 (NULL + @pytest_ar)
#             288 LOAD_ATTR               14 (_saferepr)
#             308 LOAD_FAST                5 (@py_assert2)
#             310 CALL                     1
#             318 LOAD_CONST              10 (('py0', 'py3'))
#             320 BUILD_CONST_KEY_MAP      2
#             322 BINARY_OP                6 (%)
#             326 STORE_FAST               7 (@py_format4)
#             328 LOAD_CONST              11 ('assert %(py5)s')
#             330 LOAD_CONST              12 ('py5')
#             332 LOAD_FAST                7 (@py_format4)
#             334 BUILD_MAP                1
#             336 BINARY_OP                6 (%)
#             340 STORE_FAST               8 (@py_format6)
#             342 LOAD_GLOBAL             17 (NULL + AssertionError)
#             352 LOAD_GLOBAL              5 (NULL + @pytest_ar)
#             362 LOAD_ATTR               18 (_format_explanation)
#             382 LOAD_FAST                8 (@py_format6)
#             384 CALL                     1
#             392 CALL                     1
#             400 RAISE_VARARGS            1
#         >>  402 LOAD_CONST               0 (None)
#             404 COPY                     1
#             406 STORE_FAST               6 (@py_assert1)
#             408 STORE_FAST               5 (@py_assert2)
#             410 RETURN_CONST             0 (None)
# 
# Disassembly of <code object TestContingencyAnalysisGenerate at 0x73cd93b066a0, file "/home/chenying/researches/cloudpss-toolkit/cloudpss_skills_v2/tests/test_contingency_analysis.py", line 59>:
#  59           0 RESUME                   0
#               2 LOAD_NAME                0 (__name__)
#               4 STORE_NAME               1 (__module__)
#               6 LOAD_CONST               0 ('TestContingencyAnalysisGenerate')
#               8 STORE_NAME               2 (__qualname__)
# 
#  60          10 LOAD_CONST               1 (<code object test_n1_combinations at 0x3afa5a90, file "/home/chenying/researches/cloudpss-toolkit/cloudpss_skills_v2/tests/test_contingency_analysis.py", line 60>)
#              12 MAKE_FUNCTION            0
#              14 STORE_NAME               3 (test_n1_combinations)
# 
#  66          16 LOAD_CONST               2 (<code object test_n2_combinations at 0x3afac750, file "/home/chenying/researches/cloudpss-toolkit/cloudpss_skills_v2/tests/test_contingency_analysis.py", line 66>)
#              18 MAKE_FUNCTION            0
#              20 STORE_NAME               4 (test_n2_combinations)
# 
#  72          22 LOAD_CONST               3 (<code object test_max_combinations_limit at 0x3aef1020, file "/home/chenying/researches/cloudpss-toolkit/cloudpss_skills_v2/tests/test_contingency_analysis.py", line 72>)
#              24 MAKE_FUNCTION            0
#              26 STORE_NAME               5 (test_max_combinations_limit)
# 
#  79          28 LOAD_CONST               4 (<code object test_empty_components at 0x3afa3fb0, file "/home/chenying/researches/cloudpss-toolkit/cloudpss_skills_v2/tests/test_contingency_analysis.py", line 79>)
#              30 MAKE_FUNCTION            0
#              32 STORE_NAME               6 (test_empty_components)
#              34 RETURN_CONST             5 (None)
# 
# Disassembly of <code object test_n1_combinations at 0x3afa5a90, file "/home/chenying/researches/cloudpss-toolkit/cloudpss_skills_v2/tests/test_contingency_analysis.py", line 60>:
#  60           0 RESUME                   0
# 
#  61           2 LOAD_GLOBAL              1 (NULL + ContingencyAnalysisSkill)
#              12 CALL                     0
#              20 STORE_FAST               1 (skill)
# 
#  62          22 LOAD_FAST                1 (skill)
#              24 LOAD_ATTR                3 (NULL|self + _generate_contingencies)
#              44 BUILD_LIST               0
#              46 LOAD_CONST               1 (('C1', 'C2', 'C3'))
#              48 LIST_EXTEND              1
#              50 LOAD_CONST               2 ('N-1')
#              52 LOAD_CONST               3 (1)
#              54 LOAD_CONST               4 (100)
#              56 CALL                     4
#              64 STORE_FAST               2 (combos)
# 
#  63          66 LOAD_GLOBAL              5 (NULL + len)
#              76 LOAD_FAST                2 (combos)
#              78 CALL                     1
#              86 STORE_FAST               3 (@py_assert2)
#              88 LOAD_CONST               5 (3)
#              90 STORE_FAST               4 (@py_assert5)
#              92 LOAD_FAST                3 (@py_assert2)
#              94 LOAD_FAST                4 (@py_assert5)
#              96 COMPARE_OP              40 (==)
#             100 STORE_FAST               5 (@py_assert4)
#             102 LOAD_FAST                5 (@py_assert4)
#             104 POP_JUMP_IF_TRUE       246 (to 598)
#             106 LOAD_GLOBAL              7 (NULL + @pytest_ar)
#             116 LOAD_ATTR                8 (_call_reprcompare)
#             136 LOAD_CONST               6 (('==',))
#             138 LOAD_FAST                5 (@py_assert4)
#             140 BUILD_TUPLE              1
#             142 LOAD_CONST               7 (('%(py3)s\n{%(py3)s = %(py0)s(%(py1)s)\n} == %(py6)s',))
#             144 LOAD_FAST                3 (@py_assert2)
#             146 LOAD_FAST                4 (@py_assert5)
#             148 BUILD_TUPLE              2
#             150 CALL                     4
#             158 LOAD_CONST               8 ('len')
#             160 LOAD_GLOBAL             11 (NULL + @py_builtins)
#             170 LOAD_ATTR               12 (locals)
#             190 CALL                     0
#             198 CONTAINS_OP              0
#             200 POP_JUMP_IF_TRUE        25 (to 252)
#             202 LOAD_GLOBAL              7 (NULL + @pytest_ar)
#             212 LOAD_ATTR               14 (_should_repr_global_name)
#             232 LOAD_GLOBAL              4 (len)
#             242 CALL                     1
#             250 POP_JUMP_IF_FALSE       25 (to 302)
#         >>  252 LOAD_GLOBAL              7 (NULL + @pytest_ar)
#             262 LOAD_ATTR               16 (_saferepr)
#             282 LOAD_GLOBAL              4 (len)
#             292 CALL                     1
#             300 JUMP_FORWARD             1 (to 304)
#         >>  302 LOAD_CONST               8 ('len')
#         >>  304 LOAD_CONST               9 ('combos')
#             306 LOAD_GLOBAL             11 (NULL + @py_builtins)
#             316 LOAD_ATTR               12 (locals)
#             336 CALL                     0
#             344 CONTAINS_OP              0
#             346 POP_JUMP_IF_TRUE        21 (to 390)
#             348 LOAD_GLOBAL              7 (NULL + @pytest_ar)
#             358 LOAD_ATTR               14 (_should_repr_global_name)
#             378 LOAD_FAST                2 (combos)
#             380 CALL                     1
#             388 POP_JUMP_IF_FALSE       21 (to 432)
#         >>  390 LOAD_GLOBAL              7 (NULL + @pytest_ar)
#             400 LOAD_ATTR               16 (_saferepr)
#             420 LOAD_FAST                2 (combos)
#             422 CALL                     1
#             430 JUMP_FORWARD             1 (to 434)
#         >>  432 LOAD_CONST               9 ('combos')
#         >>  434 LOAD_GLOBAL              7 (NULL + @pytest_ar)
#             444 LOAD_ATTR               16 (_saferepr)
#             464 LOAD_FAST                3 (@py_assert2)
#             466 CALL                     1
#             474 LOAD_GLOBAL              7 (NULL + @pytest_ar)
#             484 LOAD_ATTR               16 (_saferepr)
#             504 LOAD_FAST                4 (@py_assert5)
#             506 CALL                     1
#             514 LOAD_CONST              10 (('py0', 'py1', 'py3', 'py6'))
#             516 BUILD_CONST_KEY_MAP      4
#             518 BINARY_OP                6 (%)
#             522 STORE_FAST               6 (@py_format7)
#             524 LOAD_CONST              11 ('assert %(py8)s')
#             526 LOAD_CONST              12 ('py8')
#             528 LOAD_FAST                6 (@py_format7)
#             530 BUILD_MAP                1
#             532 BINARY_OP                6 (%)
#             536 STORE_FAST               7 (@py_format9)
#             538 LOAD_GLOBAL             19 (NULL + AssertionError)
#             548 LOAD_GLOBAL              7 (NULL + @pytest_ar)
#             558 LOAD_ATTR               20 (_format_explanation)
#             578 LOAD_FAST                7 (@py_format9)
#             580 CALL                     1
#             588 CALL                     1
#             596 RAISE_VARARGS            1
#         >>  598 LOAD_CONST               0 (None)
#             600 COPY                     1
#             602 STORE_FAST               3 (@py_assert2)
#             604 COPY                     1
#             606 STORE_FAST               5 (@py_assert4)
#             608 STORE_FAST               4 (@py_assert5)
# 
#  64         610 LOAD_FAST                2 (combos)
#             612 LOAD_CONST              13 (0)
#             614 BINARY_SUBSCR
#             618 LOAD_CONST              14 ('components')
#             620 BINARY_SUBSCR
#             624 STORE_FAST               8 (@py_assert0)
#             626 LOAD_CONST              15 ('C1')
#             628 BUILD_LIST               1
#             630 STORE_FAST               9 (@py_assert3)
#             632 LOAD_FAST                8 (@py_assert0)
#             634 LOAD_FAST                9 (@py_assert3)
#             636 COMPARE_OP              40 (==)
#             640 STORE_FAST               3 (@py_assert2)
#             642 LOAD_FAST                3 (@py_assert2)
#             644 POP_JUMP_IF_TRUE       108 (to 862)
#             646 LOAD_GLOBAL              7 (NULL + @pytest_ar)
#             656 LOAD_ATTR                8 (_call_reprcompare)
#             676 LOAD_CONST               6 (('==',))
#             678 LOAD_FAST                3 (@py_assert2)
#             680 BUILD_TUPLE              1
#             682 LOAD_CONST              16 (('%(py1)s == %(py4)s',))
#             684 LOAD_FAST                8 (@py_assert0)
#             686 LOAD_FAST                9 (@py_assert3)
#             688 BUILD_TUPLE              2
#             690 CALL                     4
#             698 LOAD_GLOBAL              7 (NULL + @pytest_ar)
#             708 LOAD_ATTR               16 (_saferepr)
#             728 LOAD_FAST                8 (@py_assert0)
#             730 CALL                     1
#             738 LOAD_GLOBAL              7 (NULL + @pytest_ar)
#             748 LOAD_ATTR               16 (_saferepr)
#             768 LOAD_FAST                9 (@py_assert3)
#             770 CALL                     1
#             778 LOAD_CONST              17 (('py1', 'py4'))
#             780 BUILD_CONST_KEY_MAP      2
#             782 BINARY_OP                6 (%)
#             786 STORE_FAST              10 (@py_format5)
#             788 LOAD_CONST              18 ('assert %(py6)s')
#             790 LOAD_CONST              19 ('py6')
#             792 LOAD_FAST               10 (@py_format5)
#             794 BUILD_MAP                1
#             796 BINARY_OP                6 (%)
#             800 STORE_FAST               6 (@py_format7)
#             802 LOAD_GLOBAL             19 (NULL + AssertionError)
#             812 LOAD_GLOBAL              7 (NULL + @pytest_ar)
#             822 LOAD_ATTR               20 (_format_explanation)
#             842 LOAD_FAST                6 (@py_format7)
#             844 CALL                     1
#             852 CALL                     1
#             860 RAISE_VARARGS            1
#         >>  862 LOAD_CONST               0 (None)
#             864 COPY                     1
#             866 STORE_FAST               8 (@py_assert0)
#             868 COPY                     1
#             870 STORE_FAST               3 (@py_assert2)
#             872 STORE_FAST               9 (@py_assert3)
#             874 RETURN_CONST             0 (None)
# 
# Disassembly of <code object test_n2_combinations at 0x3afac750, file "/home/chenying/researches/cloudpss-toolkit/cloudpss_skills_v2/tests/test_contingency_analysis.py", line 66>:
#  66           0 RESUME                   0
# 
#  67           2 LOAD_GLOBAL              1 (NULL + ContingencyAnalysisSkill)
#              12 CALL                     0
#              20 STORE_FAST               1 (skill)
# 
#  68          22 LOAD_FAST                1 (skill)
#              24 LOAD_ATTR                3 (NULL|self + _generate_contingencies)
#              44 BUILD_LIST               0
#              46 LOAD_CONST               1 (('C1', 'C2', 'C3'))
#              48 LIST_EXTEND              1
#              50 LOAD_CONST               2 ('N-2')
#              52 LOAD_CONST               3 (2)
#              54 LOAD_CONST               4 (100)
#              56 CALL                     4
#              64 STORE_FAST               2 (combos)
# 
#  69          66 LOAD_GLOBAL              5 (NULL + len)
#              76 LOAD_FAST                2 (combos)
#              78 CALL                     1
#              86 STORE_FAST               3 (@py_assert2)
#              88 LOAD_CONST               5 (3)
#              90 STORE_FAST               4 (@py_assert5)
#              92 LOAD_FAST                3 (@py_assert2)
#              94 LOAD_FAST                4 (@py_assert5)
#              96 COMPARE_OP              40 (==)
#             100 STORE_FAST               5 (@py_assert4)
#             102 LOAD_FAST                5 (@py_assert4)
#             104 POP_JUMP_IF_TRUE       246 (to 598)
#             106 LOAD_GLOBAL              7 (NULL + @pytest_ar)
#             116 LOAD_ATTR                8 (_call_reprcompare)
#             136 LOAD_CONST               6 (('==',))
#             138 LOAD_FAST                5 (@py_assert4)
#             140 BUILD_TUPLE              1
#             142 LOAD_CONST               7 (('%(py3)s\n{%(py3)s = %(py0)s(%(py1)s)\n} == %(py6)s',))
#             144 LOAD_FAST                3 (@py_assert2)
#             146 LOAD_FAST                4 (@py_assert5)
#             148 BUILD_TUPLE              2
#             150 CALL                     4
#             158 LOAD_CONST               8 ('len')
#             160 LOAD_GLOBAL             11 (NULL + @py_builtins)
#             170 LOAD_ATTR               12 (locals)
#             190 CALL                     0
#             198 CONTAINS_OP              0
#             200 POP_JUMP_IF_TRUE        25 (to 252)
#             202 LOAD_GLOBAL              7 (NULL + @pytest_ar)
#             212 LOAD_ATTR               14 (_should_repr_global_name)
#             232 LOAD_GLOBAL              4 (len)
#             242 CALL                     1
#             250 POP_JUMP_IF_FALSE       25 (to 302)
#         >>  252 LOAD_GLOBAL              7 (NULL + @pytest_ar)
#             262 LOAD_ATTR               16 (_saferepr)
#             282 LOAD_GLOBAL              4 (len)
#             292 CALL                     1
#             300 JUMP_FORWARD             1 (to 304)
#         >>  302 LOAD_CONST               8 ('len')
#         >>  304 LOAD_CONST               9 ('combos')
#             306 LOAD_GLOBAL             11 (NULL + @py_builtins)
#             316 LOAD_ATTR               12 (locals)
#             336 CALL                     0
#             344 CONTAINS_OP              0
#             346 POP_JUMP_IF_TRUE        21 (to 390)
#             348 LOAD_GLOBAL              7 (NULL + @pytest_ar)
#             358 LOAD_ATTR               14 (_should_repr_global_name)
#             378 LOAD_FAST                2 (combos)
#             380 CALL                     1
#             388 POP_JUMP_IF_FALSE       21 (to 432)
#         >>  390 LOAD_GLOBAL              7 (NULL + @pytest_ar)
#             400 LOAD_ATTR               16 (_saferepr)
#             420 LOAD_FAST                2 (combos)
#             422 CALL                     1
#             430 JUMP_FORWARD             1 (to 434)
#         >>  432 LOAD_CONST               9 ('combos')
#         >>  434 LOAD_GLOBAL              7 (NULL + @pytest_ar)
#             444 LOAD_ATTR               16 (_saferepr)
#             464 LOAD_FAST                3 (@py_assert2)
#             466 CALL                     1
#             474 LOAD_GLOBAL              7 (NULL + @pytest_ar)
#             484 LOAD_ATTR               16 (_saferepr)
#             504 LOAD_FAST                4 (@py_assert5)
#             506 CALL                     1
#             514 LOAD_CONST              10 (('py0', 'py1', 'py3', 'py6'))
#             516 BUILD_CONST_KEY_MAP      4
#             518 BINARY_OP                6 (%)
#             522 STORE_FAST               6 (@py_format7)
#             524 LOAD_CONST              11 ('assert %(py8)s')
#             526 LOAD_CONST              12 ('py8')
#             528 LOAD_FAST                6 (@py_format7)
#             530 BUILD_MAP                1
#             532 BINARY_OP                6 (%)
#             536 STORE_FAST               7 (@py_format9)
#             538 LOAD_GLOBAL             19 (NULL + AssertionError)
#             548 LOAD_GLOBAL              7 (NULL + @pytest_ar)
#             558 LOAD_ATTR               20 (_format_explanation)
#             578 LOAD_FAST                7 (@py_format9)
#             580 CALL                     1
#             588 CALL                     1
#             596 RAISE_VARARGS            1
#         >>  598 LOAD_CONST               0 (None)
#             600 COPY                     1
#             602 STORE_FAST               3 (@py_assert2)
#             604 COPY                     1
#             606 STORE_FAST               5 (@py_assert4)
#             608 STORE_FAST               4 (@py_assert5)
# 
#  70         610 LOAD_FAST                2 (combos)
#             612 LOAD_CONST              13 (0)
#             614 BINARY_SUBSCR
#             618 LOAD_CONST              14 ('components')
#             620 BINARY_SUBSCR
#             624 STORE_FAST               8 (@py_assert1)
#             626 LOAD_GLOBAL              5 (NULL + len)
#             636 LOAD_FAST                8 (@py_assert1)
#             638 CALL                     1
#             646 STORE_FAST               9 (@py_assert3)
#             648 LOAD_CONST               3 (2)
#             650 STORE_FAST              10 (@py_assert6)
#             652 LOAD_FAST                9 (@py_assert3)
#             654 LOAD_FAST               10 (@py_assert6)
#             656 COMPARE_OP              40 (==)
#             660 STORE_FAST               4 (@py_assert5)
#             662 LOAD_FAST                4 (@py_assert5)
#             664 POP_JUMP_IF_TRUE       201 (to 1068)
#             666 LOAD_GLOBAL              7 (NULL + @pytest_ar)
#             676 LOAD_ATTR                8 (_call_reprcompare)
#             696 LOAD_CONST               6 (('==',))
#             698 LOAD_FAST                4 (@py_assert5)
#             700 BUILD_TUPLE              1
#             702 LOAD_CONST              15 (('%(py4)s\n{%(py4)s = %(py0)s(%(py2)s)\n} == %(py7)s',))
#             704 LOAD_FAST                9 (@py_assert3)
#             706 LOAD_FAST               10 (@py_assert6)
#             708 BUILD_TUPLE              2
#             710 CALL                     4
#             718 LOAD_CONST               8 ('len')
#             720 LOAD_GLOBAL             11 (NULL + @py_builtins)
#             730 LOAD_ATTR               12 (locals)
#             750 CALL                     0
#             758 CONTAINS_OP              0
#             760 POP_JUMP_IF_TRUE        25 (to 812)
#             762 LOAD_GLOBAL              7 (NULL + @pytest_ar)
#             772 LOAD_ATTR               14 (_should_repr_global_name)
#             792 LOAD_GLOBAL              4 (len)
#             802 CALL                     1
#             810 POP_JUMP_IF_FALSE       25 (to 862)
#         >>  812 LOAD_GLOBAL              7 (NULL + @pytest_ar)
#             822 LOAD_ATTR               16 (_saferepr)
#             842 LOAD_GLOBAL              4 (len)
#             852 CALL                     1
#             860 JUMP_FORWARD             1 (to 864)
#         >>  862 LOAD_CONST               8 ('len')
#         >>  864 LOAD_GLOBAL              7 (NULL + @pytest_ar)
#             874 LOAD_ATTR               16 (_saferepr)
#             894 LOAD_FAST                8 (@py_assert1)
#             896 CALL                     1
#             904 LOAD_GLOBAL              7 (NULL + @pytest_ar)
#             914 LOAD_ATTR               16 (_saferepr)
#             934 LOAD_FAST                9 (@py_assert3)
#             936 CALL                     1
#             944 LOAD_GLOBAL              7 (NULL + @pytest_ar)
#             954 LOAD_ATTR               16 (_saferepr)
#             974 LOAD_FAST               10 (@py_assert6)
#             976 CALL                     1
#             984 LOAD_CONST              16 (('py0', 'py2', 'py4', 'py7'))
#             986 BUILD_CONST_KEY_MAP      4
#             988 BINARY_OP                6 (%)
#             992 STORE_FAST              11 (@py_format8)
#             994 LOAD_CONST              17 ('assert %(py9)s')
#             996 LOAD_CONST              18 ('py9')
#             998 LOAD_FAST               11 (@py_format8)
#            1000 BUILD_MAP                1
#            1002 BINARY_OP                6 (%)
#            1006 STORE_FAST              12 (@py_format10)
#            1008 LOAD_GLOBAL             19 (NULL + AssertionError)
#            1018 LOAD_GLOBAL              7 (NULL + @pytest_ar)
#            1028 LOAD_ATTR               20 (_format_explanation)
#            1048 LOAD_FAST               12 (@py_format10)
#            1050 CALL                     1
#            1058 CALL                     1
#            1066 RAISE_VARARGS            1
#         >> 1068 LOAD_CONST               0 (None)
#            1070 COPY                     1
#            1072 STORE_FAST               8 (@py_assert1)
#            1074 COPY                     1
#            1076 STORE_FAST               9 (@py_assert3)
#            1078 COPY                     1
#            1080 STORE_FAST               4 (@py_assert5)
#            1082 STORE_FAST              10 (@py_assert6)
#            1084 RETURN_CONST             0 (None)
# 
# Disassembly of <code object test_max_combinations_limit at 0x3aef1020, file "/home/chenying/researches/cloudpss-toolkit/cloudpss_skills_v2/tests/test_contingency_analysis.py", line 72>:
#  72           0 RESUME                   0
# 
#  73           2 LOAD_GLOBAL              1 (NULL + ContingencyAnalysisSkill)
#              12 CALL                     0
#              20 STORE_FAST               1 (skill)
# 
#  74          22 LOAD_FAST                1 (skill)
#              24 LOAD_ATTR                3 (NULL|self + _generate_contingencies)
# 
#  75          44 LOAD_GLOBAL              5 (NULL + range)
#              54 LOAD_CONST               1 (20)
#              56 CALL                     1
#              64 GET_ITER
#              66 LOAD_FAST_AND_CLEAR      2 (i)
#              68 SWAP                     2
#              70 BUILD_LIST               0
#              72 SWAP                     2
#         >>   74 FOR_ITER                 7 (to 92)
#              78 STORE_FAST               2 (i)
#              80 LOAD_CONST               2 ('C')
#              82 LOAD_FAST                2 (i)
#              84 FORMAT_VALUE             0
#              86 BUILD_STRING             2
#              88 LIST_APPEND              2
#              90 JUMP_BACKWARD            9 (to 74)
#         >>   92 END_FOR
#              94 SWAP                     2
#              96 STORE_FAST               2 (i)
#              98 LOAD_CONST               3 ('N-1')
#             100 LOAD_CONST               4 (1)
#             102 LOAD_CONST               5 (5)
# 
#  74         104 CALL                     4
#             112 STORE_FAST               3 (combos)
# 
#  77         114 LOAD_GLOBAL              7 (NULL + len)
#             124 LOAD_FAST                3 (combos)
#             126 CALL                     1
#             134 STORE_FAST               4 (@py_assert2)
#             136 LOAD_CONST               5 (5)
#             138 STORE_FAST               5 (@py_assert5)
#             140 LOAD_FAST                4 (@py_assert2)
#             142 LOAD_FAST                5 (@py_assert5)
#             144 COMPARE_OP              40 (==)
#             148 STORE_FAST               6 (@py_assert4)
#             150 LOAD_FAST                6 (@py_assert4)
#             152 POP_JUMP_IF_TRUE       246 (to 646)
#             154 LOAD_GLOBAL              9 (NULL + @pytest_ar)
#             164 LOAD_ATTR               10 (_call_reprcompare)
#             184 LOAD_CONST               6 (('==',))
#             186 LOAD_FAST                6 (@py_assert4)
#             188 BUILD_TUPLE              1
#             190 LOAD_CONST               7 (('%(py3)s\n{%(py3)s = %(py0)s(%(py1)s)\n} == %(py6)s',))
#             192 LOAD_FAST                4 (@py_assert2)
#             194 LOAD_FAST                5 (@py_assert5)
#             196 BUILD_TUPLE              2
#             198 CALL                     4
#             206 LOAD_CONST               8 ('len')
#             208 LOAD_GLOBAL             13 (NULL + @py_builtins)
#             218 LOAD_ATTR               14 (locals)
#             238 CALL                     0
#             246 CONTAINS_OP              0
#             248 POP_JUMP_IF_TRUE        25 (to 300)
#             250 LOAD_GLOBAL              9 (NULL + @pytest_ar)
#             260 LOAD_ATTR               16 (_should_repr_global_name)
#             280 LOAD_GLOBAL              6 (len)
#             290 CALL                     1
#             298 POP_JUMP_IF_FALSE       25 (to 350)
#         >>  300 LOAD_GLOBAL              9 (NULL + @pytest_ar)
#             310 LOAD_ATTR               18 (_saferepr)
#             330 LOAD_GLOBAL              6 (len)
#             340 CALL                     1
#             348 JUMP_FORWARD             1 (to 352)
#         >>  350 LOAD_CONST               8 ('len')
#         >>  352 LOAD_CONST               9 ('combos')
#             354 LOAD_GLOBAL             13 (NULL + @py_builtins)
#             364 LOAD_ATTR               14 (locals)
#             384 CALL                     0
#             392 CONTAINS_OP              0
#             394 POP_JUMP_IF_TRUE        21 (to 438)
#             396 LOAD_GLOBAL              9 (NULL + @pytest_ar)
#             406 LOAD_ATTR               16 (_should_repr_global_name)
#             426 LOAD_FAST                3 (combos)
#             428 CALL                     1
#             436 POP_JUMP_IF_FALSE       21 (to 480)
#         >>  438 LOAD_GLOBAL              9 (NULL + @pytest_ar)
#             448 LOAD_ATTR               18 (_saferepr)
#             468 LOAD_FAST                3 (combos)
#             470 CALL                     1
#             478 JUMP_FORWARD             1 (to 482)
#         >>  480 LOAD_CONST               9 ('combos')
#         >>  482 LOAD_GLOBAL              9 (NULL + @pytest_ar)
#             492 LOAD_ATTR               18 (_saferepr)
#             512 LOAD_FAST                4 (@py_assert2)
#             514 CALL                     1
#             522 LOAD_GLOBAL              9 (NULL + @pytest_ar)
#             532 LOAD_ATTR               18 (_saferepr)
#             552 LOAD_FAST                5 (@py_assert5)
#             554 CALL                     1
#             562 LOAD_CONST              10 (('py0', 'py1', 'py3', 'py6'))
#             564 BUILD_CONST_KEY_MAP      4
#             566 BINARY_OP                6 (%)
#             570 STORE_FAST               7 (@py_format7)
#             572 LOAD_CONST              11 ('assert %(py8)s')
#             574 LOAD_CONST              12 ('py8')
#             576 LOAD_FAST                7 (@py_format7)
#             578 BUILD_MAP                1
#             580 BINARY_OP                6 (%)
#             584 STORE_FAST               8 (@py_format9)
#             586 LOAD_GLOBAL             21 (NULL + AssertionError)
#             596 LOAD_GLOBAL              9 (NULL + @pytest_ar)
#             606 LOAD_ATTR               22 (_format_explanation)
#             626 LOAD_FAST                8 (@py_format9)
#             628 CALL                     1
#             636 CALL                     1
#             644 RAISE_VARARGS            1
#         >>  646 LOAD_CONST               0 (None)
#             648 COPY                     1
#             650 STORE_FAST               4 (@py_assert2)
#             652 COPY                     1
#             654 STORE_FAST               6 (@py_assert4)
#             656 STORE_FAST               5 (@py_assert5)
#             658 RETURN_CONST             0 (None)
#         >>  660 SWAP                     2
#             662 POP_TOP
# 
#  75         664 SWAP                     2
#             666 STORE_FAST               2 (i)
#             668 RERAISE                  0
# ExceptionTable:
#   70 to 92 -> 660 [4]
# 
# Disassembly of <code object test_empty_components at 0x3afa3fb0, file "/home/chenying/researches/cloudpss-toolkit/cloudpss_skills_v2/tests/test_contingency_analysis.py", line 79>:
#  79           0 RESUME                   0
# 
#  80           2 LOAD_GLOBAL              1 (NULL + ContingencyAnalysisSkill)
#              12 CALL                     0
#              20 STORE_FAST               1 (skill)
# 
#  81          22 LOAD_FAST                1 (skill)
#              24 LOAD_ATTR                3 (NULL|self + _generate_contingencies)
#              44 BUILD_LIST               0
#              46 LOAD_CONST               1 ('N-1')
#              48 LOAD_CONST               2 (1)
#              50 LOAD_CONST               3 (100)
#              52 CALL                     4
#              60 STORE_FAST               2 (combos)
# 
#  82          62 BUILD_LIST               0
#              64 STORE_FAST               3 (@py_assert2)
#              66 LOAD_FAST                2 (combos)
#              68 LOAD_FAST                3 (@py_assert2)
#              70 COMPARE_OP              40 (==)
#              74 STORE_FAST               4 (@py_assert1)
#              76 LOAD_FAST                4 (@py_assert1)
#              78 POP_JUMP_IF_TRUE       153 (to 386)
#              80 LOAD_GLOBAL              5 (NULL + @pytest_ar)
#              90 LOAD_ATTR                6 (_call_reprcompare)
#             110 LOAD_CONST               4 (('==',))
#             112 LOAD_FAST                4 (@py_assert1)
#             114 BUILD_TUPLE              1
#             116 LOAD_CONST               5 (('%(py0)s == %(py3)s',))
#             118 LOAD_FAST                2 (combos)
#             120 LOAD_FAST                3 (@py_assert2)
#             122 BUILD_TUPLE              2
#             124 CALL                     4
#             132 LOAD_CONST               6 ('combos')
#             134 LOAD_GLOBAL              9 (NULL + @py_builtins)
#             144 LOAD_ATTR               10 (locals)
#             164 CALL                     0
#             172 CONTAINS_OP              0
#             174 POP_JUMP_IF_TRUE        21 (to 218)
#             176 LOAD_GLOBAL              5 (NULL + @pytest_ar)
#             186 LOAD_ATTR               12 (_should_repr_global_name)
#             206 LOAD_FAST                2 (combos)
#             208 CALL                     1
#             216 POP_JUMP_IF_FALSE       21 (to 260)
#         >>  218 LOAD_GLOBAL              5 (NULL + @pytest_ar)
#             228 LOAD_ATTR               14 (_saferepr)
#             248 LOAD_FAST                2 (combos)
#             250 CALL                     1
#             258 JUMP_FORWARD             1 (to 262)
#         >>  260 LOAD_CONST               6 ('combos')
#         >>  262 LOAD_GLOBAL              5 (NULL + @pytest_ar)
#             272 LOAD_ATTR               14 (_saferepr)
#             292 LOAD_FAST                3 (@py_assert2)
#             294 CALL                     1
#             302 LOAD_CONST               7 (('py0', 'py3'))
#             304 BUILD_CONST_KEY_MAP      2
#             306 BINARY_OP                6 (%)
#             310 STORE_FAST               5 (@py_format4)
#             312 LOAD_CONST               8 ('assert %(py5)s')
#             314 LOAD_CONST               9 ('py5')
#             316 LOAD_FAST                5 (@py_format4)
#             318 BUILD_MAP                1
#             320 BINARY_OP                6 (%)
#             324 STORE_FAST               6 (@py_format6)
#             326 LOAD_GLOBAL             17 (NULL + AssertionError)
#             336 LOAD_GLOBAL              5 (NULL + @pytest_ar)
#             346 LOAD_ATTR               18 (_format_explanation)
#             366 LOAD_FAST                6 (@py_format6)
#             368 CALL                     1
#             376 CALL                     1
#             384 RAISE_VARARGS            1
#         >>  386 LOAD_CONST               0 (None)
#             388 COPY                     1
#             390 STORE_FAST               4 (@py_assert1)
#             392 STORE_FAST               3 (@py_assert2)
#             394 RETURN_CONST             0 (None)
# 
# Disassembly of <code object TestContingencyAnalysisSeverity at 0x73cd945fe6b0, file "/home/chenying/researches/cloudpss-toolkit/cloudpss_skills_v2/tests/test_contingency_analysis.py", line 85>:
#  85           0 RESUME                   0
#               2 LOAD_NAME                0 (__name__)
#               4 STORE_NAME               1 (__module__)
#               6 LOAD_CONST               0 ('TestContingencyAnalysisSeverity')
#               8 STORE_NAME               2 (__qualname__)
# 
#  86          10 LOAD_CONST               1 (<code object test_fail_status_severity_1 at 0x3af90d20, file "/home/chenying/researches/cloudpss-toolkit/cloudpss_skills_v2/tests/test_contingency_analysis.py", line 86>)
#              12 MAKE_FUNCTION            0
#              14 STORE_NAME               3 (test_fail_status_severity_1)
# 
#  92          16 LOAD_CONST               2 (<code object test_pass_status_severity_0 at 0x3af0c6d0, file "/home/chenying/researches/cloudpss-toolkit/cloudpss_skills_v2/tests/test_contingency_analysis.py", line 92>)
#              18 MAKE_FUNCTION            0
#              20 STORE_NAME               4 (test_pass_status_severity_0)
# 
#  98          22 LOAD_CONST               3 (<code object test_voltage_violation_severity at 0x3af8e200, file "/home/chenying/researches/cloudpss-toolkit/cloudpss_skills_v2/tests/test_contingency_analysis.py", line 98>)
#              24 MAKE_FUNCTION            0
#              26 STORE_NAME               5 (test_voltage_violation_severity)
#              28 RETURN_CONST             4 (None)
# 
# Disassembly of <code object test_fail_status_severity_1 at 0x3af90d20, file "/home/chenying/researches/cloudpss-toolkit/cloudpss_skills_v2/tests/test_contingency_analysis.py", line 86>:
#  86           0 RESUME                   0
# 
#  87           2 LOAD_GLOBAL              1 (NULL + ContingencyAnalysisSkill)
#              12 CALL                     0
#              20 STORE_FAST               1 (skill)
# 
#  88          22 LOAD_CONST               1 ('status')
#              24 LOAD_CONST               2 ('FAIL')
#              26 BUILD_MAP                1
#              28 STORE_FAST               2 (result)
# 
#  89          30 LOAD_FAST                1 (skill)
#              32 LOAD_ATTR                3 (NULL|self + _calculate_severity)
#              52 LOAD_FAST                2 (result)
#              54 LOAD_CONST               3 (0.95)
#              56 LOAD_CONST               4 (1.05)
#              58 LOAD_CONST               5 (('min', 'max'))
#              60 BUILD_CONST_KEY_MAP      2
#              62 LOAD_CONST               6 (1.0)
#              64 CALL                     3
#              72 STORE_FAST               3 (severity)
# 
#  90          74 LOAD_CONST               6 (1.0)
#              76 STORE_FAST               4 (@py_assert2)
#              78 LOAD_FAST                3 (severity)
#              80 LOAD_FAST                4 (@py_assert2)
#              82 COMPARE_OP              40 (==)
#              86 STORE_FAST               5 (@py_assert1)
#              88 LOAD_FAST                5 (@py_assert1)
#              90 POP_JUMP_IF_TRUE       153 (to 398)
#              92 LOAD_GLOBAL              5 (NULL + @pytest_ar)
#             102 LOAD_ATTR                6 (_call_reprcompare)
#             122 LOAD_CONST               7 (('==',))
#             124 LOAD_FAST                5 (@py_assert1)
#             126 BUILD_TUPLE              1
#             128 LOAD_CONST               8 (('%(py0)s == %(py3)s',))
#             130 LOAD_FAST                3 (severity)
#             132 LOAD_FAST                4 (@py_assert2)
#             134 BUILD_TUPLE              2
#             136 CALL                     4
#             144 LOAD_CONST               9 ('severity')
#             146 LOAD_GLOBAL              9 (NULL + @py_builtins)
#             156 LOAD_ATTR               10 (locals)
#             176 CALL                     0
#             184 CONTAINS_OP              0
#             186 POP_JUMP_IF_TRUE        21 (to 230)
#             188 LOAD_GLOBAL              5 (NULL + @pytest_ar)
#             198 LOAD_ATTR               12 (_should_repr_global_name)
#             218 LOAD_FAST                3 (severity)
#             220 CALL                     1
#             228 POP_JUMP_IF_FALSE       21 (to 272)
#         >>  230 LOAD_GLOBAL              5 (NULL + @pytest_ar)
#             240 LOAD_ATTR               14 (_saferepr)
#             260 LOAD_FAST                3 (severity)
#             262 CALL                     1
#             270 JUMP_FORWARD             1 (to 274)
#         >>  272 LOAD_CONST               9 ('severity')
#         >>  274 LOAD_GLOBAL              5 (NULL + @pytest_ar)
#             284 LOAD_ATTR               14 (_saferepr)
#             304 LOAD_FAST                4 (@py_assert2)
#             306 CALL                     1
#             314 LOAD_CONST              10 (('py0', 'py3'))
#             316 BUILD_CONST_KEY_MAP      2
#             318 BINARY_OP                6 (%)
#             322 STORE_FAST               6 (@py_format4)
#             324 LOAD_CONST              11 ('assert %(py5)s')
#             326 LOAD_CONST              12 ('py5')
#             328 LOAD_FAST                6 (@py_format4)
#             330 BUILD_MAP                1
#             332 BINARY_OP                6 (%)
#             336 STORE_FAST               7 (@py_format6)
#             338 LOAD_GLOBAL             17 (NULL + AssertionError)
#             348 LOAD_GLOBAL              5 (NULL + @pytest_ar)
#             358 LOAD_ATTR               18 (_format_explanation)
#             378 LOAD_FAST                7 (@py_format6)
#             380 CALL                     1
#             388 CALL                     1
#             396 RAISE_VARARGS            1
#         >>  398 LOAD_CONST               0 (None)
#             400 COPY                     1
#             402 STORE_FAST               5 (@py_assert1)
#             404 STORE_FAST               4 (@py_assert2)
#             406 RETURN_CONST             0 (None)
# 
# Disassembly of <code object test_pass_status_severity_0 at 0x3af0c6d0, file "/home/chenying/researches/cloudpss-toolkit/cloudpss_skills_v2/tests/test_contingency_analysis.py", line 92>:
#  92           0 RESUME                   0
# 
#  93           2 LOAD_GLOBAL              1 (NULL + ContingencyAnalysisSkill)
#              12 CALL                     0
#              20 STORE_FAST               1 (skill)
# 
#  94          22 LOAD_CONST               1 ('PASS')
#              24 LOAD_CONST               2 (1.0)
#              26 LOAD_CONST               2 (1.0)
#              28 LOAD_CONST               3 (('status', 'min_voltage', 'max_voltage'))
#              30 BUILD_CONST_KEY_MAP      3
#              32 STORE_FAST               2 (result)
# 
#  95          34 LOAD_FAST                1 (skill)
#              36 LOAD_ATTR                3 (NULL|self + _calculate_severity)
#              56 LOAD_FAST                2 (result)
#              58 LOAD_CONST               4 (0.95)
#              60 LOAD_CONST               5 (1.05)
#              62 LOAD_CONST               6 (('min', 'max'))
#              64 BUILD_CONST_KEY_MAP      2
#              66 LOAD_CONST               2 (1.0)
#              68 CALL                     3
#              76 STORE_FAST               3 (severity)
# 
#  96          78 LOAD_CONST               7 (0.0)
#              80 STORE_FAST               4 (@py_assert2)
#              82 LOAD_FAST                3 (severity)
#              84 LOAD_FAST                4 (@py_assert2)
#              86 COMPARE_OP              40 (==)
#              90 STORE_FAST               5 (@py_assert1)
#              92 LOAD_FAST                5 (@py_assert1)
#              94 POP_JUMP_IF_TRUE       153 (to 402)
#              96 LOAD_GLOBAL              5 (NULL + @pytest_ar)
#             106 LOAD_ATTR                6 (_call_reprcompare)
#             126 LOAD_CONST               8 (('==',))
#             128 LOAD_FAST                5 (@py_assert1)
#             130 BUILD_TUPLE              1
#             132 LOAD_CONST               9 (('%(py0)s == %(py3)s',))
#             134 LOAD_FAST                3 (severity)
#             136 LOAD_FAST                4 (@py_assert2)
#             138 BUILD_TUPLE              2
#             140 CALL                     4
#             148 LOAD_CONST              10 ('severity')
#             150 LOAD_GLOBAL              9 (NULL + @py_builtins)
#             160 LOAD_ATTR               10 (locals)
#             180 CALL                     0
#             188 CONTAINS_OP              0
#             190 POP_JUMP_IF_TRUE        21 (to 234)
#             192 LOAD_GLOBAL              5 (NULL + @pytest_ar)
#             202 LOAD_ATTR               12 (_should_repr_global_name)
#             222 LOAD_FAST                3 (severity)
#             224 CALL                     1
#             232 POP_JUMP_IF_FALSE       21 (to 276)
#         >>  234 LOAD_GLOBAL              5 (NULL + @pytest_ar)
#             244 LOAD_ATTR               14 (_saferepr)
#             264 LOAD_FAST                3 (severity)
#             266 CALL                     1
#             274 JUMP_FORWARD             1 (to 278)
#         >>  276 LOAD_CONST              10 ('severity')
#         >>  278 LOAD_GLOBAL              5 (NULL + @pytest_ar)
#             288 LOAD_ATTR               14 (_saferepr)
#             308 LOAD_FAST                4 (@py_assert2)
#             310 CALL                     1
#             318 LOAD_CONST              11 (('py0', 'py3'))
#             320 BUILD_CONST_KEY_MAP      2
#             322 BINARY_OP                6 (%)
#             326 STORE_FAST               6 (@py_format4)
#             328 LOAD_CONST              12 ('assert %(py5)s')
#             330 LOAD_CONST              13 ('py5')
#             332 LOAD_FAST                6 (@py_format4)
#             334 BUILD_MAP                1
#             336 BINARY_OP                6 (%)
#             340 STORE_FAST               7 (@py_format6)
#             342 LOAD_GLOBAL             17 (NULL + AssertionError)
#             352 LOAD_GLOBAL              5 (NULL + @pytest_ar)
#             362 LOAD_ATTR               18 (_format_explanation)
#             382 LOAD_FAST                7 (@py_format6)
#             384 CALL                     1
#             392 CALL                     1
#             400 RAISE_VARARGS            1
#         >>  402 LOAD_CONST               0 (None)
#             404 COPY                     1
#             406 STORE_FAST               5 (@py_assert1)
#             408 STORE_FAST               4 (@py_assert2)
#             410 RETURN_CONST             0 (None)
# 
# Disassembly of <code object test_voltage_violation_severity at 0x3af8e200, file "/home/chenying/researches/cloudpss-toolkit/cloudpss_skills_v2/tests/test_contingency_analysis.py", line 98>:
#  98           0 RESUME                   0
# 
#  99           2 LOAD_GLOBAL              1 (NULL + ContingencyAnalysisSkill)
#              12 CALL                     0
#              20 STORE_FAST               1 (skill)
# 
# 100          22 LOAD_CONST               1 ('VIOLATION')
#              24 LOAD_CONST               2 (0.85)
#              26 LOAD_CONST               3 (1.0)
#              28 LOAD_CONST               4 (('status', 'min_voltage', 'max_voltage'))
#              30 BUILD_CONST_KEY_MAP      3
#              32 STORE_FAST               2 (result)
# 
# 101          34 LOAD_FAST                1 (skill)
#              36 LOAD_ATTR                3 (NULL|self + _calculate_severity)
#              56 LOAD_FAST                2 (result)
#              58 LOAD_CONST               5 (0.95)
#              60 LOAD_CONST               6 (1.05)
#              62 LOAD_CONST               7 (('min', 'max'))
#              64 BUILD_CONST_KEY_MAP      2
#              66 LOAD_CONST               3 (1.0)
#              68 CALL                     3
#              76 STORE_FAST               3 (severity)
# 
# 102          78 LOAD_CONST               8 (0)
#              80 STORE_FAST               4 (@py_assert2)
#              82 LOAD_FAST                3 (severity)
#              84 LOAD_FAST                4 (@py_assert2)
#              86 COMPARE_OP              68 (>)
#              90 STORE_FAST               5 (@py_assert1)
#              92 LOAD_FAST                5 (@py_assert1)
#              94 POP_JUMP_IF_TRUE       153 (to 402)
#              96 LOAD_GLOBAL              5 (NULL + @pytest_ar)
#             106 LOAD_ATTR                6 (_call_reprcompare)
#             126 LOAD_CONST               9 (('>',))
#             128 LOAD_FAST                5 (@py_assert1)
#             130 BUILD_TUPLE              1
#             132 LOAD_CONST              10 (('%(py0)s > %(py3)s',))
#             134 LOAD_FAST                3 (severity)
#             136 LOAD_FAST                4 (@py_assert2)
#             138 BUILD_TUPLE              2
#             140 CALL                     4
#             148 LOAD_CONST              11 ('severity')
#             150 LOAD_GLOBAL              9 (NULL + @py_builtins)
#             160 LOAD_ATTR               10 (locals)
#             180 CALL                     0
#             188 CONTAINS_OP              0
#             190 POP_JUMP_IF_TRUE        21 (to 234)
#             192 LOAD_GLOBAL              5 (NULL + @pytest_ar)
#             202 LOAD_ATTR               12 (_should_repr_global_name)
#             222 LOAD_FAST                3 (severity)
#             224 CALL                     1
#             232 POP_JUMP_IF_FALSE       21 (to 276)
#         >>  234 LOAD_GLOBAL              5 (NULL + @pytest_ar)
#             244 LOAD_ATTR               14 (_saferepr)
#             264 LOAD_FAST                3 (severity)
#             266 CALL                     1
#             274 JUMP_FORWARD             1 (to 278)
#         >>  276 LOAD_CONST              11 ('severity')
#         >>  278 LOAD_GLOBAL              5 (NULL + @pytest_ar)
#             288 LOAD_ATTR               14 (_saferepr)
#             308 LOAD_FAST                4 (@py_assert2)
#             310 CALL                     1
#             318 LOAD_CONST              12 (('py0', 'py3'))
#             320 BUILD_CONST_KEY_MAP      2
#             322 BINARY_OP                6 (%)
#             326 STORE_FAST               6 (@py_format4)
#             328 LOAD_CONST              13 ('assert %(py5)s')
#             330 LOAD_CONST              14 ('py5')
#             332 LOAD_FAST                6 (@py_format4)
#             334 BUILD_MAP                1
#             336 BINARY_OP                6 (%)
#             340 STORE_FAST               7 (@py_format6)
#             342 LOAD_GLOBAL             17 (NULL + AssertionError)
#             352 LOAD_GLOBAL              5 (NULL + @pytest_ar)
#             362 LOAD_ATTR               18 (_format_explanation)
#             382 LOAD_FAST                7 (@py_format6)
#             384 CALL                     1
#             392 CALL                     1
#             400 RAISE_VARARGS            1
#         >>  402 LOAD_CONST               0 (None)
#             404 COPY                     1
#             406 STORE_FAST               5 (@py_assert1)
#             408 STORE_FAST               4 (@py_assert2)
# 
# 103         410 LOAD_CONST               3 (1.0)
#             412 STORE_FAST               4 (@py_assert2)
#             414 LOAD_FAST                3 (severity)
#             416 LOAD_FAST                4 (@py_assert2)
#             418 COMPARE_OP              26 (<=)
#             422 STORE_FAST               5 (@py_assert1)
#             424 LOAD_FAST                5 (@py_assert1)
#             426 POP_JUMP_IF_TRUE       153 (to 734)
#             428 LOAD_GLOBAL              5 (NULL + @pytest_ar)
#             438 LOAD_ATTR                6 (_call_reprcompare)
#             458 LOAD_CONST              15 (('<=',))
#             460 LOAD_FAST                5 (@py_assert1)
#             462 BUILD_TUPLE              1
#             464 LOAD_CONST              16 (('%(py0)s <= %(py3)s',))
#             466 LOAD_FAST                3 (severity)
#             468 LOAD_FAST                4 (@py_assert2)
#             470 BUILD_TUPLE              2
#             472 CALL                     4
#             480 LOAD_CONST              11 ('severity')
#             482 LOAD_GLOBAL              9 (NULL + @py_builtins)
#             492 LOAD_ATTR               10 (locals)
#             512 CALL                     0
#             520 CONTAINS_OP              0
#             522 POP_JUMP_IF_TRUE        21 (to 566)
#             524 LOAD_GLOBAL              5 (NULL + @pytest_ar)
#             534 LOAD_ATTR               12 (_should_repr_global_name)
#             554 LOAD_FAST                3 (severity)
#             556 CALL                     1
#             564 POP_JUMP_IF_FALSE       21 (to 608)
#         >>  566 LOAD_GLOBAL              5 (NULL + @pytest_ar)
#             576 LOAD_ATTR               14 (_saferepr)
#             596 LOAD_FAST                3 (severity)
#             598 CALL                     1
#             606 JUMP_FORWARD             1 (to 610)
#         >>  608 LOAD_CONST              11 ('severity')
#         >>  610 LOAD_GLOBAL              5 (NULL + @pytest_ar)
#             620 LOAD_ATTR               14 (_saferepr)
#             640 LOAD_FAST                4 (@py_assert2)
#             642 CALL                     1
#             650 LOAD_CONST              12 (('py0', 'py3'))
#             652 BUILD_CONST_KEY_MAP      2
#             654 BINARY_OP                6 (%)
#             658 STORE_FAST               6 (@py_format4)
#             660 LOAD_CONST              13 ('assert %(py5)s')
#             662 LOAD_CONST              14 ('py5')
#             664 LOAD_FAST                6 (@py_format4)
#             666 BUILD_MAP                1
#             668 BINARY_OP                6 (%)
#             672 STORE_FAST               7 (@py_format6)
#             674 LOAD_GLOBAL             17 (NULL + AssertionError)
#             684 LOAD_GLOBAL              5 (NULL + @pytest_ar)
#             694 LOAD_ATTR               18 (_format_explanation)
#             714 LOAD_FAST                7 (@py_format6)
#             716 CALL                     1
#             724 CALL                     1
#             732 RAISE_VARARGS            1
#         >>  734 LOAD_CONST               0 (None)
#             736 COPY                     1
#             738 STORE_FAST               5 (@py_assert1)
#             740 STORE_FAST               4 (@py_assert2)
#             742 RETURN_CONST             0 (None)
# 
# Disassembly of <code object TestContingencyAnalysisWeakPoints at 0x73cd945fe330, file "/home/chenying/researches/cloudpss-toolkit/cloudpss_skills_v2/tests/test_contingency_analysis.py", line 106>:
# 106           0 RESUME                   0
#               2 LOAD_NAME                0 (__name__)
#               4 STORE_NAME               1 (__module__)
#               6 LOAD_CONST               0 ('TestContingencyAnalysisWeakPoints')
#               8 STORE_NAME               2 (__qualname__)
# 
# 107          10 LOAD_CONST               1 (<code object test_identify_weak_points at 0x3afa5260, file "/home/chenying/researches/cloudpss-toolkit/cloudpss_skills_v2/tests/test_contingency_analysis.py", line 107>)
#              12 MAKE_FUNCTION            0
#              14 STORE_NAME               3 (test_identify_weak_points)
#              16 RETURN_CONST             2 (None)
# 
# Disassembly of <code object test_identify_weak_points at 0x3afa5260, file "/home/chenying/researches/cloudpss-toolkit/cloudpss_skills_v2/tests/test_contingency_analysis.py", line 107>:
# 107           0 RESUME                   0
# 
# 108           2 LOAD_GLOBAL              1 (NULL + ContingencyAnalysisSkill)
#              12 CALL                     0
#              20 STORE_FAST               1 (skill)
# 
# 110          22 LOAD_CONST               1 ('C1')
#              24 LOAD_CONST               1 ('C1')
#              26 BUILD_LIST               1
#              28 LOAD_CONST               2 (0.9)
#              30 LOAD_CONST               3 (('name', 'components', 'severity'))
#              32 BUILD_CONST_KEY_MAP      3
# 
# 111          34 LOAD_CONST               4 ('C2')
#              36 LOAD_CONST               4 ('C2')
#              38 BUILD_LIST               1
#              40 LOAD_CONST               5 (0.5)
#              42 LOAD_CONST               3 (('name', 'components', 'severity'))
#              44 BUILD_CONST_KEY_MAP      3
# 
# 112          46 LOAD_CONST               6 ('C1+C2')
#              48 LOAD_CONST               1 ('C1')
#              50 LOAD_CONST               4 ('C2')
#              52 BUILD_LIST               2
#              54 LOAD_CONST               7 (0.7)
#              56 LOAD_CONST               3 (('name', 'components', 'severity'))
#              58 BUILD_CONST_KEY_MAP      3
# 
# 109          60 BUILD_LIST               3
#              62 STORE_FAST               2 (results)
# 
# 114          64 LOAD_FAST                1 (skill)
#              66 LOAD_ATTR                3 (NULL|self + _identify_weak_points)
#              86 LOAD_FAST                2 (results)
#              88 LOAD_CONST               8 (5)
#              90 CALL                     2
#              98 STORE_FAST               3 (wp)
# 
# 115         100 LOAD_GLOBAL              5 (NULL + len)
#             110 LOAD_FAST                3 (wp)
#             112 CALL                     1
#             120 STORE_FAST               4 (@py_assert2)
#             122 LOAD_CONST               9 (0)
#             124 STORE_FAST               5 (@py_assert5)
#             126 LOAD_FAST                4 (@py_assert2)
#             128 LOAD_FAST                5 (@py_assert5)
#             130 COMPARE_OP              68 (>)
#             134 STORE_FAST               6 (@py_assert4)
#             136 LOAD_FAST                6 (@py_assert4)
#             138 POP_JUMP_IF_TRUE       246 (to 632)
#             140 LOAD_GLOBAL              7 (NULL + @pytest_ar)
#             150 LOAD_ATTR                8 (_call_reprcompare)
#             170 LOAD_CONST              10 (('>',))
#             172 LOAD_FAST                6 (@py_assert4)
#             174 BUILD_TUPLE              1
#             176 LOAD_CONST              11 (('%(py3)s\n{%(py3)s = %(py0)s(%(py1)s)\n} > %(py6)s',))
#             178 LOAD_FAST                4 (@py_assert2)
#             180 LOAD_FAST                5 (@py_assert5)
#             182 BUILD_TUPLE              2
#             184 CALL                     4
#             192 LOAD_CONST              12 ('len')
#             194 LOAD_GLOBAL             11 (NULL + @py_builtins)
#             204 LOAD_ATTR               12 (locals)
#             224 CALL                     0
#             232 CONTAINS_OP              0
#             234 POP_JUMP_IF_TRUE        25 (to 286)
#             236 LOAD_GLOBAL              7 (NULL + @pytest_ar)
#             246 LOAD_ATTR               14 (_should_repr_global_name)
#             266 LOAD_GLOBAL              4 (len)
#             276 CALL                     1
#             284 POP_JUMP_IF_FALSE       25 (to 336)
#         >>  286 LOAD_GLOBAL              7 (NULL + @pytest_ar)
#             296 LOAD_ATTR               16 (_saferepr)
#             316 LOAD_GLOBAL              4 (len)
#             326 CALL                     1
#             334 JUMP_FORWARD             1 (to 338)
#         >>  336 LOAD_CONST              12 ('len')
#         >>  338 LOAD_CONST              13 ('wp')
#             340 LOAD_GLOBAL             11 (NULL + @py_builtins)
#             350 LOAD_ATTR               12 (locals)
#             370 CALL                     0
#             378 CONTAINS_OP              0
#             380 POP_JUMP_IF_TRUE        21 (to 424)
#             382 LOAD_GLOBAL              7 (NULL + @pytest_ar)
#             392 LOAD_ATTR               14 (_should_repr_global_name)
#             412 LOAD_FAST                3 (wp)
#             414 CALL                     1
#             422 POP_JUMP_IF_FALSE       21 (to 466)
#         >>  424 LOAD_GLOBAL              7 (NULL + @pytest_ar)
#             434 LOAD_ATTR               16 (_saferepr)
#             454 LOAD_FAST                3 (wp)
#             456 CALL                     1
#             464 JUMP_FORWARD             1 (to 468)
#         >>  466 LOAD_CONST              13 ('wp')
#         >>  468 LOAD_GLOBAL              7 (NULL + @pytest_ar)
#             478 LOAD_ATTR               16 (_saferepr)
#             498 LOAD_FAST                4 (@py_assert2)
#             500 CALL                     1
#             508 LOAD_GLOBAL              7 (NULL + @pytest_ar)
#             518 LOAD_ATTR               16 (_saferepr)
#             538 LOAD_FAST                5 (@py_assert5)
#             540 CALL                     1
#             548 LOAD_CONST              14 (('py0', 'py1', 'py3', 'py6'))
#             550 BUILD_CONST_KEY_MAP      4
#             552 BINARY_OP                6 (%)
#             556 STORE_FAST               7 (@py_format7)
#             558 LOAD_CONST              15 ('assert %(py8)s')
#             560 LOAD_CONST              16 ('py8')
#             562 LOAD_FAST                7 (@py_format7)
#             564 BUILD_MAP                1
#             566 BINARY_OP                6 (%)
#             570 STORE_FAST               8 (@py_format9)
#             572 LOAD_GLOBAL             19 (NULL + AssertionError)
#             582 LOAD_GLOBAL              7 (NULL + @pytest_ar)
#             592 LOAD_ATTR               20 (_format_explanation)
#             612 LOAD_FAST                8 (@py_format9)
#             614 CALL                     1
#             622 CALL                     1
#             630 RAISE_VARARGS            1
#         >>  632 LOAD_CONST               0 (None)
#             634 COPY                     1
#             636 STORE_FAST               4 (@py_assert2)
#             638 COPY                     1
#             640 STORE_FAST               6 (@py_assert4)
#             642 STORE_FAST               5 (@py_assert5)
# 
# 116         644 LOAD_GLOBAL             23 (NULL + next)
#             654 LOAD_CONST              17 (<code object <genexpr> at 0x73cd93b31930, file "/home/chenying/researches/cloudpss-toolkit/cloudpss_skills_v2/tests/test_contingency_analysis.py", line 116>)
#             656 MAKE_FUNCTION            0
#             658 LOAD_FAST                3 (wp)
#             660 GET_ITER
#             662 CALL                     0
#             670 CALL                     1
#             678 STORE_FAST               9 (c1_entry)
# 
# 117         680 LOAD_FAST                9 (c1_entry)
#             682 LOAD_CONST              18 ('critical_cases')
#             684 BINARY_SUBSCR
#             688 STORE_FAST              10 (@py_assert0)
#             690 LOAD_CONST              19 (2)
#             692 STORE_FAST              11 (@py_assert3)
#             694 LOAD_FAST               10 (@py_assert0)
#             696 LOAD_FAST               11 (@py_assert3)
#             698 COMPARE_OP              40 (==)
#             702 STORE_FAST               4 (@py_assert2)
#             704 LOAD_FAST                4 (@py_assert2)
#             706 POP_JUMP_IF_TRUE       108 (to 924)
#             708 LOAD_GLOBAL              7 (NULL + @pytest_ar)
#             718 LOAD_ATTR                8 (_call_reprcompare)
#             738 LOAD_CONST              20 (('==',))
#             740 LOAD_FAST                4 (@py_assert2)
#             742 BUILD_TUPLE              1
#             744 LOAD_CONST              21 (('%(py1)s == %(py4)s',))
#             746 LOAD_FAST               10 (@py_assert0)
#             748 LOAD_FAST               11 (@py_assert3)
#             750 BUILD_TUPLE              2
#             752 CALL                     4
#             760 LOAD_GLOBAL              7 (NULL + @pytest_ar)
#             770 LOAD_ATTR               16 (_saferepr)
#             790 LOAD_FAST               10 (@py_assert0)
#             792 CALL                     1
#             800 LOAD_GLOBAL              7 (NULL + @pytest_ar)
#             810 LOAD_ATTR               16 (_saferepr)
#             830 LOAD_FAST               11 (@py_assert3)
#             832 CALL                     1
#             840 LOAD_CONST              22 (('py1', 'py4'))
#             842 BUILD_CONST_KEY_MAP      2
#             844 BINARY_OP                6 (%)
#             848 STORE_FAST              12 (@py_format5)
#             850 LOAD_CONST              23 ('assert %(py6)s')
#             852 LOAD_CONST              24 ('py6')
#             854 LOAD_FAST               12 (@py_format5)
#             856 BUILD_MAP                1
#             858 BINARY_OP                6 (%)
#             862 STORE_FAST               7 (@py_format7)
#             864 LOAD_GLOBAL             19 (NULL + AssertionError)
#             874 LOAD_GLOBAL              7 (NULL + @pytest_ar)
#             884 LOAD_ATTR               20 (_format_explanation)
#             904 LOAD_FAST                7 (@py_format7)
#             906 CALL                     1
#             914 CALL                     1
#             922 RAISE_VARARGS            1
#         >>  924 LOAD_CONST               0 (None)
#             926 COPY                     1
#             928 STORE_FAST              10 (@py_assert0)
#             930 COPY                     1
#             932 STORE_FAST               4 (@py_assert2)
#             934 STORE_FAST              11 (@py_assert3)
#             936 RETURN_CONST             0 (None)
# 
# Disassembly of <code object <genexpr> at 0x73cd93b31930, file "/home/chenying/researches/cloudpss-toolkit/cloudpss_skills_v2/tests/test_contingency_analysis.py", line 116>:
# 116           0 RETURN_GENERATOR
#               2 POP_TOP
#               4 RESUME                   0
#               6 LOAD_FAST                0 (.0)
#         >>    8 FOR_ITER                15 (to 42)
#              12 STORE_FAST               1 (w)
#              14 LOAD_FAST                1 (w)
#              16 LOAD_CONST               0 ('component')
#              18 BINARY_SUBSCR
#              22 LOAD_CONST               1 ('C1')
#              24 COMPARE_OP              40 (==)
#              28 POP_JUMP_IF_TRUE         1 (to 32)
#              30 JUMP_BACKWARD           12 (to 8)
#         >>   32 LOAD_FAST                1 (w)
#              34 YIELD_VALUE              1
#              36 RESUME                   1
#              38 POP_TOP
#              40 JUMP_BACKWARD           17 (to 8)
#         >>   42 END_FOR
#              44 RETURN_CONST             2 (None)
#         >>   46 CALL_INTRINSIC_1         3 (INTRINSIC_STOPITERATION_ERROR)
#              48 RERAISE                  1
# ExceptionTable:
#   4 to 28 -> 46 [0] lasti
#   32 to 44 -> 46 [0] lasti
# 
# Disassembly of <code object TestContingencyAnalysisRun at 0x73cd945fc110, file "/home/chenying/researches/cloudpss-toolkit/cloudpss_skills_v2/tests/test_contingency_analysis.py", line 120>:
# 120           0 RESUME                   0
#               2 LOAD_NAME                0 (__name__)
#               4 STORE_NAME               1 (__module__)
#               6 LOAD_CONST               0 ('TestContingencyAnalysisRun')
#               8 STORE_NAME               2 (__qualname__)
# 
# 121          10 LOAD_CONST               1 (<code object test_validation_failure_returns_failed at 0x3af9e7f0, file "/home/chenying/researches/cloudpss-toolkit/cloudpss_skills_v2/tests/test_contingency_analysis.py", line 121>)
#              12 MAKE_FUNCTION            0
#              14 STORE_NAME               3 (test_validation_failure_returns_failed)
# 
# 127          16 LOAD_CONST               2 (<code object test_run_with_components at 0x3af9d7e0, file "/home/chenying/researches/cloudpss-toolkit/cloudpss_skills_v2/tests/test_contingency_analysis.py", line 127>)
#              18 MAKE_FUNCTION            0
#              20 STORE_NAME               4 (test_run_with_components)
# 
# 148          22 LOAD_CONST               3 (<code object test_run_with_case_results at 0x3afa7720, file "/home/chenying/researches/cloudpss-toolkit/cloudpss_skills_v2/tests/test_contingency_analysis.py", line 148>)
#              24 MAKE_FUNCTION            0
#              26 STORE_NAME               5 (test_run_with_case_results)
#              28 RETURN_CONST             4 (None)
# 
# Disassembly of <code object test_validation_failure_returns_failed at 0x3af9e7f0, file "/home/chenying/researches/cloudpss-toolkit/cloudpss_skills_v2/tests/test_contingency_analysis.py", line 121>:
# 121           0 RESUME                   0
# 
# 122           2 LOAD_GLOBAL              1 (NULL + ContingencyAnalysisSkill)
#              12 CALL                     0
#              20 STORE_FAST               1 (skill)
# 
# 123          22 LOAD_FAST                1 (skill)
#              24 LOAD_ATTR                3 (NULL|self + run)
#              44 BUILD_MAP                0
#              46 CALL                     1
#              54 STORE_FAST               2 (result)
# 
# 124          56 LOAD_FAST                2 (result)
#              58 LOAD_ATTR                4 (status)
#              78 STORE_FAST               3 (@py_assert1)
#              80 LOAD_GLOBAL              6 (SkillStatus)
#              90 LOAD_ATTR                8 (FAILED)
#             110 STORE_FAST               4 (@py_assert5)
#             112 LOAD_FAST                3 (@py_assert1)
#             114 LOAD_FAST                4 (@py_assert5)
#             116 COMPARE_OP              40 (==)
#             120 STORE_FAST               5 (@py_assert3)
#             122 LOAD_FAST                5 (@py_assert3)
#             124 POP_JUMP_IF_TRUE       246 (to 618)
#             126 LOAD_GLOBAL             11 (NULL + @pytest_ar)
#             136 LOAD_ATTR               12 (_call_reprcompare)
#             156 LOAD_CONST               1 (('==',))
#             158 LOAD_FAST                5 (@py_assert3)
#             160 BUILD_TUPLE              1
#             162 LOAD_CONST               2 (('%(py2)s\n{%(py2)s = %(py0)s.status\n} == %(py6)s\n{%(py6)s = %(py4)s.FAILED\n}',))
#             164 LOAD_FAST                3 (@py_assert1)
#             166 LOAD_FAST                4 (@py_assert5)
#             168 BUILD_TUPLE              2
#             170 CALL                     4
#             178 LOAD_CONST               3 ('result')
#             180 LOAD_GLOBAL             15 (NULL + @py_builtins)
#             190 LOAD_ATTR               16 (locals)
#             210 CALL                     0
#             218 CONTAINS_OP              0
#             220 POP_JUMP_IF_TRUE        21 (to 264)
#             222 LOAD_GLOBAL             11 (NULL + @pytest_ar)
#             232 LOAD_ATTR               18 (_should_repr_global_name)
#             252 LOAD_FAST                2 (result)
#             254 CALL                     1
#             262 POP_JUMP_IF_FALSE       21 (to 306)
#         >>  264 LOAD_GLOBAL             11 (NULL + @pytest_ar)
#             274 LOAD_ATTR               20 (_saferepr)
#             294 LOAD_FAST                2 (result)
#             296 CALL                     1
#             304 JUMP_FORWARD             1 (to 308)
#         >>  306 LOAD_CONST               3 ('result')
#         >>  308 LOAD_GLOBAL             11 (NULL + @pytest_ar)
#             318 LOAD_ATTR               20 (_saferepr)
#             338 LOAD_FAST                3 (@py_assert1)
#             340 CALL                     1
#             348 LOAD_CONST               4 ('SkillStatus')
#             350 LOAD_GLOBAL             15 (NULL + @py_builtins)
#             360 LOAD_ATTR               16 (locals)
#             380 CALL                     0
#             388 CONTAINS_OP              0
#             390 POP_JUMP_IF_TRUE        25 (to 442)
#             392 LOAD_GLOBAL             11 (NULL + @pytest_ar)
#             402 LOAD_ATTR               18 (_should_repr_global_name)
#             422 LOAD_GLOBAL              6 (SkillStatus)
#             432 CALL                     1
#             440 POP_JUMP_IF_FALSE       25 (to 492)
#         >>  442 LOAD_GLOBAL             11 (NULL + @pytest_ar)
#             452 LOAD_ATTR               20 (_saferepr)
#             472 LOAD_GLOBAL              6 (SkillStatus)
#             482 CALL                     1
#             490 JUMP_FORWARD             1 (to 494)
#         >>  492 LOAD_CONST               4 ('SkillStatus')
#         >>  494 LOAD_GLOBAL             11 (NULL + @pytest_ar)
#             504 LOAD_ATTR               20 (_saferepr)
#             524 LOAD_FAST                4 (@py_assert5)
#             526 CALL                     1
#             534 LOAD_CONST               5 (('py0', 'py2', 'py4', 'py6'))
#             536 BUILD_CONST_KEY_MAP      4
#             538 BINARY_OP                6 (%)
#             542 STORE_FAST               6 (@py_format7)
#             544 LOAD_CONST               6 ('assert %(py8)s')
#             546 LOAD_CONST               7 ('py8')
#             548 LOAD_FAST                6 (@py_format7)
#             550 BUILD_MAP                1
#             552 BINARY_OP                6 (%)
#             556 STORE_FAST               7 (@py_format9)
#             558 LOAD_GLOBAL             23 (NULL + AssertionError)
#             568 LOAD_GLOBAL             11 (NULL + @pytest_ar)
#             578 LOAD_ATTR               24 (_format_explanation)
#             598 LOAD_FAST                7 (@py_format9)
#             600 CALL                     1
#             608 CALL                     1
#             616 RAISE_VARARGS            1
#         >>  618 LOAD_CONST               0 (None)
#             620 COPY                     1
#             622 STORE_FAST               3 (@py_assert1)
#             624 COPY                     1
#             626 STORE_FAST               5 (@py_assert3)
#             628 STORE_FAST               4 (@py_assert5)
# 
# 125         630 LOAD_FAST                2 (result)
#             632 LOAD_ATTR               26 (error)
#             652 STORE_FAST               3 (@py_assert1)
#             654 LOAD_CONST               0 (None)
#             656 STORE_FAST               8 (@py_assert4)
#             658 LOAD_FAST                3 (@py_assert1)
#             660 LOAD_FAST                8 (@py_assert4)
#             662 IS_OP                    1
#             664 STORE_FAST               5 (@py_assert3)
#             666 LOAD_FAST                5 (@py_assert3)
#             668 POP_JUMP_IF_TRUE       173 (to 1016)
#             670 LOAD_GLOBAL             11 (NULL + @pytest_ar)
#             680 LOAD_ATTR               12 (_call_reprcompare)
#             700 LOAD_CONST               8 (('is not',))
#             702 LOAD_FAST                5 (@py_assert3)
#             704 BUILD_TUPLE              1
#             706 LOAD_CONST               9 (('%(py2)s\n{%(py2)s = %(py0)s.error\n} is not %(py5)s',))
#             708 LOAD_FAST                3 (@py_assert1)
#             710 LOAD_FAST                8 (@py_assert4)
#             712 BUILD_TUPLE              2
#             714 CALL                     4
#             722 LOAD_CONST               3 ('result')
#             724 LOAD_GLOBAL             15 (NULL + @py_builtins)
#             734 LOAD_ATTR               16 (locals)
#             754 CALL                     0
#             762 CONTAINS_OP              0
#             764 POP_JUMP_IF_TRUE        21 (to 808)
#             766 LOAD_GLOBAL             11 (NULL + @pytest_ar)
#             776 LOAD_ATTR               18 (_should_repr_global_name)
#             796 LOAD_FAST                2 (result)
#             798 CALL                     1
#             806 POP_JUMP_IF_FALSE       21 (to 850)
#         >>  808 LOAD_GLOBAL             11 (NULL + @pytest_ar)
#             818 LOAD_ATTR               20 (_saferepr)
#             838 LOAD_FAST                2 (result)
#             840 CALL                     1
#             848 JUMP_FORWARD             1 (to 852)
#         >>  850 LOAD_CONST               3 ('result')
#         >>  852 LOAD_GLOBAL             11 (NULL + @pytest_ar)
#             862 LOAD_ATTR               20 (_saferepr)
#             882 LOAD_FAST                3 (@py_assert1)
#             884 CALL                     1
#             892 LOAD_GLOBAL             11 (NULL + @pytest_ar)
#             902 LOAD_ATTR               20 (_saferepr)
#             922 LOAD_FAST                8 (@py_assert4)
#             924 CALL                     1
#             932 LOAD_CONST              10 (('py0', 'py2', 'py5'))
#             934 BUILD_CONST_KEY_MAP      3
#             936 BINARY_OP                6 (%)
#             940 STORE_FAST               9 (@py_format6)
#             942 LOAD_CONST              11 ('assert %(py7)s')
#             944 LOAD_CONST              12 ('py7')
#             946 LOAD_FAST                9 (@py_format6)
#             948 BUILD_MAP                1
#             950 BINARY_OP                6 (%)
#             954 STORE_FAST              10 (@py_format8)
#             956 LOAD_GLOBAL             23 (NULL + AssertionError)
#             966 LOAD_GLOBAL             11 (NULL + @pytest_ar)
#             976 LOAD_ATTR               24 (_format_explanation)
#             996 LOAD_FAST               10 (@py_format8)
#             998 CALL                     1
#            1006 CALL                     1
#            1014 RAISE_VARARGS            1
#         >> 1016 LOAD_CONST               0 (None)
#            1018 COPY                     1
#            1020 STORE_FAST               3 (@py_assert1)
#            1022 COPY                     1
#            1024 STORE_FAST               5 (@py_assert3)
#            1026 STORE_FAST               8 (@py_assert4)
#            1028 RETURN_CONST             0 (None)
# 
# Disassembly of <code object test_run_with_components at 0x3af9d7e0, file "/home/chenying/researches/cloudpss-toolkit/cloudpss_skills_v2/tests/test_contingency_analysis.py", line 127>:
# 127           0 RESUME                   0
# 
# 128           2 LOAD_GLOBAL              1 (NULL + ContingencyAnalysisSkill)
#              12 CALL                     0
#              20 STORE_FAST               1 (skill)
# 
# 130          22 LOAD_CONST               1 ('rid')
#              24 LOAD_CONST               2 ('test')
#              26 BUILD_MAP                1
# 
# 132          28 LOAD_CONST               3 ('N-1')
# 
# 133          30 BUILD_LIST               0
#              32 LOAD_CONST               4 (('C1', 'C2', 'C3'))
#              34 LIST_EXTEND              1
# 
# 134          36 LOAD_CONST               5 (100)
# 
# 131          38 LOAD_CONST               6 (('level', 'components', 'max_combinations'))
#              40 BUILD_CONST_KEY_MAP      3
# 
# 137          42 LOAD_CONST               7 (0.95)
#              44 LOAD_CONST               8 (1.05)
#              46 LOAD_CONST               9 (('min', 'max'))
#              48 BUILD_CONST_KEY_MAP      2
# 
# 138          50 LOAD_CONST              10 (1.0)
# 
# 136          52 LOAD_CONST              11 (('voltage_limit', 'thermal_limit'))
#              54 BUILD_CONST_KEY_MAP      2
# 
# 140          56 LOAD_CONST              12 ('top_n')
#              58 LOAD_CONST              13 (10)
#              60 BUILD_MAP                1
# 
# 141          62 LOAD_CONST              14 ('path')
#              64 LOAD_CONST              15 ('/tmp/contingency_test/')
#              66 BUILD_MAP                1
# 
# 129          68 LOAD_CONST              16 (('model', 'contingency', 'analysis', 'ranking', 'output'))
#              70 BUILD_CONST_KEY_MAP      5
#              72 STORE_FAST               2 (config)
# 
# 143          74 LOAD_FAST                1 (skill)
#              76 LOAD_ATTR                3 (NULL|self + run)
#              96 LOAD_FAST                2 (config)
#              98 CALL                     1
#             106 STORE_FAST               3 (result)
# 
# 144         108 LOAD_FAST                3 (result)
#             110 LOAD_ATTR                4 (status)
#             130 STORE_FAST               4 (@py_assert1)
#             132 LOAD_GLOBAL              6 (SkillStatus)
#             142 LOAD_ATTR                8 (SUCCESS)
#             162 STORE_FAST               5 (@py_assert5)
#             164 LOAD_FAST                4 (@py_assert1)
#             166 LOAD_FAST                5 (@py_assert5)
#             168 COMPARE_OP              40 (==)
#             172 STORE_FAST               6 (@py_assert3)
#             174 LOAD_FAST                6 (@py_assert3)
#             176 POP_JUMP_IF_TRUE       246 (to 670)
#             178 LOAD_GLOBAL             11 (NULL + @pytest_ar)
#             188 LOAD_ATTR               12 (_call_reprcompare)
#             208 LOAD_CONST              17 (('==',))
#             210 LOAD_FAST                6 (@py_assert3)
#             212 BUILD_TUPLE              1
#             214 LOAD_CONST              18 (('%(py2)s\n{%(py2)s = %(py0)s.status\n} == %(py6)s\n{%(py6)s = %(py4)s.SUCCESS\n}',))
#             216 LOAD_FAST                4 (@py_assert1)
#             218 LOAD_FAST                5 (@py_assert5)
#             220 BUILD_TUPLE              2
#             222 CALL                     4
#             230 LOAD_CONST              19 ('result')
#             232 LOAD_GLOBAL             15 (NULL + @py_builtins)
#             242 LOAD_ATTR               16 (locals)
#             262 CALL                     0
#             270 CONTAINS_OP              0
#             272 POP_JUMP_IF_TRUE        21 (to 316)
#             274 LOAD_GLOBAL             11 (NULL + @pytest_ar)
#             284 LOAD_ATTR               18 (_should_repr_global_name)
#             304 LOAD_FAST                3 (result)
#             306 CALL                     1
#             314 POP_JUMP_IF_FALSE       21 (to 358)
#         >>  316 LOAD_GLOBAL             11 (NULL + @pytest_ar)
#             326 LOAD_ATTR               20 (_saferepr)
#             346 LOAD_FAST                3 (result)
#             348 CALL                     1
#             356 JUMP_FORWARD             1 (to 360)
#         >>  358 LOAD_CONST              19 ('result')
#         >>  360 LOAD_GLOBAL             11 (NULL + @pytest_ar)
#             370 LOAD_ATTR               20 (_saferepr)
#             390 LOAD_FAST                4 (@py_assert1)
#             392 CALL                     1
#             400 LOAD_CONST              20 ('SkillStatus')
#             402 LOAD_GLOBAL             15 (NULL + @py_builtins)
#             412 LOAD_ATTR               16 (locals)
#             432 CALL                     0
#             440 CONTAINS_OP              0
#             442 POP_JUMP_IF_TRUE        25 (to 494)
#             444 LOAD_GLOBAL             11 (NULL + @pytest_ar)
#             454 LOAD_ATTR               18 (_should_repr_global_name)
#             474 LOAD_GLOBAL              6 (SkillStatus)
#             484 CALL                     1
#             492 POP_JUMP_IF_FALSE       25 (to 544)
#         >>  494 LOAD_GLOBAL             11 (NULL + @pytest_ar)
#             504 LOAD_ATTR               20 (_saferepr)
#             524 LOAD_GLOBAL              6 (SkillStatus)
#             534 CALL                     1
#             542 JUMP_FORWARD             1 (to 546)
#         >>  544 LOAD_CONST              20 ('SkillStatus')
#         >>  546 LOAD_GLOBAL             11 (NULL + @pytest_ar)
#             556 LOAD_ATTR               20 (_saferepr)
#             576 LOAD_FAST                5 (@py_assert5)
#             578 CALL                     1
#             586 LOAD_CONST              21 (('py0', 'py2', 'py4', 'py6'))
#             588 BUILD_CONST_KEY_MAP      4
#             590 BINARY_OP                6 (%)
#             594 STORE_FAST               7 (@py_format7)
#             596 LOAD_CONST              22 ('assert %(py8)s')
#             598 LOAD_CONST              23 ('py8')
#             600 LOAD_FAST                7 (@py_format7)
#             602 BUILD_MAP                1
#             604 BINARY_OP                6 (%)
#             608 STORE_FAST               8 (@py_format9)
#             610 LOAD_GLOBAL             23 (NULL + AssertionError)
#             620 LOAD_GLOBAL             11 (NULL + @pytest_ar)
#             630 LOAD_ATTR               24 (_format_explanation)
#             650 LOAD_FAST                8 (@py_format9)
#             652 CALL                     1
#             660 CALL                     1
#             668 RAISE_VARARGS            1
#         >>  670 LOAD_CONST               0 (None)
#             672 COPY                     1
#             674 STORE_FAST               4 (@py_assert1)
#             676 COPY                     1
#             678 STORE_FAST               6 (@py_assert3)
#             680 STORE_FAST               5 (@py_assert5)
# 
# 145         682 LOAD_CONST              24 ('summary')
#             684 STORE_FAST               9 (@py_assert0)
#             686 LOAD_FAST                3 (result)
#             688 LOAD_ATTR               26 (data)
#             708 STORE_FAST              10 (@py_assert4)
#             710 LOAD_FAST                9 (@py_assert0)
#             712 LOAD_FAST               10 (@py_assert4)
#             714 CONTAINS_OP              0
#             716 STORE_FAST              11 (@py_assert2)
#             718 LOAD_FAST               11 (@py_assert2)
#             720 POP_JUMP_IF_TRUE       173 (to 1068)
#             722 LOAD_GLOBAL             11 (NULL + @pytest_ar)
#             732 LOAD_ATTR               12 (_call_reprcompare)
#             752 LOAD_CONST              25 (('in',))
#             754 LOAD_FAST               11 (@py_assert2)
#             756 BUILD_TUPLE              1
#             758 LOAD_CONST              26 (('%(py1)s in %(py5)s\n{%(py5)s = %(py3)s.data\n}',))
#             760 LOAD_FAST                9 (@py_assert0)
#             762 LOAD_FAST               10 (@py_assert4)
#             764 BUILD_TUPLE              2
#             766 CALL                     4
#             774 LOAD_GLOBAL             11 (NULL + @pytest_ar)
#             784 LOAD_ATTR               20 (_saferepr)
#             804 LOAD_FAST                9 (@py_assert0)
#             806 CALL                     1
#             814 LOAD_CONST              19 ('result')
#             816 LOAD_GLOBAL             15 (NULL + @py_builtins)
#             826 LOAD_ATTR               16 (locals)
#             846 CALL                     0
#             854 CONTAINS_OP              0
#             856 POP_JUMP_IF_TRUE        21 (to 900)
#             858 LOAD_GLOBAL             11 (NULL + @pytest_ar)
#             868 LOAD_ATTR               18 (_should_repr_global_name)
#             888 LOAD_FAST                3 (result)
#             890 CALL                     1
#             898 POP_JUMP_IF_FALSE       21 (to 942)
#         >>  900 LOAD_GLOBAL             11 (NULL + @pytest_ar)
#             910 LOAD_ATTR               20 (_saferepr)
#             930 LOAD_FAST                3 (result)
#             932 CALL                     1
#             940 JUMP_FORWARD             1 (to 944)
#         >>  942 LOAD_CONST              19 ('result')
#         >>  944 LOAD_GLOBAL             11 (NULL + @pytest_ar)
#             954 LOAD_ATTR               20 (_saferepr)
#             974 LOAD_FAST               10 (@py_assert4)
#             976 CALL                     1
#             984 LOAD_CONST              27 (('py1', 'py3', 'py5'))
#             986 BUILD_CONST_KEY_MAP      3
#             988 BINARY_OP                6 (%)
#             992 STORE_FAST              12 (@py_format6)
#             994 LOAD_CONST              28 ('assert %(py7)s')
#             996 LOAD_CONST              29 ('py7')
#             998 LOAD_FAST               12 (@py_format6)
#            1000 BUILD_MAP                1
#            1002 BINARY_OP                6 (%)
#            1006 STORE_FAST              13 (@py_format8)
#            1008 LOAD_GLOBAL             23 (NULL + AssertionError)
#            1018 LOAD_GLOBAL             11 (NULL + @pytest_ar)
#            1028 LOAD_ATTR               24 (_format_explanation)
#            1048 LOAD_FAST               13 (@py_format8)
#            1050 CALL                     1
#            1058 CALL                     1
#            1066 RAISE_VARARGS            1
#         >> 1068 LOAD_CONST               0 (None)
#            1070 COPY                     1
#            1072 STORE_FAST               9 (@py_assert0)
#            1074 COPY                     1
#            1076 STORE_FAST              11 (@py_assert2)
#            1078 STORE_FAST              10 (@py_assert4)
# 
# 146        1080 LOAD_FAST                3 (result)
#            1082 LOAD_ATTR               26 (data)
#            1102 LOAD_CONST              24 ('summary')
#            1104 BINARY_SUBSCR
#            1108 LOAD_CONST              30 ('total_cases')
#            1110 BINARY_SUBSCR
#            1114 STORE_FAST               9 (@py_assert0)
#            1116 LOAD_CONST              31 (3)
#            1118 STORE_FAST               6 (@py_assert3)
#            1120 LOAD_FAST                9 (@py_assert0)
#            1122 LOAD_FAST                6 (@py_assert3)
#            1124 COMPARE_OP              40 (==)
#            1128 STORE_FAST              11 (@py_assert2)
#            1130 LOAD_FAST               11 (@py_assert2)
#            1132 POP_JUMP_IF_TRUE       108 (to 1350)
#            1134 LOAD_GLOBAL             11 (NULL + @pytest_ar)
#            1144 LOAD_ATTR               12 (_call_reprcompare)
#            1164 LOAD_CONST              17 (('==',))
#            1166 LOAD_FAST               11 (@py_assert2)
#            1168 BUILD_TUPLE              1
#            1170 LOAD_CONST              32 (('%(py1)s == %(py4)s',))
#            1172 LOAD_FAST                9 (@py_assert0)
#            1174 LOAD_FAST                6 (@py_assert3)
#            1176 BUILD_TUPLE              2
#            1178 CALL                     4
#            1186 LOAD_GLOBAL             11 (NULL + @pytest_ar)
#            1196 LOAD_ATTR               20 (_saferepr)
#            1216 LOAD_FAST                9 (@py_assert0)
#            1218 CALL                     1
#            1226 LOAD_GLOBAL             11 (NULL + @pytest_ar)
#            1236 LOAD_ATTR               20 (_saferepr)
#            1256 LOAD_FAST                6 (@py_assert3)
#            1258 CALL                     1
#            1266 LOAD_CONST              33 (('py1', 'py4'))
#            1268 BUILD_CONST_KEY_MAP      2
#            1270 BINARY_OP                6 (%)
#            1274 STORE_FAST              14 (@py_format5)
#            1276 LOAD_CONST              34 ('assert %(py6)s')
#            1278 LOAD_CONST              35 ('py6')
#            1280 LOAD_FAST               14 (@py_format5)
#            1282 BUILD_MAP                1
#            1284 BINARY_OP                6 (%)
#            1288 STORE_FAST               7 (@py_format7)
#            1290 LOAD_GLOBAL             23 (NULL + AssertionError)
#            1300 LOAD_GLOBAL             11 (NULL + @pytest_ar)
#            1310 LOAD_ATTR               24 (_format_explanation)
#            1330 LOAD_FAST                7 (@py_format7)
#            1332 CALL                     1
#            1340 CALL                     1
#            1348 RAISE_VARARGS            1
#         >> 1350 LOAD_CONST               0 (None)
#            1352 COPY                     1
#            1354 STORE_FAST               9 (@py_assert0)
#            1356 COPY                     1
#            1358 STORE_FAST              11 (@py_assert2)
#            1360 STORE_FAST               6 (@py_assert3)
#            1362 RETURN_CONST             0 (None)
# 
# Disassembly of <code object test_run_with_case_results at 0x3afa7720, file "/home/chenying/researches/cloudpss-toolkit/cloudpss_skills_v2/tests/test_contingency_analysis.py", line 148>:
# 148           0 RESUME                   0
# 
# 149           2 LOAD_GLOBAL              1 (NULL + ContingencyAnalysisSkill)
#              12 CALL                     0
#              20 STORE_FAST               1 (skill)
# 
# 151          22 LOAD_CONST               1 ('rid')
#              24 LOAD_CONST               2 ('test')
#              26 BUILD_MAP                1
# 
# 153          28 LOAD_CONST               3 ('N-1')
# 
# 154          30 LOAD_CONST               4 ('C1')
#              32 LOAD_CONST               5 ('C2')
#              34 BUILD_LIST               2
# 
# 155          36 LOAD_CONST               6 (100)
# 
# 152          38 LOAD_CONST               7 (('level', 'components', 'max_combinations'))
#              40 BUILD_CONST_KEY_MAP      3
# 
# 158          42 LOAD_CONST               8 (0.95)
#              44 LOAD_CONST               9 (1.05)
#              46 LOAD_CONST              10 (('min', 'max'))
#              48 BUILD_CONST_KEY_MAP      2
# 
# 159          50 LOAD_CONST              11 (1.0)
# 
# 157          52 LOAD_CONST              12 (('voltage_limit', 'thermal_limit'))
#              54 BUILD_CONST_KEY_MAP      2
# 
# 161          56 LOAD_CONST              13 ('top_n')
#              58 LOAD_CONST              14 (10)
#              60 BUILD_MAP                1
# 
# 162          62 LOAD_CONST              15 ('path')
#              64 LOAD_CONST              16 ('/tmp/contingency_test2/')
#              66 BUILD_MAP                1
# 
# 164          68 LOAD_CONST              17 ('PASS')
#              70 LOAD_CONST              11 (1.0)
#              72 LOAD_CONST              11 (1.0)
#              74 LOAD_CONST              18 (('status', 'min_voltage', 'max_voltage'))
#              76 BUILD_CONST_KEY_MAP      3
# 
# 165          78 LOAD_CONST              19 ('status')
#              80 LOAD_CONST              20 ('FAIL')
#              82 BUILD_MAP                1
# 
# 163          84 BUILD_LIST               2
# 
# 150          86 LOAD_CONST              21 (('model', 'contingency', 'analysis', 'ranking', 'output', 'case_results'))
#              88 BUILD_CONST_KEY_MAP      6
#              90 STORE_FAST               2 (config)
# 
# 168          92 LOAD_FAST                1 (skill)
#              94 LOAD_ATTR                3 (NULL|self + run)
#             114 LOAD_FAST                2 (config)
#             116 CALL                     1
#             124 STORE_FAST               3 (result)
# 
# 169         126 LOAD_FAST                3 (result)
#             128 LOAD_ATTR                4 (status)
#             148 STORE_FAST               4 (@py_assert1)
#             150 LOAD_GLOBAL              6 (SkillStatus)
#             160 LOAD_ATTR                8 (SUCCESS)
#             180 STORE_FAST               5 (@py_assert5)
#             182 LOAD_FAST                4 (@py_assert1)
#             184 LOAD_FAST                5 (@py_assert5)
#             186 COMPARE_OP              40 (==)
#             190 STORE_FAST               6 (@py_assert3)
#             192 LOAD_FAST                6 (@py_assert3)
#             194 POP_JUMP_IF_TRUE       246 (to 688)
#             196 LOAD_GLOBAL             11 (NULL + @pytest_ar)
#             206 LOAD_ATTR               12 (_call_reprcompare)
#             226 LOAD_CONST              22 (('==',))
#             228 LOAD_FAST                6 (@py_assert3)
#             230 BUILD_TUPLE              1
#             232 LOAD_CONST              23 (('%(py2)s\n{%(py2)s = %(py0)s.status\n} == %(py6)s\n{%(py6)s = %(py4)s.SUCCESS\n}',))
#             234 LOAD_FAST                4 (@py_assert1)
#             236 LOAD_FAST                5 (@py_assert5)
#             238 BUILD_TUPLE              2
#             240 CALL                     4
#             248 LOAD_CONST              24 ('result')
#             250 LOAD_GLOBAL             15 (NULL + @py_builtins)
#             260 LOAD_ATTR               16 (locals)
#             280 CALL                     0
#             288 CONTAINS_OP              0
#             290 POP_JUMP_IF_TRUE        21 (to 334)
#             292 LOAD_GLOBAL             11 (NULL + @pytest_ar)
#             302 LOAD_ATTR               18 (_should_repr_global_name)
#             322 LOAD_FAST                3 (result)
#             324 CALL                     1
#             332 POP_JUMP_IF_FALSE       21 (to 376)
#         >>  334 LOAD_GLOBAL             11 (NULL + @pytest_ar)
#             344 LOAD_ATTR               20 (_saferepr)
#             364 LOAD_FAST                3 (result)
#             366 CALL                     1
#             374 JUMP_FORWARD             1 (to 378)
#         >>  376 LOAD_CONST              24 ('result')
#         >>  378 LOAD_GLOBAL             11 (NULL + @pytest_ar)
#             388 LOAD_ATTR               20 (_saferepr)
#             408 LOAD_FAST                4 (@py_assert1)
#             410 CALL                     1
#             418 LOAD_CONST              25 ('SkillStatus')
#             420 LOAD_GLOBAL             15 (NULL + @py_builtins)
#             430 LOAD_ATTR               16 (locals)
#             450 CALL                     0
#             458 CONTAINS_OP              0
#             460 POP_JUMP_IF_TRUE        25 (to 512)
#             462 LOAD_GLOBAL             11 (NULL + @pytest_ar)
#             472 LOAD_ATTR               18 (_should_repr_global_name)
#             492 LOAD_GLOBAL              6 (SkillStatus)
#             502 CALL                     1
#             510 POP_JUMP_IF_FALSE       25 (to 562)
#         >>  512 LOAD_GLOBAL             11 (NULL + @pytest_ar)
#             522 LOAD_ATTR               20 (_saferepr)
#             542 LOAD_GLOBAL              6 (SkillStatus)
#             552 CALL                     1
#             560 JUMP_FORWARD             1 (to 564)
#         >>  562 LOAD_CONST              25 ('SkillStatus')
#         >>  564 LOAD_GLOBAL             11 (NULL + @pytest_ar)
#             574 LOAD_ATTR               20 (_saferepr)
#             594 LOAD_FAST                5 (@py_assert5)
#             596 CALL                     1
#             604 LOAD_CONST              26 (('py0', 'py2', 'py4', 'py6'))
#             606 BUILD_CONST_KEY_MAP      4
#             608 BINARY_OP                6 (%)
#             612 STORE_FAST               7 (@py_format7)
#             614 LOAD_CONST              27 ('assert %(py8)s')
#             616 LOAD_CONST              28 ('py8')
#             618 LOAD_FAST                7 (@py_format7)
#             620 BUILD_MAP                1
#             622 BINARY_OP                6 (%)
#             626 STORE_FAST               8 (@py_format9)
#             628 LOAD_GLOBAL             23 (NULL + AssertionError)
#             638 LOAD_GLOBAL             11 (NULL + @pytest_ar)
#             648 LOAD_ATTR               24 (_format_explanation)
#             668 LOAD_FAST                8 (@py_format9)
#             670 CALL                     1
#             678 CALL                     1
#             686 RAISE_VARARGS            1
#         >>  688 LOAD_CONST               0 (None)
#             690 COPY                     1
#             692 STORE_FAST               4 (@py_assert1)
#             694 COPY                     1
#             696 STORE_FAST               6 (@py_assert3)
#             698 STORE_FAST               5 (@py_assert5)
# 
# 170         700 LOAD_FAST                3 (result)
#             702 LOAD_ATTR               26 (data)
#             722 LOAD_CONST              29 ('summary')
#             724 BINARY_SUBSCR
#             728 LOAD_CONST              30 ('total_cases')
#             730 BINARY_SUBSCR
#             734 STORE_FAST               9 (@py_assert0)
#             736 LOAD_CONST              31 (2)
#             738 STORE_FAST               6 (@py_assert3)
#             740 LOAD_FAST                9 (@py_assert0)
#             742 LOAD_FAST                6 (@py_assert3)
#             744 COMPARE_OP              40 (==)
#             748 STORE_FAST              10 (@py_assert2)
#             750 LOAD_FAST               10 (@py_assert2)
#             752 POP_JUMP_IF_TRUE       108 (to 970)
#             754 LOAD_GLOBAL             11 (NULL + @pytest_ar)
#             764 LOAD_ATTR               12 (_call_reprcompare)
#             784 LOAD_CONST              22 (('==',))
#             786 LOAD_FAST               10 (@py_assert2)
#             788 BUILD_TUPLE              1
#             790 LOAD_CONST              32 (('%(py1)s == %(py4)s',))
#             792 LOAD_FAST                9 (@py_assert0)
#             794 LOAD_FAST                6 (@py_assert3)
#             796 BUILD_TUPLE              2
#             798 CALL                     4
#             806 LOAD_GLOBAL             11 (NULL + @pytest_ar)
#             816 LOAD_ATTR               20 (_saferepr)
#             836 LOAD_FAST                9 (@py_assert0)
#             838 CALL                     1
#             846 LOAD_GLOBAL             11 (NULL + @pytest_ar)
#             856 LOAD_ATTR               20 (_saferepr)
#             876 LOAD_FAST                6 (@py_assert3)
#             878 CALL                     1
#             886 LOAD_CONST              33 (('py1', 'py4'))
#             888 BUILD_CONST_KEY_MAP      2
#             890 BINARY_OP                6 (%)
#             894 STORE_FAST              11 (@py_format5)
#             896 LOAD_CONST              34 ('assert %(py6)s')
#             898 LOAD_CONST              35 ('py6')
#             900 LOAD_FAST               11 (@py_format5)
#             902 BUILD_MAP                1
#             904 BINARY_OP                6 (%)
#             908 STORE_FAST               7 (@py_format7)
#             910 LOAD_GLOBAL             23 (NULL + AssertionError)
#             920 LOAD_GLOBAL             11 (NULL + @pytest_ar)
#             930 LOAD_ATTR               24 (_format_explanation)
#             950 LOAD_FAST                7 (@py_format7)
#             952 CALL                     1
#             960 CALL                     1
#             968 RAISE_VARARGS            1
#         >>  970 LOAD_CONST               0 (None)
#             972 COPY                     1
#             974 STORE_FAST               9 (@py_assert0)
#             976 COPY                     1
#             978 STORE_FAST              10 (@py_assert2)
#             980 STORE_FAST               6 (@py_assert3)
# 
# 171         982 LOAD_FAST                3 (result)
#             984 LOAD_ATTR               26 (data)
#            1004 LOAD_CONST              29 ('summary')
#            1006 BINARY_SUBSCR
#            1010 LOAD_CONST              36 ('passed')
#            1012 BINARY_SUBSCR
#            1016 STORE_FAST               9 (@py_assert0)
#            1018 LOAD_CONST              37 (1)
#            1020 STORE_FAST               6 (@py_assert3)
#            1022 LOAD_FAST                9 (@py_assert0)
#            1024 LOAD_FAST                6 (@py_assert3)
#            1026 COMPARE_OP              40 (==)
#            1030 STORE_FAST              10 (@py_assert2)
#            1032 LOAD_FAST               10 (@py_assert2)
#            1034 POP_JUMP_IF_TRUE       108 (to 1252)
#            1036 LOAD_GLOBAL             11 (NULL + @pytest_ar)
#            1046 LOAD_ATTR               12 (_call_reprcompare)
#            1066 LOAD_CONST              22 (('==',))
#            1068 LOAD_FAST               10 (@py_assert2)
#            1070 BUILD_TUPLE              1
#            1072 LOAD_CONST              32 (('%(py1)s == %(py4)s',))
#            1074 LOAD_FAST                9 (@py_assert0)
#            1076 LOAD_FAST                6 (@py_assert3)
#            1078 BUILD_TUPLE              2
#            1080 CALL                     4
#            1088 LOAD_GLOBAL             11 (NULL + @pytest_ar)
#            1098 LOAD_ATTR               20 (_saferepr)
#            1118 LOAD_FAST                9 (@py_assert0)
#            1120 CALL                     1
#            1128 LOAD_GLOBAL             11 (NULL + @pytest_ar)
#            1138 LOAD_ATTR               20 (_saferepr)
#            1158 LOAD_FAST                6 (@py_assert3)
#            1160 CALL                     1
#            1168 LOAD_CONST              33 (('py1', 'py4'))
#            1170 BUILD_CONST_KEY_MAP      2
#            1172 BINARY_OP                6 (%)
#            1176 STORE_FAST              11 (@py_format5)
#            1178 LOAD_CONST              34 ('assert %(py6)s')
#            1180 LOAD_CONST              35 ('py6')
#            1182 LOAD_FAST               11 (@py_format5)
#            1184 BUILD_MAP                1
#            1186 BINARY_OP                6 (%)
#            1190 STORE_FAST               7 (@py_format7)
#            1192 LOAD_GLOBAL             23 (NULL + AssertionError)
#            1202 LOAD_GLOBAL             11 (NULL + @pytest_ar)
#            1212 LOAD_ATTR               24 (_format_explanation)
#            1232 LOAD_FAST                7 (@py_format7)
#            1234 CALL                     1
#            1242 CALL                     1
#            1250 RAISE_VARARGS            1
#         >> 1252 LOAD_CONST               0 (None)
#            1254 COPY                     1
#            1256 STORE_FAST               9 (@py_assert0)
#            1258 COPY                     1
#            1260 STORE_FAST              10 (@py_assert2)
#            1262 STORE_FAST               6 (@py_assert3)
#            1264 RETURN_CONST             0 (None)
# 