# Recovered from: /home/chenying/researches/cloudpss-toolkit/cloudpss_skills_v2/tests/__pycache__/test_orthogonal_sensitivity.cpython-312-pytest-9.0.2.pyc
# Original source: /home/chenying/researches/cloudpss-toolkit/cloudpss_skills_v2/tests/test_orthogonal_sensitivity.py
# WARNING: This file was reconstructed from .pyc bytecode.
# The structure is accurate but implementation details may need manual review.


def TestOrthogonalValidation():
    """TestOrthogonalValidation"""
pass  # TODO: restore


def TestOrthogonalTableSelection():
    """TestOrthogonalTableSelection"""
pass  # TODO: restore


def TestOrthogonalRunMatrix():
    """TestOrthogonalRunMatrix"""
pass  # TODO: restore


def TestOrthogonalSensitivity():
    """TestOrthogonalSensitivity"""
pass  # TODO: restore


def TestOrthogonalTables():
    """TestOrthogonalTables"""
pass  # TODO: restore


def TestParameterLevel():
    """TestParameterLevel"""
pass  # TODO: restore


def TestOrthogonalRun():
    """TestOrthogonalRun"""
pass  # TODO: restore



# === FULL DISASSEMBLY (for manual reconstruction) ===
#   0           0 RESUME                   0
# 
#   1           2 LOAD_CONST               0 ('Tests for OrthogonalSensitivitySkill v2.')
#               4 STORE_NAME               0 (__doc__)
# 
#   3           6 LOAD_CONST               1 (0)
#               8 LOAD_CONST               2 (None)
#              10 IMPORT_NAME              1 (builtins)
#              12 STORE_NAME               2 (@py_builtins)
#              14 LOAD_CONST               1 (0)
#              16 LOAD_CONST               2 (None)
#              18 IMPORT_NAME              3 (_pytest.assertion.rewrite)
#              20 IMPORT_FROM              4 (assertion)
#              22 SWAP                     2
#              24 POP_TOP
#              26 IMPORT_FROM              5 (rewrite)
#              28 STORE_NAME               6 (@pytest_ar)
#              30 POP_TOP
#              32 LOAD_CONST               1 (0)
#              34 LOAD_CONST               2 (None)
#              36 IMPORT_NAME              7 (pytest)
#              38 STORE_NAME               7 (pytest)
# 
#   4          40 LOAD_CONST               1 (0)
#              42 LOAD_CONST               3 (('OrthogonalSensitivitySkill', 'ParameterLevel', 'SensitivityResult', 'ORTHOGONAL_TABLES'))
#              44 IMPORT_NAME              8 (cloudpss_skills_v2.skills.orthogonal_sensitivity)
#              46 IMPORT_FROM              9 (OrthogonalSensitivitySkill)
#              48 STORE_NAME               9 (OrthogonalSensitivitySkill)
#              50 IMPORT_FROM             10 (ParameterLevel)
#              52 STORE_NAME              10 (ParameterLevel)
#              54 IMPORT_FROM             11 (SensitivityResult)
#              56 STORE_NAME              11 (SensitivityResult)
#              58 IMPORT_FROM             12 (ORTHOGONAL_TABLES)
#              60 STORE_NAME              12 (ORTHOGONAL_TABLES)
#              62 POP_TOP
# 
#  12          64 PUSH_NULL
#              66 LOAD_BUILD_CLASS
#              68 LOAD_CONST               4 (<code object TestOrthogonalValidation at 0x73cd93b06970, file "/home/chenying/researches/cloudpss-toolkit/cloudpss_skills_v2/tests/test_orthogonal_sensitivity.py", line 12>)
#              70 MAKE_FUNCTION            0
#              72 LOAD_CONST               5 ('TestOrthogonalValidation')
#              74 CALL                     2
#              82 STORE_NAME              13 (TestOrthogonalValidation)
# 
#  52          84 PUSH_NULL
#              86 LOAD_BUILD_CLASS
#              88 LOAD_CONST               6 (<code object TestOrthogonalTableSelection at 0x73cd945fc110, file "/home/chenying/researches/cloudpss-toolkit/cloudpss_skills_v2/tests/test_orthogonal_sensitivity.py", line 52>)
#              90 MAKE_FUNCTION            0
#              92 LOAD_CONST               7 ('TestOrthogonalTableSelection')
#              94 CALL                     2
#             102 STORE_NAME              14 (TestOrthogonalTableSelection)
# 
#  76         104 PUSH_NULL
#             106 LOAD_BUILD_CLASS
#             108 LOAD_CONST               8 (<code object TestOrthogonalRunMatrix at 0x73cd945fedb0, file "/home/chenying/researches/cloudpss-toolkit/cloudpss_skills_v2/tests/test_orthogonal_sensitivity.py", line 76>)
#             110 MAKE_FUNCTION            0
#             112 LOAD_CONST               9 ('TestOrthogonalRunMatrix')
#             114 CALL                     2
#             122 STORE_NAME              15 (TestOrthogonalRunMatrix)
# 
#  91         124 PUSH_NULL
#             126 LOAD_BUILD_CLASS
#             128 LOAD_CONST              10 (<code object TestOrthogonalSensitivity at 0x73cd945fe250, file "/home/chenying/researches/cloudpss-toolkit/cloudpss_skills_v2/tests/test_orthogonal_sensitivity.py", line 91>)
#             130 MAKE_FUNCTION            0
#             132 LOAD_CONST              11 ('TestOrthogonalSensitivity')
#             134 CALL                     2
#             142 STORE_NAME              16 (TestOrthogonalSensitivity)
# 
# 135         144 PUSH_NULL
#             146 LOAD_BUILD_CLASS
#             148 LOAD_CONST              12 (<code object TestOrthogonalTables at 0x73cd945febf0, file "/home/chenying/researches/cloudpss-toolkit/cloudpss_skills_v2/tests/test_orthogonal_sensitivity.py", line 135>)
#             150 MAKE_FUNCTION            0
#             152 LOAD_CONST              13 ('TestOrthogonalTables')
#             154 CALL                     2
#             162 STORE_NAME              17 (TestOrthogonalTables)
# 
# 150         164 PUSH_NULL
#             166 LOAD_BUILD_CLASS
#             168 LOAD_CONST              14 (<code object TestParameterLevel at 0x73cd945fecd0, file "/home/chenying/researches/cloudpss-toolkit/cloudpss_skills_v2/tests/test_orthogonal_sensitivity.py", line 150>)
#             170 MAKE_FUNCTION            0
#             172 LOAD_CONST              15 ('TestParameterLevel')
#             174 CALL                     2
#             182 STORE_NAME              18 (TestParameterLevel)
# 
# 157         184 PUSH_NULL
#             186 LOAD_BUILD_CLASS
#             188 LOAD_CONST              16 (<code object TestOrthogonalRun at 0x73cd945fe870, file "/home/chenying/researches/cloudpss-toolkit/cloudpss_skills_v2/tests/test_orthogonal_sensitivity.py", line 157>)
#             190 MAKE_FUNCTION            0
#             192 LOAD_CONST              17 ('TestOrthogonalRun')
#             194 CALL                     2
#             202 STORE_NAME              19 (TestOrthogonalRun)
#             204 RETURN_CONST             2 (None)
# 
# Disassembly of <code object TestOrthogonalValidation at 0x73cd93b06970, file "/home/chenying/researches/cloudpss-toolkit/cloudpss_skills_v2/tests/test_orthogonal_sensitivity.py", line 12>:
#  12           0 RESUME                   0
#               2 LOAD_NAME                0 (__name__)
#               4 STORE_NAME               1 (__module__)
#               6 LOAD_CONST               0 ('TestOrthogonalValidation')
#               8 STORE_NAME               2 (__qualname__)
# 
#  13          10 LOAD_CONST               1 (<code object test_validate_missing_model at 0x3af0c6d0, file "/home/chenying/researches/cloudpss-toolkit/cloudpss_skills_v2/tests/test_orthogonal_sensitivity.py", line 13>)
#              12 MAKE_FUNCTION            0
#              14 STORE_NAME               3 (test_validate_missing_model)
# 
#  23          16 LOAD_CONST               2 (<code object test_validate_no_parameters at 0x3afa3fb0, file "/home/chenying/researches/cloudpss-toolkit/cloudpss_skills_v2/tests/test_orthogonal_sensitivity.py", line 23>)
#              18 MAKE_FUNCTION            0
#              20 STORE_NAME               4 (test_validate_no_parameters)
# 
#  30          22 LOAD_CONST               3 (<code object test_validate_parameter_missing_levels at 0x3af3fb70, file "/home/chenying/researches/cloudpss-toolkit/cloudpss_skills_v2/tests/test_orthogonal_sensitivity.py", line 30>)
#              24 MAKE_FUNCTION            0
#              26 STORE_NAME               5 (test_validate_parameter_missing_levels)
# 
#  41          28 LOAD_CONST               4 (<code object test_validate_valid_config at 0x3af937b0, file "/home/chenying/researches/cloudpss-toolkit/cloudpss_skills_v2/tests/test_orthogonal_sensitivity.py", line 41>)
#              30 MAKE_FUNCTION            0
#              32 STORE_NAME               6 (test_validate_valid_config)
#              34 RETURN_CONST             5 (None)
# 
# Disassembly of <code object test_validate_missing_model at 0x3af0c6d0, file "/home/chenying/researches/cloudpss-toolkit/cloudpss_skills_v2/tests/test_orthogonal_sensitivity.py", line 13>:
#  13           0 RESUME                   0
# 
#  14           2 LOAD_GLOBAL              1 (NULL + OrthogonalSensitivitySkill)
#              12 CALL                     0
#              20 STORE_FAST               1 (skill)
# 
#  15          22 LOAD_FAST                1 (skill)
#              24 LOAD_ATTR                3 (NULL|self + validate)
# 
#  17          44 LOAD_CONST               1 ('P')
#              46 LOAD_CONST               2 (1.0)
#              48 LOAD_CONST               3 (2.0)
#              50 BUILD_LIST               2
#              52 LOAD_CONST               4 (('name', 'levels'))
#              54 BUILD_CONST_KEY_MAP      2
#              56 BUILD_LIST               1
# 
#  18          58 LOAD_CONST               5 ('metric')
#              60 LOAD_CONST               6 ('voltage')
#              62 BUILD_MAP                1
# 
#  16          64 LOAD_CONST               7 (('parameters', 'target'))
#              66 BUILD_CONST_KEY_MAP      2
# 
#  15          68 CALL                     1
#              76 UNPACK_SEQUENCE          2
#              80 STORE_FAST               2 (valid)
#              82 STORE_FAST               3 (errors)
# 
#  21          84 LOAD_CONST               8 (False)
#              86 STORE_FAST               4 (@py_assert2)
#              88 LOAD_FAST                2 (valid)
#              90 LOAD_FAST                4 (@py_assert2)
#              92 IS_OP                    0
#              94 STORE_FAST               5 (@py_assert1)
#              96 LOAD_FAST                5 (@py_assert1)
#              98 POP_JUMP_IF_TRUE       153 (to 406)
#             100 LOAD_GLOBAL              5 (NULL + @pytest_ar)
#             110 LOAD_ATTR                6 (_call_reprcompare)
#             130 LOAD_CONST               9 (('is',))
#             132 LOAD_FAST                5 (@py_assert1)
#             134 BUILD_TUPLE              1
#             136 LOAD_CONST              10 (('%(py0)s is %(py3)s',))
#             138 LOAD_FAST                2 (valid)
#             140 LOAD_FAST                4 (@py_assert2)
#             142 BUILD_TUPLE              2
#             144 CALL                     4
#             152 LOAD_CONST              11 ('valid')
#             154 LOAD_GLOBAL              9 (NULL + @py_builtins)
#             164 LOAD_ATTR               10 (locals)
#             184 CALL                     0
#             192 CONTAINS_OP              0
#             194 POP_JUMP_IF_TRUE        21 (to 238)
#             196 LOAD_GLOBAL              5 (NULL + @pytest_ar)
#             206 LOAD_ATTR               12 (_should_repr_global_name)
#             226 LOAD_FAST                2 (valid)
#             228 CALL                     1
#             236 POP_JUMP_IF_FALSE       21 (to 280)
#         >>  238 LOAD_GLOBAL              5 (NULL + @pytest_ar)
#             248 LOAD_ATTR               14 (_saferepr)
#             268 LOAD_FAST                2 (valid)
#             270 CALL                     1
#             278 JUMP_FORWARD             1 (to 282)
#         >>  280 LOAD_CONST              11 ('valid')
#         >>  282 LOAD_GLOBAL              5 (NULL + @pytest_ar)
#             292 LOAD_ATTR               14 (_saferepr)
#             312 LOAD_FAST                4 (@py_assert2)
#             314 CALL                     1
#             322 LOAD_CONST              12 (('py0', 'py3'))
#             324 BUILD_CONST_KEY_MAP      2
#             326 BINARY_OP                6 (%)
#             330 STORE_FAST               6 (@py_format4)
#             332 LOAD_CONST              13 ('assert %(py5)s')
#             334 LOAD_CONST              14 ('py5')
#             336 LOAD_FAST                6 (@py_format4)
#             338 BUILD_MAP                1
#             340 BINARY_OP                6 (%)
#             344 STORE_FAST               7 (@py_format6)
#             346 LOAD_GLOBAL             17 (NULL + AssertionError)
#             356 LOAD_GLOBAL              5 (NULL + @pytest_ar)
#             366 LOAD_ATTR               18 (_format_explanation)
#             386 LOAD_FAST                7 (@py_format6)
#             388 CALL                     1
#             396 CALL                     1
#             404 RAISE_VARARGS            1
#         >>  406 LOAD_CONST               0 (None)
#             408 COPY                     1
#             410 STORE_FAST               5 (@py_assert1)
#             412 STORE_FAST               4 (@py_assert2)
#             414 RETURN_CONST             0 (None)
# 
# Disassembly of <code object test_validate_no_parameters at 0x3afa3fb0, file "/home/chenying/researches/cloudpss-toolkit/cloudpss_skills_v2/tests/test_orthogonal_sensitivity.py", line 23>:
#  23           0 RESUME                   0
# 
#  24           2 LOAD_GLOBAL              1 (NULL + OrthogonalSensitivitySkill)
#              12 CALL                     0
#              20 STORE_FAST               1 (skill)
# 
#  25          22 LOAD_FAST                1 (skill)
#              24 LOAD_ATTR                3 (NULL|self + validate)
# 
#  26          44 LOAD_CONST               1 ('rid')
#              46 LOAD_CONST               2 ('test')
#              48 BUILD_MAP                1
#              50 LOAD_CONST               3 ('metric')
#              52 LOAD_CONST               4 ('voltage')
#              54 BUILD_MAP                1
#              56 LOAD_CONST               5 (('model', 'target'))
#              58 BUILD_CONST_KEY_MAP      2
# 
#  25          60 CALL                     1
#              68 UNPACK_SEQUENCE          2
#              72 STORE_FAST               2 (valid)
#              74 STORE_FAST               3 (errors)
# 
#  28          76 LOAD_CONST               6 (False)
#              78 STORE_FAST               4 (@py_assert2)
#              80 LOAD_FAST                2 (valid)
#              82 LOAD_FAST                4 (@py_assert2)
#              84 IS_OP                    0
#              86 STORE_FAST               5 (@py_assert1)
#              88 LOAD_FAST                5 (@py_assert1)
#              90 POP_JUMP_IF_TRUE       153 (to 398)
#              92 LOAD_GLOBAL              5 (NULL + @pytest_ar)
#             102 LOAD_ATTR                6 (_call_reprcompare)
#             122 LOAD_CONST               7 (('is',))
#             124 LOAD_FAST                5 (@py_assert1)
#             126 BUILD_TUPLE              1
#             128 LOAD_CONST               8 (('%(py0)s is %(py3)s',))
#             130 LOAD_FAST                2 (valid)
#             132 LOAD_FAST                4 (@py_assert2)
#             134 BUILD_TUPLE              2
#             136 CALL                     4
#             144 LOAD_CONST               9 ('valid')
#             146 LOAD_GLOBAL              9 (NULL + @py_builtins)
#             156 LOAD_ATTR               10 (locals)
#             176 CALL                     0
#             184 CONTAINS_OP              0
#             186 POP_JUMP_IF_TRUE        21 (to 230)
#             188 LOAD_GLOBAL              5 (NULL + @pytest_ar)
#             198 LOAD_ATTR               12 (_should_repr_global_name)
#             218 LOAD_FAST                2 (valid)
#             220 CALL                     1
#             228 POP_JUMP_IF_FALSE       21 (to 272)
#         >>  230 LOAD_GLOBAL              5 (NULL + @pytest_ar)
#             240 LOAD_ATTR               14 (_saferepr)
#             260 LOAD_FAST                2 (valid)
#             262 CALL                     1
#             270 JUMP_FORWARD             1 (to 274)
#         >>  272 LOAD_CONST               9 ('valid')
#         >>  274 LOAD_GLOBAL              5 (NULL + @pytest_ar)
#             284 LOAD_ATTR               14 (_saferepr)
#             304 LOAD_FAST                4 (@py_assert2)
#             306 CALL                     1
#             314 LOAD_CONST              10 (('py0', 'py3'))
#             316 BUILD_CONST_KEY_MAP      2
#             318 BINARY_OP                6 (%)
#             322 STORE_FAST               6 (@py_format4)
#             324 LOAD_CONST              11 ('assert %(py5)s')
#             326 LOAD_CONST              12 ('py5')
#             328 LOAD_FAST                6 (@py_format4)
#             330 BUILD_MAP                1
#             332 BINARY_OP                6 (%)
#             336 STORE_FAST               7 (@py_format6)
#             338 LOAD_GLOBAL             17 (NULL + AssertionError)
#             348 LOAD_GLOBAL              5 (NULL + @pytest_ar)
#             358 LOAD_ATTR               18 (_format_explanation)
#             378 LOAD_FAST                7 (@py_format6)
#             380 CALL                     1
#             388 CALL                     1
#             396 RAISE_VARARGS            1
#         >>  398 LOAD_CONST               0 (None)
#             400 COPY                     1
#             402 STORE_FAST               5 (@py_assert1)
#             404 STORE_FAST               4 (@py_assert2)
#             406 RETURN_CONST             0 (None)
# 
# Disassembly of <code object test_validate_parameter_missing_levels at 0x3af3fb70, file "/home/chenying/researches/cloudpss-toolkit/cloudpss_skills_v2/tests/test_orthogonal_sensitivity.py", line 30>:
#  30           0 RESUME                   0
# 
#  31           2 LOAD_GLOBAL              1 (NULL + OrthogonalSensitivitySkill)
#              12 CALL                     0
#              20 STORE_FAST               1 (skill)
# 
#  32          22 LOAD_FAST                1 (skill)
#              24 LOAD_ATTR                3 (NULL|self + validate)
# 
#  34          44 LOAD_CONST               1 ('rid')
#              46 LOAD_CONST               2 ('test')
#              48 BUILD_MAP                1
# 
#  35          50 LOAD_CONST               3 ('name')
#              52 LOAD_CONST               4 ('P')
#              54 BUILD_MAP                1
#              56 BUILD_LIST               1
# 
#  36          58 LOAD_CONST               5 ('metric')
#              60 LOAD_CONST               6 ('voltage')
#              62 BUILD_MAP                1
# 
#  33          64 LOAD_CONST               7 (('model', 'parameters', 'target'))
#              66 BUILD_CONST_KEY_MAP      3
# 
#  32          68 CALL                     1
#              76 UNPACK_SEQUENCE          2
#              80 STORE_FAST               2 (valid)
#              82 STORE_FAST               3 (errors)
# 
#  39          84 LOAD_CONST               8 (False)
#              86 STORE_FAST               4 (@py_assert2)
#              88 LOAD_FAST                2 (valid)
#              90 LOAD_FAST                4 (@py_assert2)
#              92 IS_OP                    0
#              94 STORE_FAST               5 (@py_assert1)
#              96 LOAD_FAST                5 (@py_assert1)
#              98 POP_JUMP_IF_TRUE       153 (to 406)
#             100 LOAD_GLOBAL              5 (NULL + @pytest_ar)
#             110 LOAD_ATTR                6 (_call_reprcompare)
#             130 LOAD_CONST               9 (('is',))
#             132 LOAD_FAST                5 (@py_assert1)
#             134 BUILD_TUPLE              1
#             136 LOAD_CONST              10 (('%(py0)s is %(py3)s',))
#             138 LOAD_FAST                2 (valid)
#             140 LOAD_FAST                4 (@py_assert2)
#             142 BUILD_TUPLE              2
#             144 CALL                     4
#             152 LOAD_CONST              11 ('valid')
#             154 LOAD_GLOBAL              9 (NULL + @py_builtins)
#             164 LOAD_ATTR               10 (locals)
#             184 CALL                     0
#             192 CONTAINS_OP              0
#             194 POP_JUMP_IF_TRUE        21 (to 238)
#             196 LOAD_GLOBAL              5 (NULL + @pytest_ar)
#             206 LOAD_ATTR               12 (_should_repr_global_name)
#             226 LOAD_FAST                2 (valid)
#             228 CALL                     1
#             236 POP_JUMP_IF_FALSE       21 (to 280)
#         >>  238 LOAD_GLOBAL              5 (NULL + @pytest_ar)
#             248 LOAD_ATTR               14 (_saferepr)
#             268 LOAD_FAST                2 (valid)
#             270 CALL                     1
#             278 JUMP_FORWARD             1 (to 282)
#         >>  280 LOAD_CONST              11 ('valid')
#         >>  282 LOAD_GLOBAL              5 (NULL + @pytest_ar)
#             292 LOAD_ATTR               14 (_saferepr)
#             312 LOAD_FAST                4 (@py_assert2)
#             314 CALL                     1
#             322 LOAD_CONST              12 (('py0', 'py3'))
#             324 BUILD_CONST_KEY_MAP      2
#             326 BINARY_OP                6 (%)
#             330 STORE_FAST               6 (@py_format4)
#             332 LOAD_CONST              13 ('assert %(py5)s')
#             334 LOAD_CONST              14 ('py5')
#             336 LOAD_FAST                6 (@py_format4)
#             338 BUILD_MAP                1
#             340 BINARY_OP                6 (%)
#             344 STORE_FAST               7 (@py_format6)
#             346 LOAD_GLOBAL             17 (NULL + AssertionError)
#             356 LOAD_GLOBAL              5 (NULL + @pytest_ar)
#             366 LOAD_ATTR               18 (_format_explanation)
#             386 LOAD_FAST                7 (@py_format6)
#             388 CALL                     1
#             396 CALL                     1
#             404 RAISE_VARARGS            1
#         >>  406 LOAD_CONST               0 (None)
#             408 COPY                     1
#             410 STORE_FAST               5 (@py_assert1)
#             412 STORE_FAST               4 (@py_assert2)
#             414 RETURN_CONST             0 (None)
# 
# Disassembly of <code object test_validate_valid_config at 0x3af937b0, file "/home/chenying/researches/cloudpss-toolkit/cloudpss_skills_v2/tests/test_orthogonal_sensitivity.py", line 41>:
#  41           0 RESUME                   0
# 
#  42           2 LOAD_GLOBAL              1 (NULL + OrthogonalSensitivitySkill)
#              12 CALL                     0
#              20 STORE_FAST               1 (skill)
# 
#  44          22 LOAD_CONST               1 ('rid')
#              24 LOAD_CONST               2 ('test')
#              26 BUILD_MAP                1
# 
#  45          28 LOAD_CONST               3 ('P')
#              30 LOAD_CONST               4 (1.0)
#              32 LOAD_CONST               5 (2.0)
#              34 BUILD_LIST               2
#              36 LOAD_CONST               6 (('name', 'levels'))
#              38 BUILD_CONST_KEY_MAP      2
#              40 BUILD_LIST               1
# 
#  46          42 LOAD_CONST               7 ('metric')
#              44 LOAD_CONST               8 ('voltage')
#              46 BUILD_MAP                1
# 
#  43          48 LOAD_CONST               9 (('model', 'parameters', 'target'))
#              50 BUILD_CONST_KEY_MAP      3
#              52 STORE_FAST               2 (config)
# 
#  48          54 LOAD_FAST                1 (skill)
#              56 LOAD_ATTR                3 (NULL|self + validate)
#              76 LOAD_FAST                2 (config)
#              78 CALL                     1
#              86 UNPACK_SEQUENCE          2
#              90 STORE_FAST               3 (valid)
#              92 STORE_FAST               4 (errors)
# 
#  49          94 LOAD_CONST              10 (True)
#              96 STORE_FAST               5 (@py_assert2)
#              98 LOAD_FAST                3 (valid)
#             100 LOAD_FAST                5 (@py_assert2)
#             102 IS_OP                    0
#             104 STORE_FAST               6 (@py_assert1)
#             106 LOAD_FAST                6 (@py_assert1)
#             108 POP_JUMP_IF_TRUE       153 (to 416)
#             110 LOAD_GLOBAL              5 (NULL + @pytest_ar)
#             120 LOAD_ATTR                6 (_call_reprcompare)
#             140 LOAD_CONST              11 (('is',))
#             142 LOAD_FAST                6 (@py_assert1)
#             144 BUILD_TUPLE              1
#             146 LOAD_CONST              12 (('%(py0)s is %(py3)s',))
#             148 LOAD_FAST                3 (valid)
#             150 LOAD_FAST                5 (@py_assert2)
#             152 BUILD_TUPLE              2
#             154 CALL                     4
#             162 LOAD_CONST              13 ('valid')
#             164 LOAD_GLOBAL              9 (NULL + @py_builtins)
#             174 LOAD_ATTR               10 (locals)
#             194 CALL                     0
#             202 CONTAINS_OP              0
#             204 POP_JUMP_IF_TRUE        21 (to 248)
#             206 LOAD_GLOBAL              5 (NULL + @pytest_ar)
#             216 LOAD_ATTR               12 (_should_repr_global_name)
#             236 LOAD_FAST                3 (valid)
#             238 CALL                     1
#             246 POP_JUMP_IF_FALSE       21 (to 290)
#         >>  248 LOAD_GLOBAL              5 (NULL + @pytest_ar)
#             258 LOAD_ATTR               14 (_saferepr)
#             278 LOAD_FAST                3 (valid)
#             280 CALL                     1
#             288 JUMP_FORWARD             1 (to 292)
#         >>  290 LOAD_CONST              13 ('valid')
#         >>  292 LOAD_GLOBAL              5 (NULL + @pytest_ar)
#             302 LOAD_ATTR               14 (_saferepr)
#             322 LOAD_FAST                5 (@py_assert2)
#             324 CALL                     1
#             332 LOAD_CONST              14 (('py0', 'py3'))
#             334 BUILD_CONST_KEY_MAP      2
#             336 BINARY_OP                6 (%)
#             340 STORE_FAST               7 (@py_format4)
#             342 LOAD_CONST              15 ('assert %(py5)s')
#             344 LOAD_CONST              16 ('py5')
#             346 LOAD_FAST                7 (@py_format4)
#             348 BUILD_MAP                1
#             350 BINARY_OP                6 (%)
#             354 STORE_FAST               8 (@py_format6)
#             356 LOAD_GLOBAL             17 (NULL + AssertionError)
#             366 LOAD_GLOBAL              5 (NULL + @pytest_ar)
#             376 LOAD_ATTR               18 (_format_explanation)
#             396 LOAD_FAST                8 (@py_format6)
#             398 CALL                     1
#             406 CALL                     1
#             414 RAISE_VARARGS            1
#         >>  416 LOAD_CONST               0 (None)
#             418 COPY                     1
#             420 STORE_FAST               6 (@py_assert1)
#             422 STORE_FAST               5 (@py_assert2)
#             424 RETURN_CONST             0 (None)
# 
# Disassembly of <code object TestOrthogonalTableSelection at 0x73cd945fc110, file "/home/chenying/researches/cloudpss-toolkit/cloudpss_skills_v2/tests/test_orthogonal_sensitivity.py", line 52>:
#  52           0 RESUME                   0
#               2 LOAD_NAME                0 (__name__)
#               4 STORE_NAME               1 (__module__)
#               6 LOAD_CONST               0 ('TestOrthogonalTableSelection')
#               8 STORE_NAME               2 (__qualname__)
# 
#  53          10 LOAD_CONST               1 (<code object test_select_orthogonal_table_auto_2level at 0x3af97180, file "/home/chenying/researches/cloudpss-toolkit/cloudpss_skills_v2/tests/test_orthogonal_sensitivity.py", line 53>)
#              12 MAKE_FUNCTION            0
#              14 STORE_NAME               3 (test_select_orthogonal_table_auto_2level)
# 
#  63          16 LOAD_CONST               2 (<code object test_select_orthogonal_table_auto_3level at 0x3af9b370, file "/home/chenying/researches/cloudpss-toolkit/cloudpss_skills_v2/tests/test_orthogonal_sensitivity.py", line 63>)
#              18 MAKE_FUNCTION            0
#              20 STORE_NAME               4 (test_select_orthogonal_table_auto_3level)
# 
#  69          22 LOAD_CONST               3 (<code object test_select_orthogonal_table_explicit at 0x3af90d20, file "/home/chenying/researches/cloudpss-toolkit/cloudpss_skills_v2/tests/test_orthogonal_sensitivity.py", line 69>)
#              24 MAKE_FUNCTION            0
#              26 STORE_NAME               5 (test_select_orthogonal_table_explicit)
#              28 RETURN_CONST             4 (None)
# 
# Disassembly of <code object test_select_orthogonal_table_auto_2level at 0x3af97180, file "/home/chenying/researches/cloudpss-toolkit/cloudpss_skills_v2/tests/test_orthogonal_sensitivity.py", line 53>:
#  53           0 RESUME                   0
# 
#  54           2 LOAD_GLOBAL              1 (NULL + OrthogonalSensitivitySkill)
#              12 CALL                     0
#              20 STORE_FAST               1 (skill)
# 
#  56          22 LOAD_CONST               1 ('A')
#              24 LOAD_CONST               2 (1)
#              26 LOAD_CONST               3 (2)
#              28 BUILD_LIST               2
#              30 LOAD_CONST               4 (('name', 'levels'))
#              32 BUILD_CONST_KEY_MAP      2
# 
#  57          34 LOAD_CONST               5 ('B')
#              36 LOAD_CONST               6 (3)
#              38 LOAD_CONST               7 (4)
#              40 BUILD_LIST               2
#              42 LOAD_CONST               4 (('name', 'levels'))
#              44 BUILD_CONST_KEY_MAP      2
# 
#  58          46 LOAD_CONST               8 ('C')
#              48 LOAD_CONST               9 (5)
#              50 LOAD_CONST              10 (6)
#              52 BUILD_LIST               2
#              54 LOAD_CONST               4 (('name', 'levels'))
#              56 BUILD_CONST_KEY_MAP      2
# 
#  55          58 BUILD_LIST               3
#              60 STORE_FAST               2 (params)
# 
#  60          62 LOAD_FAST                1 (skill)
#              64 LOAD_ATTR                3 (NULL|self + _select_orthogonal_table)
#              84 LOAD_FAST                2 (params)
#              86 LOAD_CONST              11 ('auto')
#              88 CALL                     2
#              96 STORE_FAST               3 (result)
# 
#  61          98 LOAD_CONST              12 ('L4_2_3')
#             100 STORE_FAST               4 (@py_assert2)
#             102 LOAD_FAST                3 (result)
#             104 LOAD_FAST                4 (@py_assert2)
#             106 COMPARE_OP              40 (==)
#             110 STORE_FAST               5 (@py_assert1)
#             112 LOAD_FAST                5 (@py_assert1)
#             114 POP_JUMP_IF_TRUE       153 (to 422)
#             116 LOAD_GLOBAL              5 (NULL + @pytest_ar)
#             126 LOAD_ATTR                6 (_call_reprcompare)
#             146 LOAD_CONST              13 (('==',))
#             148 LOAD_FAST                5 (@py_assert1)
#             150 BUILD_TUPLE              1
#             152 LOAD_CONST              14 (('%(py0)s == %(py3)s',))
#             154 LOAD_FAST                3 (result)
#             156 LOAD_FAST                4 (@py_assert2)
#             158 BUILD_TUPLE              2
#             160 CALL                     4
#             168 LOAD_CONST              15 ('result')
#             170 LOAD_GLOBAL              9 (NULL + @py_builtins)
#             180 LOAD_ATTR               10 (locals)
#             200 CALL                     0
#             208 CONTAINS_OP              0
#             210 POP_JUMP_IF_TRUE        21 (to 254)
#             212 LOAD_GLOBAL              5 (NULL + @pytest_ar)
#             222 LOAD_ATTR               12 (_should_repr_global_name)
#             242 LOAD_FAST                3 (result)
#             244 CALL                     1
#             252 POP_JUMP_IF_FALSE       21 (to 296)
#         >>  254 LOAD_GLOBAL              5 (NULL + @pytest_ar)
#             264 LOAD_ATTR               14 (_saferepr)
#             284 LOAD_FAST                3 (result)
#             286 CALL                     1
#             294 JUMP_FORWARD             1 (to 298)
#         >>  296 LOAD_CONST              15 ('result')
#         >>  298 LOAD_GLOBAL              5 (NULL + @pytest_ar)
#             308 LOAD_ATTR               14 (_saferepr)
#             328 LOAD_FAST                4 (@py_assert2)
#             330 CALL                     1
#             338 LOAD_CONST              16 (('py0', 'py3'))
#             340 BUILD_CONST_KEY_MAP      2
#             342 BINARY_OP                6 (%)
#             346 STORE_FAST               6 (@py_format4)
#             348 LOAD_CONST              17 ('assert %(py5)s')
#             350 LOAD_CONST              18 ('py5')
#             352 LOAD_FAST                6 (@py_format4)
#             354 BUILD_MAP                1
#             356 BINARY_OP                6 (%)
#             360 STORE_FAST               7 (@py_format6)
#             362 LOAD_GLOBAL             17 (NULL + AssertionError)
#             372 LOAD_GLOBAL              5 (NULL + @pytest_ar)
#             382 LOAD_ATTR               18 (_format_explanation)
#             402 LOAD_FAST                7 (@py_format6)
#             404 CALL                     1
#             412 CALL                     1
#             420 RAISE_VARARGS            1
#         >>  422 LOAD_CONST               0 (None)
#             424 COPY                     1
#             426 STORE_FAST               5 (@py_assert1)
#             428 STORE_FAST               4 (@py_assert2)
#             430 RETURN_CONST             0 (None)
# 
# Disassembly of <code object test_select_orthogonal_table_auto_3level at 0x3af9b370, file "/home/chenying/researches/cloudpss-toolkit/cloudpss_skills_v2/tests/test_orthogonal_sensitivity.py", line 63>:
#  63           0 RESUME                   0
# 
#  64           2 LOAD_GLOBAL              1 (NULL + OrthogonalSensitivitySkill)
#              12 CALL                     0
#              20 STORE_FAST               1 (skill)
# 
#  65          22 LOAD_GLOBAL              3 (NULL + range)
#              32 LOAD_CONST               1 (4)
#              34 CALL                     1
#              42 GET_ITER
#              44 LOAD_FAST_AND_CLEAR      2 (_)
#              46 SWAP                     2
#              48 BUILD_LIST               0
#              50 SWAP                     2
#         >>   52 FOR_ITER                 9 (to 74)
#              56 STORE_FAST               2 (_)
#              58 LOAD_CONST               2 ('A')
#              60 BUILD_LIST               0
#              62 LOAD_CONST               3 ((1, 2, 3))
#              64 LIST_EXTEND              1
#              66 LOAD_CONST               4 (('name', 'levels'))
#              68 BUILD_CONST_KEY_MAP      2
#              70 LIST_APPEND              2
#              72 JUMP_BACKWARD           11 (to 52)
#         >>   74 END_FOR
#              76 STORE_FAST               3 (params)
#              78 STORE_FAST               2 (_)
# 
#  66          80 LOAD_FAST                1 (skill)
#              82 LOAD_ATTR                5 (NULL|self + _select_orthogonal_table)
#             102 LOAD_FAST                3 (params)
#             104 LOAD_CONST               5 ('auto')
#             106 CALL                     2
#             114 STORE_FAST               4 (result)
# 
#  67         116 LOAD_CONST               6 ('L9_3_4')
#             118 STORE_FAST               5 (@py_assert2)
#             120 LOAD_FAST                4 (result)
#             122 LOAD_FAST                5 (@py_assert2)
#             124 COMPARE_OP              40 (==)
#             128 STORE_FAST               6 (@py_assert1)
#             130 LOAD_FAST                6 (@py_assert1)
#             132 POP_JUMP_IF_TRUE       153 (to 440)
#             134 LOAD_GLOBAL              7 (NULL + @pytest_ar)
#             144 LOAD_ATTR                8 (_call_reprcompare)
#             164 LOAD_CONST               7 (('==',))
#             166 LOAD_FAST                6 (@py_assert1)
#             168 BUILD_TUPLE              1
#             170 LOAD_CONST               8 (('%(py0)s == %(py3)s',))
#             172 LOAD_FAST                4 (result)
#             174 LOAD_FAST                5 (@py_assert2)
#             176 BUILD_TUPLE              2
#             178 CALL                     4
#             186 LOAD_CONST               9 ('result')
#             188 LOAD_GLOBAL             11 (NULL + @py_builtins)
#             198 LOAD_ATTR               12 (locals)
#             218 CALL                     0
#             226 CONTAINS_OP              0
#             228 POP_JUMP_IF_TRUE        21 (to 272)
#             230 LOAD_GLOBAL              7 (NULL + @pytest_ar)
#             240 LOAD_ATTR               14 (_should_repr_global_name)
#             260 LOAD_FAST                4 (result)
#             262 CALL                     1
#             270 POP_JUMP_IF_FALSE       21 (to 314)
#         >>  272 LOAD_GLOBAL              7 (NULL + @pytest_ar)
#             282 LOAD_ATTR               16 (_saferepr)
#             302 LOAD_FAST                4 (result)
#             304 CALL                     1
#             312 JUMP_FORWARD             1 (to 316)
#         >>  314 LOAD_CONST               9 ('result')
#         >>  316 LOAD_GLOBAL              7 (NULL + @pytest_ar)
#             326 LOAD_ATTR               16 (_saferepr)
#             346 LOAD_FAST                5 (@py_assert2)
#             348 CALL                     1
#             356 LOAD_CONST              10 (('py0', 'py3'))
#             358 BUILD_CONST_KEY_MAP      2
#             360 BINARY_OP                6 (%)
#             364 STORE_FAST               7 (@py_format4)
#             366 LOAD_CONST              11 ('assert %(py5)s')
#             368 LOAD_CONST              12 ('py5')
#             370 LOAD_FAST                7 (@py_format4)
#             372 BUILD_MAP                1
#             374 BINARY_OP                6 (%)
#             378 STORE_FAST               8 (@py_format6)
#             380 LOAD_GLOBAL             19 (NULL + AssertionError)
#             390 LOAD_GLOBAL              7 (NULL + @pytest_ar)
#             400 LOAD_ATTR               20 (_format_explanation)
#             420 LOAD_FAST                8 (@py_format6)
#             422 CALL                     1
#             430 CALL                     1
#             438 RAISE_VARARGS            1
#         >>  440 LOAD_CONST               0 (None)
#             442 COPY                     1
#             444 STORE_FAST               6 (@py_assert1)
#             446 STORE_FAST               5 (@py_assert2)
#             448 RETURN_CONST             0 (None)
#         >>  450 SWAP                     2
#             452 POP_TOP
# 
#  65         454 SWAP                     2
#             456 STORE_FAST               2 (_)
#             458 RERAISE                  0
# ExceptionTable:
#   48 to 74 -> 450 [2]
# 
# Disassembly of <code object test_select_orthogonal_table_explicit at 0x3af90d20, file "/home/chenying/researches/cloudpss-toolkit/cloudpss_skills_v2/tests/test_orthogonal_sensitivity.py", line 69>:
#  69           0 RESUME                   0
# 
#  70           2 LOAD_GLOBAL              1 (NULL + OrthogonalSensitivitySkill)
#              12 CALL                     0
#              20 STORE_FAST               1 (skill)
# 
#  71          22 LOAD_CONST               1 ('A')
#              24 LOAD_CONST               2 (1)
#              26 LOAD_CONST               3 (2)
#              28 BUILD_LIST               2
#              30 LOAD_CONST               4 (('name', 'levels'))
#              32 BUILD_CONST_KEY_MAP      2
#              34 BUILD_LIST               1
#              36 STORE_FAST               2 (params)
# 
#  72          38 LOAD_FAST                1 (skill)
#              40 LOAD_ATTR                3 (NULL|self + _select_orthogonal_table)
#              60 LOAD_FAST                2 (params)
#              62 LOAD_CONST               5 ('L8_2_7')
#              64 CALL                     2
#              72 STORE_FAST               3 (result)
# 
#  73          74 LOAD_CONST               5 ('L8_2_7')
#              76 STORE_FAST               4 (@py_assert2)
#              78 LOAD_FAST                3 (result)
#              80 LOAD_FAST                4 (@py_assert2)
#              82 COMPARE_OP              40 (==)
#              86 STORE_FAST               5 (@py_assert1)
#              88 LOAD_FAST                5 (@py_assert1)
#              90 POP_JUMP_IF_TRUE       153 (to 398)
#              92 LOAD_GLOBAL              5 (NULL + @pytest_ar)
#             102 LOAD_ATTR                6 (_call_reprcompare)
#             122 LOAD_CONST               6 (('==',))
#             124 LOAD_FAST                5 (@py_assert1)
#             126 BUILD_TUPLE              1
#             128 LOAD_CONST               7 (('%(py0)s == %(py3)s',))
#             130 LOAD_FAST                3 (result)
#             132 LOAD_FAST                4 (@py_assert2)
#             134 BUILD_TUPLE              2
#             136 CALL                     4
#             144 LOAD_CONST               8 ('result')
#             146 LOAD_GLOBAL              9 (NULL + @py_builtins)
#             156 LOAD_ATTR               10 (locals)
#             176 CALL                     0
#             184 CONTAINS_OP              0
#             186 POP_JUMP_IF_TRUE        21 (to 230)
#             188 LOAD_GLOBAL              5 (NULL + @pytest_ar)
#             198 LOAD_ATTR               12 (_should_repr_global_name)
#             218 LOAD_FAST                3 (result)
#             220 CALL                     1
#             228 POP_JUMP_IF_FALSE       21 (to 272)
#         >>  230 LOAD_GLOBAL              5 (NULL + @pytest_ar)
#             240 LOAD_ATTR               14 (_saferepr)
#             260 LOAD_FAST                3 (result)
#             262 CALL                     1
#             270 JUMP_FORWARD             1 (to 274)
#         >>  272 LOAD_CONST               8 ('result')
#         >>  274 LOAD_GLOBAL              5 (NULL + @pytest_ar)
#             284 LOAD_ATTR               14 (_saferepr)
#             304 LOAD_FAST                4 (@py_assert2)
#             306 CALL                     1
#             314 LOAD_CONST               9 (('py0', 'py3'))
#             316 BUILD_CONST_KEY_MAP      2
#             318 BINARY_OP                6 (%)
#             322 STORE_FAST               6 (@py_format4)
#             324 LOAD_CONST              10 ('assert %(py5)s')
#             326 LOAD_CONST              11 ('py5')
#             328 LOAD_FAST                6 (@py_format4)
#             330 BUILD_MAP                1
#             332 BINARY_OP                6 (%)
#             336 STORE_FAST               7 (@py_format6)
#             338 LOAD_GLOBAL             17 (NULL + AssertionError)
#             348 LOAD_GLOBAL              5 (NULL + @pytest_ar)
#             358 LOAD_ATTR               18 (_format_explanation)
#             378 LOAD_FAST                7 (@py_format6)
#             380 CALL                     1
#             388 CALL                     1
#             396 RAISE_VARARGS            1
#         >>  398 LOAD_CONST               0 (None)
#             400 COPY                     1
#             402 STORE_FAST               5 (@py_assert1)
#             404 STORE_FAST               4 (@py_assert2)
#             406 RETURN_CONST             0 (None)
# 
# Disassembly of <code object TestOrthogonalRunMatrix at 0x73cd945fedb0, file "/home/chenying/researches/cloudpss-toolkit/cloudpss_skills_v2/tests/test_orthogonal_sensitivity.py", line 76>:
#  76           0 RESUME                   0
#               2 LOAD_NAME                0 (__name__)
#               4 STORE_NAME               1 (__module__)
#               6 LOAD_CONST               0 ('TestOrthogonalRunMatrix')
#               8 STORE_NAME               2 (__qualname__)
# 
#  77          10 LOAD_CONST               1 (<code object test_build_run_matrix at 0x3af9d7e0, file "/home/chenying/researches/cloudpss-toolkit/cloudpss_skills_v2/tests/test_orthogonal_sensitivity.py", line 77>)
#              12 MAKE_FUNCTION            0
#              14 STORE_NAME               3 (test_build_run_matrix)
#              16 RETURN_CONST             2 (None)
# 
# Disassembly of <code object test_build_run_matrix at 0x3af9d7e0, file "/home/chenying/researches/cloudpss-toolkit/cloudpss_skills_v2/tests/test_orthogonal_sensitivity.py", line 77>:
#  77           0 RESUME                   0
# 
#  78           2 LOAD_GLOBAL              1 (NULL + OrthogonalSensitivitySkill)
#              12 CALL                     0
#              20 STORE_FAST               1 (skill)
# 
#  80          22 LOAD_CONST               1 ('A')
#              24 LOAD_CONST               2 (10)
#              26 LOAD_CONST               3 (20)
#              28 BUILD_LIST               2
#              30 LOAD_CONST               4 (('name', 'levels'))
#              32 BUILD_CONST_KEY_MAP      2
# 
#  81          34 LOAD_CONST               5 ('B')
#              36 LOAD_CONST               6 (30)
#              38 LOAD_CONST               7 (40)
#              40 BUILD_LIST               2
#              42 LOAD_CONST               4 (('name', 'levels'))
#              44 BUILD_CONST_KEY_MAP      2
# 
#  79          46 BUILD_LIST               2
#              48 STORE_FAST               2 (params)
# 
#  83          50 LOAD_FAST                1 (skill)
#              52 LOAD_ATTR                3 (NULL|self + _build_run_matrix)
#              72 LOAD_FAST                2 (params)
#              74 LOAD_CONST               8 ('L4_2_3')
#              76 CALL                     2
#              84 STORE_FAST               3 (matrix)
# 
#  84          86 LOAD_GLOBAL              5 (NULL + len)
#              96 LOAD_FAST                3 (matrix)
#              98 CALL                     1
#             106 STORE_FAST               4 (@py_assert2)
#             108 LOAD_CONST               9 (4)
#             110 STORE_FAST               5 (@py_assert5)
#             112 LOAD_FAST                4 (@py_assert2)
#             114 LOAD_FAST                5 (@py_assert5)
#             116 COMPARE_OP              40 (==)
#             120 STORE_FAST               6 (@py_assert4)
#             122 LOAD_FAST                6 (@py_assert4)
#             124 POP_JUMP_IF_TRUE       246 (to 618)
#             126 LOAD_GLOBAL              7 (NULL + @pytest_ar)
#             136 LOAD_ATTR                8 (_call_reprcompare)
#             156 LOAD_CONST              10 (('==',))
#             158 LOAD_FAST                6 (@py_assert4)
#             160 BUILD_TUPLE              1
#             162 LOAD_CONST              11 (('%(py3)s\n{%(py3)s = %(py0)s(%(py1)s)\n} == %(py6)s',))
#             164 LOAD_FAST                4 (@py_assert2)
#             166 LOAD_FAST                5 (@py_assert5)
#             168 BUILD_TUPLE              2
#             170 CALL                     4
#             178 LOAD_CONST              12 ('len')
#             180 LOAD_GLOBAL             11 (NULL + @py_builtins)
#             190 LOAD_ATTR               12 (locals)
#             210 CALL                     0
#             218 CONTAINS_OP              0
#             220 POP_JUMP_IF_TRUE        25 (to 272)
#             222 LOAD_GLOBAL              7 (NULL + @pytest_ar)
#             232 LOAD_ATTR               14 (_should_repr_global_name)
#             252 LOAD_GLOBAL              4 (len)
#             262 CALL                     1
#             270 POP_JUMP_IF_FALSE       25 (to 322)
#         >>  272 LOAD_GLOBAL              7 (NULL + @pytest_ar)
#             282 LOAD_ATTR               16 (_saferepr)
#             302 LOAD_GLOBAL              4 (len)
#             312 CALL                     1
#             320 JUMP_FORWARD             1 (to 324)
#         >>  322 LOAD_CONST              12 ('len')
#         >>  324 LOAD_CONST              13 ('matrix')
#             326 LOAD_GLOBAL             11 (NULL + @py_builtins)
#             336 LOAD_ATTR               12 (locals)
#             356 CALL                     0
#             364 CONTAINS_OP              0
#             366 POP_JUMP_IF_TRUE        21 (to 410)
#             368 LOAD_GLOBAL              7 (NULL + @pytest_ar)
#             378 LOAD_ATTR               14 (_should_repr_global_name)
#             398 LOAD_FAST                3 (matrix)
#             400 CALL                     1
#             408 POP_JUMP_IF_FALSE       21 (to 452)
#         >>  410 LOAD_GLOBAL              7 (NULL + @pytest_ar)
#             420 LOAD_ATTR               16 (_saferepr)
#             440 LOAD_FAST                3 (matrix)
#             442 CALL                     1
#             450 JUMP_FORWARD             1 (to 454)
#         >>  452 LOAD_CONST              13 ('matrix')
#         >>  454 LOAD_GLOBAL              7 (NULL + @pytest_ar)
#             464 LOAD_ATTR               16 (_saferepr)
#             484 LOAD_FAST                4 (@py_assert2)
#             486 CALL                     1
#             494 LOAD_GLOBAL              7 (NULL + @pytest_ar)
#             504 LOAD_ATTR               16 (_saferepr)
#             524 LOAD_FAST                5 (@py_assert5)
#             526 CALL                     1
#             534 LOAD_CONST              14 (('py0', 'py1', 'py3', 'py6'))
#             536 BUILD_CONST_KEY_MAP      4
#             538 BINARY_OP                6 (%)
#             542 STORE_FAST               7 (@py_format7)
#             544 LOAD_CONST              15 ('assert %(py8)s')
#             546 LOAD_CONST              16 ('py8')
#             548 LOAD_FAST                7 (@py_format7)
#             550 BUILD_MAP                1
#             552 BINARY_OP                6 (%)
#             556 STORE_FAST               8 (@py_format9)
#             558 LOAD_GLOBAL             19 (NULL + AssertionError)
#             568 LOAD_GLOBAL              7 (NULL + @pytest_ar)
#             578 LOAD_ATTR               20 (_format_explanation)
#             598 LOAD_FAST                8 (@py_format9)
#             600 CALL                     1
#             608 CALL                     1
#             616 RAISE_VARARGS            1
#         >>  618 LOAD_CONST               0 (None)
#             620 COPY                     1
#             622 STORE_FAST               4 (@py_assert2)
#             624 COPY                     1
#             626 STORE_FAST               6 (@py_assert4)
#             628 STORE_FAST               5 (@py_assert5)
# 
#  85         630 LOAD_FAST                3 (matrix)
#             632 LOAD_CONST              17 (0)
#             634 BINARY_SUBSCR
#             638 STORE_FAST               9 (@py_assert0)
#             640 LOAD_CONST               2 (10)
#             642 LOAD_CONST               6 (30)
#             644 LOAD_CONST              18 (('A', 'B'))
#             646 BUILD_CONST_KEY_MAP      2
#             648 STORE_FAST              10 (@py_assert3)
#             650 LOAD_FAST                9 (@py_assert0)
#             652 LOAD_FAST               10 (@py_assert3)
#             654 COMPARE_OP              40 (==)
#             658 STORE_FAST               4 (@py_assert2)
#             660 LOAD_FAST                4 (@py_assert2)
#             662 POP_JUMP_IF_TRUE       108 (to 880)
#             664 LOAD_GLOBAL              7 (NULL + @pytest_ar)
#             674 LOAD_ATTR                8 (_call_reprcompare)
#             694 LOAD_CONST              10 (('==',))
#             696 LOAD_FAST                4 (@py_assert2)
#             698 BUILD_TUPLE              1
#             700 LOAD_CONST              19 (('%(py1)s == %(py4)s',))
#             702 LOAD_FAST                9 (@py_assert0)
#             704 LOAD_FAST               10 (@py_assert3)
#             706 BUILD_TUPLE              2
#             708 CALL                     4
#             716 LOAD_GLOBAL              7 (NULL + @pytest_ar)
#             726 LOAD_ATTR               16 (_saferepr)
#             746 LOAD_FAST                9 (@py_assert0)
#             748 CALL                     1
#             756 LOAD_GLOBAL              7 (NULL + @pytest_ar)
#             766 LOAD_ATTR               16 (_saferepr)
#             786 LOAD_FAST               10 (@py_assert3)
#             788 CALL                     1
#             796 LOAD_CONST              20 (('py1', 'py4'))
#             798 BUILD_CONST_KEY_MAP      2
#             800 BINARY_OP                6 (%)
#             804 STORE_FAST              11 (@py_format5)
#             806 LOAD_CONST              21 ('assert %(py6)s')
#             808 LOAD_CONST              22 ('py6')
#             810 LOAD_FAST               11 (@py_format5)
#             812 BUILD_MAP                1
#             814 BINARY_OP                6 (%)
#             818 STORE_FAST               7 (@py_format7)
#             820 LOAD_GLOBAL             19 (NULL + AssertionError)
#             830 LOAD_GLOBAL              7 (NULL + @pytest_ar)
#             840 LOAD_ATTR               20 (_format_explanation)
#             860 LOAD_FAST                7 (@py_format7)
#             862 CALL                     1
#             870 CALL                     1
#             878 RAISE_VARARGS            1
#         >>  880 LOAD_CONST               0 (None)
#             882 COPY                     1
#             884 STORE_FAST               9 (@py_assert0)
#             886 COPY                     1
#             888 STORE_FAST               4 (@py_assert2)
#             890 STORE_FAST              10 (@py_assert3)
# 
#  86         892 LOAD_FAST                3 (matrix)
#             894 LOAD_CONST              23 (1)
#             896 BINARY_SUBSCR
#             900 STORE_FAST               9 (@py_assert0)
#             902 LOAD_CONST               2 (10)
#             904 LOAD_CONST               7 (40)
#             906 LOAD_CONST              18 (('A', 'B'))
#             908 BUILD_CONST_KEY_MAP      2
#             910 STORE_FAST              10 (@py_assert3)
#             912 LOAD_FAST                9 (@py_assert0)
#             914 LOAD_FAST               10 (@py_assert3)
#             916 COMPARE_OP              40 (==)
#             920 STORE_FAST               4 (@py_assert2)
#             922 LOAD_FAST                4 (@py_assert2)
#             924 POP_JUMP_IF_TRUE       108 (to 1142)
#             926 LOAD_GLOBAL              7 (NULL + @pytest_ar)
#             936 LOAD_ATTR                8 (_call_reprcompare)
#             956 LOAD_CONST              10 (('==',))
#             958 LOAD_FAST                4 (@py_assert2)
#             960 BUILD_TUPLE              1
#             962 LOAD_CONST              19 (('%(py1)s == %(py4)s',))
#             964 LOAD_FAST                9 (@py_assert0)
#             966 LOAD_FAST               10 (@py_assert3)
#             968 BUILD_TUPLE              2
#             970 CALL                     4
#             978 LOAD_GLOBAL              7 (NULL + @pytest_ar)
#             988 LOAD_ATTR               16 (_saferepr)
#            1008 LOAD_FAST                9 (@py_assert0)
#            1010 CALL                     1
#            1018 LOAD_GLOBAL              7 (NULL + @pytest_ar)
#            1028 LOAD_ATTR               16 (_saferepr)
#            1048 LOAD_FAST               10 (@py_assert3)
#            1050 CALL                     1
#            1058 LOAD_CONST              20 (('py1', 'py4'))
#            1060 BUILD_CONST_KEY_MAP      2
#            1062 BINARY_OP                6 (%)
#            1066 STORE_FAST              11 (@py_format5)
#            1068 LOAD_CONST              21 ('assert %(py6)s')
#            1070 LOAD_CONST              22 ('py6')
#            1072 LOAD_FAST               11 (@py_format5)
#            1074 BUILD_MAP                1
#            1076 BINARY_OP                6 (%)
#            1080 STORE_FAST               7 (@py_format7)
#            1082 LOAD_GLOBAL             19 (NULL + AssertionError)
#            1092 LOAD_GLOBAL              7 (NULL + @pytest_ar)
#            1102 LOAD_ATTR               20 (_format_explanation)
#            1122 LOAD_FAST                7 (@py_format7)
#            1124 CALL                     1
#            1132 CALL                     1
#            1140 RAISE_VARARGS            1
#         >> 1142 LOAD_CONST               0 (None)
#            1144 COPY                     1
#            1146 STORE_FAST               9 (@py_assert0)
#            1148 COPY                     1
#            1150 STORE_FAST               4 (@py_assert2)
#            1152 STORE_FAST              10 (@py_assert3)
# 
#  87        1154 LOAD_FAST                3 (matrix)
#            1156 LOAD_CONST              24 (2)
#            1158 BINARY_SUBSCR
#            1162 STORE_FAST               9 (@py_assert0)
#            1164 LOAD_CONST               3 (20)
#            1166 LOAD_CONST               6 (30)
#            1168 LOAD_CONST              18 (('A', 'B'))
#            1170 BUILD_CONST_KEY_MAP      2
#            1172 STORE_FAST              10 (@py_assert3)
#            1174 LOAD_FAST                9 (@py_assert0)
#            1176 LOAD_FAST               10 (@py_assert3)
#            1178 COMPARE_OP              40 (==)
#            1182 STORE_FAST               4 (@py_assert2)
#            1184 LOAD_FAST                4 (@py_assert2)
#            1186 POP_JUMP_IF_TRUE       108 (to 1404)
#            1188 LOAD_GLOBAL              7 (NULL + @pytest_ar)
#            1198 LOAD_ATTR                8 (_call_reprcompare)
#            1218 LOAD_CONST              10 (('==',))
#            1220 LOAD_FAST                4 (@py_assert2)
#            1222 BUILD_TUPLE              1
#            1224 LOAD_CONST              19 (('%(py1)s == %(py4)s',))
#            1226 LOAD_FAST                9 (@py_assert0)
#            1228 LOAD_FAST               10 (@py_assert3)
#            1230 BUILD_TUPLE              2
#            1232 CALL                     4
#            1240 LOAD_GLOBAL              7 (NULL + @pytest_ar)
#            1250 LOAD_ATTR               16 (_saferepr)
#            1270 LOAD_FAST                9 (@py_assert0)
#            1272 CALL                     1
#            1280 LOAD_GLOBAL              7 (NULL + @pytest_ar)
#            1290 LOAD_ATTR               16 (_saferepr)
#            1310 LOAD_FAST               10 (@py_assert3)
#            1312 CALL                     1
#            1320 LOAD_CONST              20 (('py1', 'py4'))
#            1322 BUILD_CONST_KEY_MAP      2
#            1324 BINARY_OP                6 (%)
#            1328 STORE_FAST              11 (@py_format5)
#            1330 LOAD_CONST              21 ('assert %(py6)s')
#            1332 LOAD_CONST              22 ('py6')
#            1334 LOAD_FAST               11 (@py_format5)
#            1336 BUILD_MAP                1
#            1338 BINARY_OP                6 (%)
#            1342 STORE_FAST               7 (@py_format7)
#            1344 LOAD_GLOBAL             19 (NULL + AssertionError)
#            1354 LOAD_GLOBAL              7 (NULL + @pytest_ar)
#            1364 LOAD_ATTR               20 (_format_explanation)
#            1384 LOAD_FAST                7 (@py_format7)
#            1386 CALL                     1
#            1394 CALL                     1
#            1402 RAISE_VARARGS            1
#         >> 1404 LOAD_CONST               0 (None)
#            1406 COPY                     1
#            1408 STORE_FAST               9 (@py_assert0)
#            1410 COPY                     1
#            1412 STORE_FAST               4 (@py_assert2)
#            1414 STORE_FAST              10 (@py_assert3)
# 
#  88        1416 LOAD_FAST                3 (matrix)
#            1418 LOAD_CONST              25 (3)
#            1420 BINARY_SUBSCR
#            1424 STORE_FAST               9 (@py_assert0)
#            1426 LOAD_CONST               3 (20)
#            1428 LOAD_CONST               7 (40)
#            1430 LOAD_CONST              18 (('A', 'B'))
#            1432 BUILD_CONST_KEY_MAP      2
#            1434 STORE_FAST              10 (@py_assert3)
#            1436 LOAD_FAST                9 (@py_assert0)
#            1438 LOAD_FAST               10 (@py_assert3)
#            1440 COMPARE_OP              40 (==)
#            1444 STORE_FAST               4 (@py_assert2)
#            1446 LOAD_FAST                4 (@py_assert2)
#            1448 POP_JUMP_IF_TRUE       108 (to 1666)
#            1450 LOAD_GLOBAL              7 (NULL + @pytest_ar)
#            1460 LOAD_ATTR                8 (_call_reprcompare)
#            1480 LOAD_CONST              10 (('==',))
#            1482 LOAD_FAST                4 (@py_assert2)
#            1484 BUILD_TUPLE              1
#            1486 LOAD_CONST              19 (('%(py1)s == %(py4)s',))
#            1488 LOAD_FAST                9 (@py_assert0)
#            1490 LOAD_FAST               10 (@py_assert3)
#            1492 BUILD_TUPLE              2
#            1494 CALL                     4
#            1502 LOAD_GLOBAL              7 (NULL + @pytest_ar)
#            1512 LOAD_ATTR               16 (_saferepr)
#            1532 LOAD_FAST                9 (@py_assert0)
#            1534 CALL                     1
#            1542 LOAD_GLOBAL              7 (NULL + @pytest_ar)
#            1552 LOAD_ATTR               16 (_saferepr)
#            1572 LOAD_FAST               10 (@py_assert3)
#            1574 CALL                     1
#            1582 LOAD_CONST              20 (('py1', 'py4'))
#            1584 BUILD_CONST_KEY_MAP      2
#            1586 BINARY_OP                6 (%)
#            1590 STORE_FAST              11 (@py_format5)
#            1592 LOAD_CONST              21 ('assert %(py6)s')
#            1594 LOAD_CONST              22 ('py6')
#            1596 LOAD_FAST               11 (@py_format5)
#            1598 BUILD_MAP                1
#            1600 BINARY_OP                6 (%)
#            1604 STORE_FAST               7 (@py_format7)
#            1606 LOAD_GLOBAL             19 (NULL + AssertionError)
#            1616 LOAD_GLOBAL              7 (NULL + @pytest_ar)
#            1626 LOAD_ATTR               20 (_format_explanation)
#            1646 LOAD_FAST                7 (@py_format7)
#            1648 CALL                     1
#            1656 CALL                     1
#            1664 RAISE_VARARGS            1
#         >> 1666 LOAD_CONST               0 (None)
#            1668 COPY                     1
#            1670 STORE_FAST               9 (@py_assert0)
#            1672 COPY                     1
#            1674 STORE_FAST               4 (@py_assert2)
#            1676 STORE_FAST              10 (@py_assert3)
#            1678 RETURN_CONST             0 (None)
# 
# Disassembly of <code object TestOrthogonalSensitivity at 0x73cd945fe250, file "/home/chenying/researches/cloudpss-toolkit/cloudpss_skills_v2/tests/test_orthogonal_sensitivity.py", line 91>:
#  91           0 RESUME                   0
#               2 LOAD_NAME                0 (__name__)
#               4 STORE_NAME               1 (__module__)
#               6 LOAD_CONST               0 ('TestOrthogonalSensitivity')
#               8 STORE_NAME               2 (__qualname__)
# 
#  92          10 LOAD_CONST               1 (<code object test_calculate_sensitivity at 0x3afaa120, file "/home/chenying/researches/cloudpss-toolkit/cloudpss_skills_v2/tests/test_orthogonal_sensitivity.py", line 92>)
#              12 MAKE_FUNCTION            0
#              14 STORE_NAME               3 (test_calculate_sensitivity)
# 
# 128          16 LOAD_CONST               2 (<code object test_calculate_sensitivity_no_success at 0x3afad0d0, file "/home/chenying/researches/cloudpss-toolkit/cloudpss_skills_v2/tests/test_orthogonal_sensitivity.py", line 128>)
#              18 MAKE_FUNCTION            0
#              20 STORE_NAME               4 (test_calculate_sensitivity_no_success)
#              22 RETURN_CONST             3 (None)
# 
# Disassembly of <code object test_calculate_sensitivity at 0x3afaa120, file "/home/chenying/researches/cloudpss-toolkit/cloudpss_skills_v2/tests/test_orthogonal_sensitivity.py", line 92>:
#  92           0 RESUME                   0
# 
#  93           2 LOAD_GLOBAL              1 (NULL + OrthogonalSensitivitySkill)
#              12 CALL                     0
#              20 STORE_FAST               1 (skill)
# 
#  95          22 LOAD_CONST               1 ('A')
#              24 LOAD_CONST               2 (10)
#              26 LOAD_CONST               3 (20)
#              28 BUILD_LIST               2
#              30 LOAD_CONST               4 (('name', 'levels'))
#              32 BUILD_CONST_KEY_MAP      2
# 
#  96          34 LOAD_CONST               5 ('B')
#              36 LOAD_CONST               6 (30)
#              38 LOAD_CONST               7 (40)
#              40 BUILD_LIST               2
#              42 LOAD_CONST               4 (('name', 'levels'))
#              44 BUILD_CONST_KEY_MAP      2
# 
#  94          46 BUILD_LIST               2
#              48 STORE_FAST               2 (parameters)
# 
# 100          50 LOAD_CONST               8 ('success')
# 
# 101          52 LOAD_CONST               9 (100.0)
# 
# 102          54 LOAD_CONST               2 (10)
#              56 LOAD_CONST               6 (30)
#              58 LOAD_CONST              10 (('A', 'B'))
#              60 BUILD_CONST_KEY_MAP      2
# 
#  99          62 LOAD_CONST              11 (('status', 'result', 'parameter_values'))
#              64 BUILD_CONST_KEY_MAP      3
# 
# 105          66 LOAD_CONST               8 ('success')
# 
# 106          68 LOAD_CONST              12 (110.0)
# 
# 107          70 LOAD_CONST               2 (10)
#              72 LOAD_CONST               7 (40)
#              74 LOAD_CONST              10 (('A', 'B'))
#              76 BUILD_CONST_KEY_MAP      2
# 
# 104          78 LOAD_CONST              11 (('status', 'result', 'parameter_values'))
#              80 BUILD_CONST_KEY_MAP      3
# 
# 110          82 LOAD_CONST               8 ('success')
# 
# 111          84 LOAD_CONST              13 (130.0)
# 
# 112          86 LOAD_CONST               3 (20)
#              88 LOAD_CONST               6 (30)
#              90 LOAD_CONST              10 (('A', 'B'))
#              92 BUILD_CONST_KEY_MAP      2
# 
# 109          94 LOAD_CONST              11 (('status', 'result', 'parameter_values'))
#              96 BUILD_CONST_KEY_MAP      3
# 
# 115          98 LOAD_CONST               8 ('success')
# 
# 116         100 LOAD_CONST              14 (140.0)
# 
# 117         102 LOAD_CONST               3 (20)
#             104 LOAD_CONST               7 (40)
#             106 LOAD_CONST              10 (('A', 'B'))
#             108 BUILD_CONST_KEY_MAP      2
# 
# 114         110 LOAD_CONST              11 (('status', 'result', 'parameter_values'))
#             112 BUILD_CONST_KEY_MAP      3
# 
#  98         114 BUILD_LIST               4
#             116 STORE_FAST               3 (runs)
# 
# 120         118 LOAD_FAST                1 (skill)
#             120 LOAD_ATTR                3 (NULL|self + _calculate_sensitivity)
#             140 LOAD_FAST                3 (runs)
#             142 LOAD_FAST                2 (parameters)
#             144 CALL                     2
#             152 STORE_FAST               4 (results)
# 
# 121         154 LOAD_GLOBAL              5 (NULL + len)
#             164 LOAD_FAST                4 (results)
#             166 CALL                     1
#             174 STORE_FAST               5 (@py_assert2)
#             176 LOAD_CONST              15 (2)
#             178 STORE_FAST               6 (@py_assert5)
#             180 LOAD_FAST                5 (@py_assert2)
#             182 LOAD_FAST                6 (@py_assert5)
#             184 COMPARE_OP              40 (==)
#             188 STORE_FAST               7 (@py_assert4)
#             190 LOAD_FAST                7 (@py_assert4)
#             192 POP_JUMP_IF_TRUE       246 (to 686)
#             194 LOAD_GLOBAL              7 (NULL + @pytest_ar)
#             204 LOAD_ATTR                8 (_call_reprcompare)
#             224 LOAD_CONST              16 (('==',))
#             226 LOAD_FAST                7 (@py_assert4)
#             228 BUILD_TUPLE              1
#             230 LOAD_CONST              17 (('%(py3)s\n{%(py3)s = %(py0)s(%(py1)s)\n} == %(py6)s',))
#             232 LOAD_FAST                5 (@py_assert2)
#             234 LOAD_FAST                6 (@py_assert5)
#             236 BUILD_TUPLE              2
#             238 CALL                     4
#             246 LOAD_CONST              18 ('len')
#             248 LOAD_GLOBAL             11 (NULL + @py_builtins)
#             258 LOAD_ATTR               12 (locals)
#             278 CALL                     0
#             286 CONTAINS_OP              0
#             288 POP_JUMP_IF_TRUE        25 (to 340)
#             290 LOAD_GLOBAL              7 (NULL + @pytest_ar)
#             300 LOAD_ATTR               14 (_should_repr_global_name)
#             320 LOAD_GLOBAL              4 (len)
#             330 CALL                     1
#             338 POP_JUMP_IF_FALSE       25 (to 390)
#         >>  340 LOAD_GLOBAL              7 (NULL + @pytest_ar)
#             350 LOAD_ATTR               16 (_saferepr)
#             370 LOAD_GLOBAL              4 (len)
#             380 CALL                     1
#             388 JUMP_FORWARD             1 (to 392)
#         >>  390 LOAD_CONST              18 ('len')
#         >>  392 LOAD_CONST              19 ('results')
#             394 LOAD_GLOBAL             11 (NULL + @py_builtins)
#             404 LOAD_ATTR               12 (locals)
#             424 CALL                     0
#             432 CONTAINS_OP              0
#             434 POP_JUMP_IF_TRUE        21 (to 478)
#             436 LOAD_GLOBAL              7 (NULL + @pytest_ar)
#             446 LOAD_ATTR               14 (_should_repr_global_name)
#             466 LOAD_FAST                4 (results)
#             468 CALL                     1
#             476 POP_JUMP_IF_FALSE       21 (to 520)
#         >>  478 LOAD_GLOBAL              7 (NULL + @pytest_ar)
#             488 LOAD_ATTR               16 (_saferepr)
#             508 LOAD_FAST                4 (results)
#             510 CALL                     1
#             518 JUMP_FORWARD             1 (to 522)
#         >>  520 LOAD_CONST              19 ('results')
#         >>  522 LOAD_GLOBAL              7 (NULL + @pytest_ar)
#             532 LOAD_ATTR               16 (_saferepr)
#             552 LOAD_FAST                5 (@py_assert2)
#             554 CALL                     1
#             562 LOAD_GLOBAL              7 (NULL + @pytest_ar)
#             572 LOAD_ATTR               16 (_saferepr)
#             592 LOAD_FAST                6 (@py_assert5)
#             594 CALL                     1
#             602 LOAD_CONST              20 (('py0', 'py1', 'py3', 'py6'))
#             604 BUILD_CONST_KEY_MAP      4
#             606 BINARY_OP                6 (%)
#             610 STORE_FAST               8 (@py_format7)
#             612 LOAD_CONST              21 ('assert %(py8)s')
#             614 LOAD_CONST              22 ('py8')
#             616 LOAD_FAST                8 (@py_format7)
#             618 BUILD_MAP                1
#             620 BINARY_OP                6 (%)
#             624 STORE_FAST               9 (@py_format9)
#             626 LOAD_GLOBAL             19 (NULL + AssertionError)
#             636 LOAD_GLOBAL              7 (NULL + @pytest_ar)
#             646 LOAD_ATTR               20 (_format_explanation)
#             666 LOAD_FAST                9 (@py_format9)
#             668 CALL                     1
#             676 CALL                     1
#             684 RAISE_VARARGS            1
#         >>  686 LOAD_CONST               0 (None)
#             688 COPY                     1
#             690 STORE_FAST               5 (@py_assert2)
#             692 COPY                     1
#             694 STORE_FAST               7 (@py_assert4)
#             696 STORE_FAST               6 (@py_assert5)
# 
# 122         698 LOAD_CONST              23 (<code object <genexpr> at 0x73cd93b31430, file "/home/chenying/researches/cloudpss-toolkit/cloudpss_skills_v2/tests/test_orthogonal_sensitivity.py", line 122>)
#             700 MAKE_FUNCTION            0
#             702 LOAD_FAST                4 (results)
#             704 GET_ITER
#             706 CALL                     0
#             714 STORE_FAST              10 (@py_assert1)
#             716 LOAD_GLOBAL             23 (NULL + all)
#             726 LOAD_FAST               10 (@py_assert1)
#             728 CALL                     1
#             736 STORE_FAST              11 (@py_assert3)
#             738 LOAD_FAST               11 (@py_assert3)
#             740 POP_JUMP_IF_TRUE       149 (to 1040)
#             742 LOAD_CONST              24 ('assert %(py4)s\n{%(py4)s = %(py0)s(%(py2)s)\n}')
#             744 LOAD_CONST              25 ('all')
#             746 LOAD_GLOBAL             11 (NULL + @py_builtins)
#             756 LOAD_ATTR               12 (locals)
#             776 CALL                     0
#             784 CONTAINS_OP              0
#             786 POP_JUMP_IF_TRUE        25 (to 838)
#             788 LOAD_GLOBAL              7 (NULL + @pytest_ar)
#             798 LOAD_ATTR               14 (_should_repr_global_name)
#             818 LOAD_GLOBAL             22 (all)
#             828 CALL                     1
#             836 POP_JUMP_IF_FALSE       25 (to 888)
#         >>  838 LOAD_GLOBAL              7 (NULL + @pytest_ar)
#             848 LOAD_ATTR               16 (_saferepr)
#             868 LOAD_GLOBAL             22 (all)
#             878 CALL                     1
#             886 JUMP_FORWARD             1 (to 890)
#         >>  888 LOAD_CONST              25 ('all')
#         >>  890 LOAD_GLOBAL              7 (NULL + @pytest_ar)
#             900 LOAD_ATTR               16 (_saferepr)
#             920 LOAD_FAST               10 (@py_assert1)
#             922 CALL                     1
#             930 LOAD_GLOBAL              7 (NULL + @pytest_ar)
#             940 LOAD_ATTR               16 (_saferepr)
#             960 LOAD_FAST               11 (@py_assert3)
#             962 CALL                     1
#             970 LOAD_CONST              26 (('py0', 'py2', 'py4'))
#             972 BUILD_CONST_KEY_MAP      3
#             974 BINARY_OP                6 (%)
#             978 STORE_FAST              12 (@py_format5)
#             980 LOAD_GLOBAL             19 (NULL + AssertionError)
#             990 LOAD_GLOBAL              7 (NULL + @pytest_ar)
#            1000 LOAD_ATTR               20 (_format_explanation)
#            1020 LOAD_FAST               12 (@py_format5)
#            1022 CALL                     1
#            1030 CALL                     1
#            1038 RAISE_VARARGS            1
#         >> 1040 LOAD_CONST               0 (None)
#            1042 COPY                     1
#            1044 STORE_FAST              10 (@py_assert1)
#            1046 STORE_FAST              11 (@py_assert3)
# 
# 124        1048 LOAD_FAST                4 (results)
#            1050 LOAD_CONST              27 (0)
#            1052 BINARY_SUBSCR
# 
# 123        1056 STORE_FAST              10 (@py_assert1)
# 
# 124        1058 LOAD_FAST               10 (@py_assert1)
#            1060 LOAD_ATTR               24 (contribution_ratio)
# 
# 123        1080 STORE_FAST              11 (@py_assert3)
# 
# 124        1082 LOAD_FAST                4 (results)
#            1084 LOAD_CONST              28 (1)
#            1086 BINARY_SUBSCR
# 
# 123        1090 STORE_FAST               6 (@py_assert5)
# 
# 124        1092 LOAD_FAST                6 (@py_assert5)
#            1094 LOAD_ATTR               24 (contribution_ratio)
# 
# 123        1114 STORE_FAST              13 (@py_assert7)
# 
# 124        1116 LOAD_FAST               11 (@py_assert3)
#            1118 LOAD_FAST               13 (@py_assert7)
#            1120 BINARY_OP                0 (+)
# 
# 123        1124 STORE_FAST              14 (@py_assert9)
# 
# 124        1126 LOAD_CONST              29 (1.0)
# 
# 123        1128 STORE_FAST              15 (@py_assert10)
# 
# 124        1130 LOAD_FAST               14 (@py_assert9)
#            1132 LOAD_FAST               15 (@py_assert10)
#            1134 BINARY_OP               10 (-)
# 
# 123        1138 STORE_FAST              16 (@py_assert12)
# 
# 124        1140 LOAD_GLOBAL             27 (NULL + abs)
#            1150 LOAD_FAST               16 (@py_assert12)
#            1152 CALL                     1
# 
# 123        1160 STORE_FAST              17 (@py_assert13)
# 
# 125        1162 LOAD_CONST              30 (1e-10)
# 
# 123        1164 STORE_FAST              18 (@py_assert16)
# 
# 124        1166 LOAD_FAST               17 (@py_assert13)
# 
# 125        1168 LOAD_FAST               18 (@py_assert16)
# 
# 124        1170 COMPARE_OP               2 (<)
# 
# 123        1174 STORE_FAST              19 (@py_assert15)
#            1176 LOAD_FAST               19 (@py_assert15)
#            1178 EXTENDED_ARG             1
#            1180 POP_JUMP_IF_TRUE       281 (to 1744)
#            1182 LOAD_GLOBAL              7 (NULL + @pytest_ar)
# 
# 126        1192 LOAD_ATTR                8 (_call_reprcompare)
# 
# 123        1212 LOAD_CONST              31 (('<',))
#            1214 LOAD_FAST               19 (@py_assert15)
#            1216 BUILD_TUPLE              1
#            1218 LOAD_CONST              32 (('%(py14)s\n{%(py14)s = %(py0)s(((%(py4)s\n{%(py4)s = %(py2)s.contribution_ratio\n} + %(py8)s\n{%(py8)s = %(py6)s.contribution_ratio\n}) - %(py11)s))\n} < %(py17)s',))
# 
# 124        1220 LOAD_FAST               17 (@py_assert13)
# 
# 125        1222 LOAD_FAST               18 (@py_assert16)
# 
# 123        1224 BUILD_TUPLE              2
#            1226 CALL                     4
#            1234 LOAD_CONST              33 ('abs')
#            1236 LOAD_GLOBAL             11 (NULL + @py_builtins)
# 
# 126        1246 LOAD_ATTR               12 (locals)
# 
# 123        1266 CALL                     0
#            1274 CONTAINS_OP              0
#            1276 POP_JUMP_IF_TRUE        25 (to 1328)
#            1278 LOAD_GLOBAL              7 (NULL + @pytest_ar)
# 
# 126        1288 LOAD_ATTR               14 (_should_repr_global_name)
# 
# 124        1308 LOAD_GLOBAL             26 (abs)
# 
# 123        1318 CALL                     1
#            1326 POP_JUMP_IF_FALSE       25 (to 1378)
#         >> 1328 LOAD_GLOBAL              7 (NULL + @pytest_ar)
# 
# 126        1338 LOAD_ATTR               16 (_saferepr)
# 
# 124        1358 LOAD_GLOBAL             26 (abs)
# 
# 123        1368 CALL                     1
#            1376 JUMP_FORWARD             1 (to 1380)
#         >> 1378 LOAD_CONST              33 ('abs')
#         >> 1380 LOAD_GLOBAL              7 (NULL + @pytest_ar)
# 
# 126        1390 LOAD_ATTR               16 (_saferepr)
# 
# 124        1410 LOAD_FAST               10 (@py_assert1)
# 
# 123        1412 CALL                     1
#            1420 LOAD_GLOBAL              7 (NULL + @pytest_ar)
# 
# 126        1430 LOAD_ATTR               16 (_saferepr)
# 
# 124        1450 LOAD_FAST               11 (@py_assert3)
# 
# 123        1452 CALL                     1
#            1460 LOAD_GLOBAL              7 (NULL + @pytest_ar)
# 
# 126        1470 LOAD_ATTR               16 (_saferepr)
# 
# 124        1490 LOAD_FAST                6 (@py_assert5)
# 
# 123        1492 CALL                     1
#            1500 LOAD_GLOBAL              7 (NULL + @pytest_ar)
# 
# 126        1510 LOAD_ATTR               16 (_saferepr)
# 
# 124        1530 LOAD_FAST               13 (@py_assert7)
# 
# 123        1532 CALL                     1
#            1540 LOAD_GLOBAL              7 (NULL + @pytest_ar)
# 
# 126        1550 LOAD_ATTR               16 (_saferepr)
# 
# 124        1570 LOAD_FAST               15 (@py_assert10)
# 
# 123        1572 CALL                     1
#            1580 LOAD_GLOBAL              7 (NULL + @pytest_ar)
# 
# 126        1590 LOAD_ATTR               16 (_saferepr)
# 
# 124        1610 LOAD_FAST               17 (@py_assert13)
# 
# 123        1612 CALL                     1
#            1620 LOAD_GLOBAL              7 (NULL + @pytest_ar)
# 
# 126        1630 LOAD_ATTR               16 (_saferepr)
# 
# 125        1650 LOAD_FAST               18 (@py_assert16)
# 
# 123        1652 CALL                     1
#            1660 LOAD_CONST              34 (('py0', 'py2', 'py4', 'py6', 'py8', 'py11', 'py14', 'py17'))
#            1662 BUILD_CONST_KEY_MAP      8
#            1664 BINARY_OP                6 (%)
#            1668 STORE_FAST              20 (@py_format18)
#            1670 LOAD_CONST              35 ('assert %(py19)s')
#            1672 LOAD_CONST              36 ('py19')
#            1674 LOAD_FAST               20 (@py_format18)
#            1676 BUILD_MAP                1
#            1678 BINARY_OP                6 (%)
#            1682 STORE_FAST              21 (@py_format20)
#            1684 LOAD_GLOBAL             19 (NULL + AssertionError)
#            1694 LOAD_GLOBAL              7 (NULL + @pytest_ar)
# 
# 126        1704 LOAD_ATTR               20 (_format_explanation)
# 
# 123        1724 LOAD_FAST               21 (@py_format20)
#            1726 CALL                     1
#            1734 CALL                     1
#            1742 RAISE_VARARGS            1
#         >> 1744 LOAD_CONST               0 (None)
#            1746 COPY                     1
#            1748 STORE_FAST              10 (@py_assert1)
#            1750 COPY                     1
#            1752 STORE_FAST              11 (@py_assert3)
#            1754 COPY                     1
#            1756 STORE_FAST               6 (@py_assert5)
#            1758 COPY                     1
#            1760 STORE_FAST              13 (@py_assert7)
#            1762 COPY                     1
#            1764 STORE_FAST              14 (@py_assert9)
#            1766 COPY                     1
#            1768 STORE_FAST              15 (@py_assert10)
#            1770 COPY                     1
#            1772 STORE_FAST              16 (@py_assert12)
#            1774 COPY                     1
#            1776 STORE_FAST              17 (@py_assert13)
#            1778 COPY                     1
#            1780 STORE_FAST              19 (@py_assert15)
#            1782 STORE_FAST              18 (@py_assert16)
#            1784 RETURN_CONST             0 (None)
# 
# Disassembly of <code object <genexpr> at 0x73cd93b31430, file "/home/chenying/researches/cloudpss-toolkit/cloudpss_skills_v2/tests/test_orthogonal_sensitivity.py", line 122>:
# 122           0 RETURN_GENERATOR
#               2 POP_TOP
#               4 RESUME                   0
#               6 LOAD_FAST                0 (.0)
#         >>    8 FOR_ITER                20 (to 52)
#              12 STORE_FAST               1 (r)
#              14 LOAD_GLOBAL              1 (NULL + isinstance)
#              24 LOAD_FAST                1 (r)
#              26 LOAD_GLOBAL              2 (SensitivityResult)
#              36 CALL                     2
#              44 YIELD_VALUE              1
#              46 RESUME                   1
#              48 POP_TOP
#              50 JUMP_BACKWARD           22 (to 8)
#         >>   52 END_FOR
#              54 RETURN_CONST             0 (None)
#         >>   56 CALL_INTRINSIC_1         3 (INTRINSIC_STOPITERATION_ERROR)
#              58 RERAISE                  1
# ExceptionTable:
#   4 to 54 -> 56 [0] lasti
# 
# Disassembly of <code object test_calculate_sensitivity_no_success at 0x3afad0d0, file "/home/chenying/researches/cloudpss-toolkit/cloudpss_skills_v2/tests/test_orthogonal_sensitivity.py", line 128>:
# 128           0 RESUME                   0
# 
# 129           2 LOAD_GLOBAL              1 (NULL + OrthogonalSensitivitySkill)
#              12 CALL                     0
#              20 STORE_FAST               1 (skill)
# 
# 130          22 LOAD_CONST               1 ('failed')
#              24 LOAD_CONST               0 (None)
#              26 BUILD_MAP                0
#              28 LOAD_CONST               2 (('status', 'result', 'parameter_values'))
#              30 BUILD_CONST_KEY_MAP      3
#              32 BUILD_LIST               1
#              34 STORE_FAST               2 (runs)
# 
# 131          36 LOAD_FAST                1 (skill)
#              38 LOAD_ATTR                3 (NULL|self + _calculate_sensitivity)
#              58 LOAD_FAST                2 (runs)
#              60 LOAD_CONST               3 ('A')
#              62 LOAD_CONST               4 (1)
#              64 LOAD_CONST               5 (2)
#              66 BUILD_LIST               2
#              68 LOAD_CONST               6 (('name', 'levels'))
#              70 BUILD_CONST_KEY_MAP      2
#              72 BUILD_LIST               1
#              74 CALL                     2
#              82 STORE_FAST               3 (results)
# 
# 132          84 BUILD_LIST               0
#              86 STORE_FAST               4 (@py_assert2)
#              88 LOAD_FAST                3 (results)
#              90 LOAD_FAST                4 (@py_assert2)
#              92 COMPARE_OP              40 (==)
#              96 STORE_FAST               5 (@py_assert1)
#              98 LOAD_FAST                5 (@py_assert1)
#             100 POP_JUMP_IF_TRUE       153 (to 408)
#             102 LOAD_GLOBAL              5 (NULL + @pytest_ar)
#             112 LOAD_ATTR                6 (_call_reprcompare)
#             132 LOAD_CONST               7 (('==',))
#             134 LOAD_FAST                5 (@py_assert1)
#             136 BUILD_TUPLE              1
#             138 LOAD_CONST               8 (('%(py0)s == %(py3)s',))
#             140 LOAD_FAST                3 (results)
#             142 LOAD_FAST                4 (@py_assert2)
#             144 BUILD_TUPLE              2
#             146 CALL                     4
#             154 LOAD_CONST               9 ('results')
#             156 LOAD_GLOBAL              9 (NULL + @py_builtins)
#             166 LOAD_ATTR               10 (locals)
#             186 CALL                     0
#             194 CONTAINS_OP              0
#             196 POP_JUMP_IF_TRUE        21 (to 240)
#             198 LOAD_GLOBAL              5 (NULL + @pytest_ar)
#             208 LOAD_ATTR               12 (_should_repr_global_name)
#             228 LOAD_FAST                3 (results)
#             230 CALL                     1
#             238 POP_JUMP_IF_FALSE       21 (to 282)
#         >>  240 LOAD_GLOBAL              5 (NULL + @pytest_ar)
#             250 LOAD_ATTR               14 (_saferepr)
#             270 LOAD_FAST                3 (results)
#             272 CALL                     1
#             280 JUMP_FORWARD             1 (to 284)
#         >>  282 LOAD_CONST               9 ('results')
#         >>  284 LOAD_GLOBAL              5 (NULL + @pytest_ar)
#             294 LOAD_ATTR               14 (_saferepr)
#             314 LOAD_FAST                4 (@py_assert2)
#             316 CALL                     1
#             324 LOAD_CONST              10 (('py0', 'py3'))
#             326 BUILD_CONST_KEY_MAP      2
#             328 BINARY_OP                6 (%)
#             332 STORE_FAST               6 (@py_format4)
#             334 LOAD_CONST              11 ('assert %(py5)s')
#             336 LOAD_CONST              12 ('py5')
#             338 LOAD_FAST                6 (@py_format4)
#             340 BUILD_MAP                1
#             342 BINARY_OP                6 (%)
#             346 STORE_FAST               7 (@py_format6)
#             348 LOAD_GLOBAL             17 (NULL + AssertionError)
#             358 LOAD_GLOBAL              5 (NULL + @pytest_ar)
#             368 LOAD_ATTR               18 (_format_explanation)
#             388 LOAD_FAST                7 (@py_format6)
#             390 CALL                     1
#             398 CALL                     1
#             406 RAISE_VARARGS            1
#         >>  408 LOAD_CONST               0 (None)
#             410 COPY                     1
#             412 STORE_FAST               5 (@py_assert1)
#             414 STORE_FAST               4 (@py_assert2)
#             416 RETURN_CONST             0 (None)
# 
# Disassembly of <code object TestOrthogonalTables at 0x73cd945febf0, file "/home/chenying/researches/cloudpss-toolkit/cloudpss_skills_v2/tests/test_orthogonal_sensitivity.py", line 135>:
# 135           0 RESUME                   0
#               2 LOAD_NAME                0 (__name__)
#               4 STORE_NAME               1 (__module__)
#               6 LOAD_CONST               0 ('TestOrthogonalTables')
#               8 STORE_NAME               2 (__qualname__)
# 
# 136          10 LOAD_CONST               1 (<code object test_orthogonal_tables_exist at 0x3afaaed0, file "/home/chenying/researches/cloudpss-toolkit/cloudpss_skills_v2/tests/test_orthogonal_sensitivity.py", line 136>)
#              12 MAKE_FUNCTION            0
#              14 STORE_NAME               3 (test_orthogonal_tables_exist)
# 
# 142          16 LOAD_CONST               2 (<code object test_l4_table_structure at 0x3aed0fc0, file "/home/chenying/researches/cloudpss-toolkit/cloudpss_skills_v2/tests/test_orthogonal_sensitivity.py", line 142>)
#              18 MAKE_FUNCTION            0
#              20 STORE_NAME               4 (test_l4_table_structure)
#              22 RETURN_CONST             3 (None)
# 
# Disassembly of <code object test_orthogonal_tables_exist at 0x3afaaed0, file "/home/chenying/researches/cloudpss-toolkit/cloudpss_skills_v2/tests/test_orthogonal_sensitivity.py", line 136>:
# 136           0 RESUME                   0
# 
# 137           2 LOAD_CONST               1 ('L4_2_3')
#               4 STORE_FAST               1 (@py_assert0)
#               6 LOAD_FAST                1 (@py_assert0)
#               8 LOAD_GLOBAL              0 (ORTHOGONAL_TABLES)
#              18 CONTAINS_OP              0
#              20 STORE_FAST               2 (@py_assert2)
#              22 LOAD_FAST                2 (@py_assert2)
#              24 POP_JUMP_IF_TRUE       165 (to 356)
#              26 LOAD_GLOBAL              3 (NULL + @pytest_ar)
#              36 LOAD_ATTR                4 (_call_reprcompare)
#              56 LOAD_CONST               2 (('in',))
#              58 LOAD_FAST                2 (@py_assert2)
#              60 BUILD_TUPLE              1
#              62 LOAD_CONST               3 (('%(py1)s in %(py3)s',))
#              64 LOAD_FAST                1 (@py_assert0)
#              66 LOAD_GLOBAL              0 (ORTHOGONAL_TABLES)
#              76 BUILD_TUPLE              2
#              78 CALL                     4
#              86 LOAD_GLOBAL              3 (NULL + @pytest_ar)
#              96 LOAD_ATTR                6 (_saferepr)
#             116 LOAD_FAST                1 (@py_assert0)
#             118 CALL                     1
#             126 LOAD_CONST               4 ('ORTHOGONAL_TABLES')
#             128 LOAD_GLOBAL              9 (NULL + @py_builtins)
#             138 LOAD_ATTR               10 (locals)
#             158 CALL                     0
#             166 CONTAINS_OP              0
#             168 POP_JUMP_IF_TRUE        25 (to 220)
#             170 LOAD_GLOBAL              3 (NULL + @pytest_ar)
#             180 LOAD_ATTR               12 (_should_repr_global_name)
#             200 LOAD_GLOBAL              0 (ORTHOGONAL_TABLES)
#             210 CALL                     1
#             218 POP_JUMP_IF_FALSE       25 (to 270)
#         >>  220 LOAD_GLOBAL              3 (NULL + @pytest_ar)
#             230 LOAD_ATTR                6 (_saferepr)
#             250 LOAD_GLOBAL              0 (ORTHOGONAL_TABLES)
#             260 CALL                     1
#             268 JUMP_FORWARD             1 (to 272)
#         >>  270 LOAD_CONST               4 ('ORTHOGONAL_TABLES')
#         >>  272 LOAD_CONST               5 (('py1', 'py3'))
#             274 BUILD_CONST_KEY_MAP      2
#             276 BINARY_OP                6 (%)
#             280 STORE_FAST               3 (@py_format4)
#             282 LOAD_CONST               6 ('assert %(py5)s')
#             284 LOAD_CONST               7 ('py5')
#             286 LOAD_FAST                3 (@py_format4)
#             288 BUILD_MAP                1
#             290 BINARY_OP                6 (%)
#             294 STORE_FAST               4 (@py_format6)
#             296 LOAD_GLOBAL             15 (NULL + AssertionError)
#             306 LOAD_GLOBAL              3 (NULL + @pytest_ar)
#             316 LOAD_ATTR               16 (_format_explanation)
#             336 LOAD_FAST                4 (@py_format6)
#             338 CALL                     1
#             346 CALL                     1
#             354 RAISE_VARARGS            1
#         >>  356 LOAD_CONST               0 (None)
#             358 COPY                     1
#             360 STORE_FAST               1 (@py_assert0)
#             362 STORE_FAST               2 (@py_assert2)
# 
# 138         364 LOAD_CONST               8 ('L8_2_7')
#             366 STORE_FAST               1 (@py_assert0)
#             368 LOAD_FAST                1 (@py_assert0)
#             370 LOAD_GLOBAL              0 (ORTHOGONAL_TABLES)
#             380 CONTAINS_OP              0
#             382 STORE_FAST               2 (@py_assert2)
#             384 LOAD_FAST                2 (@py_assert2)
#             386 POP_JUMP_IF_TRUE       165 (to 718)
#             388 LOAD_GLOBAL              3 (NULL + @pytest_ar)
#             398 LOAD_ATTR                4 (_call_reprcompare)
#             418 LOAD_CONST               2 (('in',))
#             420 LOAD_FAST                2 (@py_assert2)
#             422 BUILD_TUPLE              1
#             424 LOAD_CONST               3 (('%(py1)s in %(py3)s',))
#             426 LOAD_FAST                1 (@py_assert0)
#             428 LOAD_GLOBAL              0 (ORTHOGONAL_TABLES)
#             438 BUILD_TUPLE              2
#             440 CALL                     4
#             448 LOAD_GLOBAL              3 (NULL + @pytest_ar)
#             458 LOAD_ATTR                6 (_saferepr)
#             478 LOAD_FAST                1 (@py_assert0)
#             480 CALL                     1
#             488 LOAD_CONST               4 ('ORTHOGONAL_TABLES')
#             490 LOAD_GLOBAL              9 (NULL + @py_builtins)
#             500 LOAD_ATTR               10 (locals)
#             520 CALL                     0
#             528 CONTAINS_OP              0
#             530 POP_JUMP_IF_TRUE        25 (to 582)
#             532 LOAD_GLOBAL              3 (NULL + @pytest_ar)
#             542 LOAD_ATTR               12 (_should_repr_global_name)
#             562 LOAD_GLOBAL              0 (ORTHOGONAL_TABLES)
#             572 CALL                     1
#             580 POP_JUMP_IF_FALSE       25 (to 632)
#         >>  582 LOAD_GLOBAL              3 (NULL + @pytest_ar)
#             592 LOAD_ATTR                6 (_saferepr)
#             612 LOAD_GLOBAL              0 (ORTHOGONAL_TABLES)
#             622 CALL                     1
#             630 JUMP_FORWARD             1 (to 634)
#         >>  632 LOAD_CONST               4 ('ORTHOGONAL_TABLES')
#         >>  634 LOAD_CONST               5 (('py1', 'py3'))
#             636 BUILD_CONST_KEY_MAP      2
#             638 BINARY_OP                6 (%)
#             642 STORE_FAST               3 (@py_format4)
#             644 LOAD_CONST               6 ('assert %(py5)s')
#             646 LOAD_CONST               7 ('py5')
#             648 LOAD_FAST                3 (@py_format4)
#             650 BUILD_MAP                1
#             652 BINARY_OP                6 (%)
#             656 STORE_FAST               4 (@py_format6)
#             658 LOAD_GLOBAL             15 (NULL + AssertionError)
#             668 LOAD_GLOBAL              3 (NULL + @pytest_ar)
#             678 LOAD_ATTR               16 (_format_explanation)
#             698 LOAD_FAST                4 (@py_format6)
#             700 CALL                     1
#             708 CALL                     1
#             716 RAISE_VARARGS            1
#         >>  718 LOAD_CONST               0 (None)
#             720 COPY                     1
#             722 STORE_FAST               1 (@py_assert0)
#             724 STORE_FAST               2 (@py_assert2)
# 
# 139         726 LOAD_CONST               9 ('L9_3_4')
#             728 STORE_FAST               1 (@py_assert0)
#             730 LOAD_FAST                1 (@py_assert0)
#             732 LOAD_GLOBAL              0 (ORTHOGONAL_TABLES)
#             742 CONTAINS_OP              0
#             744 STORE_FAST               2 (@py_assert2)
#             746 LOAD_FAST                2 (@py_assert2)
#             748 POP_JUMP_IF_TRUE       165 (to 1080)
#             750 LOAD_GLOBAL              3 (NULL + @pytest_ar)
#             760 LOAD_ATTR                4 (_call_reprcompare)
#             780 LOAD_CONST               2 (('in',))
#             782 LOAD_FAST                2 (@py_assert2)
#             784 BUILD_TUPLE              1
#             786 LOAD_CONST               3 (('%(py1)s in %(py3)s',))
#             788 LOAD_FAST                1 (@py_assert0)
#             790 LOAD_GLOBAL              0 (ORTHOGONAL_TABLES)
#             800 BUILD_TUPLE              2
#             802 CALL                     4
#             810 LOAD_GLOBAL              3 (NULL + @pytest_ar)
#             820 LOAD_ATTR                6 (_saferepr)
#             840 LOAD_FAST                1 (@py_assert0)
#             842 CALL                     1
#             850 LOAD_CONST               4 ('ORTHOGONAL_TABLES')
#             852 LOAD_GLOBAL              9 (NULL + @py_builtins)
#             862 LOAD_ATTR               10 (locals)
#             882 CALL                     0
#             890 CONTAINS_OP              0
#             892 POP_JUMP_IF_TRUE        25 (to 944)
#             894 LOAD_GLOBAL              3 (NULL + @pytest_ar)
#             904 LOAD_ATTR               12 (_should_repr_global_name)
#             924 LOAD_GLOBAL              0 (ORTHOGONAL_TABLES)
#             934 CALL                     1
#             942 POP_JUMP_IF_FALSE       25 (to 994)
#         >>  944 LOAD_GLOBAL              3 (NULL + @pytest_ar)
#             954 LOAD_ATTR                6 (_saferepr)
#             974 LOAD_GLOBAL              0 (ORTHOGONAL_TABLES)
#             984 CALL                     1
#             992 JUMP_FORWARD             1 (to 996)
#         >>  994 LOAD_CONST               4 ('ORTHOGONAL_TABLES')
#         >>  996 LOAD_CONST               5 (('py1', 'py3'))
#             998 BUILD_CONST_KEY_MAP      2
#            1000 BINARY_OP                6 (%)
#            1004 STORE_FAST               3 (@py_format4)
#            1006 LOAD_CONST               6 ('assert %(py5)s')
#            1008 LOAD_CONST               7 ('py5')
#            1010 LOAD_FAST                3 (@py_format4)
#            1012 BUILD_MAP                1
#            1014 BINARY_OP                6 (%)
#            1018 STORE_FAST               4 (@py_format6)
#            1020 LOAD_GLOBAL             15 (NULL + AssertionError)
#            1030 LOAD_GLOBAL              3 (NULL + @pytest_ar)
#            1040 LOAD_ATTR               16 (_format_explanation)
#            1060 LOAD_FAST                4 (@py_format6)
#            1062 CALL                     1
#            1070 CALL                     1
#            1078 RAISE_VARARGS            1
#         >> 1080 LOAD_CONST               0 (None)
#            1082 COPY                     1
#            1084 STORE_FAST               1 (@py_assert0)
#            1086 STORE_FAST               2 (@py_assert2)
# 
# 140        1088 LOAD_CONST              10 ('L16_4_5')
#            1090 STORE_FAST               1 (@py_assert0)
#            1092 LOAD_FAST                1 (@py_assert0)
#            1094 LOAD_GLOBAL              0 (ORTHOGONAL_TABLES)
#            1104 CONTAINS_OP              0
#            1106 STORE_FAST               2 (@py_assert2)
#            1108 LOAD_FAST                2 (@py_assert2)
#            1110 POP_JUMP_IF_TRUE       165 (to 1442)
#            1112 LOAD_GLOBAL              3 (NULL + @pytest_ar)
#            1122 LOAD_ATTR                4 (_call_reprcompare)
#            1142 LOAD_CONST               2 (('in',))
#            1144 LOAD_FAST                2 (@py_assert2)
#            1146 BUILD_TUPLE              1
#            1148 LOAD_CONST               3 (('%(py1)s in %(py3)s',))
#            1150 LOAD_FAST                1 (@py_assert0)
#            1152 LOAD_GLOBAL              0 (ORTHOGONAL_TABLES)
#            1162 BUILD_TUPLE              2
#            1164 CALL                     4
#            1172 LOAD_GLOBAL              3 (NULL + @pytest_ar)
#            1182 LOAD_ATTR                6 (_saferepr)
#            1202 LOAD_FAST                1 (@py_assert0)
#            1204 CALL                     1
#            1212 LOAD_CONST               4 ('ORTHOGONAL_TABLES')
#            1214 LOAD_GLOBAL              9 (NULL + @py_builtins)
#            1224 LOAD_ATTR               10 (locals)
#            1244 CALL                     0
#            1252 CONTAINS_OP              0
#            1254 POP_JUMP_IF_TRUE        25 (to 1306)
#            1256 LOAD_GLOBAL              3 (NULL + @pytest_ar)
#            1266 LOAD_ATTR               12 (_should_repr_global_name)
#            1286 LOAD_GLOBAL              0 (ORTHOGONAL_TABLES)
#            1296 CALL                     1
#            1304 POP_JUMP_IF_FALSE       25 (to 1356)
#         >> 1306 LOAD_GLOBAL              3 (NULL + @pytest_ar)
#            1316 LOAD_ATTR                6 (_saferepr)
#            1336 LOAD_GLOBAL              0 (ORTHOGONAL_TABLES)
#            1346 CALL                     1
#            1354 JUMP_FORWARD             1 (to 1358)
#         >> 1356 LOAD_CONST               4 ('ORTHOGONAL_TABLES')
#         >> 1358 LOAD_CONST               5 (('py1', 'py3'))
#            1360 BUILD_CONST_KEY_MAP      2
#            1362 BINARY_OP                6 (%)
#            1366 STORE_FAST               3 (@py_format4)
#            1368 LOAD_CONST               6 ('assert %(py5)s')
#            1370 LOAD_CONST               7 ('py5')
#            1372 LOAD_FAST                3 (@py_format4)
#            1374 BUILD_MAP                1
#            1376 BINARY_OP                6 (%)
#            1380 STORE_FAST               4 (@py_format6)
#            1382 LOAD_GLOBAL             15 (NULL + AssertionError)
#            1392 LOAD_GLOBAL              3 (NULL + @pytest_ar)
#            1402 LOAD_ATTR               16 (_format_explanation)
#            1422 LOAD_FAST                4 (@py_format6)
#            1424 CALL                     1
#            1432 CALL                     1
#            1440 RAISE_VARARGS            1
#         >> 1442 LOAD_CONST               0 (None)
#            1444 COPY                     1
#            1446 STORE_FAST               1 (@py_assert0)
#            1448 STORE_FAST               2 (@py_assert2)
#            1450 RETURN_CONST             0 (None)
# 
# Disassembly of <code object test_l4_table_structure at 0x3aed0fc0, file "/home/chenying/researches/cloudpss-toolkit/cloudpss_skills_v2/tests/test_orthogonal_sensitivity.py", line 142>:
# 142           0 RESUME                   0
# 
# 143           2 LOAD_GLOBAL              0 (ORTHOGONAL_TABLES)
#              12 LOAD_CONST               1 ('L4_2_3')
#              14 BINARY_SUBSCR
#              18 STORE_FAST               1 (t)
# 
# 144          20 LOAD_FAST                1 (t)
#              22 LOAD_CONST               2 ('runs')
#              24 BINARY_SUBSCR
#              28 STORE_FAST               2 (@py_assert0)
#              30 LOAD_CONST               3 (4)
#              32 STORE_FAST               3 (@py_assert3)
#              34 LOAD_FAST                2 (@py_assert0)
#              36 LOAD_FAST                3 (@py_assert3)
#              38 COMPARE_OP              40 (==)
#              42 STORE_FAST               4 (@py_assert2)
#              44 LOAD_FAST                4 (@py_assert2)
#              46 POP_JUMP_IF_TRUE       108 (to 264)
#              48 LOAD_GLOBAL              3 (NULL + @pytest_ar)
#              58 LOAD_ATTR                4 (_call_reprcompare)
#              78 LOAD_CONST               4 (('==',))
#              80 LOAD_FAST                4 (@py_assert2)
#              82 BUILD_TUPLE              1
#              84 LOAD_CONST               5 (('%(py1)s == %(py4)s',))
#              86 LOAD_FAST                2 (@py_assert0)
#              88 LOAD_FAST                3 (@py_assert3)
#              90 BUILD_TUPLE              2
#              92 CALL                     4
#             100 LOAD_GLOBAL              3 (NULL + @pytest_ar)
#             110 LOAD_ATTR                6 (_saferepr)
#             130 LOAD_FAST                2 (@py_assert0)
#             132 CALL                     1
#             140 LOAD_GLOBAL              3 (NULL + @pytest_ar)
#             150 LOAD_ATTR                6 (_saferepr)
#             170 LOAD_FAST                3 (@py_assert3)
#             172 CALL                     1
#             180 LOAD_CONST               6 (('py1', 'py4'))
#             182 BUILD_CONST_KEY_MAP      2
#             184 BINARY_OP                6 (%)
#             188 STORE_FAST               5 (@py_format5)
#             190 LOAD_CONST               7 ('assert %(py6)s')
#             192 LOAD_CONST               8 ('py6')
#             194 LOAD_FAST                5 (@py_format5)
#             196 BUILD_MAP                1
#             198 BINARY_OP                6 (%)
#             202 STORE_FAST               6 (@py_format7)
#             204 LOAD_GLOBAL              9 (NULL + AssertionError)
#             214 LOAD_GLOBAL              3 (NULL + @pytest_ar)
#             224 LOAD_ATTR               10 (_format_explanation)
#             244 LOAD_FAST                6 (@py_format7)
#             246 CALL                     1
#             254 CALL                     1
#             262 RAISE_VARARGS            1
#         >>  264 LOAD_CONST               0 (None)
#             266 COPY                     1
#             268 STORE_FAST               2 (@py_assert0)
#             270 COPY                     1
#             272 STORE_FAST               4 (@py_assert2)
#             274 STORE_FAST               3 (@py_assert3)
# 
# 145         276 LOAD_FAST                1 (t)
#             278 LOAD_CONST               9 ('levels')
#             280 BINARY_SUBSCR
#             284 STORE_FAST               2 (@py_assert0)
#             286 LOAD_CONST              10 (2)
#             288 STORE_FAST               3 (@py_assert3)
#             290 LOAD_FAST                2 (@py_assert0)
#             292 LOAD_FAST                3 (@py_assert3)
#             294 COMPARE_OP              40 (==)
#             298 STORE_FAST               4 (@py_assert2)
#             300 LOAD_FAST                4 (@py_assert2)
#             302 POP_JUMP_IF_TRUE       108 (to 520)
#             304 LOAD_GLOBAL              3 (NULL + @pytest_ar)
#             314 LOAD_ATTR                4 (_call_reprcompare)
#             334 LOAD_CONST               4 (('==',))
#             336 LOAD_FAST                4 (@py_assert2)
#             338 BUILD_TUPLE              1
#             340 LOAD_CONST               5 (('%(py1)s == %(py4)s',))
#             342 LOAD_FAST                2 (@py_assert0)
#             344 LOAD_FAST                3 (@py_assert3)
#             346 BUILD_TUPLE              2
#             348 CALL                     4
#             356 LOAD_GLOBAL              3 (NULL + @pytest_ar)
#             366 LOAD_ATTR                6 (_saferepr)
#             386 LOAD_FAST                2 (@py_assert0)
#             388 CALL                     1
#             396 LOAD_GLOBAL              3 (NULL + @pytest_ar)
#             406 LOAD_ATTR                6 (_saferepr)
#             426 LOAD_FAST                3 (@py_assert3)
#             428 CALL                     1
#             436 LOAD_CONST               6 (('py1', 'py4'))
#             438 BUILD_CONST_KEY_MAP      2
#             440 BINARY_OP                6 (%)
#             444 STORE_FAST               5 (@py_format5)
#             446 LOAD_CONST               7 ('assert %(py6)s')
#             448 LOAD_CONST               8 ('py6')
#             450 LOAD_FAST                5 (@py_format5)
#             452 BUILD_MAP                1
#             454 BINARY_OP                6 (%)
#             458 STORE_FAST               6 (@py_format7)
#             460 LOAD_GLOBAL              9 (NULL + AssertionError)
#             470 LOAD_GLOBAL              3 (NULL + @pytest_ar)
#             480 LOAD_ATTR               10 (_format_explanation)
#             500 LOAD_FAST                6 (@py_format7)
#             502 CALL                     1
#             510 CALL                     1
#             518 RAISE_VARARGS            1
#         >>  520 LOAD_CONST               0 (None)
#             522 COPY                     1
#             524 STORE_FAST               2 (@py_assert0)
#             526 COPY                     1
#             528 STORE_FAST               4 (@py_assert2)
#             530 STORE_FAST               3 (@py_assert3)
# 
# 146         532 LOAD_FAST                1 (t)
#             534 LOAD_CONST              11 ('factors')
#             536 BINARY_SUBSCR
#             540 STORE_FAST               2 (@py_assert0)
#             542 LOAD_CONST              12 (3)
#             544 STORE_FAST               3 (@py_assert3)
#             546 LOAD_FAST                2 (@py_assert0)
#             548 LOAD_FAST                3 (@py_assert3)
#             550 COMPARE_OP              40 (==)
#             554 STORE_FAST               4 (@py_assert2)
#             556 LOAD_FAST                4 (@py_assert2)
#             558 POP_JUMP_IF_TRUE       108 (to 776)
#             560 LOAD_GLOBAL              3 (NULL + @pytest_ar)
#             570 LOAD_ATTR                4 (_call_reprcompare)
#             590 LOAD_CONST               4 (('==',))
#             592 LOAD_FAST                4 (@py_assert2)
#             594 BUILD_TUPLE              1
#             596 LOAD_CONST               5 (('%(py1)s == %(py4)s',))
#             598 LOAD_FAST                2 (@py_assert0)
#             600 LOAD_FAST                3 (@py_assert3)
#             602 BUILD_TUPLE              2
#             604 CALL                     4
#             612 LOAD_GLOBAL              3 (NULL + @pytest_ar)
#             622 LOAD_ATTR                6 (_saferepr)
#             642 LOAD_FAST                2 (@py_assert0)
#             644 CALL                     1
#             652 LOAD_GLOBAL              3 (NULL + @pytest_ar)
#             662 LOAD_ATTR                6 (_saferepr)
#             682 LOAD_FAST                3 (@py_assert3)
#             684 CALL                     1
#             692 LOAD_CONST               6 (('py1', 'py4'))
#             694 BUILD_CONST_KEY_MAP      2
#             696 BINARY_OP                6 (%)
#             700 STORE_FAST               5 (@py_format5)
#             702 LOAD_CONST               7 ('assert %(py6)s')
#             704 LOAD_CONST               8 ('py6')
#             706 LOAD_FAST                5 (@py_format5)
#             708 BUILD_MAP                1
#             710 BINARY_OP                6 (%)
#             714 STORE_FAST               6 (@py_format7)
#             716 LOAD_GLOBAL              9 (NULL + AssertionError)
#             726 LOAD_GLOBAL              3 (NULL + @pytest_ar)
#             736 LOAD_ATTR               10 (_format_explanation)
#             756 LOAD_FAST                6 (@py_format7)
#             758 CALL                     1
#             766 CALL                     1
#             774 RAISE_VARARGS            1
#         >>  776 LOAD_CONST               0 (None)
#             778 COPY                     1
#             780 STORE_FAST               2 (@py_assert0)
#             782 COPY                     1
#             784 STORE_FAST               4 (@py_assert2)
#             786 STORE_FAST               3 (@py_assert3)
# 
# 147         788 LOAD_FAST                1 (t)
#             790 LOAD_CONST              13 ('table')
#             792 BINARY_SUBSCR
#             796 STORE_FAST               7 (@py_assert1)
#             798 LOAD_GLOBAL             13 (NULL + len)
#             808 LOAD_FAST                7 (@py_assert1)
#             810 CALL                     1
#             818 STORE_FAST               3 (@py_assert3)
#             820 LOAD_CONST               3 (4)
#             822 STORE_FAST               8 (@py_assert6)
#             824 LOAD_FAST                3 (@py_assert3)
#             826 LOAD_FAST                8 (@py_assert6)
#             828 COMPARE_OP              40 (==)
#             832 STORE_FAST               9 (@py_assert5)
#             834 LOAD_FAST                9 (@py_assert5)
#             836 POP_JUMP_IF_TRUE       201 (to 1240)
#             838 LOAD_GLOBAL              3 (NULL + @pytest_ar)
#             848 LOAD_ATTR                4 (_call_reprcompare)
#             868 LOAD_CONST               4 (('==',))
#             870 LOAD_FAST                9 (@py_assert5)
#             872 BUILD_TUPLE              1
#             874 LOAD_CONST              14 (('%(py4)s\n{%(py4)s = %(py0)s(%(py2)s)\n} == %(py7)s',))
#             876 LOAD_FAST                3 (@py_assert3)
#             878 LOAD_FAST                8 (@py_assert6)
#             880 BUILD_TUPLE              2
#             882 CALL                     4
#             890 LOAD_CONST              15 ('len')
#             892 LOAD_GLOBAL             15 (NULL + @py_builtins)
#             902 LOAD_ATTR               16 (locals)
#             922 CALL                     0
#             930 CONTAINS_OP              0
#             932 POP_JUMP_IF_TRUE        25 (to 984)
#             934 LOAD_GLOBAL              3 (NULL + @pytest_ar)
#             944 LOAD_ATTR               18 (_should_repr_global_name)
#             964 LOAD_GLOBAL             12 (len)
#             974 CALL                     1
#             982 POP_JUMP_IF_FALSE       25 (to 1034)
#         >>  984 LOAD_GLOBAL              3 (NULL + @pytest_ar)
#             994 LOAD_ATTR                6 (_saferepr)
#            1014 LOAD_GLOBAL             12 (len)
#            1024 CALL                     1
#            1032 JUMP_FORWARD             1 (to 1036)
#         >> 1034 LOAD_CONST              15 ('len')
#         >> 1036 LOAD_GLOBAL              3 (NULL + @pytest_ar)
#            1046 LOAD_ATTR                6 (_saferepr)
#            1066 LOAD_FAST                7 (@py_assert1)
#            1068 CALL                     1
#            1076 LOAD_GLOBAL              3 (NULL + @pytest_ar)
#            1086 LOAD_ATTR                6 (_saferepr)
#            1106 LOAD_FAST                3 (@py_assert3)
#            1108 CALL                     1
#            1116 LOAD_GLOBAL              3 (NULL + @pytest_ar)
#            1126 LOAD_ATTR                6 (_saferepr)
#            1146 LOAD_FAST                8 (@py_assert6)
#            1148 CALL                     1
#            1156 LOAD_CONST              16 (('py0', 'py2', 'py4', 'py7'))
#            1158 BUILD_CONST_KEY_MAP      4
#            1160 BINARY_OP                6 (%)
#            1164 STORE_FAST              10 (@py_format8)
#            1166 LOAD_CONST              17 ('assert %(py9)s')
#            1168 LOAD_CONST              18 ('py9')
#            1170 LOAD_FAST               10 (@py_format8)
#            1172 BUILD_MAP                1
#            1174 BINARY_OP                6 (%)
#            1178 STORE_FAST              11 (@py_format10)
#            1180 LOAD_GLOBAL              9 (NULL + AssertionError)
#            1190 LOAD_GLOBAL              3 (NULL + @pytest_ar)
#            1200 LOAD_ATTR               10 (_format_explanation)
#            1220 LOAD_FAST               11 (@py_format10)
#            1222 CALL                     1
#            1230 CALL                     1
#            1238 RAISE_VARARGS            1
#         >> 1240 LOAD_CONST               0 (None)
#            1242 COPY                     1
#            1244 STORE_FAST               7 (@py_assert1)
#            1246 COPY                     1
#            1248 STORE_FAST               3 (@py_assert3)
#            1250 COPY                     1
#            1252 STORE_FAST               9 (@py_assert5)
#            1254 STORE_FAST               8 (@py_assert6)
#            1256 RETURN_CONST             0 (None)
# 
# Disassembly of <code object TestParameterLevel at 0x73cd945fecd0, file "/home/chenying/researches/cloudpss-toolkit/cloudpss_skills_v2/tests/test_orthogonal_sensitivity.py", line 150>:
# 150           0 RESUME                   0
#               2 LOAD_NAME                0 (__name__)
#               4 STORE_NAME               1 (__module__)
#               6 LOAD_CONST               0 ('TestParameterLevel')
#               8 STORE_NAME               2 (__qualname__)
# 
# 151          10 LOAD_CONST               1 (<code object test_parameter_level_dataclass at 0x3af9e7f0, file "/home/chenying/researches/cloudpss-toolkit/cloudpss_skills_v2/tests/test_orthogonal_sensitivity.py", line 151>)
#              12 MAKE_FUNCTION            0
#              14 STORE_NAME               3 (test_parameter_level_dataclass)
#              16 RETURN_CONST             2 (None)
# 
# Disassembly of <code object test_parameter_level_dataclass at 0x3af9e7f0, file "/home/chenying/researches/cloudpss-toolkit/cloudpss_skills_v2/tests/test_orthogonal_sensitivity.py", line 151>:
# 151           0 RESUME                   0
# 
# 152           2 LOAD_GLOBAL              1 (NULL + ParameterLevel)
#              12 LOAD_CONST               1 ('Power')
#              14 BUILD_LIST               0
#              16 LOAD_CONST               2 ((1.0, 2.0, 3.0))
#              18 LIST_EXTEND              1
#              20 KW_NAMES                 3 (('name', 'levels'))
#              22 CALL                     2
#              30 STORE_FAST               1 (p)
# 
# 153          32 LOAD_FAST                1 (p)
#              34 LOAD_ATTR                2 (name)
#              54 STORE_FAST               2 (@py_assert1)
#              56 LOAD_CONST               1 ('Power')
#              58 STORE_FAST               3 (@py_assert4)
#              60 LOAD_FAST                2 (@py_assert1)
#              62 LOAD_FAST                3 (@py_assert4)
#              64 COMPARE_OP              40 (==)
#              68 STORE_FAST               4 (@py_assert3)
#              70 LOAD_FAST                4 (@py_assert3)
#              72 POP_JUMP_IF_TRUE       173 (to 420)
#              74 LOAD_GLOBAL              5 (NULL + @pytest_ar)
#              84 LOAD_ATTR                6 (_call_reprcompare)
#             104 LOAD_CONST               4 (('==',))
#             106 LOAD_FAST                4 (@py_assert3)
#             108 BUILD_TUPLE              1
#             110 LOAD_CONST               5 (('%(py2)s\n{%(py2)s = %(py0)s.name\n} == %(py5)s',))
#             112 LOAD_FAST                2 (@py_assert1)
#             114 LOAD_FAST                3 (@py_assert4)
#             116 BUILD_TUPLE              2
#             118 CALL                     4
#             126 LOAD_CONST               6 ('p')
#             128 LOAD_GLOBAL              9 (NULL + @py_builtins)
#             138 LOAD_ATTR               10 (locals)
#             158 CALL                     0
#             166 CONTAINS_OP              0
#             168 POP_JUMP_IF_TRUE        21 (to 212)
#             170 LOAD_GLOBAL              5 (NULL + @pytest_ar)
#             180 LOAD_ATTR               12 (_should_repr_global_name)
#             200 LOAD_FAST                1 (p)
#             202 CALL                     1
#             210 POP_JUMP_IF_FALSE       21 (to 254)
#         >>  212 LOAD_GLOBAL              5 (NULL + @pytest_ar)
#             222 LOAD_ATTR               14 (_saferepr)
#             242 LOAD_FAST                1 (p)
#             244 CALL                     1
#             252 JUMP_FORWARD             1 (to 256)
#         >>  254 LOAD_CONST               6 ('p')
#         >>  256 LOAD_GLOBAL              5 (NULL + @pytest_ar)
#             266 LOAD_ATTR               14 (_saferepr)
#             286 LOAD_FAST                2 (@py_assert1)
#             288 CALL                     1
#             296 LOAD_GLOBAL              5 (NULL + @pytest_ar)
#             306 LOAD_ATTR               14 (_saferepr)
#             326 LOAD_FAST                3 (@py_assert4)
#             328 CALL                     1
#             336 LOAD_CONST               7 (('py0', 'py2', 'py5'))
#             338 BUILD_CONST_KEY_MAP      3
#             340 BINARY_OP                6 (%)
#             344 STORE_FAST               5 (@py_format6)
#             346 LOAD_CONST               8 ('assert %(py7)s')
#             348 LOAD_CONST               9 ('py7')
#             350 LOAD_FAST                5 (@py_format6)
#             352 BUILD_MAP                1
#             354 BINARY_OP                6 (%)
#             358 STORE_FAST               6 (@py_format8)
#             360 LOAD_GLOBAL             17 (NULL + AssertionError)
#             370 LOAD_GLOBAL              5 (NULL + @pytest_ar)
#             380 LOAD_ATTR               18 (_format_explanation)
#             400 LOAD_FAST                6 (@py_format8)
#             402 CALL                     1
#             410 CALL                     1
#             418 RAISE_VARARGS            1
#         >>  420 LOAD_CONST               0 (None)
#             422 COPY                     1
#             424 STORE_FAST               2 (@py_assert1)
#             426 COPY                     1
#             428 STORE_FAST               4 (@py_assert3)
#             430 STORE_FAST               3 (@py_assert4)
# 
# 154         432 LOAD_FAST                1 (p)
#             434 LOAD_ATTR               20 (levels)
#             454 STORE_FAST               7 (@py_assert2)
#             456 LOAD_GLOBAL             23 (NULL + len)
#             466 LOAD_FAST                7 (@py_assert2)
#             468 CALL                     1
#             476 STORE_FAST               3 (@py_assert4)
#             478 LOAD_CONST              10 (3)
#             480 STORE_FAST               8 (@py_assert7)
#             482 LOAD_FAST                3 (@py_assert4)
#             484 LOAD_FAST                8 (@py_assert7)
#             486 COMPARE_OP              40 (==)
#             490 STORE_FAST               9 (@py_assert6)
#             492 LOAD_FAST                9 (@py_assert6)
#             494 EXTENDED_ARG             1
#             496 POP_JUMP_IF_TRUE       266 (to 1030)
#             498 LOAD_GLOBAL              5 (NULL + @pytest_ar)
#             508 LOAD_ATTR                6 (_call_reprcompare)
#             528 LOAD_CONST               4 (('==',))
#             530 LOAD_FAST                9 (@py_assert6)
#             532 BUILD_TUPLE              1
#             534 LOAD_CONST              11 (('%(py5)s\n{%(py5)s = %(py0)s(%(py3)s\n{%(py3)s = %(py1)s.levels\n})\n} == %(py8)s',))
#             536 LOAD_FAST                3 (@py_assert4)
#             538 LOAD_FAST                8 (@py_assert7)
#             540 BUILD_TUPLE              2
#             542 CALL                     4
#             550 LOAD_CONST              12 ('len')
#             552 LOAD_GLOBAL              9 (NULL + @py_builtins)
#             562 LOAD_ATTR               10 (locals)
#             582 CALL                     0
#             590 CONTAINS_OP              0
#             592 POP_JUMP_IF_TRUE        25 (to 644)
#             594 LOAD_GLOBAL              5 (NULL + @pytest_ar)
#             604 LOAD_ATTR               12 (_should_repr_global_name)
#             624 LOAD_GLOBAL             22 (len)
#             634 CALL                     1
#             642 POP_JUMP_IF_FALSE       25 (to 694)
#         >>  644 LOAD_GLOBAL              5 (NULL + @pytest_ar)
#             654 LOAD_ATTR               14 (_saferepr)
#             674 LOAD_GLOBAL             22 (len)
#             684 CALL                     1
#             692 JUMP_FORWARD             1 (to 696)
#         >>  694 LOAD_CONST              12 ('len')
#         >>  696 LOAD_CONST               6 ('p')
#             698 LOAD_GLOBAL              9 (NULL + @py_builtins)
#             708 LOAD_ATTR               10 (locals)
#             728 CALL                     0
#             736 CONTAINS_OP              0
#             738 POP_JUMP_IF_TRUE        21 (to 782)
#             740 LOAD_GLOBAL              5 (NULL + @pytest_ar)
#             750 LOAD_ATTR               12 (_should_repr_global_name)
#             770 LOAD_FAST                1 (p)
#             772 CALL                     1
#             780 POP_JUMP_IF_FALSE       21 (to 824)
#         >>  782 LOAD_GLOBAL              5 (NULL + @pytest_ar)
#             792 LOAD_ATTR               14 (_saferepr)
#             812 LOAD_FAST                1 (p)
#             814 CALL                     1
#             822 JUMP_FORWARD             1 (to 826)
#         >>  824 LOAD_CONST               6 ('p')
#         >>  826 LOAD_GLOBAL              5 (NULL + @pytest_ar)
#             836 LOAD_ATTR               14 (_saferepr)
#             856 LOAD_FAST                7 (@py_assert2)
#             858 CALL                     1
#             866 LOAD_GLOBAL              5 (NULL + @pytest_ar)
#             876 LOAD_ATTR               14 (_saferepr)
#             896 LOAD_FAST                3 (@py_assert4)
#             898 CALL                     1
#             906 LOAD_GLOBAL              5 (NULL + @pytest_ar)
#             916 LOAD_ATTR               14 (_saferepr)
#             936 LOAD_FAST                8 (@py_assert7)
#             938 CALL                     1
#             946 LOAD_CONST              13 (('py0', 'py1', 'py3', 'py5', 'py8'))
#             948 BUILD_CONST_KEY_MAP      5
#             950 BINARY_OP                6 (%)
#             954 STORE_FAST              10 (@py_format9)
#             956 LOAD_CONST              14 ('assert %(py10)s')
#             958 LOAD_CONST              15 ('py10')
#             960 LOAD_FAST               10 (@py_format9)
#             962 BUILD_MAP                1
#             964 BINARY_OP                6 (%)
#             968 STORE_FAST              11 (@py_format11)
#             970 LOAD_GLOBAL             17 (NULL + AssertionError)
#             980 LOAD_GLOBAL              5 (NULL + @pytest_ar)
#             990 LOAD_ATTR               18 (_format_explanation)
#            1010 LOAD_FAST               11 (@py_format11)
#            1012 CALL                     1
#            1020 CALL                     1
#            1028 RAISE_VARARGS            1
#         >> 1030 LOAD_CONST               0 (None)
#            1032 COPY                     1
#            1034 STORE_FAST               7 (@py_assert2)
#            1036 COPY                     1
#            1038 STORE_FAST               3 (@py_assert4)
#            1040 COPY                     1
#            1042 STORE_FAST               9 (@py_assert6)
#            1044 STORE_FAST               8 (@py_assert7)
#            1046 RETURN_CONST             0 (None)
# 
# Disassembly of <code object TestOrthogonalRun at 0x73cd945fe870, file "/home/chenying/researches/cloudpss-toolkit/cloudpss_skills_v2/tests/test_orthogonal_sensitivity.py", line 157>:
# 157           0 RESUME                   0
#               2 LOAD_NAME                0 (__name__)
#               4 STORE_NAME               1 (__module__)
#               6 LOAD_CONST               0 ('TestOrthogonalRun')
#               8 STORE_NAME               2 (__qualname__)
# 
# 158          10 LOAD_CONST               1 (<code object test_run_invalid_config_returns_failure at 0x3af9ee00, file "/home/chenying/researches/cloudpss-toolkit/cloudpss_skills_v2/tests/test_orthogonal_sensitivity.py", line 158>)
#              12 MAKE_FUNCTION            0
#              14 STORE_NAME               3 (test_run_invalid_config_returns_failure)
#              16 RETURN_CONST             2 (None)
# 
# Disassembly of <code object test_run_invalid_config_returns_failure at 0x3af9ee00, file "/home/chenying/researches/cloudpss-toolkit/cloudpss_skills_v2/tests/test_orthogonal_sensitivity.py", line 158>:
# 158           0 RESUME                   0
# 
# 159           2 LOAD_GLOBAL              1 (NULL + OrthogonalSensitivitySkill)
#              12 CALL                     0
#              20 STORE_FAST               1 (skill)
# 
# 160          22 LOAD_FAST                1 (skill)
#              24 LOAD_ATTR                3 (NULL|self + run)
#              44 BUILD_MAP                0
#              46 CALL                     1
#              54 STORE_FAST               2 (result)
# 
# 161          56 LOAD_FAST                2 (result)
#              58 LOAD_ATTR                4 (status)
#              78 STORE_FAST               3 (@py_assert1)
#              80 LOAD_FAST                3 (@py_assert1)
#              82 LOAD_ATTR                6 (value)
#             102 STORE_FAST               4 (@py_assert3)
#             104 LOAD_CONST               1 ('FAILED')
#             106 LOAD_CONST               2 ('failed')
#             108 BUILD_LIST               2
#             110 STORE_FAST               5 (@py_assert6)
#             112 LOAD_FAST                4 (@py_assert3)
#             114 LOAD_FAST                5 (@py_assert6)
#             116 CONTAINS_OP              0
#             118 STORE_FAST               6 (@py_assert5)
#             120 LOAD_FAST                6 (@py_assert5)
#             122 POP_JUMP_IF_TRUE       193 (to 510)
#             124 LOAD_GLOBAL              9 (NULL + @pytest_ar)
#             134 LOAD_ATTR               10 (_call_reprcompare)
#             154 LOAD_CONST               3 (('in',))
#             156 LOAD_FAST                6 (@py_assert5)
#             158 BUILD_TUPLE              1
#             160 LOAD_CONST               4 (('%(py4)s\n{%(py4)s = %(py2)s\n{%(py2)s = %(py0)s.status\n}.value\n} in %(py7)s',))
#             162 LOAD_FAST                4 (@py_assert3)
#             164 LOAD_FAST                5 (@py_assert6)
#             166 BUILD_TUPLE              2
#             168 CALL                     4
#             176 LOAD_CONST               5 ('result')
#             178 LOAD_GLOBAL             13 (NULL + @py_builtins)
#             188 LOAD_ATTR               14 (locals)
#             208 CALL                     0
#             216 CONTAINS_OP              0
#             218 POP_JUMP_IF_TRUE        21 (to 262)
#             220 LOAD_GLOBAL              9 (NULL + @pytest_ar)
#             230 LOAD_ATTR               16 (_should_repr_global_name)
#             250 LOAD_FAST                2 (result)
#             252 CALL                     1
#             260 POP_JUMP_IF_FALSE       21 (to 304)
#         >>  262 LOAD_GLOBAL              9 (NULL + @pytest_ar)
#             272 LOAD_ATTR               18 (_saferepr)
#             292 LOAD_FAST                2 (result)
#             294 CALL                     1
#             302 JUMP_FORWARD             1 (to 306)
#         >>  304 LOAD_CONST               5 ('result')
#         >>  306 LOAD_GLOBAL              9 (NULL + @pytest_ar)
#             316 LOAD_ATTR               18 (_saferepr)
#             336 LOAD_FAST                3 (@py_assert1)
#             338 CALL                     1
#             346 LOAD_GLOBAL              9 (NULL + @pytest_ar)
#             356 LOAD_ATTR               18 (_saferepr)
#             376 LOAD_FAST                4 (@py_assert3)
#             378 CALL                     1
#             386 LOAD_GLOBAL              9 (NULL + @pytest_ar)
#             396 LOAD_ATTR               18 (_saferepr)
#             416 LOAD_FAST                5 (@py_assert6)
#             418 CALL                     1
#             426 LOAD_CONST               6 (('py0', 'py2', 'py4', 'py7'))
#             428 BUILD_CONST_KEY_MAP      4
#             430 BINARY_OP                6 (%)
#             434 STORE_FAST               7 (@py_format8)
#             436 LOAD_CONST               7 ('assert %(py9)s')
#             438 LOAD_CONST               8 ('py9')
#             440 LOAD_FAST                7 (@py_format8)
#             442 BUILD_MAP                1
#             444 BINARY_OP                6 (%)
#             448 STORE_FAST               8 (@py_format10)
#             450 LOAD_GLOBAL             21 (NULL + AssertionError)
#             460 LOAD_GLOBAL              9 (NULL + @pytest_ar)
#             470 LOAD_ATTR               22 (_format_explanation)
#             490 LOAD_FAST                8 (@py_format10)
#             492 CALL                     1
#             500 CALL                     1
#             508 RAISE_VARARGS            1
#         >>  510 LOAD_CONST               0 (None)
#             512 COPY                     1
#             514 STORE_FAST               3 (@py_assert1)
#             516 COPY                     1
#             518 STORE_FAST               4 (@py_assert3)
#             520 COPY                     1
#             522 STORE_FAST               6 (@py_assert5)
#             524 STORE_FAST               5 (@py_assert6)
#             526 RETURN_CONST             0 (None)
# 